Workbook

Sheet 通报
A1: =N6&"日10086投诉一级督办单占比通报" -> 19日10086投诉一级督办单占比通报 | S1: 每日新增 | X1: 无重复投诉（重点客户、网课） | AC1: 7天内重复投诉 | AH1: 大于7天小于30天
A2: 序号 | B2: 区县 | C2: =TEXT(NOW()-1,"dd")&"日新增" -> 19日新增 | J2: 累计一级督办单 | K2: 累计一级督办单占比 | L2: 区县 | S2: =_xlfn.TEXTJOIN(",",1,V3:V14) | V2: 前3 | X2: =_xlfn.TEXTJOIN(",",1,AA3:AA14) | AA2: 前3 | AC2: =_xlfn.TEXTJOIN(",",1,AF3:AF14) | AF2: 前3 | AH2: =_xlfn.TEXTJOIN(",",1,AK3:AK14) | AK2: 前3
C3: 重复投诉时间段 | H3: 一级督办单新增 | I3: 一级督办单占比新增 | V3: =VLOOKUP(1,$S$6:$T$17,2,0) | W3: 1 | AA3: =VLOOKUP(1,$X$6:$Y$17,2,0) | AB3: 1 | AF3: =VLOOKUP(1,$AC$6:$AD$17,2,0) | AG3: 1 | AK3: =VLOOKUP(1,$AH$6:$AI$17,2,0) | AL3: 1
C4: 无重复投诉（网课、重点客户） | D4: 7天内重复投诉 | E4: 7-30天以内重复投诉 | F4: 30-60天以内重复投诉 | G4: 60-90天以内重复投诉 | V4: =VLOOKUP(2,$S$6:$T$17,2,0) | W4: 2 | AA4: =VLOOKUP(2,$X$6:$Y$17,2,0) | AB4: 2 | AF4: =VLOOKUP(2,$AC$6:$AD$17,2,0) | AG4: 2 | AK4: =VLOOKUP(2,$AH$6:$AI$17,2,0) | AL4: 2
O5: 对比列 | P5: =VLOOKUP(1,O6:P17,2,0)&","&VLOOKUP(2,O6:P17,2,0)&","&VLOOKUP(3,O6:P17,2,0) -> 坊子(9.86%),潍城(9.34%),安丘(8.95%) | Q5: 对比列 | R5: =VLOOKUP(1,Q6:R17,2,0)&","&VLOOKUP(2,Q6:R17,2,0)&","&VLOOKUP(3,Q6:R17,2,0) -> #N/A | V5: =VLOOKUP(3,$S$6:$T$17,2,0) | W5: 3 | AA5: =VLOOKUP(3,$X$6:$Y$17,2,0) | AB5: 3 | AF5: =VLOOKUP(3,$AC$6:$AD$17,2,0) | AG5: 3 | AK5: =VLOOKUP(3,$AH$6:$AI$17,2,0) | AL5: 3
A6: 1 | B6: 坊子 | C6: =COUNTIFS(督办单!L:L,B:B,督办单!M:M,$M$6,督办单!P:P,"无",督办单!C:C,"*一级*") -> 0 | D6: =COUNTIFS(督办单!L:L,B:B,督办单!M:M,$M$6,督办单!P:P,"7天内",督办单!C:C,"*一级*") -> 0 | E6: =COUNTIFS(督办单!L:L,B:B,督办单!M:M,$M$6,督办单!P:P,"30天内",督办单!C:C,"*一级*") -> 0 | F6: =COUNTIFS(督办单!L:L,B:B,督办单!M:M,$M$6,督办单!P:P,"60天内",督办单!C:C,"*一级*") -> 0 | G6: =COUNTIFS(督办单!L:L,B:B,督办单!M:M,$M$6,督办单!P:P,"90天内",督办单!C:C,"*一级*") -> 0 | H6: =COUNTIFS(督办单!L:L,B:B,督办单!C:C,"*一级*",督办单!M:M,$M$6) -> 0 | I6: =COUNTIFS(督办单!L:L,B:B,督办单!C:C,"*一级*",督办单!M:M,$M$6)/(COUNTIFS(累计派单!R:R,B:B,累计派单!S:S,$M$6)-COUNTIFS(累计派单!R:R,B:B,累计派单!I:I,"*业务受理*",累计派单!S:S,$M$6)) -> #DIV/0! | J6: =COUNTIFS(督办单!L:L,B:B,督办单!C:C,"*一级*") -> 35 | K6: =J6/(COUNTIFS(累计派单!R:R,B:B)-COUNTIFS(累计派单!R:R,B:B,累计派单!I:I,"*业务受理*")-COUNTIFS(累计派单!I:I,"*客户咨询*")) -> 0.098591549 | L6: 坊子 | M6: =TEXT(TODAY()-1,"mmdd") -> 0119 | N6: =TEXT(NOW()-1,"dd") -> 19 | O6: =_xlfn.RANK.EQ(K6,$K$6:$K$17,0)+COUNTIF($K$6:$K6,K6)-1 -> 1 | P6: =B6&"("&ROUND(K6*100,2)&"%)" -> 坊子(9.86%) | Q6: =_xlfn.RANK.EQ(I6,$I$6:$I$17,0)+COUNTIF($I$6:$I6,I6)-1 -> #DIV/0! | R6: =B6&"("&ROUND(I6*100,2)&"%)" -> #DIV/0! | S6: =_xlfn.RANK.EQ(H6,$H$6:$H$17,0)+COUNTIF($H$6:$H6,H6)-1 -> 1 | T6: =IF(H6=0,"",B6&H6&"件") | U6: =H6 -> 0 | V6: =IF(V5="","",IF(VLOOKUP(W5,$S$6:$U$17,3,0)=VLOOKUP(W6,$S$6:$U$17,3,0),VLOOKUP(W6,$S$6:$U$17,2,0),"")) | W6: 4 | X6: =_xlfn.RANK.EQ(C6,$C$6:$C$17,0)+COUNTIF($C$6:$C6,C6)-1 -> 1 | Y6: =IF(Z6=0,"",B6&C6&"件") | Z6: =C6 -> 0 | AA6: =IF(AA5="","",IF(VLOOKUP(AB5,$AC$6:$AE$17,3,0)=VLOOKUP(AB6,$AC$6:$AE$17,3,0),VLOOKUP(AB6,$AC$6:$AE$17,2,0),"")) | AB6: 4 | AC6: =_xlfn.RANK.EQ(D6,$D$6:$D$17,0)+COUNTIF($D$6:$D6,D6)-1 -> 1 | AD6: =IF(AE6=0,"",B6&D6&"件") | AE6: =D6 -> 0 | AF6: =IF(AF5="","",IF(VLOOKUP(AG5,$AC$6:$AE$17,3,0)=VLOOKUP(AG6,$AC$6:$AE$17,3,0),VLOOKUP(AG6,$AC$6:$AE$17,2,0),"")) | AG6: 4 | AH6: =_xlfn.RANK.EQ(E6,$E$6:$E$17,0)+COUNTIF($E$6:$E6,E6)-1 -> 1 | AI6: =IF(AJ6=0,"",B6&E6&"件") | AJ6: =E6 -> 0 | AK6: =IF(AK5="","",IF(VLOOKUP(AL5,$AH$6:$AJ$17,3,0)=VLOOKUP(AL6,$AH$6:$AJ$17,3,0),VLOOKUP(AL6,$AH$6:$AJ$17,2,0),"")) | AL6: 4
A7: 2 | B7: 潍城 | C7: =COUNTIFS(督办单!L:L,B:B,督办单!M:M,$M$6,督办单!P:P,"无",督办单!C:C,"*一级*") -> 0 | D7: =COUNTIFS(督办单!L:L,B:B,督办单!M:M,$M$6,督办单!P:P,"7天内",督办单!C:C,"*一级*") -> 0 | E7: =COUNTIFS(督办单!L:L,B:B,督办单!M:M,$M$6,督办单!P:P,"30天内",督办单!C:C,"*一级*") -> 0 | F7: =COUNTIFS(督办单!L:L,B:B,督办单!M:M,$M$6,督办单!P:P,"60天内",督办单!C:C,"*一级*") -> 0 | G7: =COUNTIFS(督办单!L:L,B:B,督办单!M:M,$M$6,督办单!P:P,"90天内",督办单!C:C,"*一级*") -> 0 | H7: =COUNTIFS(督办单!L:L,B:B,督办单!C:C,"*一级*",督办单!M:M,$M$6) -> 0 | I7: =COUNTIFS(督办单!L:L,B:B,督办单!C:C,"*一级*",督办单!M:M,$M$6)/(COUNTIFS(累计派单!R:R,B:B,累计派单!S:S,$M$6)-COUNTIFS(累计派单!R:R,B:B,累计派单!I:I,"*业务受理*",累计派单!S:S,$M$6)) -> #DIV/0! | J7: =COUNTIFS(督办单!L:L,B:B,督办单!C:C,"*一级*") -> 58 | K7: =J7/(COUNTIFS(累计派单!R:R,B:B)-COUNTIFS(累计派单!R:R,B:B,累计派单!I:I,"*业务受理*")-COUNTIFS(累计派单!I:I,"*客户咨询*")) -> 0.093397746 | L7: 潍城 | O7: =_xlfn.RANK.EQ(K7,$K$6:$K$17,0)+COUNTIF($K$6:$K7,K7)-1 -> 2 | P7: =B7&"("&ROUND(K7*100,2)&"%)" -> 潍城(9.34%) | Q7: =_xlfn.RANK.EQ(I7,$I$6:$I$17,0)+COUNTIF($I$6:$I7,I7)-1 -> #DIV/0! | R7: =B7&"("&ROUND(I7*100,2)&"%)" -> #DIV/0! | S7: =_xlfn.RANK.EQ(H7,$H$6:$H$17,0)+COUNTIF($H$6:$H7,H7)-1 -> 2 | T7: =IF(H7=0,"",B7&H7&"件") | U7: =H7 -> 0 | V7: =IF(V6="","",IF(VLOOKUP(W6,$S$6:$U$17,3,0)=VLOOKUP(W7,$S$6:$U$17,3,0),VLOOKUP(W7,$S$6:$U$17,2,0),"")) | W7: 5 | X7: =_xlfn.RANK.EQ(C7,$C$6:$C$17,0)+COUNTIF($C$6:$C7,C7)-1 -> 2 | Y7: =IF(Z7=0,"",B7&C7&"件") | Z7: =C7 -> 0 | AA7: =IF(AA6="","",IF(VLOOKUP(AB6,$AC$6:$AE$17,3,0)=VLOOKUP(AB7,$AC$6:$AE$17,3,0),VLOOKUP(AB7,$AC$6:$AE$17,2,0),"")) | AB7: 5 | AC7: =_xlfn.RANK.EQ(D7,$D$6:$D$17,0)+COUNTIF($D$6:$D7,D7)-1 -> 2 | AD7: =IF(AE7=0,"",B7&D7&"件") | AE7: =D7 -> 0 | AF7: =IF(AF6="","",IF(VLOOKUP(AG6,$AC$6:$AE$17,3,0)=VLOOKUP(AG7,$AC$6:$AE$17,3,0),VLOOKUP(AG7,$AC$6:$AE$17,2,0),"")) | AG7: 5 | AH7: =_xlfn.RANK.EQ(E7,$E$6:$E$17,0)+COUNTIF($E$6:$E7,E7)-1 -> 2 | AI7: =IF(AJ7=0,"",B7&E7&"件") | AJ7: =E7 -> 0 | AK7: =IF(AK6="","",IF(VLOOKUP(AL6,$AH$6:$AJ$17,3,0)=VLOOKUP(AL7,$AH$6:$AJ$17,3,0),VLOOKUP(AL7,$AH$6:$AJ$17,2,0),"")) | AL7: 5
A8: 3 | B8: 奎文 | C8: =COUNTIFS(督办单!L:L,B:B,督办单!M:M,$M$6,督办单!P:P,"无",督办单!C:C,"*一级*") -> 0 | D8: =COUNTIFS(督办单!L:L,B:B,督办单!M:M,$M$6,督办单!P:P,"7天内",督办单!C:C,"*一级*") -> 0 | E8: =COUNTIFS(督办单!L:L,B:B,督办单!M:M,$M$6,督办单!P:P,"30天内",督办单!C:C,"*一级*") -> 0 | F8: =COUNTIFS(督办单!L:L,B:B,督办单!M:M,$M$6,督办单!P:P,"60天内",督办单!C:C,"*一级*") -> 0 | G8: =COUNTIFS(督办单!L:L,B:B,督办单!M:M,$M$6,督办单!P:P,"90天内",督办单!C:C,"*一级*") -> 0 | H8: =COUNTIFS(督办单!L:L,B:B,督办单!C:C,"*一级*",督办单!M:M,$M$6) -> 0 | I8: =COUNTIFS(督办单!L:L,B:B,督办单!C:C,"*一级*",督办单!M:M,$M$6)/(COUNTIFS(累计派单!R:R,B:B,累计派单!S:S,$M$6)-COUNTIFS(累计派单!R:R,B:B,累计派单!I:I,"*业务受理*",累计派单!S:S,$M$6)) -> #DIV/0! | J8: =COUNTIFS(督办单!L:L,B:B,督办单!C:C,"*一级*") -> 102 | K8: =J8/(COUNTIFS(累计派单!R:R,B:B)-COUNTIFS(累计派单!R:R,B:B,累计派单!I:I,"*业务受理*")-COUNTIFS(累计派单!I:I,"*客户咨询*")) -> 0.086587436 | L8: 奎文 | O8: =_xlfn.RANK.EQ(K8,$K$6:$K$17,0)+COUNTIF($K$6:$K8,K8)-1 -> 4 | P8: =B8&"("&ROUND(K8*100,2)&"%)" -> 奎文(8.66%) | Q8: =_xlfn.RANK.EQ(I8,$I$6:$I$17,0)+COUNTIF($I$6:$I8,I8)-1 -> #DIV/0! | R8: =B8&"("&ROUND(I8*100,2)&"%)" -> #DIV/0! | S8: =_xlfn.RANK.EQ(H8,$H$6:$H$17,0)+COUNTIF($H$6:$H8,H8)-1 -> 3 | T8: =IF(H8=0,"",B8&H8&"件") | U8: =H8 -> 0 | V8: =IF(V7="","",IF(VLOOKUP(W7,$S$6:$U$17,3,0)=VLOOKUP(W8,$S$6:$U$17,3,0),VLOOKUP(W8,$S$6:$U$17,2,0),"")) | W8: 6 | X8: =_xlfn.RANK.EQ(C8,$C$6:$C$17,0)+COUNTIF($C$6:$C8,C8)-1 -> 3 | Y8: =IF(Z8=0,"",B8&C8&"件") | Z8: =C8 -> 0 | AA8: =IF(AA7="","",IF(VLOOKUP(AB7,$AC$6:$AE$17,3,0)=VLOOKUP(AB8,$AC$6:$AE$17,3,0),VLOOKUP(AB8,$AC$6:$AE$17,2,0),"")) | AB8: 6 | AC8: =_xlfn.RANK.EQ(D8,$D$6:$D$17,0)+COUNTIF($D$6:$D8,D8)-1 -> 3 | AD8: =IF(AE8=0,"",B8&D8&"件") | AE8: =D8 -> 0 | AF8: =IF(AF7="","",IF(VLOOKUP(AG7,$AC$6:$AE$17,3,0)=VLOOKUP(AG8,$AC$6:$AE$17,3,0),VLOOKUP(AG8,$AC$6:$AE$17,2,0),"")) | AG8: 6 | AH8: =_xlfn.RANK.EQ(E8,$E$6:$E$17,0)+COUNTIF($E$6:$E8,E8)-1 -> 3 | AI8: =IF(AJ8=0,"",B8&E8&"件") | AJ8: =E8 -> 0 | AK8: =IF(AK7="","",IF(VLOOKUP(AL7,$AH$6:$AJ$17,3,0)=VLOOKUP(AL8,$AH$6:$AJ$17,3,0),VLOOKUP(AL8,$AH$6:$AJ$17,2,0),"")) | AL8: 6
A9: 4 | B9: 安丘 | C9: =COUNTIFS(督办单!L:L,B:B,督办单!M:M,$M$6,督办单!P:P,"无",督办单!C:C,"*一级*") -> 0 | D9: =COUNTIFS(督办单!L:L,B:B,督办单!M:M,$M$6,督办单!P:P,"7天内",督办单!C:C,"*一级*") -> 0 | E9: =COUNTIFS(督办单!L:L,B:B,督办单!M:M,$M$6,督办单!P:P,"30天内",督办单!C:C,"*一级*") -> 0 | F9: =COUNTIFS(督办单!L:L,B:B,督办单!M:M,$M$6,督办单!P:P,"60天内",督办单!C:C,"*一级*") -> 0 | G9: =COUNTIFS(督办单!L:L,B:B,督办单!M:M,$M$6,督办单!P:P,"90天内",督办单!C:C,"*一级*") -> 0 | H9: =COUNTIFS(督办单!L:L,B:B,督办单!C:C,"*一级*",督办单!M:M,$M$6) -> 0 | I9: =COUNTIFS(督办单!L:L,B:B,督办单!C:C,"*一级*",督办单!M:M,$M$6)/(COUNTIFS(累计派单!R:R,B:B,累计派单!S:S,$M$6)-COUNTIFS(累计派单!R:R,B:B,累计派单!I:I,"*业务受理*",累计派单!S:S,$M$6)) -> #DIV/0! | J9: =COUNTIFS(督办单!L:L,B:B,督办单!C:C,"*一级*") -> 67 | K9: =J9/(COUNTIFS(累计派单!R:R,B:B)-COUNTIFS(累计派单!R:R,B:B,累计派单!I:I,"*业务受理*")-COUNTIFS(累计派单!I:I,"*客户咨询*")) -> 0.089452603 | L9: 安丘 | O9: =_xlfn.RANK.EQ(K9,$K$6:$K$17,0)+COUNTIF($K$6:$K9,K9)-1 -> 3 | P9: =B9&"("&ROUND(K9*100,2)&"%)" -> 安丘(8.95%) | Q9: =_xlfn.RANK.EQ(I9,$I$6:$I$17,0)+COUNTIF($I$6:$I9,I9)-1 -> #DIV/0! | R9: =B9&"("&ROUND(I9*100,2)&"%)" -> #DIV/0! | S9: =_xlfn.RANK.EQ(H9,$H$6:$H$17,0)+COUNTIF($H$6:$H9,H9)-1 -> 4 | T9: =IF(H9=0,"",B9&H9&"件") | U9: =H9 -> 0 | V9: =IF(V8="","",IF(VLOOKUP(W8,$S$6:$U$17,3,0)=VLOOKUP(W9,$S$6:$U$17,3,0),VLOOKUP(W9,$S$6:$U$17,2,0),"")) | W9: 7 | X9: =_xlfn.RANK.EQ(C9,$C$6:$C$17,0)+COUNTIF($C$6:$C9,C9)-1 -> 4 | Y9: =IF(Z9=0,"",B9&C9&"件") | Z9: =C9 -> 0 | AA9: =IF(AA8="","",IF(VLOOKUP(AB8,$AC$6:$AE$17,3,0)=VLOOKUP(AB9,$AC$6:$AE$17,3,0),VLOOKUP(AB9,$AC$6:$AE$17,2,0),"")) | AB9: 7 | AC9: =_xlfn.RANK.EQ(D9,$D$6:$D$17,0)+COUNTIF($D$6:$D9,D9)-1 -> 4 | AD9: =IF(AE9=0,"",B9&D9&"件") | AE9: =D9 -> 0 | AF9: =IF(AF8="","",IF(VLOOKUP(AG8,$AC$6:$AE$17,3,0)=VLOOKUP(AG9,$AC$6:$AE$17,3,0),VLOOKUP(AG9,$AC$6:$AE$17,2,0),"")) | AG9: 7 | AH9: =_xlfn.RANK.EQ(E9,$E$6:$E$17,0)+COUNTIF($E$6:$E9,E9)-1 -> 4 | AI9: =IF(AJ9=0,"",B9&E9&"件") | AJ9: =E9 -> 0 | AK9: =IF(AK8="","",IF(VLOOKUP(AL8,$AH$6:$AJ$17,3,0)=VLOOKUP(AL9,$AH$6:$AJ$17,3,0),VLOOKUP(AL9,$AH$6:$AJ$17,2,0),"")) | AL9: 7
A10: 5 | B10: 寿光 | C10: =COUNTIFS(督办单!L:L,B:B,督办单!M:M,$M$6,督办单!P:P,"无",督办单!C:C,"*一级*") -> 0 | D10: =COUNTIFS(督办单!L:L,B:B,督办单!M:M,$M$6,督办单!P:P,"7天内",督办单!C:C,"*一级*") -> 0 | E10: =COUNTIFS(督办单!L:L,B:B,督办单!M:M,$M$6,督办单!P:P,"30天内",督办单!C:C,"*一级*") -> 0 | F10: =COUNTIFS(督办单!L:L,B:B,督办单!M:M,$M$6,督办单!P:P,"60天内",督办单!C:C,"*一级*") -> 0 | G10: =COUNTIFS(督办单!L:L,B:B,督办单!M:M,$M$6,督办单!P:P,"90天内",督办单!C:C,"*一级*") -> 0 | H10: =COUNTIFS(督办单!L:L,B:B,督办单!C:C,"*一级*",督办单!M:M,$M$6) -> 0 | I10: =COUNTIFS(督办单!L:L,B:B,督办单!C:C,"*一级*",督办单!M:M,$M$6)/(COUNTIFS(累计派单!R:R,B:B,累计派单!S:S,$M$6)-COUNTIFS(累计派单!R:R,B:B,累计派单!I:I,"*业务受理*",累计派单!S:S,$M$6)) -> #DIV/0! | J10: =COUNTIFS(督办单!L:L,B:B,督办单!C:C,"*一级*") -> 98 | K10: =J10/(COUNTIFS(累计派单!R:R,B:B)-COUNTIFS(累计派单!R:R,B:B,累计派单!I:I,"*业务受理*")-COUNTIFS(累计派单!I:I,"*客户咨询*")) -> 0.083050847 | L10: 寿光 | O10: =_xlfn.RANK.EQ(K10,$K$6:$K$17,0)+COUNTIF($K$6:$K10,K10)-1 -> 5 | P10: =B10&"("&ROUND(K10*100,2)&"%)" -> 寿光(8.31%) | Q10: =_xlfn.RANK.EQ(I10,$I$6:$I$17,0)+COUNTIF($I$6:$I10,I10)-1 -> #DIV/0! | R10: =B10&"("&ROUND(I10*100,2)&"%)" -> #DIV/0! | S10: =_xlfn.RANK.EQ(H10,$H$6:$H$17,0)+COUNTIF($H$6:$H10,H10)-1 -> 5 | T10: =IF(H10=0,"",B10&H10&"件") | U10: =H10 -> 0 | V10: =IF(V9="","",IF(VLOOKUP(W9,$S$6:$U$17,3,0)=VLOOKUP(W10,$S$6:$U$17,3,0),VLOOKUP(W10,$S$6:$U$17,2,0),"")) | W10: 8 | X10: =_xlfn.RANK.EQ(C10,$C$6:$C$17,0)+COUNTIF($C$6:$C10,C10)-1 -> 5 | Y10: =IF(Z10=0,"",B10&C10&"件") | Z10: =C10 -> 0 | AA10: =IF(AA9="","",IF(VLOOKUP(AB9,$AC$6:$AE$17,3,0)=VLOOKUP(AB10,$AC$6:$AE$17,3,0),VLOOKUP(AB10,$AC$6:$AE$17,2,0),"")) | AB10: 8 | AC10: =_xlfn.RANK.EQ(D10,$D$6:$D$17,0)+COUNTIF($D$6:$D10,D10)-1 -> 5 | AD10: =IF(AE10=0,"",B10&D10&"件") | AE10: =D10 -> 0 | AF10: =IF(AF9="","",IF(VLOOKUP(AG9,$AC$6:$AE$17,3,0)=VLOOKUP(AG10,$AC$6:$AE$17,3,0),VLOOKUP(AG10,$AC$6:$AE$17,2,0),"")) | AG10: 8 | AH10: =_xlfn.RANK.EQ(E10,$E$6:$E$17,0)+COUNTIF($E$6:$E10,E10)-1 -> 5 | AI10: =IF(AJ10=0,"",B10&E10&"件") | AJ10: =E10 -> 0 | AK10: =IF(AK9="","",IF(VLOOKUP(AL9,$AH$6:$AJ$17,3,0)=VLOOKUP(AL10,$AH$6:$AJ$17,3,0),VLOOKUP(AL10,$AH$6:$AJ$17,2,0),"")) | AL10: 8
A11: 6 | B11: 昌邑 | C11: =COUNTIFS(督办单!L:L,B:B,督办单!M:M,$M$6,督办单!P:P,"无",督办单!C:C,"*一级*") -> 0 | D11: =COUNTIFS(督办单!L:L,B:B,督办单!M:M,$M$6,督办单!P:P,"7天内",督办单!C:C,"*一级*") -> 0 | E11: =COUNTIFS(督办单!L:L,B:B,督办单!M:M,$M$6,督办单!P:P,"30天内",督办单!C:C,"*一级*") -> 0 | F11: =COUNTIFS(督办单!L:L,B:B,督办单!M:M,$M$6,督办单!P:P,"60天内",督办单!C:C,"*一级*") -> 0 | G11: =COUNTIFS(督办单!L:L,B:B,督办单!M:M,$M$6,督办单!P:P,"90天内",督办单!C:C,"*一级*") -> 0 | H11: =COUNTIFS(督办单!L:L,B:B,督办单!C:C,"*一级*",督办单!M:M,$M$6) -> 0 | I11: =COUNTIFS(督办单!L:L,B:B,督办单!C:C,"*一级*",督办单!M:M,$M$6)/(COUNTIFS(累计派单!R:R,B:B,累计派单!S:S,$M$6)-COUNTIFS(累计派单!R:R,B:B,累计派单!I:I,"*业务受理*",累计派单!S:S,$M$6)) -> #DIV/0! | J11: =COUNTIFS(督办单!L:L,B:B,督办单!C:C,"*一级*") -> 33 | K11: =J11/(COUNTIFS(累计派单!R:R,B:B)-COUNTIFS(累计派单!R:R,B:B,累计派单!I:I,"*业务受理*")-COUNTIFS(累计派单!I:I,"*客户咨询*")) -> 0.075514874 | L11: 昌邑 | O11: =_xlfn.RANK.EQ(K11,$K$6:$K$17,0)+COUNTIF($K$6:$K11,K11)-1 -> 7 | P11: =B11&"("&ROUND(K11*100,2)&"%)" -> 昌邑(7.55%) | Q11: =_xlfn.RANK.EQ(I11,$I$6:$I$17,0)+COUNTIF($I$6:$I11,I11)-1 -> #DIV/0! | R11: =B11&"("&ROUND(I11*100,2)&"%)" -> #DIV/0! | S11: =_xlfn.RANK.EQ(H11,$H$6:$H$17,0)+COUNTIF($H$6:$H11,H11)-1 -> 6 | T11: =IF(H11=0,"",B11&H11&"件") | U11: =H11 -> 0 | V11: =IF(V10="","",IF(VLOOKUP(W10,$S$6:$U$17,3,0)=VLOOKUP(W11,$S$6:$U$17,3,0),VLOOKUP(W11,$S$6:$U$17,2,0),"")) | W11: 9 | X11: =_xlfn.RANK.EQ(C11,$C$6:$C$17,0)+COUNTIF($C$6:$C11,C11)-1 -> 6 | Y11: =IF(Z11=0,"",B11&C11&"件") | Z11: =C11 -> 0 | AA11: =IF(AA10="","",IF(VLOOKUP(AB10,$AC$6:$AE$17,3,0)=VLOOKUP(AB11,$AC$6:$AE$17,3,0),VLOOKUP(AB11,$AC$6:$AE$17,2,0),"")) | AB11: 9 | AC11: =_xlfn.RANK.EQ(D11,$D$6:$D$17,0)+COUNTIF($D$6:$D11,D11)-1 -> 6 | AD11: =IF(AE11=0,"",B11&D11&"件") | AE11: =D11 -> 0 | AF11: =IF(AF10="","",IF(VLOOKUP(AG10,$AC$6:$AE$17,3,0)=VLOOKUP(AG11,$AC$6:$AE$17,3,0),VLOOKUP(AG11,$AC$6:$AE$17,2,0),"")) | AG11: 9 | AH11: =_xlfn.RANK.EQ(E11,$E$6:$E$17,0)+COUNTIF($E$6:$E11,E11)-1 -> 6 | AI11: =IF(AJ11=0,"",B11&E11&"件") | AJ11: =E11 -> 0 | AK11: =IF(AK10="","",IF(VLOOKUP(AL10,$AH$6:$AJ$17,3,0)=VLOOKUP(AL11,$AH$6:$AJ$17,3,0),VLOOKUP(AL11,$AH$6:$AJ$17,2,0),"")) | AL11: 9
A12: 7 | B12: 寒亭 | C12: =COUNTIFS(督办单!L:L,B:B,督办单!M:M,$M$6,督办单!P:P,"无",督办单!C:C,"*一级*") -> 0 | D12: =COUNTIFS(督办单!L:L,B:B,督办单!M:M,$M$6,督办单!P:P,"7天内",督办单!C:C,"*一级*") -> 0 | E12: =COUNTIFS(督办单!L:L,B:B,督办单!M:M,$M$6,督办单!P:P,"30天内",督办单!C:C,"*一级*") -> 0 | F12: =COUNTIFS(督办单!L:L,B:B,督办单!M:M,$M$6,督办单!P:P,"60天内",督办单!C:C,"*一级*") -> 0 | G12: =COUNTIFS(督办单!L:L,B:B,督办单!M:M,$M$6,督办单!P:P,"90天内",督办单!C:C,"*一级*") -> 0 | H12: =COUNTIFS(督办单!L:L,B:B,督办单!C:C,"*一级*",督办单!M:M,$M$6) -> 0 | I12: =COUNTIFS(督办单!L:L,B:B,督办单!C:C,"*一级*",督办单!M:M,$M$6)/(COUNTIFS(累计派单!R:R,B:B,累计派单!S:S,$M$6)-COUNTIFS(累计派单!R:R,B:B,累计派单!I:I,"*业务受理*",累计派单!S:S,$M$6)) -> #DIV/0! | J12: =COUNTIFS(督办单!L:L,B:B,督办单!C:C,"*一级*") -> 37 | K12: =J12/(COUNTIFS(累计派单!R:R,B:B)-COUNTIFS(累计派单!R:R,B:B,累计派单!I:I,"*业务受理*")-COUNTIFS(累计派单!I:I,"*客户咨询*")) -> 0.077568134 | L12: 寒亭 | O12: =_xlfn.RANK.EQ(K12,$K$6:$K$17,0)+COUNTIF($K$6:$K12,K12)-1 -> 6 | P12: =B12&"("&ROUND(K12*100,2)&"%)" -> 寒亭(7.76%) | Q12: =_xlfn.RANK.EQ(I12,$I$6:$I$17,0)+COUNTIF($I$6:$I12,I12)-1 -> #DIV/0! | R12: =B12&"("&ROUND(I12*100,2)&"%)" -> #DIV/0! | S12: =_xlfn.RANK.EQ(H12,$H$6:$H$17,0)+COUNTIF($H$6:$H12,H12)-1 -> 7 | T12: =IF(H12=0,"",B12&H12&"件") | U12: =H12 -> 0 | V12: =IF(V11="","",IF(VLOOKUP(W11,$S$6:$U$17,3,0)=VLOOKUP(W12,$S$6:$U$17,3,0),VLOOKUP(W12,$S$6:$U$17,2,0),"")) | W12: 10 | X12: =_xlfn.RANK.EQ(C12,$C$6:$C$17,0)+COUNTIF($C$6:$C12,C12)-1 -> 7 | Y12: =IF(Z12=0,"",B12&C12&"件") | Z12: =C12 -> 0 | AA12: =IF(AA11="","",IF(VLOOKUP(AB11,$AC$6:$AE$17,3,0)=VLOOKUP(AB12,$AC$6:$AE$17,3,0),VLOOKUP(AB12,$AC$6:$AE$17,2,0),"")) | AB12: 10 | AC12: =_xlfn.RANK.EQ(D12,$D$6:$D$17,0)+COUNTIF($D$6:$D12,D12)-1 -> 7 | AD12: =IF(AE12=0,"",B12&D12&"件") | AE12: =D12 -> 0 | AF12: =IF(AF11="","",IF(VLOOKUP(AG11,$AC$6:$AE$17,3,0)=VLOOKUP(AG12,$AC$6:$AE$17,3,0),VLOOKUP(AG12,$AC$6:$AE$17,2,0),"")) | AG12: 10 | AH12: =_xlfn.RANK.EQ(E12,$E$6:$E$17,0)+COUNTIF($E$6:$E12,E12)-1 -> 7 | AI12: =IF(AJ12=0,"",B12&E12&"件") | AJ12: =E12 -> 0 | AK12: =IF(AK11="","",IF(VLOOKUP(AL11,$AH$6:$AJ$17,3,0)=VLOOKUP(AL12,$AH$6:$AJ$17,3,0),VLOOKUP(AL12,$AH$6:$AJ$17,2,0),"")) | AL12: 10
A13: 8 | B13: 高密 | C13: =COUNTIFS(督办单!L:L,B:B,督办单!M:M,$M$6,督办单!P:P,"无",督办单!C:C,"*一级*") -> 0 | D13: =COUNTIFS(督办单!L:L,B:B,督办单!M:M,$M$6,督办单!P:P,"7天内",督办单!C:C,"*一级*") -> 0 | E13: =COUNTIFS(督办单!L:L,B:B,督办单!M:M,$M$6,督办单!P:P,"30天内",督办单!C:C,"*一级*") -> 0 | F13: =COUNTIFS(督办单!L:L,B:B,督办单!M:M,$M$6,督办单!P:P,"60天内",督办单!C:C,"*一级*") -> 0 | G13: =COUNTIFS(督办单!L:L,B:B,督办单!M:M,$M$6,督办单!P:P,"90天内",督办单!C:C,"*一级*") -> 0 | H13: =COUNTIFS(督办单!L:L,B:B,督办单!C:C,"*一级*",督办单!M:M,$M$6) -> 0 | I13: =COUNTIFS(督办单!L:L,B:B,督办单!C:C,"*一级*",督办单!M:M,$M$6)/(COUNTIFS(累计派单!R:R,B:B,累计派单!S:S,$M$6)-COUNTIFS(累计派单!R:R,B:B,累计派单!I:I,"*业务受理*",累计派单!S:S,$M$6)) -> #DIV/0! | J13: =COUNTIFS(督办单!L:L,B:B,督办单!C:C,"*一级*") -> 38 | K13: =J13/(COUNTIFS(累计派单!R:R,B:B)-COUNTIFS(累计派单!R:R,B:B,累计派单!I:I,"*业务受理*")-COUNTIFS(累计派单!I:I,"*客户咨询*")) -> 0.0642978 | L13: 高密 | O13: =_xlfn.RANK.EQ(K13,$K$6:$K$17,0)+COUNTIF($K$6:$K13,K13)-1 -> 8 | P13: =B13&"("&ROUND(K13*100,2)&"%)" -> 高密(6.43%) | Q13: =_xlfn.RANK.EQ(I13,$I$6:$I$17,0)+COUNTIF($I$6:$I13,I13)-1 -> #DIV/0! | R13: =B13&"("&ROUND(I13*100,2)&"%)" -> #DIV/0! | S13: =_xlfn.RANK.EQ(H13,$H$6:$H$17,0)+COUNTIF($H$6:$H13,H13)-1 -> 8 | T13: =IF(H13=0,"",B13&H13&"件") | U13: =H13 -> 0 | V13: =IF(V12="","",IF(VLOOKUP(W12,$S$6:$U$17,3,0)=VLOOKUP(W13,$S$6:$U$17,3,0),VLOOKUP(W13,$S$6:$U$17,2,0),"")) | W13: 11 | X13: =_xlfn.RANK.EQ(C13,$C$6:$C$17,0)+COUNTIF($C$6:$C13,C13)-1 -> 8 | Y13: =IF(Z13=0,"",B13&C13&"件") | Z13: =C13 -> 0 | AA13: =IF(AA12="","",IF(VLOOKUP(AB12,$AC$6:$AE$17,3,0)=VLOOKUP(AB13,$AC$6:$AE$17,3,0),VLOOKUP(AB13,$AC$6:$AE$17,2,0),"")) | AB13: 11 | AC13: =_xlfn.RANK.EQ(D13,$D$6:$D$17,0)+COUNTIF($D$6:$D13,D13)-1 -> 8 | AD13: =IF(AE13=0,"",B13&D13&"件") | AE13: =D13 -> 0 | AF13: =IF(AF12="","",IF(VLOOKUP(AG12,$AC$6:$AE$17,3,0)=VLOOKUP(AG13,$AC$6:$AE$17,3,0),VLOOKUP(AG13,$AC$6:$AE$17,2,0),"")) | AG13: 11 | AH13: =_xlfn.RANK.EQ(E13,$E$6:$E$17,0)+COUNTIF($E$6:$E13,E13)-1 -> 8 | AI13: =IF(AJ13=0,"",B13&E13&"件") | AJ13: =E13 -> 0 | AK13: =IF(AK12="","",IF(VLOOKUP(AL12,$AH$6:$AJ$17,3,0)=VLOOKUP(AL13,$AH$6:$AJ$17,3,0),VLOOKUP(AL13,$AH$6:$AJ$17,2,0),"")) | AL13: 11
A14: 9 | B14: 青州 | C14: =COUNTIFS(督办单!L:L,B:B,督办单!M:M,$M$6,督办单!P:P,"无",督办单!C:C,"*一级*") -> 0 | D14: =COUNTIFS(督办单!L:L,B:B,督办单!M:M,$M$6,督办单!P:P,"7天内",督办单!C:C,"*一级*") -> 0 | E14: =COUNTIFS(督办单!L:L,B:B,督办单!M:M,$M$6,督办单!P:P,"30天内",督办单!C:C,"*一级*") -> 0 | F14: =COUNTIFS(督办单!L:L,B:B,督办单!M:M,$M$6,督办单!P:P,"60天内",督办单!C:C,"*一级*") -> 0 | G14: =COUNTIFS(督办单!L:L,B:B,督办单!M:M,$M$6,督办单!P:P,"90天内",督办单!C:C,"*一级*") -> 0 | H14: =COUNTIFS(督办单!L:L,B:B,督办单!C:C,"*一级*",督办单!M:M,$M$6) -> 0 | I14: =COUNTIFS(督办单!L:L,B:B,督办单!C:C,"*一级*",督办单!M:M,$M$6)/(COUNTIFS(累计派单!R:R,B:B,累计派单!S:S,$M$6)-COUNTIFS(累计派单!R:R,B:B,累计派单!I:I,"*业务受理*",累计派单!S:S,$M$6)) -> #DIV/0! | J14: =COUNTIFS(督办单!L:L,B:B,督办单!C:C,"*一级*") -> 43 | K14: =J14/(COUNTIFS(累计派单!R:R,B:B)-COUNTIFS(累计派单!R:R,B:B,累计派单!I:I,"*业务受理*")-COUNTIFS(累计派单!I:I,"*客户咨询*")) -> 0.057486631 | L14: 青州 | O14: =_xlfn.RANK.EQ(K14,$K$6:$K$17,0)+COUNTIF($K$6:$K14,K14)-1 -> 9 | P14: =B14&"("&ROUND(K14*100,2)&"%)" -> 青州(5.75%) | Q14: =_xlfn.RANK.EQ(I14,$I$6:$I$17,0)+COUNTIF($I$6:$I14,I14)-1 -> #DIV/0! | R14: =B14&"("&ROUND(I14*100,2)&"%)" -> #DIV/0! | S14: =_xlfn.RANK.EQ(H14,$H$6:$H$17,0)+COUNTIF($H$6:$H14,H14)-1 -> 9 | T14: =IF(H14=0,"",B14&H14&"件") | U14: =H14 -> 0 | V14: =IF(V13="","",IF(VLOOKUP(W13,$S$6:$U$17,3,0)=VLOOKUP(W14,$S$6:$U$17,3,0),VLOOKUP(W14,$S$6:$U$17,2,0),"")) | W14: 12 | X14: =_xlfn.RANK.EQ(C14,$C$6:$C$17,0)+COUNTIF($C$6:$C14,C14)-1 -> 9 | Y14: =IF(Z14=0,"",B14&C14&"件") | Z14: =C14 -> 0 | AA14: =IF(AA13="","",IF(VLOOKUP(AB13,$AC$6:$AE$17,3,0)=VLOOKUP(AB14,$AC$6:$AE$17,3,0),VLOOKUP(AB14,$AC$6:$AE$17,2,0),"")) | AB14: 12 | AC14: =_xlfn.RANK.EQ(D14,$D$6:$D$17,0)+COUNTIF($D$6:$D14,D14)-1 -> 9 | AD14: =IF(AE14=0,"",B14&D14&"件") | AE14: =D14 -> 0 | AF14: =IF(AF13="","",IF(VLOOKUP(AG13,$AC$6:$AE$17,3,0)=VLOOKUP(AG14,$AC$6:$AE$17,3,0),VLOOKUP(AG14,$AC$6:$AE$17,2,0),"")) | AG14: 12 | AH14: =_xlfn.RANK.EQ(E14,$E$6:$E$17,0)+COUNTIF($E$6:$E14,E14)-1 -> 9 | AI14: =IF(AJ14=0,"",B14&E14&"件") | AJ14: =E14 -> 0 | AK14: =IF(AK13="","",IF(VLOOKUP(AL13,$AH$6:$AJ$17,3,0)=VLOOKUP(AL14,$AH$6:$AJ$17,3,0),VLOOKUP(AL14,$AH$6:$AJ$17,2,0),"")) | AL14: 12
A15: 10 | B15: 诸城 | C15: =COUNTIFS(督办单!L:L,B:B,督办单!M:M,$M$6,督办单!P:P,"无",督办单!C:C,"*一级*") -> 0 | D15: =COUNTIFS(督办单!L:L,B:B,督办单!M:M,$M$6,督办单!P:P,"7天内",督办单!C:C,"*一级*") -> 0 | E15: =COUNTIFS(督办单!L:L,B:B,督办单!M:M,$M$6,督办单!P:P,"30天内",督办单!C:C,"*一级*") -> 0 | F15: =COUNTIFS(督办单!L:L,B:B,督办单!M:M,$M$6,督办单!P:P,"60天内",督办单!C:C,"*一级*") -> 0 | G15: =COUNTIFS(督办单!L:L,B:B,督办单!M:M,$M$6,督办单!P:P,"90天内",督办单!C:C,"*一级*") -> 0 | H15: =COUNTIFS(督办单!L:L,B:B,督办单!C:C,"*一级*",督办单!M:M,$M$6) -> 0 | I15: =COUNTIFS(督办单!L:L,B:B,督办单!C:C,"*一级*",督办单!M:M,$M$6)/(COUNTIFS(累计派单!R:R,B:B,累计派单!S:S,$M$6)-COUNTIFS(累计派单!R:R,B:B,累计派单!I:I,"*业务受理*",累计派单!S:S,$M$6)) -> #DIV/0! | J15: =COUNTIFS(督办单!L:L,B:B,督办单!C:C,"*一级*") -> 38 | K15: =J15/(COUNTIFS(累计派单!R:R,B:B)-COUNTIFS(累计派单!R:R,B:B,累计派单!I:I,"*业务受理*")-COUNTIFS(累计派单!I:I,"*客户咨询*")) -> 0.048780488 | L15: 诸城 | O15: =_xlfn.RANK.EQ(K15,$K$6:$K$17,0)+COUNTIF($K$6:$K15,K15)-1 -> 10 | P15: =B15&"("&ROUND(K15*100,2)&"%)" -> 诸城(4.88%) | Q15: =_xlfn.RANK.EQ(I15,$I$6:$I$17,0)+COUNTIF($I$6:$I15,I15)-1 -> #DIV/0! | R15: =B15&"("&ROUND(I15*100,2)&"%)" -> #DIV/0! | S15: =_xlfn.RANK.EQ(H15,$H$6:$H$17,0)+COUNTIF($H$6:$H15,H15)-1 -> 10 | T15: =IF(H15=0,"",B15&H15&"件") | U15: =H15 -> 0 | X15: =_xlfn.RANK.EQ(C15,$C$6:$C$17,0)+COUNTIF($C$6:$C15,C15)-1 -> 10 | Y15: =IF(Z15=0,"",B15&C15&"件") | Z15: =C15 -> 0 | AC15: =_xlfn.RANK.EQ(D15,$D$6:$D$17,0)+COUNTIF($D$6:$D15,D15)-1 -> 10 | AD15: =IF(AE15=0,"",B15&D15&"件") | AE15: =D15 -> 0 | AH15: =_xlfn.RANK.EQ(E15,$E$6:$E$17,0)+COUNTIF($E$6:$E15,E15)-1 -> 10 | AI15: =IF(AJ15=0,"",B15&E15&"件") | AJ15: =E15 -> 0
A16: 11 | B16: 临朐 | C16: =COUNTIFS(督办单!L:L,B:B,督办单!M:M,$M$6,督办单!P:P,"无",督办单!C:C,"*一级*") -> 0 | D16: =COUNTIFS(督办单!L:L,B:B,督办单!M:M,$M$6,督办单!P:P,"7天内",督办单!C:C,"*一级*") -> 0 | E16: =COUNTIFS(督办单!L:L,B:B,督办单!M:M,$M$6,督办单!P:P,"30天内",督办单!C:C,"*一级*") -> 0 | F16: =COUNTIFS(督办单!L:L,B:B,督办单!M:M,$M$6,督办单!P:P,"60天内",督办单!C:C,"*一级*") -> 0 | G16: =COUNTIFS(督办单!L:L,B:B,督办单!M:M,$M$6,督办单!P:P,"90天内",督办单!C:C,"*一级*") -> 0 | H16: =COUNTIFS(督办单!L:L,B:B,督办单!C:C,"*一级*",督办单!M:M,$M$6) -> 0 | I16: =COUNTIFS(督办单!L:L,B:B,督办单!C:C,"*一级*",督办单!M:M,$M$6)/(COUNTIFS(累计派单!R:R,B:B,累计派单!S:S,$M$6)-COUNTIFS(累计派单!R:R,B:B,累计派单!I:I,"*业务受理*",累计派单!S:S,$M$6)) -> #DIV/0! | J16: =COUNTIFS(督办单!L:L,B:B,督办单!C:C,"*一级*") -> 19 | K16: =J16/(COUNTIFS(累计派单!R:R,B:B)-COUNTIFS(累计派单!R:R,B:B,累计派单!I:I,"*业务受理*")-COUNTIFS(累计派单!I:I,"*客户咨询*")) -> 0.03909465 | L16: 临朐 | O16: =_xlfn.RANK.EQ(K16,$K$6:$K$17,0)+COUNTIF($K$6:$K16,K16)-1 -> 12 | P16: =B16&"("&ROUND(K16*100,2)&"%)" -> 临朐(3.91%) | Q16: =_xlfn.RANK.EQ(I16,$I$6:$I$17,0)+COUNTIF($I$6:$I16,I16)-1 -> #DIV/0! | R16: =B16&"("&ROUND(I16*100,2)&"%)" -> #DIV/0! | S16: =_xlfn.RANK.EQ(H16,$H$6:$H$17,0)+COUNTIF($H$6:$H16,H16)-1 -> 11 | T16: =IF(H16=0,"",B16&H16&"件") | U16: =H16 -> 0 | X16: =_xlfn.RANK.EQ(C16,$C$6:$C$17,0)+COUNTIF($C$6:$C16,C16)-1 -> 11 | Y16: =IF(Z16=0,"",B16&C16&"件") | Z16: =C16 -> 0 | AC16: =_xlfn.RANK.EQ(D16,$D$6:$D$17,0)+COUNTIF($D$6:$D16,D16)-1 -> 11 | AD16: =IF(AE16=0,"",B16&D16&"件") | AE16: =D16 -> 0 | AH16: =_xlfn.RANK.EQ(E16,$E$6:$E$17,0)+COUNTIF($E$6:$E16,E16)-1 -> 11 | AI16: =IF(AJ16=0,"",B16&E16&"件") | AJ16: =E16 -> 0
A17: 12 | B17: 昌乐 | C17: =COUNTIFS(督办单!L:L,B:B,督办单!M:M,$M$6,督办单!P:P,"无",督办单!C:C,"*一级*") -> 0 | D17: =COUNTIFS(督办单!L:L,B:B,督办单!M:M,$M$6,督办单!P:P,"7天内",督办单!C:C,"*一级*") -> 0 | E17: =COUNTIFS(督办单!L:L,B:B,督办单!M:M,$M$6,督办单!P:P,"30天内",督办单!C:C,"*一级*") -> 0 | F17: =COUNTIFS(督办单!L:L,B:B,督办单!M:M,$M$6,督办单!P:P,"60天内",督办单!C:C,"*一级*") -> 0 | G17: =COUNTIFS(督办单!L:L,B:B,督办单!M:M,$M$6,督办单!P:P,"90天内",督办单!C:C,"*一级*") -> 0 | H17: =COUNTIFS(督办单!L:L,B:B,督办单!C:C,"*一级*",督办单!M:M,$M$6) -> 0 | I17: =COUNTIFS(督办单!L:L,B:B,督办单!C:C,"*一级*",督办单!M:M,$M$6)/(COUNTIFS(累计派单!R:R,B:B,累计派单!S:S,$M$6)-COUNTIFS(累计派单!R:R,B:B,累计派单!I:I,"*业务受理*",累计派单!S:S,$M$6)) -> #DIV/0! | J17: =COUNTIFS(督办单!L:L,B:B,督办单!C:C,"*一级*") -> 13 | K17: =J17/(COUNTIFS(累计派单!R:R,B:B)-COUNTIFS(累计派单!R:R,B:B,累计派单!I:I,"*业务受理*")-COUNTIFS(累计派单!I:I,"*客户咨询*")) -> 0.04 | L17: 昌乐 | O17: =_xlfn.RANK.EQ(K17,$K$6:$K$17,0)+COUNTIF($K$6:$K17,K17)-1 -> 11 | P17: =B17&"("&ROUND(K17*100,2)&"%)" -> 昌乐(4%) | Q17: =_xlfn.RANK.EQ(I17,$I$6:$I$17,0)+COUNTIF($I$6:$I17,I17)-1 -> #DIV/0! | R17: =B17&"("&ROUND(I17*100,2)&"%)" -> #DIV/0! | S17: =_xlfn.RANK.EQ(H17,$H$6:$H$17,0)+COUNTIF($H$6:$H17,H17)-1 -> 12 | T17: =IF(H17=0,"",B17&H17&"件") | U17: =H17 -> 0 | X17: =_xlfn.RANK.EQ(C17,$C$6:$C$17,0)+COUNTIF($C$6:$C17,C17)-1 -> 12 | Y17: =IF(Z17=0,"",B17&C17&"件") | Z17: =C17 -> 0 | AC17: =_xlfn.RANK.EQ(D17,$D$6:$D$17,0)+COUNTIF($D$6:$D17,D17)-1 -> 12 | AD17: =IF(AE17=0,"",B17&D17&"件") | AE17: =D17 -> 0 | AH17: =_xlfn.RANK.EQ(E17,$E$6:$E$17,0)+COUNTIF($E$6:$E17,E17)-1 -> 12 | AI17: =IF(AJ17=0,"",B17&E17&"件") | AJ17: =E17 -> 0
A18: 合计 | C18: =SUM(C6:C17) -> 0 | D18: =SUM(D6:D17) -> 0 | E18: =SUM(E6:E17) -> 0 | F18: =SUM(F6:F17) -> 0 | G18: =SUM(G6:G17) -> 0 | H18: =SUM(H6:H17) -> 0 | I18: =H18/(COUNTIFS(累计派单!S:S,$M$6)-COUNTIFS(累计派单!I:I,"*业务受理*",累计派单!S:S,$M$6)-COUNTIFS(累计派单!I:I,"*修复*",累计派单!S:S,$M$6)-COUNTIFS(累计派单!I:I,"*客户咨询*",累计派单!S:S,$M$6)) -> #DIV/0! | J18: =SUM(J6:J17) -> 581 | K18: =J18/(COUNTIFS(累计派单!C:C,"潍坊")-COUNTIFS(累计派单!I:I,"*业务受理*")-COUNTIFS(累计派单!I:I,"*客户咨询*")) -> 0.071737252 | L18: 合计
C20: ="关于10086投诉一级督办占比的通报-截止"&N6&"日 一、整体情况： 1、截止"&N6&"日，累计产生一级督办单"&J18&"件，一级督办单占比"&ROUND(K18*100,2)&"%。 2、一级督办单累计增长："&P5&"较高。 二、单日情况： 1、"&R5&"较多。 2、"&N6&"日新增"&H18&"件："&S2&"较多。 三、分析情况： 1、无重复投诉（重点客户、网课）："&C18&"件"&IF(X2="","。",":"&X2&"。")&" 2、7天内重复投诉"&D18&"件："&AC2&"。 3、大于7天小于30天"&E18&"件："&AH2&"。" -> #N/A

Sheet 督办单
A1: 督办工单号 | B1: 督办工单发起时间 | C1: 督办单主题 | D1: 投诉主题 | E1: 投诉内容 | F1: 投诉地市 | G1: 投诉区县 | H1: 投诉电话 | I1: 投诉工单号 | J1: 重复投诉工单号 | K1: 是否处理 | L1: =IF(OR(LEFT(G1,2)="高新"),"奎文",IF(LEFT(G1,2)="峡山","坊子",IF(LEFT(G1,2)="滨海","寒亭",LEFT(G1,2)))) -> 投诉 | M1: =TEXT(B1,"yyyymmdd") -> 督办工单发起时间 | N1: 工号 | O1: 时间段 | P1: 时间段 | Q1: 网格
A2: SD-db051-250101-931207-37 | B2: 2025-01-01 09:03:51 | C2: (家客)潍坊-青州市-重复投诉投诉督办通知-一级督办13668669581-202501010000116152 | D2: 【调研】-普通区域-青州市-东坝新村-13668669581-200M-宽带上网投诉-次数0-202501010000116152 | E2: 202501010000116152#13668669581客户来电反映宽带无法使用/客户不配合操作/，要求维修人员上门维修，请尽快协助处理，谢谢 联系人：女士 联系电话：13668669581本机 流水：2025010109001361920892105 | F2: 潍坊 | G2: 青州市 | H2: 13668669581 | I2: SD-057-250101-072469-452 | J2: 'SD-057-241009-042561-2426' | K2: 是 | L2: =IF(OR(LEFT(G2,2)="高新"),"奎文",IF(LEFT(G2,2)="峡山","坊子",IF(LEFT(G2,2)="滨海","寒亭",LEFT(G2,2)))) -> 青州 | M2: =TEXT(B2,"mmdd") -> 0101 | N2: =VLOOKUP(I2,累计派单!A:O,15,0) -> dw3_jk_wangzhenhai | O2: =IF(LEN(J2)<2,0,DATEDIF(DATE(IF(MID(J2,9,2)="23",2023,2024),MID(J2,11,2),MID(J2,13,2)),B2,"d")) -> 84 | P2: =IF(O2=0,"无",IF(O2<8,"7天内",IF(O2<31,"30天内",IF(O2<61,"60天内",IF(O2<91,"90天内"))))) -> 90天内 | Q2: =VLOOKUP(I2,累计派单!A:O,13,0) -> 家客铁通潍坊青州-黄楼乡镇装维组
A3: SD-db051-250101-751364-63 | B3: 2025-01-01 09:35:58 | C3: (家客)潍坊-奎文区-重复投诉投诉督办通知-一级督办15963669532-202501010000145903 | D3: 普通区域-奎文区-北王茶城J-15963669532-200M-宽带上网投诉-次数0-202501010000145903 | E3: 202501010000145903#宽带账号：15963669532；联系电话：18463055553宽带地址：潍坊奎文区潍州路街道潍州路北王茶城J3号商品房；客户来电反映宽带无法使用，客户异机来电报修，线上指导无法配合操作，要求上门处理，来电流水：2025010109341165020889173 | F3: 潍坊 | G3: 奎文区 | H3: 15963669532 | I3: SD-057-250101-521943-751 | J3: 'SD-057-241230-495167-1456' | K3: 是 | L3: =IF(OR(LEFT(G3,2)="高新"),"奎文",IF(LEFT(G3,2)="峡山","坊子",IF(LEFT(G3,2)="滨海","寒亭",LEFT(G3,2)))) -> 奎文 | M3: =TEXT(B3,"mmdd") -> 0101 | N3: =VLOOKUP(I3,累计派单!A:O,15,0) -> dw3_jk_zhuwenjie | O3: =IF(LEN(J3)<2,0,DATEDIF(DATE(IF(MID(J3,9,2)="23",2023,2024),MID(J3,11,2),MID(J3,13,2)),B3,"d")) -> 2 | P3: =IF(O3=0,"无",IF(O3<8,"7天内",IF(O3<31,"30天内",IF(O3<61,"60天内",IF(O3<91,"90天内"))))) -> 7天内 | Q3: =VLOOKUP(I3,累计派单!A:O,13,0) -> 家客铁通潍坊奎文-潍州路城区装维组
A4: SD-db051-250101-895720-70 | B4: 2025-01-01 09:45:05 | C4: (家客)潍坊-奎文区-重复投诉投诉督办通知-一级督办15910111711-202501010000151577 | D4: 【调研】-80+白金-普通区域-奎文区-赋海仁居-15910111711-1000M-宽带上网投诉-次数0-202501010000151577 | E4: 202501010000151577#宽带账号：15910111711；宽带地址：潍坊高新高新城区福寿街赋海仁居7号楼*；客户来电反映移动高清无法上网*，经查询客户侧为质差机顶盒，请协助上门更换设备并一并处理故障问题，谢谢！联系电话本机；联系人先生来电流 | F4: 潍坊 | G4: 奎文区 | H4: 15910111711 | I4: SD-057-250101-586490-818 | J4: 'SD-057-241230-152379-8347' | K4: 是 | L4: =IF(OR(LEFT(G4,2)="高新"),"奎文",IF(LEFT(G4,2)="峡山","坊子",IF(LEFT(G4,2)="滨海","寒亭",LEFT(G4,2)))) -> 奎文 | M4: =TEXT(B4,"mmdd") -> 0101 | N4: =VLOOKUP(I4,累计派单!A:O,15,0) -> dw3_jk_wangxingang | O4: =IF(LEN(J4)<2,0,DATEDIF(DATE(IF(MID(J4,9,2)="23",2023,2024),MID(J4,11,2),MID(J4,13,2)),B4,"d")) -> 2 | P4: =IF(O4=0,"无",IF(O4<8,"7天内",IF(O4<31,"30天内",IF(O4<61,"60天内",IF(O4<91,"90天内"))))) -> 7天内 | Q4: =VLOOKUP(I4,累计派单!A:O,13,0) -> 家客铁通潍坊奎文-北宫街城区装维组
A5: SD-db051-250101-172648-114 | B5: 2025-01-01 10:37:00 | C5: (家客)潍坊-临朐县-重复投诉投诉督办通知-一级督办18660665489-202501010000200739 | D5: 【调研】-普通区域-临朐县-城关王家楼小区-18660665489-200M-业务受理宽带-次数0-202501010000200739 | E5: 202501010000200739# 宽带账号:18660665489; 联系电话：18660665489，问题类型：此工单为群障修复工单，根据群障全量闭环修复管理要求，为确保客户网络通畅，请装维人员跟进修复网络问题，谢谢！ 群障标题：公告。故障描述：潍坊临朐县城关王家楼小区光缆故障，预估24小时恢复，请帮忙拦截,如有需要请联系片区装维师傅王兆兵15706307568主叫号码：18660665489.0;该号码仅供参考，请优先联系宽带账号。 | F5: 潍坊 | G5: 临朐县 | H5: 18660665489 | I5: SD-057-250101-847932-1270 | J5: 'SD-057-241219-791403-934' | K5: 是 | L5: =IF(OR(LEFT(G5,2)="高新"),"奎文",IF(LEFT(G5,2)="峡山","坊子",IF(LEFT(G5,2)="滨海","寒亭",LEFT(G5,2)))) -> 临朐 | M5: =TEXT(B5,"mmdd") -> 0101 | N5: =VLOOKUP(I5,累计派单!A:O,15,0) -> #N/A | O5: =IF(LEN(J5)<2,0,DATEDIF(DATE(IF(MID(J5,9,2)="23",2023,2024),MID(J5,11,2),MID(J5,13,2)),B5,"d")) -> 13 | P5: =IF(O5=0,"无",IF(O5<8,"7天内",IF(O5<31,"30天内",IF(O5<61,"60天内",IF(O5<91,"90天内"))))) -> 30天内 | Q5: =VLOOKUP(I5,累计派单!A:O,13,0) -> #N/A
A6: SD-db051-250101-683490-133 | B6: 2025-01-01 10:50:29 | C6: (家客)潍坊-坊子区-重复投诉投诉督办通知-一级督办18764639188-20250101104807X687351747 | D6: 80+银卡-普通区域-坊子区-营子花园-18764639188-1000M-魔百和投诉 | E6: 【农村网络投诉】【预处理派单】宽带账号：18764639188，宽带地址： 潍坊坊子区坊子新区辛李家村营子花园坊子营子花园3号楼*********，故障现象：，故障现象类型：，客户诉求：客户来点反应有部分频道缺失，操作了恢复出厂设置，没有恢复，请协助处理，谢谢，联系电话：18764639188，通话流水：2025010110395658720845521。接入方式：，当前是否在线：，端到端诊断结果：，是否智能网关：，光功率。,单组播状态:组播 | F6: 潍坊 | G6: 坊子区 | H6: 18764639188 | I6: SD-057-250101-503642-1409 | J6: 'SD-057-241230-724903-7676' | K6: 是 | L6: =IF(OR(LEFT(G6,2)="高新"),"奎文",IF(LEFT(G6,2)="峡山","坊子",IF(LEFT(G6,2)="滨海","寒亭",LEFT(G6,2)))) -> 坊子 | M6: =TEXT(B6,"mmdd") -> 0101 | N6: =VLOOKUP(I6,累计派单!A:O,15,0) -> dw3_jk_wangfufeng | O6: =IF(LEN(J6)<2,0,DATEDIF(DATE(IF(MID(J6,9,2)="23",2023,2024),MID(J6,11,2),MID(J6,13,2)),B6,"d")) -> 2 | P6: =IF(O6=0,"无",IF(O6<8,"7天内",IF(O6<31,"30天内",IF(O6<61,"60天内",IF(O6<91,"90天内"))))) -> 7天内 | Q6: =VLOOKUP(I6,累计派单!A:O,13,0) -> 家客铁通潍坊坊子-凤凰城区装维组
A7: SD-db051-250101-795423-183 | B7: 2025-01-01 12:24:27 | C7: (家客)潍坊-安丘市-重复投诉投诉督办通知-一级督办15169416903-202501010000293890 | D7: 普通区域-安丘市-于家河村自然村-15169416903-100M-宽带上网投诉-次数0-202501010000293890 | E7: 202501010000293890#宽带账号：15169416903；宽带地址：潍坊安丘市石埠子镇于家河村于家河村自然村于家河二次追加4号箱*****；客户来电反映宽带上网慢卡顿，测速1-2M，lan1端口1000M，经查询客户侧为质差路由器，请协助上门更换终端并一并处理故障问题，谢谢！ 联系电话：15169416903；联系人：先生；来电流水：2025010112221543720809124 | F7: 潍坊 | G7: 安丘市 | H7: 15169416903 | I7: SD-057-250101-927548-2247 | J7: 'SD-057-241004-169572-211' | K7: 否 | L7: =IF(OR(LEFT(G7,2)="高新"),"奎文",IF(LEFT(G7,2)="峡山","坊子",IF(LEFT(G7,2)="滨海","寒亭",LEFT(G7,2)))) -> 安丘 | M7: =TEXT(B7,"mmdd") -> 0101 | N7: =VLOOKUP(I7,累计派单!A:O,15,0) -> dw3_jk_juzhibin | O7: =IF(LEN(J7)<2,0,DATEDIF(DATE(IF(MID(J7,9,2)="23",2023,2024),MID(J7,11,2),MID(J7,13,2)),B7,"d")) -> 89 | P7: =IF(O7=0,"无",IF(O7<8,"7天内",IF(O7<31,"30天内",IF(O7<61,"60天内",IF(O7<91,"90天内"))))) -> 90天内 | Q7: =VLOOKUP(I7,累计派单!A:O,13,0) -> 家客铁通潍坊安丘-石埠子乡镇装维组
A8: SD-db051-250101-362178-214 | B8: 2025-01-01 13:03:55 | C8: (家客)潍坊-寿光市-重复投诉投诉督办通知-一级督办15753605816-202501010000321429 | D8: 【重投】-【调研】-80+普通-普通区域-寿光市-西稻田村自然村-15753605816-500M-宽带上网投诉-次数0-202501010000321429 | E8: 202501010000321429#流程受理流水号：20250101130138157536058161082732 客户号码:15753605816 客户姓名:宋** 投诉地市:潍坊 来话流水:2025010112580794320837705 宽带账号:15753605816 宽带账号归属地市:潍坊 宽带账号归属区县:寿光市 故障地址:潍坊寿光市稻田镇西稻田村西稻田村自然村扩容131号箱********* 联系电话:15753605816 联系人:先生/女士 工单紧急程度:一般 是否有升级投诉倾向:否 是否重复投诉:否 是否携转意向:否 是否投诉倾向:否 是否智能网关:智能网关 当前是否在线:否 接入方式:FTTH 端到端诊断结果:状态正常 是否质差终端:无质差信息 光功率:无 故障大类:宽带/电视 故障细类:宽带无法上网 携转原因: 故障时间:2025-01-01 13:01:53 具体故障现象:客户的宽带两天了完全没有网，要求维修人员处理。请协助谢谢提示网络无法连接， 客户其他诉求: ;宽带小区$[西稻田村自然村]$ | F8: 潍坊 | G8: 寿光市 | H8: 15753605816 | I8: SD-057-250101-019825-2563 | J8: 'SD-057-241105-729180-1524' | K8: 否 | L8: =IF(OR(LEFT(G8,2)="高新"),"奎文",IF(LEFT(G8,2)="峡山","坊子",IF(LEFT(G8,2)="滨海","寒亭",LEFT(G8,2)))) -> 寿光 | M8: =TEXT(B8,"mmdd") -> 0101 | N8: =VLOOKUP(I8,累计派单!A:O,15,0) -> dw3_jk_songyujie | O8: =IF(LEN(J8)<2,0,DATEDIF(DATE(IF(MID(J8,9,2)="23",2023,2024),MID(J8,11,2),MID(J8,13,2)),B8,"d")) -> 57 | P8: =IF(O8=0,"无",IF(O8<8,"7天内",IF(O8<31,"30天内",IF(O8<61,"60天内",IF(O8<91,"90天内"))))) -> 60天内 | Q8: =VLOOKUP(I8,累计派单!A:O,13,0) -> 家客铁通潍坊寿光-稻田乡镇装维组
A9: SD-db051-250101-958124-218 | B9: 2025-01-01 13:07:33 | C9: (家客)潍坊-高密市-重复投诉投诉督办通知-一级督办19558518557-202501010000325332 | D9: 普通区域-高密市-王家官庄自然村（夏庄恒馨家园）-19558518557-100M-业务受理宽带-次数0-202501010000325332 | E9: 202501010000325332# 宽带账号:19558518557; 联系电话：19558518557，问题类型：此工单为群障修复工单，根据群障全量闭环修复管理要求，为确保客户网络通畅，请装维人员跟进修复网络问题，谢谢！ 群障标题：公告。故障描述：潍坊高密市王家官庄自然村（夏庄恒馨家园）光缆故障，预估24小时恢复，请帮忙拦截,如有需要请联系片区装维师傅高强15706307285主叫号码：19558518557.0;该号码仅供参考，请优先联系宽带账号。 | F9: 潍坊 | G9: 高密市 | H9: 19558518557 | I9: SD-057-250101-043572-2594 | J9: 'SD-057-241024-908576-4509' | K9: 否 | L9: =IF(OR(LEFT(G9,2)="高新"),"奎文",IF(LEFT(G9,2)="峡山","坊子",IF(LEFT(G9,2)="滨海","寒亭",LEFT(G9,2)))) -> 高密 | M9: =TEXT(B9,"mmdd") -> 0101 | N9: =VLOOKUP(I9,累计派单!A:O,15,0) -> #N/A | O9: =IF(LEN(J9)<2,0,DATEDIF(DATE(IF(MID(J9,9,2)="23",2023,2024),MID(J9,11,2),MID(J9,13,2)),B9,"d")) -> 69 | P9: =IF(O9=0,"无",IF(O9<8,"7天内",IF(O9<31,"30天内",IF(O9<61,"60天内",IF(O9<91,"90天内"))))) -> 90天内 | Q9: =VLOOKUP(I9,累计派单!A:O,13,0) -> #N/A
A10: SD-db051-250101-657180-224 | B10: 2025-01-01 13:14:14 | C10: (家客)潍坊-诸城市-重复投诉投诉督办通知-一级督办18106368046-20250101131139X299254251 | D10: 【调研】-普通区域-诸城市-新郎公寓-18106368046-1000M-宽带上网投诉-次数0-20250101131139X299254251 | E10: 流程受理流水号：20250101131101181063680461085049 客户号码:18106368046 客户姓名:葛** 投诉地市:潍坊 来话流水:2025010113094220220839271 宽带账号:18106368046 宽带账号归属地市:潍坊 宽带账号归属区县:诸城市 故障地址:潍坊诸城市密州街道东外环新郎公寓L楼********* 联系电话:13356763517 联系人:先生 工单紧急程度:非常紧急 是否有升级投诉倾向:否 是否重复投诉:否 是否携转意向:否 是否投诉倾向:否 是否智能网关:智能网关 当前是否在线:是 接入方式:FTTH 端到端诊断结果:客户侧设备问题（新增） 是否质差终端:无质差信息 光功率:-18.38 故障大类:宽带/电视 故障细类:宽带无法上网(专席) 携转原因: 故障时间:2025-01-01 13:12:26 具体故障现象:光猫灯正常但电脑手机无法上网， 客户其他诉求: | F10: 潍坊 | G10: 诸城市 | H10: 18106368046 | I10: SD-057-250101-196537-2653 | J10: 'SD-057-241026-924351-6212' | K10: 否 | L10: =IF(OR(LEFT(G10,2)="高新"),"奎文",IF(LEFT(G10,2)="峡山","坊子",IF(LEFT(G10,2)="滨海","寒亭",LEFT(G10,2)))) -> 诸城 | M10: =TEXT(B10,"mmdd") -> 0101 | N10: =VLOOKUP(I10,累计派单!A:O,15,0) -> dw3_jk_shizhen | O10: =IF(LEN(J10)<2,0,DATEDIF(DATE(IF(MID(J10,9,2)="23",2023,2024),MID(J10,11,2),MID(J10,13,2)),B10,"d")) -> 67 | P10: =IF(O10=0,"无",IF(O10<8,"7天内",IF(O10<31,"30天内",IF(O10<61,"60天内",IF(O10<91,"90天内"))))) -> 90天内 | Q10: =VLOOKUP(I10,累计派单!A:O,13,0) -> 家客铁通潍坊诸城-兴华东路城区装维组
A11: SD-db051-250101-528340-230 | B11: 2025-01-01 13:25:50 | C11: (家客)潍坊-诸城市-重复投诉投诉督办通知-一级督办13953667855-202501010000333472 | D11: 【调研】-普通区域-诸城市-金屋小区北区-13953667855-300M-宽带上网投诉-次数0-202501010000333472 | E11: 202501010000333472#客户反映电视无法观看，提示蓝屏，不配合，线上排障未恢复，请协助处理。谢谢 联系人：女士 联系电话：13953667855 流水：2025010113223263220850457 | F11: 潍坊 | G11: 诸城市 | H11: 13953667855 | I11: SD-057-250101-681795-2746 | J11: 'SD-057-241031-481269-2245' | K11: 否 | L11: =IF(OR(LEFT(G11,2)="高新"),"奎文",IF(LEFT(G11,2)="峡山","坊子",IF(LEFT(G11,2)="滨海","寒亭",LEFT(G11,2)))) -> 诸城 | M11: =TEXT(B11,"mmdd") -> 0101 | N11: =VLOOKUP(I11,累计派单!A:O,15,0) -> dw3_jk_xuguodong | O11: =IF(LEN(J11)<2,0,DATEDIF(DATE(IF(MID(J11,9,2)="23",2023,2024),MID(J11,11,2),MID(J11,13,2)),B11,"d")) -> 62 | P11: =IF(O11=0,"无",IF(O11<8,"7天内",IF(O11<31,"30天内",IF(O11<61,"60天内",IF(O11<91,"90天内"))))) -> 90天内 | Q11: =VLOOKUP(I11,累计派单!A:O,13,0) -> 家客铁通潍坊诸城-兴华东路城区装维组
A12: SD-db051-250101-751439-247 | B12: 2025-01-01 14:03:30 | C12: (家客)潍坊-诸城市-重复投诉投诉督办通知-一级督办15006635638-202501010000359256 | D12: 【调研】-80+银卡-普通区域-诸城市-御台苑-15006635638-500M-宽带上网投诉-次数0-202501010000359256 | E12: 202501010000359256#宽带账号：15006635638；宽带地址：潍坊诸城舜王街道御台苑18号楼18号楼 3单元201；客户来电反映电视无法观看，要求师傅上门，请协助处理，谢谢！联系电话：15006635638；联系人：先生；来电流水：2025010113515884320818930。 | F12: 潍坊 | G12: 诸城市 | H12: 15006635638 | I12: SD-057-250101-283641-3107 | J12: 'SD-057-241018-538602-4457' | K12: 否 | L12: =IF(OR(LEFT(G12,2)="高新"),"奎文",IF(LEFT(G12,2)="峡山","坊子",IF(LEFT(G12,2)="滨海","寒亭",LEFT(G12,2)))) -> 诸城 | M12: =TEXT(B12,"mmdd") -> 0101 | N12: =VLOOKUP(I12,累计派单!A:O,15,0) -> dw3_jk_gaoyongkang | O12: =IF(LEN(J12)<2,0,DATEDIF(DATE(IF(MID(J12,9,2)="23",2023,2024),MID(J12,11,2),MID(J12,13,2)),B12,"d")) -> 75 | P12: =IF(O12=0,"无",IF(O12<8,"7天内",IF(O12<31,"30天内",IF(O12<61,"60天内",IF(O12<91,"90天内"))))) -> 90天内 | Q12: =VLOOKUP(I12,累计派单!A:O,13,0) -> 家客铁通潍坊诸城-经开区乡镇装维组
A13: SD-db051-250101-248791-249 | B13: 2025-01-01 14:05:39 | C13: (家客)潍坊-寒亭区-重复投诉投诉督办通知-一级督办17865609592-202501010000363427 | D13: 80+普通-普通区域-寒亭区-蔡家栏子小区-17865609592-1000M-宽带上网投诉-次数0-202501010000363427 | E13: 202501010000363427#流程受理流水号：20250101140451178656095921098738 客户号码:17865609592 客户姓名:邵** 投诉地市:潍坊 来话流水:2025010113544363020845912 宽带账号:17865609592 宽带账号归属地市:潍坊 宽带账号归属区县:寒亭区 故障地址:潍坊寒亭区泊子镇泊南路蔡家栏子小区92号楼箱蔡家春外墙********* 联系电话:15169608022 联系人:先生/女士 工单紧急程度:紧急 是否有升级投诉倾向:否 是否重复投诉:否 是否携转意向:否 是否投诉倾向:否 是否智能网关:智能网关 当前是否在线:是 接入方式:FTTH 端到端诊断结果:客户侧设备问题（新增） 是否质差终端:无质差信息 光功率:-14.78 故障大类:宽带/电视 故障细类:网速慢/上网掉线(专席) 携转原因: 故障时间:2025-01-01 13:59:46 具体故障现象:网速慢卡顿， 客户其他诉求:请审核 ;宽带小区$[蔡家栏子小区]$ | F13: 潍坊 | G13: 寒亭区 | H13: 17865609592 | I13: SD-057-250101-741529-3124 | J13: 'SD-057-241016-462137-2911' | K13: 否 | L13: =IF(OR(LEFT(G13,2)="高新"),"奎文",IF(LEFT(G13,2)="峡山","坊子",IF(LEFT(G13,2)="滨海","寒亭",LEFT(G13,2)))) -> 寒亭 | M13: =TEXT(B13,"mmdd") -> 0101 | N13: =VLOOKUP(I13,累计派单!A:O,15,0) -> dw3_jk_wangweiwei | O13: =IF(LEN(J13)<2,0,DATEDIF(DATE(IF(MID(J13,9,2)="23",2023,2024),MID(J13,11,2),MID(J13,13,2)),B13,"d")) -> 77 | P13: =IF(O13=0,"无",IF(O13<8,"7天内",IF(O13<31,"30天内",IF(O13<61,"60天内",IF(O13<91,"90天内"))))) -> 90天内 | Q13: =VLOOKUP(I13,累计派单!A:O,13,0) -> 家客铁通潍坊寒亭-固高乡镇装维组
... A87: SD-db051-250104-324098-36 | B87: 2025-01-04 09:00:12 | C87: (家客)潍坊-安丘市-重复投诉投诉督办通知-一级督办15653430270-202501040000114033 | D87: 普通区域-安丘市-夹埠村自然村-15653430270-300M-宽带上网投诉-次数0-202501040000114033 | E87: 202501040000114033#流程受理流水号：20250104085921156534302701009734 客户号码:15653430270 客户姓名:刘** 投诉地市:潍坊 来话流水:2025010408585532720832962 宽带账号:15653430270 账号归属区县:潍坊-昌乐-全福元网格-全福元中潍委托 联系电话:15653430270 联系人:先生/女士 宽带地址:潍坊 工单紧急程度:一般 是否投诉倾向:否 是否重复投诉:否 是否携转意向:否 是否有升级投诉倾向:否 *业务名称:业务融合开机流程宽带 投诉内容:手机号码：15653430270，【问题描述】客户已办理宽带业务，有开通单，要求装维尽快联系上门，请处理，谢谢。联系电话：15653430270，联系人：先生/女士，录音流水号：2025010408585532720832962。受理明细：531920062399999999。 在途开通单信息：536241122710709652，15653430270，2024-11-22 14:07:01，业务融合开机流程宽带，处理中，装维选址 是否到厅:否 业务名称:业务融合开机流程宽带 ;宽带小区$[夹埠村自然村]$ | F87: 潍坊 | G87: 安丘市 | H87: 15653430270 | I87: SD-057-250104-092473-405 | J87: 'SD-057-241130-653017-4809' | K87: 是 | L87: =IF(OR(LEFT(G87,2)="高新"),"奎文",IF(LEFT(G87,2)="峡山","坊子",IF(LEFT(G87,2)="滨海","寒亭",LEFT(G87,2)))) -> 安丘 | M87: =TEXT(B87,"mmdd") -> 0104 | N87: =VLOOKUP(I87,累计派单!A:O,15,0) -> dw3_jk_liutongtong | O87: =IF(LEN(J87)<2,0,DATEDIF(DATE(IF(MID(J87,9,2)="23",2023,2024),MID(J87,11,2),MID(J87,13,2)),B87,"d")) -> 35 | P87: =IF(O87=0,"无",IF(O87<8,"7天内",IF(O87<31,"30天内",IF(O87<61,"60天内",IF(O87<91,"90天内"))))) -> 60天内 | Q87: =VLOOKUP(I87,累计派单!A:O,13,0) -> 家客铁通潍坊安丘-贾戈乡镇装维组
A88: SD-db051-250104-546290-37 | B88: 2025-01-04 09:02:23 | C88: (家客)潍坊--重复投诉投诉督办通知-一级督办13562697156-202501040000118386 | D88: 普通区域--null-13562697156-宽带上网投诉-次数0-202501040000118386 | E88: 202501040000118386#流程受理流水号：20250104090114135626971561010353 客户号码:13562697156 客户姓名:王** 投诉地市:潍坊 来话流水:2025010409004447920850038 宽带账号:13562697156 账号归属区县:潍坊-坊子-凤凰网格-吉客便利店 联系电话:13562697156 联系人:先生 宽带地址:潍坊 工单紧急程度:一般 是否投诉倾向:否 是否重复投诉:否 是否携转意向:否 是否有升级投诉倾向:否 *业务名称:业务融合开机流程宽带 投诉内容:手机号码：13562697156，【问题描述】客户已办理宽带业务，有开通单，要求装维尽快联系上门，请处理，谢谢。联系电话：13562697156，联系人：先生，录音流水号：2025010409004447920850038。受理明细：531920062399999999。 在途开通单信息：536241230852788118，13562697156，2024-12-30 12:17:59，业务融合开机流程宽带，处理中，黄单扩容 是否到厅:否 业务名称:业务融合开机流程宽带 ;宽带小区$[null]$ | F88: 潍坊 | H88: 13562697156 | I88: SD-057-250104-018529-422 | J88: 'SD-057-250101-425139-1028' | K88: 是 | L88: =IF(OR(LEFT(G88,2)="高新"),"奎文",IF(LEFT(G88,2)="峡山","坊子",IF(LEFT(G88,2)="滨海","寒亭",LEFT(G88,2)))) | M88: =TEXT(B88,"mmdd") -> 0104 | N88: =VLOOKUP(I88,累计派单!A:O,15,0) -> wangkunwf | O88: =IF(LEN(J88)<2,0,DATEDIF(DATE(IF(MID(J88,9,2)="23",2023,2024),MID(J88,11,2),MID(J88,13,2)),B88,"d")) -> 369 | P88: =IF(O88=0,"无",IF(O88<8,"7天内",IF(O88<31,"30天内",IF(O88<61,"60天内",IF(O88<91,"90天内"))))) -> FALSE | Q88: =VLOOKUP(I88,累计派单!A:O,13,0) -> 0
A89: SD-db051-250104-307829-51 | B89: 2025-01-04 09:17:35 | C89: (家客)潍坊-潍城区-重复投诉投诉督办通知-一级督办13562697000-202501040000129163 | D89: 【调研】-80+普通-普通区域-潍城区-大庄子-13562697000-200M-宽带上网投诉-次数0-202501040000129163 | E89: 202501040000129163#流程受理流水号：20250104091537135626970001015157 客户号码:13562697000 客户姓名:刘** 投诉地市:潍坊 来话流水:2025010409150229320811002 宽带账号:13562697000 宽带账号归属地市:潍坊 宽带账号归属区县:潍城区 故障地址:潍坊潍城区南关街道宝通街大庄子7号楼********* 联系电话:18854323019 联系人:先生/女士 工单紧急程度:一般 是否有升级投诉倾向:否 是否重复投诉:否 是否携转意向:否 是否投诉倾向:否 是否智能网关:智能网关 当前是否在线:是 接入方式:FTTH 端到端诊断结果:客户侧设备问题（新增） 是否质差终端:无质差信息 光功率:-23.76 故障大类:宽带/电视 故障细类:宽带无法上网 携转原因: 故障时间:2025-01-04 09:25:10 具体故障现象:用户无法提供具体故障现象， 客户其他诉求: ;宽带小区$[大庄子]$ | F89: 潍坊 | G89: 潍城区 | H89: 13562697000 | I89: SD-057-250104-405671-571 | J89: 'SD-057-250103-857412-5505' | K89: 是 | L89: =IF(OR(LEFT(G89,2)="高新"),"奎文",IF(LEFT(G89,2)="峡山","坊子",IF(LEFT(G89,2)="滨海","寒亭",LEFT(G89,2)))) -> 潍城 | M89: =TEXT(B89,"mmdd") -> 0104 | N89: =VLOOKUP(I89,累计派单!A:O,15,0) -> dw3_jk_wcliuchao | O89: =IF(LEN(J89)<2,0,DATEDIF(DATE(IF(MID(J89,9,2)="23",2023,2024),MID(J89,11,2),MID(J89,13,2)),B89,"d")) -> 367 | P89: =IF(O89=0,"无",IF(O89<8,"7天内",IF(O89<31,"30天内",IF(O89<61,"60天内",IF(O89<91,"90天内"))))) -> FALSE | Q89: =VLOOKUP(I89,累计派单!A:O,13,0) -> 家客铁通潍坊潍城-胜利街城区装维组
A90: SD-db051-250104-873461-69 | B90: 2025-01-04 09:37:24 | C90: (家客)潍坊-寿光市-重复投诉投诉督办通知-一级督办18766892197-202501040000149608 | D90: 普通区域-寿光市-田二村自然村-18766892197-300M-业务受理宽带-次数0-202501040000149608 | E90: 202501040000149608# 宽带账号:18766892197; 联系电话：18766892197，问题类型：此工单为群障修复工单，根据群障全量闭环修复管理要求，为确保客户网络通畅，请装维人员跟进修复网络问题，谢谢！ 群障标题：公告。故障描述：潍坊寿光市田二村自然村光缆故障，预估24小时恢复，请帮忙拦截,如有需要请联系片区装维师傅王兵15706307817主叫号码：18766892197.0;该号码仅供参考，请优先联系宽带账号。 | F90: 潍坊 | G90: 寿光市 | H90: 18766892197 | I90: SD-057-250104-697348-776 | J90: 'SD-057-250103-642831-2219' | K90: 是 | L90: =IF(OR(LEFT(G90,2)="高新"),"奎文",IF(LEFT(G90,2)="峡山","坊子",IF(LEFT(G90,2)="滨海","寒亭",LEFT(G90,2)))) -> 寿光 | M90: =TEXT(B90,"mmdd") -> 0104 | N90: =VLOOKUP(I90,累计派单!A:O,15,0) -> dw3_jk_wangbing | O90: =IF(LEN(J90)<2,0,DATEDIF(DATE(IF(MID(J90,9,2)="23",2023,2024),MID(J90,11,2),MID(J90,13,2)),B90,"d")) -> 367 | P90: =IF(O90=0,"无",IF(O90<8,"7天内",IF(O90<31,"30天内",IF(O90<61,"60天内",IF(O90<91,"90天内"))))) -> FALSE | Q90: =VLOOKUP(I90,累计派单!A:O,13,0) -> 家客铁通潍坊寿光-稻田乡镇装维组
A91: SD-db051-250104-926540-72 | B91: 2025-01-04 09:37:58 | C91: (家客)潍坊-奎文区-重复投诉投诉督办通知-一级督办15169562082-202501040000148678 | D91: 80+银卡-普通区域-奎文区-世纪花苑-15169562082-1000M-业务受理宽带-次数0-202501040000148678 | E91: 202501040000148678#【已关注中国移动10086微信公众号】 宽带账号:15169562082; 联系电话：15169562082，问题类型：此工单为群障修复工单，根据群障全量闭环修复管理要求，为确保客户网络通畅，请装维人员跟进修复网络问题，谢谢！ 群障标题：公告。故障描述：潍坊奎文区世纪花苑光缆故障，预估24小时恢复，请帮忙拦截,如有需要请联系片区装维师傅张永鸿15706366537主叫号码：15169562082.0;该号码仅供参考，请优先联系宽带账号。 | F91: 潍坊 | G91: 奎文区 | H91: 15169562082 | I91: SD-057-250104-214638-792 | J91: 'SD-057-250103-492305-240' | K91: 是 | L91: =IF(OR(LEFT(G91,2)="高新"),"奎文",IF(LEFT(G91,2)="峡山","坊子",IF(LEFT(G91,2)="滨海","寒亭",LEFT(G91,2)))) -> 奎文 | M91: =TEXT(B91,"mmdd") -> 0104 | N91: =VLOOKUP(I91,累计派单!A:O,15,0) -> dw3_jk_zhangyonghong | O91: =IF(LEN(J91)<2,0,DATEDIF(DATE(IF(MID(J91,9,2)="23",2023,2024),MID(J91,11,2),MID(J91,13,2)),B91,"d")) -> 367 | P91: =IF(O91=0,"无",IF(O91<8,"7天内",IF(O91<31,"30天内",IF(O91<61,"60天内",IF(O91<91,"90天内"))))) -> FALSE | Q91: =VLOOKUP(I91,累计派单!A:O,13,0) -> 家客铁通潍坊奎文-鸢飞路城区装维组
A92: SD-db051-250104-673589-112 | B92: 2025-01-04 10:26:20 | C92: (家客)潍坊-潍城区-重复投诉投诉督办通知-一级督办13963657285-202501040000199165 | D92: 【调研】-80+银卡-普通区域-潍城区-鲁发名城西区-13963657285-1000M-魔百和投诉-次数0-202501040000199165 | E92: 202501040000199165#客户来电投诉 潍城和平路营业厅 客户表示前期机顶盒不好用了营业厅给更换 新的需要缴纳100元对此不满 （客户换了个旧的未收钱）客户表示每个月都收取移动高清（智能版）13元/月 更换时新的也不应该收取费用 我处已按口径解释，客户不满，请协助处理，谢谢！流水2025010410152929420826793 | F92: 潍坊 | G92: 潍城区 | H92: 13963657285 | I92: SD-057-250104-083945-1272 | J92: 'SD-057-241223-931865-479' | K92: 是 | L92: =IF(OR(LEFT(G92,2)="高新"),"奎文",IF(LEFT(G92,2)="峡山","坊子",IF(LEFT(G92,2)="滨海","寒亭",LEFT(G92,2)))) -> 潍城 | M92: =TEXT(B92,"mmdd") -> 0104 | N92: =VLOOKUP(I92,累计派单!A:O,15,0) -> dw3_jk_yaoguoqiang | O92: =IF(LEN(J92)<2,0,DATEDIF(DATE(IF(MID(J92,9,2)="23",2023,2024),MID(J92,11,2),MID(J92,13,2)),B92,"d")) -> 12 | P92: =IF(O92=0,"无",IF(O92<8,"7天内",IF(O92<31,"30天内",IF(O92<61,"60天内",IF(O92<91,"90天内"))))) -> 30天内 | Q92: =VLOOKUP(I92,累计派单!A:O,13,0) -> 家客铁通潍坊潍城-东风街城区装维组
A93: SD-db051-250104-397504-116 | B93: 2025-01-04 10:27:44 | C93: (家客)潍坊-潍城区-重复投诉投诉督办通知-一级督办18806365639-202501040000205383 | D93: 【调研】-80+银卡-普通区域-潍城区-南季自然村-18806365639-300M-业务受理宽带-次数0-202501040000205383 | E93: 202501040000205383# 宽带账号:18806365639; 联系电话：18806365639，问题类型：此工单为群障修复工单，根据群障全量闭环修复管理要求，为确保客户网络通畅，请装维人员跟进修复网络问题，谢谢！ 群障标题：公告。故障描述：潍坊潍城区南季自然村光缆故障，预估24小时恢复，请帮忙拦截,如有需要请联系片区装维师傅张翔宇15706307859主叫号码：18806365639.0;该号码仅供参考，请优先联系宽带账号。 | F93: 潍坊 | G93: 潍城区 | H93: 18806365639 | I93: SD-057-250104-856047-1301 | J93: 'SD-057-250103-983174-6155' | K93: 是 | L93: =IF(OR(LEFT(G93,2)="高新"),"奎文",IF(LEFT(G93,2)="峡山","坊子",IF(LEFT(G93,2)="滨海","寒亭",LEFT(G93,2)))) -> 潍城 | M93: =TEXT(B93,"mmdd") -> 0104 | N93: =VLOOKUP(I93,累计派单!A:O,15,0) -> dw3_jk_wczhangxiangyu | O93: =IF(LEN(J93)<2,0,DATEDIF(DATE(IF(MID(J93,9,2)="23",2023,2024),MID(J93,11,2),MID(J93,13,2)),B93,"d")) -> 367 | P93: =IF(O93=0,"无",IF(O93<8,"7天内",IF(O93<31,"30天内",IF(O93<61,"60天内",IF(O93<91,"90天内"))))) -> FALSE | Q93: =VLOOKUP(I93,累计派单!A:O,13,0) -> 家客铁通潍坊潍城-胜利街城区装维组
A94: SD-db051-250104-398716-130 | B94: 2025-01-04 10:43:39 | C94: (家客)潍坊-安丘市-重复投诉投诉督办通知-一级督办18453631559-202501040000223118 | D94: 普通区域-安丘市-青云瑞景园(含锦绣上河园)-18453631559-100M-宽带上网投诉-次数0-202501040000223118 | E94: 202501040000223118#18453631559客户来电反映宽带无法使用，卡顿。慢。延迟高，线上排障不认可，客户表示多次来电修复，重启，客户表示未解决！要求维修人员上门维修，请尽快协助处理，谢谢 联系人：先生 联系电话：本机 来电流水：）来话流水2025010410390434220865030 | F94: 潍坊 | G94: 安丘市 | H94: 18453631559 | I94: SD-057-250104-123678-1487 | J94: 'SD-057-241110-934185-6546' | K94: 是 | L94: =IF(OR(LEFT(G94,2)="高新"),"奎文",IF(LEFT(G94,2)="峡山","坊子",IF(LEFT(G94,2)="滨海","寒亭",LEFT(G94,2)))) -> 安丘 | M94: =TEXT(B94,"mmdd") -> 0104 | N94: =VLOOKUP(I94,累计派单!A:O,15,0) -> dw3_jk_chenyujun | O94: =IF(LEN(J94)<2,0,DATEDIF(DATE(IF(MID(J94,9,2)="23",2023,2024),MID(J94,11,2),MID(J94,13,2)),B94,"d")) -> 55 | P94: =IF(O94=0,"无",IF(O94<8,"7天内",IF(O94<31,"30天内",IF(O94<61,"60天内",IF(O94<91,"90天内"))))) -> 60天内 | Q94: =VLOOKUP(I94,累计派单!A:O,13,0) -> 家客铁通潍坊安丘-贾戈乡镇装维组
A95: SD-db051-250104-391786-132 | B95: 2025-01-04 10:47:08 | C95: (家客)潍坊-诸城市-重复投诉投诉督办通知-一级督办13791882713-20250104104438X678546266 | D95: FTTR-普通区域-诸城市-金东世纪城-13791882713-1000M-宽带上网投诉-次数0-20250104104438X678546266 | E95: 流程受理流水号：20250104104035137918827131047296 客户号码:13791882713 客户姓名:刘** 投诉地市:潍坊 来话流水:2025010410375796520849253 宽带账号:13791882713 宽带账号归属地市:潍坊 宽带账号归属区县:诸城市 故障地址:潍坊诸城市密州街道东武街金东世纪城18号楼********* 联系电话:13791882713 联系人:先生/女士 工单紧急程度:非常紧急 是否有升级投诉倾向:否 是否重复投诉:否 是否携转意向:否 是否投诉倾向:否 是否智能网关:智能网关 当前是否在线:是 接入方式:-- 端到端诊断结果:客户侧设备问题（新增） 是否质差终端:无质差信息 光功率:-21.36 故障大类:宽带/电视 故障细类:宽带网速慢/卡顿 携转原因: 故障时间:2025-01-04 10:43:02 网站/APP/游戏名称:刷视频 具体故障现象:网速慢卡顿， 客户其他诉求: | F95: 潍坊 | G95: 诸城市 | H95: 13791882713 | I95: SD-057-250104-028361-1510 | J95: 'SD-057-241006-385469-5692' | K95: 是 | L95: =IF(OR(LEFT(G95,2)="高新"),"奎文",IF(LEFT(G95,2)="峡山","坊子",IF(LEFT(G95,2)="滨海","寒亭",LEFT(G95,2)))) -> 诸城 | M95: =TEXT(B95,"mmdd") -> 0104 | N95: =VLOOKUP(I95,累计派单!A:O,15,0) -> dw3_jk_suidongwei | O95: =IF(LEN(J95)<2,0,DATEDIF(DATE(IF(MID(J95,9,2)="23",2023,2024),MID(J95,11,2),MID(J95,13,2)),B95,"d")) -> 90 | P95: =IF(O95=0,"无",IF(O95<8,"7天内",IF(O95<31,"30天内",IF(O95<61,"60天内",IF(O95<91,"90天内"))))) -> 90天内 | Q95: =VLOOKUP(I95,累计派单!A:O,13,0) -> 家客铁通潍坊诸城-繁荣路城区装维组
A96: SD-db051-250104-526048-138 | B96: 2025-01-04 10:50:24 | C96: (家客)潍坊--重复投诉投诉督办通知-一级督办18953660076-202501040000230777 | D96: 普通区域--null-18953660076-宽带上网投诉-次数0-202501040000230777 | E96: 202501040000230777#流程受理流水号：20250104104953189536600761050759 客户号码:18953660076 客户姓名:王** 投诉地市:潍坊 来话流水:2025010410472076120883690 宽带账号:18953660076 账号归属区县:开发区-城区-潍坊高新区弘毅手机通讯店 联系电话:13020591569 联系人:先生/女士 宽带地址:潍坊 工单紧急程度:一般 是否投诉倾向:否 是否重复投诉:否 是否携转意向:否 是否有升级投诉倾向:否 *业务名称:业务融合开机流程宽带+OTT 投诉内容:手机号码：18953660076，【问题描述】客户已办理宽带业务，有开通单，要求装维尽快联系上门，请处理，谢谢。联系电话：13020591569，联系人：先生/女士，录音流水号：2025010410472076120883690。受理明细：531920062399999999。 在途开通单信息：536250104110475424，18953660076，2025-01-04 10:34:47，业务融合开机流程宽带+OTT，处理中，手写判断和地址录入 是否到厅:否 业务名称:业务融合开机流程宽带+OTT ;宽带小区$[null]$ | F96: 潍坊 | H96: 18953660076 | I96: SD-057-250104-294807-1553 | J96: 'SD-057-250103-148562-344' | K96: 否 | L96: =IF(OR(LEFT(G96,2)="高新"),"奎文",IF(LEFT(G96,2)="峡山","坊子",IF(LEFT(G96,2)="滨海","寒亭",LEFT(G96,2)))) | M96: =TEXT(B96,"mmdd") -> 0104 | N96: =VLOOKUP(I96,累计派单!A:O,15,0) -> wangkunwf | O96: =IF(LEN(J96)<2,0,DATEDIF(DATE(IF(MID(J96,9,2)="23",2023,2024),MID(J96,11,2),MID(J96,13,2)),B96,"d")) -> 367 | P96: =IF(O96=0,"无",IF(O96<8,"7天内",IF(O96<31,"30天内",IF(O96<61,"60天内",IF(O96<91,"90天内"))))) -> FALSE | Q96: =VLOOKUP(I96,累计派单!A:O,13,0) -> 0
A97: SD-db051-250104-736419-143 | B97: 2025-01-04 10:57:32 | C97: (家客)潍坊-寒亭区-重复投诉投诉督办通知-一级督办15863615468-202501040000240291 | D97: 普通区域-寒亭区-蔡家栏子小区-15863615468-100M-业务受理宽带-次数0-202501040000240291 | E97: 202501040000240291# 宽带账号:15863615468; 联系电话：15863615468，问题类型：此工单为群障修复工单，根据群障全量闭环修复管理要求，为确保客户网络通畅，请装维人员跟进修复网络问题，谢谢！ 群障标题：公告。故障描述：潍坊寒亭区蔡家栏子小区光缆故障，预估24小时恢复，请帮忙拦截,如有需要请联系片区装维师傅王伟伟15706307460主叫号码：15863615468.0;该号码仅供参考，请优先联系宽带账号。 | F97: 潍坊 | G97: 寒亭区 | H97: 15863615468 | I97: SD-057-250104-132864-1616 | J97: 'SD-057-241103-283659-7245' | K97: 是 | L97: =IF(OR(LEFT(G97,2)="高新"),"奎文",IF(LEFT(G97,2)="峡山","坊子",IF(LEFT(G97,2)="滨海","寒亭",LEFT(G97,2)))) -> 寒亭 | M97: =TEXT(B97,"mmdd") -> 0104 | N97: =VLOOKUP(I97,累计派单!A:O,15,0) -> dw3_jk_wangweiwei | O97: =IF(LEN(J97)<2,0,DATEDIF(DATE(IF(MID(J97,9,2)="23",2023,2024),MID(J97,11,2),MID(J97,13,2)),B97,"d")) -> 62 | P97: =IF(O97=0,"无",IF(O97<8,"7天内",IF(O97<31,"30天内",IF(O97<61,"60天内",IF(O97<91,"90天内"))))) -> 90天内 | Q97: =VLOOKUP(I97,累计派单!A:O,13,0) -> 家客铁通潍坊寒亭-固高乡镇装维组
A98: SD-db051-250104-431795-151 | B98: 2025-01-04 11:05:57 | C98: (家客)潍坊-寒亭区-重复投诉投诉督办通知-一级督办13869623195-202501040000248302 | D98: 普通区域-寒亭区-锦程中学宿舍-13869623195-100M-宽带上网投诉-次数0-202501040000248302 | E98: 202501040000248302#流程受理流水号：20250104110212138696231951055576 客户号码:13869623195 客户姓名:刘** 投诉地市:潍坊 来话流水:2025010411011528720882243 宽带账号:13869623195 宽带账号归属地市:潍坊 宽带账号归属区县:寒亭区 故障地址:潍坊寒亭区经济开发区月河路锦程中学宿舍1号楼********* 联系电话:13869623195 联系人:先生/女士 工单紧急程度:一般 是否有升级投诉倾向:否 是否重复投诉:否 是否携转意向:否 是否投诉倾向:否 是否智能网关:智能网关 当前是否在线:否 接入方式:FTTH 端到端诊断结果:状态正常 是否质差终端:无质差信息 光功率:无 故障大类:宽带/电视 故障细类:宽带无法上网 携转原因: 故障时间:2025-01-04 11:01:56 具体故障现象:提示网络无法连接， 客户其他诉求: ;宽带小区$[锦程中学宿舍]$ | F98: 潍坊 | G98: 寒亭区 | H98: 13869623195 | I98: SD-057-250104-273104-1723 | J98: 'SD-057-250103-273145-3993' | K98: 是 | L98: =IF(OR(LEFT(G98,2)="高新"),"奎文",IF(LEFT(G98,2)="峡山","坊子",IF(LEFT(G98,2)="滨海","寒亭",LEFT(G98,2)))) -> 寒亭 | M98: =TEXT(B98,"mmdd") -> 0104 | N98: =VLOOKUP(I98,累计派单!A:O,15,0) -> dw3_jk_liyuan | O98: =IF(LEN(J98)<2,0,DATEDIF(DATE(IF(MID(J98,9,2)="23",2023,2024),MID(J98,11,2),MID(J98,13,2)),B98,"d")) -> 367 | P98: =IF(O98=0,"无",IF(O98<8,"7天内",IF(O98<31,"30天内",IF(O98<61,"60天内",IF(O98<91,"90天内"))))) -> FALSE | Q98: =VLOOKUP(I98,累计派单!A:O,13,0) -> 家客铁通潍坊寒亭-开发区乡镇装维组
A99: SD-db051-250104-642895-154 | B99: 2025-01-04 11:08:15 | C99: (家客)潍坊-奎文区-重复投诉投诉督办通知-一级督办15806483000-20250104110349X829853776 | D99: 80+银卡-普通区域-奎文区-金鼎华府-15806483000-300M-宽带上网投诉-次数0-20250104110349X829853776 | E99: 流程受理流水号：20250103133856158064830001102152 客户号码:15806483000 客户姓名:田* 投诉地市:潍坊 来话流水:2025010313362065420816638 宽带账号:15806483000 宽带账号归属地市:潍坊 宽带账号归属区县:奎文区 故障地址:潍坊奎文区大虞街道鸢飞路金鼎华府6号楼********* 联系电话:15806483000 联系人:先生/女士 工单紧急程度:一般 是否有升级投诉倾向:否 是否重复投诉:否 是否携转意向:否 是否投诉倾向:否 是否智能网关:智能网关 当前是否在线:否 接入方式:FTTH 端到端诊断结果:大面积故障 是否质差终端:无质差信息 光功率:无 故障大类:宽带/电视 故障细类:宽带无法上网 携转原因: 故障时间:2025-01-03 13:39:28 具体故障现象:光猫亮红灯， 客户其他诉求: 前期工单20250103134017X817138296，要求继续处理，谢谢 | F99: 潍坊 | G99: 奎文区 | H99: 15806483000 | I99: SD-057-250104-073421-1766 | J99: 'SD-057-250103-783015-2547' | K99: 是 | L99: =IF(OR(LEFT(G99,2)="高新"),"奎文",IF(LEFT(G99,2)="峡山","坊子",IF(LEFT(G99,2)="滨海","寒亭",LEFT(G99,2)))) -> 奎文 | M99: =TEXT(B99,"mmdd") -> 0104 | N99: =VLOOKUP(I99,累计派单!A:O,15,0) -> dw3_jk_renfeng | O99: =IF(LEN(J99)<2,0,DATEDIF(DATE(IF(MID(J99,9,2)="23",2023,2024),MID(J99,11,2),MID(J99,13,2)),B99,"d")) -> 367 | P99: =IF(O99=0,"无",IF(O99<8,"7天内",IF(O99<31,"30天内",IF(O99<61,"60天内",IF(O99<91,"90天内"))))) -> FALSE | Q99: =VLOOKUP(I99,累计派单!A:O,13,0) -> 家客铁通潍坊奎文-鸢飞路城区装维组
A100: SD-db051-250104-913672-155 | B100: 2025-01-04 11:08:46 | C100: (家客)潍坊-高密市-重复投诉投诉督办通知-一级督办18863647333-202501040000250943 | D100: 【调研】-80+金卡-普通区域-高密市-书香漫步-18863647333-1000M-宽带上网投诉-次数0-202501040000250943 | E100: 202501040000250943#【已关注中国移动10086微信公众号】流程受理流水号：20250104110639188636473331057311 客户号码:18863647333 客户姓名:李* 投诉地市:潍坊 来话流水:2025010411004360620874673 宽带账号:18863647333 宽带账号归属地市:潍坊 宽带账号归属区县:高密市 故障地址:潍坊高密市醴泉街道站南街书香漫步6号楼********* 联系电话:18863647333 联系人:先生 工单紧急程度:非常紧急 是否有升级投诉倾向:否 是否重复投诉:否 是否携转意向:否 是否投诉倾向:否 是否智能网关:智能网关 当前是否在线:是 接入方式:FTTH 端到端诊断结果:客户侧设备问题（新增） 是否质差终端:无质差信息 光功率:-21.24 故障大类:宽带/电视 故障细类:网速慢/上网掉线(专席) 携转原因: 故障时间:2025-01-04 11:10:36 具体故障现象:网速慢卡顿， 客户其他诉求:客户拒绝联系工作人员过去排查，并要求解决宽带网速慢的问题，请协助处理，谢谢 ;宽带小区$[书香漫步]$ | F100: 潍坊 | G100: 高密市 | H100: 18863647333 | I100: SD-057-250104-702368-1777 | J100: 'SD-057-241220-851467-5701' | K100: 否 | L100: =IF(OR(LEFT(G100,2)="高新"),"奎文",IF(LEFT(G100,2)="峡山","坊子",IF(LEFT(G100,2)="滨海","寒亭",LEFT(G100,2)))) -> 高密 | M100: =TEXT(B100,"mmdd") -> 0104 | N100: =VLOOKUP(I100,累计派单!A:O,15,0) -> dw3_jk_liuzhigang | O100: =IF(LEN(J100)<2,0,DATEDIF(DATE(IF(MID(J100,9,2)="23",2023,2024),MID(J100,11,2),MID(J100,13,2)),B100,"d")) -> 15 | P100: =IF(O100=0,"无",IF(O100<8,"7天内",IF(O100<31,"30天内",IF(O100<61,"60天内",IF(O100<91,"90天内"))))) -> 30天内 | Q100: =VLOOKUP(I100,累计派单!A:O,13,0) -> 家客铁通潍坊高密-朝阳城区装维组
A101: SD-db051-250104-952648-178 | B101: 2025-01-04 11:39:15 | C101: (家客)潍坊-青州市-重复投诉投诉督办通知-一级督办13455683982-202501040000278356 | D101: 【调研】-80+银卡-普通区域-青州市-东郝村自然村-13455683982-300M-宽带上网投诉-次数0-202501040000278356 | E101: 202501040000278356#13455683982客户来电表示线路全部拔掉了 客户无法自行安装 要求师傅上门 请尽快处理 谢谢 联系人：先生 联系电话：13455683982 来电流水：2025010411341478520847139 | F101: 潍坊 | G101: 青州市 | H101: 13455683982 | I101: SD-057-250104-837269-2047 | J101: 'SD-057-241105-790162-2543' | K101: 否 | L101: =IF(OR(LEFT(G101,2)="高新"),"奎文",IF(LEFT(G101,2)="峡山","坊子",IF(LEFT(G101,2)="滨海","寒亭",LEFT(G101,2)))) -> 青州 | M101: =TEXT(B101,"mmdd") -> 0104 | N101: =VLOOKUP(I101,累计派单!A:O,15,0) -> 0 | O101: =IF(LEN(J101)<2,0,DATEDIF(DATE(IF(MID(J101,9,2)="23",2023,2024),MID(J101,11,2),MID(J101,13,2)),B101,"d")) -> 60 | P101: =IF(O101=0,"无",IF(O101<8,"7天内",IF(O101<31,"30天内",IF(O101<61,"60天内",IF(O101<91,"90天内"))))) -> 60天内 | Q101: =VLOOKUP(I101,累计派单!A:O,13,0) -> 家客铁通潍坊青州-谭坊乡镇装维组
A102: SD-db051-250104-053729-225 | B102: 2025-01-04 12:41:12 | C102: (家客)潍坊-寒亭区-重复投诉投诉督办通知-一级督办15963645371-20250104124032X632172397 | D102: 【调研】-80+普通-普通区域-寒亭区-海盛花苑小区-15963645371-1000M-宽带上网投诉-次数0-20250104124032X632172397 | E102: 流程受理流水号：20250104123509159636453711086288 客户号码:15963645371 客户姓名:张** 投诉地市:潍坊 来话流水:2025010412344224520891362 宽带账号:15963645371 宽带账号归属地市:潍坊 宽带账号归属区县:寒亭区 故障地址:潍坊寒亭区寒亭街道丰华路海盛花苑小区6号楼********* 联系电话:15963645371 联系人:先生/女士 工单紧急程度:非常紧急 是否有升级投诉倾向:否 是否重复投诉:否 是否携转意向:否 是否投诉倾向:否 是否智能网关:智能网关 当前是否在线:否 接入方式:FTTH 端到端诊断结果:状态正常 是否质差终端:无质差信息 光功率:无 故障大类:宽带/电视 故障细类:宽带无法上网 携转原因: 故障时间:2025-01-04 12:39:28 具体故障现象:无法上网 客户其他诉求:要求恢复正常 | F102: 潍坊 | G102: 寒亭区 | H102: 15963645371 | I102: SD-057-250104-089534-2583 | J102: 'SD-057-241229-639502-6307' | K102: 否 | L102: =IF(OR(LEFT(G102,2)="高新"),"奎文",IF(LEFT(G102,2)="峡山","坊子",IF(LEFT(G102,2)="滨海","寒亭",LEFT(G102,2)))) -> 寒亭 | M102: =TEXT(B102,"mmdd") -> 0104 | N102: =VLOOKUP(I102,累计派单!A:O,15,0) -> dw3_jk_zhangdeqian | O102: =IF(LEN(J102)<2,0,DATEDIF(DATE(IF(MID(J102,9,2)="23",2023,2024),MID(J102,11,2),MID(J102,13,2)),B102,"d")) -> 6 | P102: =IF(O102=0,"无",IF(O102<8,"7天内",IF(O102<31,"30天内",IF(O102<61,"60天内",IF(O102<91,"90天内"))))) -> 7天内 | Q102: =VLOOKUP(I102,累计派单!A:O,13,0) -> 家客铁通潍坊寒亭-城东城区装维组
A103: SD-db051-250104-794620-243 | B103: 2025-01-04 13:16:54 | C103: (家客)潍坊-潍城区-重复投诉投诉督办通知-一级督办15269616887-202501040000353803 | D103: 普通区域-潍城区-丽景酒店片区-15269616887-300M-业务受理宽带-次数0-202501040000353803 | E103: 202501040000353803#【已关注中国移动10086微信公众号】 宽带账号:15269616887; 联系电话：15269616887，问题类型：此工单为群障修复工单，根据群障全量闭环修复管理要求，为确保客户网络通畅，请装维人员跟进修复网络问题，谢谢！ 群障标题：公告。故障描述：丽景酒店片区主叫号码：15269616887.0;该号码仅供参考，请优先联系宽带账号。 | F103: 潍坊 | G103: 潍城区 | H103: 15269616887 | I103: SD-057-250104-705631-2863 | J103: 'SD-057-241106-752468-3692' | K103: 否 | L103: =IF(OR(LEFT(G103,2)="高新"),"奎文",IF(LEFT(G103,2)="峡山","坊子",IF(LEFT(G103,2)="滨海","寒亭",LEFT(G103,2)))) -> 潍城 | M103: =TEXT(B103,"mmdd") -> 0104 | N103: =VLOOKUP(I103,累计派单!A:O,15,0) -> dw3_jk_wcduwangfeng | O103: =IF(LEN(J103)<2,0,DATEDIF(DATE(IF(MID(J103,9,2)="23",2023,2024),MID(J103,11,2),MID(J103,13,2)),B103,"d")) -> 59 | P103: =IF(O103=0,"无",IF(O103<8,"7天内",IF(O103<31,"30天内",IF(O103<61,"60天内",IF(O103<91,"90天内"))))) -> 60天内 | Q103: =VLOOKUP(I103,累计派单!A:O,13,0) -> 家客铁通潍坊潍城-胜利街城区装维组
A104: SD-db051-250104-302176-257 | B104: 2025-01-04 13:46:24 | C104: (家客)潍坊-诸城市-重复投诉投诉督办通知-一级督办13953667716-202501040000373154 | D104: 80+白金-普通区域-诸城市-南湖公安小区-13953667716-300M-宽带上网投诉-次数0-202501040000373154 | E104: 202501040000373154#宽带账号：13953667716；宽带地址：潍坊诸城市密州街道文化路南湖公安小区南湖公安小区；客户来电反映宽带无法上网，客户已将光猫路由器断电并按顺序重启后仍未恢复，要求上门，请协助处理，谢谢！联系电话：本机；联系人：女士；来电流水：2025010413422040720837077。 | F104: 潍坊 | G104: 诸城市 | H104: 13953667716 | I104: SD-057-250104-586042-3131 | J104: 'SD-057-241014-742638-4356' | K104: 否 | L104: =IF(OR(LEFT(G104,2)="高新"),"奎文",IF(LEFT(G104,2)="峡山","坊子",IF(LEFT(G104,2)="滨海","寒亭",LEFT(G104,2)))) -> 诸城 | M104: =TEXT(B104,"mmdd") -> 0104 | N104: =VLOOKUP(I104,累计派单!A:O,15,0) -> dw3_jk_xuguodong | O104: =IF(LEN(J104)<2,0,DATEDIF(DATE(IF(MID(J104,9,2)="23",2023,2024),MID(J104,11,2),MID(J104,13,2)),B104,"d")) -> 82 | P104: =IF(O104=0,"无",IF(O104<8,"7天内",IF(O104<31,"30天内",IF(O104<61,"60天内",IF(O104<91,"90天内"))))) -> 90天内 | Q104: =VLOOKUP(I104,累计派单!A:O,13,0) -> 家客铁通潍坊诸城-兴华东路城区装维组
A105: SD-db051-250104-950467-345 | B105: 2025-01-04 15:37:05 | C105: (家客)潍坊-昌邑市-重复投诉投诉督办通知-一级督办15610610734-202501040000477560 | D105: 【重投】-【调研】-普通区域-昌邑市-山前村-15610610734-1000M-业务受理宽带-次数0-202501040000477560 | E105: 202501040000477560#【已关注中国移动10086微信公众号】 宽带账号:15610610734; 联系电话：15610610734，问题类型：此工单为群障修复工单，根据群障全量闭环修复管理要求，为确保客户网络通畅，请装维人员跟进修复网络问题，谢谢！ 群障标题：公告。故障描述：潍坊昌邑市山前村光缆故障，预估24小时恢复，请帮忙拦截,如有需要请联系片区装维师傅邓艺浩15706307216主叫号码：15610610734.0;该号码仅供参考，请优先联系宽带账号。 | F105: 潍坊 | G105: 昌邑市 | H105: 15610610734 | I105: SD-057-250104-386409-4338 | J105: 'SD-057-241215-378254-6559' | K105: 否 | L105: =IF(OR(LEFT(G105,2)="高新"),"奎文",IF(LEFT(G105,2)="峡山","坊子",IF(LEFT(G105,2)="滨海","寒亭",LEFT(G105,2)))) -> 昌邑 | M105: =TEXT(B105,"mmdd") -> 0104 | N105: =VLOOKUP(I105,累计派单!A:O,15,0) -> dw3_jk_dengyihao | O105: =IF(LEN(J105)<2,0,DATEDIF(DATE(IF(MID(J105,9,2)="23",2023,2024),MID(J105,11,2),MID(J105,13,2)),B105,"d")) -> 20 | P105: =IF(O105=0,"无",IF(O105<8,"7天内",IF(O105<31,"30天内",IF(O105<61,"60天内",IF(O105<91,"90天内"))))) -> 30天内 | Q105: =VLOOKUP(I105,累计派单!A:O,13,0) -> 家客铁通潍坊昌邑-城西城区装维组
A106: SD-db051-250104-756849-365 | B106: 2025-01-04 16:03:33 | C106: (家客)潍坊-寿光市-重复投诉投诉督办通知-一级督办15154480806-202501040000502106 | D106: 80+普通-普通区域-寿光市-五台台后村自然村-15154480806-200M-宽带上网投诉-次数0-202501040000502106 | E106: 202501040000502106#15154480806客户来电反映宽带无法使用，客户拒绝线上排障，要求维修人员上门维修，请尽快协助处理，谢谢 联系人：女士联系电话： 15154480806 流水：2025010416014367820844373 | F106: 潍坊 | G106: 寿光市 | H106: 15154480806 | I106: SD-057-250104-098731-4583 | J106: 'SD-057-241225-049785-1678' | K106: 否 | L106: =IF(OR(LEFT(G106,2)="高新"),"奎文",IF(LEFT(G106,2)="峡山","坊子",IF(LEFT(G106,2)="滨海","寒亭",LEFT(G106,2)))) -> 寿光 | M106: =TEXT(B106,"mmdd") -> 0104 | N106: =VLOOKUP(I106,累计派单!A:O,15,0) -> dw3_jk_wangshuaisg | O106: =IF(LEN(J106)<2,0,DATEDIF(DATE(IF(MID(J106,9,2)="23",2023,2024),MID(J106,11,2),MID(J106,13,2)),B106,"d")) -> 10 | P106: =IF(O106=0,"无",IF(O106<8,"7天内",IF(O106<31,"30天内",IF(O106<61,"60天内",IF(O106<91,"90天内"))))) -> 30天内 | Q106: =VLOOKUP(I106,累计派单!A:O,13,0) -> 家客铁通潍坊寿光-侯镇乡镇装维组
A107: SD-db051-250104-402635-382 | B107: 2025-01-04 16:25:14 | C107: (家客)潍坊-青州市-重复投诉投诉督办通知-一级督办15854880672-202501040000520451 | D107: 普通区域-青州市-孙旺村-15854880672-300M-宽带上网投诉-次数0-202501040000520451 | E107: 202501040000520451#宽带账号：15854880672；宽带地址：潍坊青州市王坟镇卜家卜家庄2号箱（村委门头）*********；客户来电反映宽带无法使用，客户不在现场，无法配合线上指导/客户不配合排障，要求上门，请协助处理，谢谢！！来电流水：2025010416224324520830540，联系电话：15854880672 | F107: 潍坊 | G107: 青州市 | H107: 15854880672 | I107: SD-057-250104-862795-4794 | J107: 'SD-057-241129-805964-2208' | K107: 否 | L107: =IF(OR(LEFT(G107,2)="高新"),"奎文",IF(LEFT(G107,2)="峡山","坊子",IF(LEFT(G107,2)="滨海","寒亭",LEFT(G107,2)))) -> 青州 | M107: =TEXT(B107,"mmdd") -> 0104 | N107: =VLOOKUP(I107,累计派单!A:O,15,0) -> dw3_jk_zhanglijie | O107: =IF(LEN(J107)<2,0,DATEDIF(DATE(IF(MID(J107,9,2)="23",2023,2024),MID(J107,11,2),MID(J107,13,2)),B107,"d")) -> 36 | P107: =IF(O107=0,"无",IF(O107<8,"7天内",IF(O107<31,"30天内",IF(O107<61,"60天内",IF(O107<91,"90天内"))))) -> 60天内 | Q107: =VLOOKUP(I107,累计派单!A:O,13,0) -> 家客铁通潍坊青州-弥河乡镇装维组
A108: SD-db051-250104-163754-408 | B108: 2025-01-04 17:04:24 | C108: (家客)潍坊-青州市-重复投诉投诉督办通知-一级督办13854461732-202501040000561405 | D108: 普通区域-青州市-东李村-13854461732-500M-宽带上网投诉-次数0-202501040000561405 | E108: 202501040000561405#流程受理流水号：20250104165727138544617321165824 客户号码:13854461732 客户姓名:秦** 投诉地市:潍坊 来话流水:2025010416542379620849999 宽带账号:13854461732 宽带账号归属地市:潍坊 宽带账号归属区县:青州市 故障地址:潍坊青州市黄楼街道东李东李村11号箱(贾永军）********* 联系电话:13854461732 联系人:先生/女士 工单紧急程度:一般 是否有升级投诉倾向:否 是否重复投诉:否 是否携转意向:否 是否投诉倾向:否 是否智能网关:智能网关 当前是否在线:是 接入方式:FTTH 端到端诊断结果:客户侧设备问题 是否质差终端:是 光功率:-21.24 故障大类:宽带/电视 故障细类:宽带无法上网 携转原因: 故障时间:2025-01-04 17:04:02 具体故障现象:提示网络无法连接， 客户其他诉求:客户侧为质差终端，要求上门更换终端并一并处理故障问题。 | F108: 潍坊 | G108: 青州市 | H108: 13854461732 | I108: SD-057-250104-314082-5173 | J108: 'SD-057-241114-729016-3028' | K108: 否 | L108: =IF(OR(LEFT(G108,2)="高新"),"奎文",IF(LEFT(G108,2)="峡山","坊子",IF(LEFT(G108,2)="滨海","寒亭",LEFT(G108,2)))) -> 青州 | M108: =TEXT(B108,"mmdd") -> 0104 | N108: =VLOOKUP(I108,累计派单!A:O,15,0) -> dw3_jk_yangjianqiang | O108: =IF(LEN(J108)<2,0,DATEDIF(DATE(IF(MID(J108,9,2)="23",2023,2024),MID(J108,11,2),MID(J108,13,2)),B108,"d")) -> 51 | P108: =IF(O108=0,"无",IF(O108<8,"7天内",IF(O108<31,"30天内",IF(O108<61,"60天内",IF(O108<91,"90天内"))))) -> 60天内 | Q108: =VLOOKUP(I108,累计派单!A:O,13,0) -> 家客铁通潍坊青州-黄楼乡镇装维组
... A116: SD-db051-250104-783610-454 | B116: 2025-01-04 18:17:26 | C116: (家客)潍坊-寿光市-重复投诉投诉督办通知-一级督办15069637710-20250104181652X812640621 | D116: 80+银卡-普通区域-寿光市-北洋头-15069637710-300M-宽带上网投诉-次数0-20250104181652X812640621 | E116: 【农村网络投诉】流程受理流水号：20250104181535150696377101188721 客户号码:15069637710 客户姓名:李** 投诉地市:潍坊 来话流水:2025010418150686520861645 宽带账号:15069637710 宽带账号归属地市:潍坊 宽带账号归属区县:寿光市 故障地址:潍坊寿光市台头镇付家庄村北洋头北洋头10号箱********* 联系电话:15095189709 联系人:女士 工单紧急程度:一般 是否有升级投诉倾向:否 是否重复投诉:否 是否携转意向:否 是否投诉倾向:否 是否智能网关:智能网关 当前是否在线:否 接入方式:FTTH 端到端诊断结果:状态正常 是否质差终端:无质差信息 光功率:无 故障大类:宽带/电视 故障细类:宽带无法上网 携转原因: 故障时间:2025-01-04 18:16:25 具体故障现象:光猫亮红灯， 客户其他诉求: | F116: 潍坊 | G116: 寿光市 | H116: 15069637710 | I116: SD-057-250104-541678-5825 | J116: 'SD-057-241211-921540-222' | K116: 否 | L116: =IF(OR(LEFT(G116,2)="高新"),"奎文",IF(LEFT(G116,2)="峡山","坊子",IF(LEFT(G116,2)="滨海","寒亭",LEFT(G116,2)))) -> 寿光 | M116: =TEXT(B116,"mmdd") -> 0104 | N116: =VLOOKUP(I116,累计派单!A:O,15,0) -> dw3_jk_chuyanting | O116: =IF(LEN(J116)<2,0,DATEDIF(DATE(IF(MID(J116,9,2)="23",2023,2024),MID(J116,11,2),MID(J116,13,2)),B116,"d")) -> 24 | P116: =IF(O116=0,"无",IF(O116<8,"7天内",IF(O116<31,"30天内",IF(O116<61,"60天内",IF(O116<91,"90天内"))))) -> 30天内 | Q116: =VLOOKUP(I116,累计派单!A:O,13,0) -> 家客铁通潍坊寿光-台头乡镇装维组
A117: SD-db051-250104-930621-467 | B117: 2025-01-04 18:37:14 | C117: (家客)潍坊--重复投诉投诉督办通知-一级督办13573656737-202501040000636284 | D117: 普通区域--null-13573656737-业务受理宽带-次数0-202501040000636284 | E117: 202501040000636284# 宽带账号:13573656737; 联系电话：13573656737，问题类型：此工单为群障修复工单，根据群障全量闭环修复管理要求，为确保客户网络通畅，请装维人员跟进修复网络问题，谢谢！ 群障标题：公告。故障描述：陈家马村自然村主叫号码：13573656737.0;该号码仅供参考，请优先联系宽带账号。 | F117: 潍坊 | H117: 13573656737 | I117: SD-057-250104-475132-5978 | J117: 'SD-057-241024-865073-6590' | K117: 否 | L117: =IF(OR(LEFT(G117,2)="高新"),"奎文",IF(LEFT(G117,2)="峡山","坊子",IF(LEFT(G117,2)="滨海","寒亭",LEFT(G117,2)))) | M117: =TEXT(B117,"mmdd") -> 0104 | N117: =VLOOKUP(I117,累计派单!A:O,15,0) -> 0 | O117: =IF(LEN(J117)<2,0,DATEDIF(DATE(IF(MID(J117,9,2)="23",2023,2024),MID(J117,11,2),MID(J117,13,2)),B117,"d")) -> 72 | P117: =IF(O117=0,"无",IF(O117<8,"7天内",IF(O117<31,"30天内",IF(O117<61,"60天内",IF(O117<91,"90天内"))))) -> 90天内 | Q117: =VLOOKUP(I117,累计派单!A:O,13,0) -> 0
A118: SD-db051-250104-025916-474 | B118: 2025-01-04 18:47:38 | C118: (家客)潍坊-坊子区-重复投诉投诉督办通知-一级督办18866187698-202501040000644137 | D118: 80+普通-普通区域-坊子区-怡水家园-18866187698-500M-宽带上网投诉-次数0-202501040000644137 | E118: 202501040000644137#流程受理流水号：20250104184136188661876981195028 客户号码:18866187698 客户姓名:梁** 投诉地市:潍坊 来话流水:2025010418394946820858728 宽带账号:18866187698 宽带账号归属地市:潍坊 宽带账号归属区县:峡山区 故障地址:潍坊峡山区太堡庄街道（太堡庄）兴峡路文华苑小区文华苑二期10号********* 联系电话:18866187698 联系人:先生 工单紧急程度:非常紧急 是否有升级投诉倾向:否 是否重复投诉:否 是否携转意向:否 是否投诉倾向:否 是否智能网关:智能网关 当前是否在线:是 接入方式:FTTH 端到端诊断结果:客户侧设备问题（新增） 是否质差终端:无质差信息 光功率:-19.87 故障大类:宽带/电视 故障细类:网速慢/上网掉线(专席) 携转原因: 故障时间:2025-01-04 18:40:23 具体故障现象:网速慢卡顿，客户来电表示宽带网速慢线上不方便操作要求解决问题，表示工作人员已经测过网速正常但是更新软件下载软件还是慢 客户其他诉求: ;宽带小区$[怡水家园]$ | F118: 潍坊 | G118: 坊子区 | H118: 18866187698 | I118: SD-057-250104-179240-6076 | J118: 'SD-057-241228-807631-1753' | K118: 否 | L118: =IF(OR(LEFT(G118,2)="高新"),"奎文",IF(LEFT(G118,2)="峡山","坊子",IF(LEFT(G118,2)="滨海","寒亭",LEFT(G118,2)))) -> 坊子 | M118: =TEXT(B118,"mmdd") -> 0104 | N118: =VLOOKUP(I118,累计派单!A:O,15,0) -> dw3_jk_zhongzilong | O118: =IF(LEN(J118)<2,0,DATEDIF(DATE(IF(MID(J118,9,2)="23",2023,2024),MID(J118,11,2),MID(J118,13,2)),B118,"d")) -> 7 | P118: =IF(O118=0,"无",IF(O118<8,"7天内",IF(O118<31,"30天内",IF(O118<61,"60天内",IF(O118<91,"90天内"))))) -> 7天内 | Q118: =VLOOKUP(I118,累计派单!A:O,13,0) -> 家客铁通潍坊坊子-太保庄乡镇装维组
A119: SD-db051-250104-972104-489 | B119: 2025-01-04 19:07:31 | C119: (家客)潍坊-安丘市-重复投诉投诉督办通知-一级督办15264638823-202501040000656822 | D119: 80+银卡-普通区域-安丘市-周家院庄-15264638823-300M-业务受理宽带-次数0-202501040000656822 | E119: 202501040000656822# 宽带账号:15264638823; 联系电话：15264638823，问题类型：此工单为群障修复工单，根据群障全量闭环修复管理要求，为确保客户网络通畅，请装维人员跟进修复网络问题，谢谢！ 群障标题：公告。故障描述：主干光纤断或OLT检测不到预期的光信号（LOS）主叫号码：15264638823.0;该号码仅供参考，请优先联系宽带账号。 | F119: 潍坊 | G119: 安丘市 | H119: 15264638823 | I119: SD-057-250104-035927-6243 | J119: 'SD-057-241130-846013-7818' | K119: 否 | L119: =IF(OR(LEFT(G119,2)="高新"),"奎文",IF(LEFT(G119,2)="峡山","坊子",IF(LEFT(G119,2)="滨海","寒亭",LEFT(G119,2)))) -> 安丘 | M119: =TEXT(B119,"mmdd") -> 0104 | N119: =VLOOKUP(I119,累计派单!A:O,15,0) -> dw3_jk_wangyonglinaq | O119: =IF(LEN(J119)<2,0,DATEDIF(DATE(IF(MID(J119,9,2)="23",2023,2024),MID(J119,11,2),MID(J119,13,2)),B119,"d")) -> 35 | P119: =IF(O119=0,"无",IF(O119<8,"7天内",IF(O119<31,"30天内",IF(O119<61,"60天内",IF(O119<91,"90天内"))))) -> 60天内 | Q119: =VLOOKUP(I119,累计派单!A:O,13,0) -> 家客铁通潍坊安丘-贾戈乡镇装维组
A120: SD-db051-250104-613254-517 | B120: 2025-01-04 20:02:17 | C120: (家客)潍坊-坊子区-重复投诉投诉督办通知-一级督办18006469985-20250104200111X714445820 | D120: 【调研】-普通区域-坊子区-隆鑫盛景-18006469985-1000M-宽带上网投诉-次数0-20250104200111X714445820 | E120: 流程受理流水号：20250104195107180064699851209056 客户号码:18006469985 客户姓名:李* 投诉地市:潍坊 来话流水:2025010419572357520844078 宽带账号:18006469985 宽带账号归属地市:潍坊 宽带账号归属区县:坊子区 故障地址:潍坊坊子区坊子新区龙泉街隆鑫盛景潍坊坊子隆鑫盛景11号楼2单元601室 联系电话:15726362620 联系人:先生/女士 工单紧急程度:非常紧急 是否有升级投诉倾向:是 是否重复投诉:否 是否携转意向:否 是否投诉倾向:否 是否智能网关:智能网关 当前是否在线:是 接入方式:FTTH 端到端诊断结果:客户侧设备问题（新增） 是否质差终端:无质差信息 光功率:-18.26 故障大类:宽带/电视 故障细类:网速慢/上网掉线(专席) 携转原因: 故障时间:2025-01-04 19:58:57 具体故障现象:客户反应网络频繁掉线，从安装上就这样，反应师傅一直木有给其维修好，客户有升级投诉意向，请尽快给其联系处理，谢谢 客户其他诉求: | F120: 潍坊 | G120: 坊子区 | H120: 18006469985 | I120: SD-057-250104-401972-6643 | J120: 'SD-057-241205-294057-981' | K120: 否 | L120: =IF(OR(LEFT(G120,2)="高新"),"奎文",IF(LEFT(G120,2)="峡山","坊子",IF(LEFT(G120,2)="滨海","寒亭",LEFT(G120,2)))) -> 坊子 | M120: =TEXT(B120,"mmdd") -> 0104 | N120: =VLOOKUP(I120,累计派单!A:O,15,0) -> dw3_jk_fzzhangyan | O120: =IF(LEN(J120)<2,0,DATEDIF(DATE(IF(MID(J120,9,2)="23",2023,2024),MID(J120,11,2),MID(J120,13,2)),B120,"d")) -> 30 | P120: =IF(O120=0,"无",IF(O120<8,"7天内",IF(O120<31,"30天内",IF(O120<61,"60天内",IF(O120<91,"90天内"))))) -> 30天内 | Q120: =VLOOKUP(I120,累计派单!A:O,13,0) -> 家客铁通潍坊坊子-凤凰城区装维组
A121: SD-db051-250104-036158-539 | B121: 2025-01-04 20:47:04 | C121: (家客)潍坊-坊子区-重复投诉投诉督办通知-一级督办13906362992-20250104204422X662381719 | D121: 普通区域-坊子区-韩尔庄王家社区-13906362992-300M-宽带上网投诉-次数0-20250104204422X662381719 | E121: 流程受理流水号：20250104203943139063629921216502 客户号码:13906362992 客户姓名:王** 投诉地市:潍坊 来话流水:2025010420384988420845357 宽带账号:13906362992 宽带账号归属地市:潍坊 宽带账号归属区县:坊子区 故障地址:潍坊坊子区坊子新区龙泉街韩尔庄王家社区3号楼 联系电话:13906362992 联系人:先生/女士 工单紧急程度:一般 是否有升级投诉倾向:否 是否重复投诉:否 是否携转意向:否 是否投诉倾向:否 是否智能网关:智能网关 当前是否在线:否 接入方式:FTTH 端到端诊断结果:光猫掉电 是否质差终端:无质差信息 光功率:无 故障大类:宽带/电视 故障细类:宽带无法上网(专席) 携转原因: 故障时间:2025-01-04 20:46:14 具体故障现象:光猫灯正常但电脑手机无法上网， 客户其他诉求: | F121: 潍坊 | G121: 坊子区 | H121: 13906362992 | I121: SD-057-250104-894170-6915 | J121: 'SD-057-241217-457816-5047' | K121: 否 | L121: =IF(OR(LEFT(G121,2)="高新"),"奎文",IF(LEFT(G121,2)="峡山","坊子",IF(LEFT(G121,2)="滨海","寒亭",LEFT(G121,2)))) -> 坊子 | M121: =TEXT(B121,"mmdd") -> 0104 | N121: =VLOOKUP(I121,累计派单!A:O,15,0) -> dw3_jk_fangtizhuang | O121: =IF(LEN(J121)<2,0,DATEDIF(DATE(IF(MID(J121,9,2)="23",2023,2024),MID(J121,11,2),MID(J121,13,2)),B121,"d")) -> 18 | P121: =IF(O121=0,"无",IF(O121<8,"7天内",IF(O121<31,"30天内",IF(O121<61,"60天内",IF(O121<91,"90天内"))))) -> 30天内 | Q121: =VLOOKUP(I121,累计派单!A:O,13,0) -> 家客铁通潍坊坊子-凤凰城区装维组
A122: SD-db051-250104-126735-571 | B122: 2025-01-04 23:36:28 | C122: (家客)潍坊-奎文区-重复投诉投诉督办通知-一级督办13402261155-202501040000715056 | D122: 【调研】-80+金卡-普通区域-奎文区-吉祥家园-13402261155-1000M-宽带上网投诉-次数0-202501040000715056 | E122: 202501040000715056#【已关注中国移动10086微信公众号】流程受理流水号：20250104233431134022611551222886 客户号码:13402261155 客户姓名:尤* 投诉地市:潍坊 来话流水:2025010423341338920825076 宽带账号:13402261155 宽带账号归属地市:潍坊 宽带账号归属区县:奎文区 故障地址:潍坊奎文区北苑街道乐川街吉祥家园18号楼********* 联系电话:13402261155 联系人:先生 工单紧急程度:非常紧急 是否有升级投诉倾向:否 是否重复投诉:否 是否携转意向:否 是否投诉倾向:否 是否智能网关:智能网关 当前是否在线:否 接入方式:FTTH 端到端诊断结果:大面积故障 是否质差终端:无质差信息 光功率:无 故障大类:宽带/电视 故障细类:宽带无法上网 携转原因: 故障时间:2025-01-04 23:37:00 具体故障现象:光猫亮红灯，要求补偿 客户其他诉求:要求补偿 ;宽带小区$[吉祥家园]$ | F122: 潍坊 | G122: 奎文区 | H122: 13402261155 | I122: SD-057-250104-526308-7253 | J122: 'SD-057-250102-871502-6389' | K122: 否 | L122: =IF(OR(LEFT(G122,2)="高新"),"奎文",IF(LEFT(G122,2)="峡山","坊子",IF(LEFT(G122,2)="滨海","寒亭",LEFT(G122,2)))) -> 奎文 | M122: =TEXT(B122,"mmdd") -> 0104 | N122: =VLOOKUP(I122,累计派单!A:O,15,0) -> dw3_jk_zhangentao | O122: =IF(LEN(J122)<2,0,DATEDIF(DATE(IF(MID(J122,9,2)="23",2023,2024),MID(J122,11,2),MID(J122,13,2)),B122,"d")) -> 368 | P122: =IF(O122=0,"无",IF(O122<8,"7天内",IF(O122<31,"30天内",IF(O122<61,"60天内",IF(O122<91,"90天内"))))) -> FALSE | Q122: =VLOOKUP(I122,累计派单!A:O,13,0) -> 家客铁通潍坊奎文-鸢飞路城区装维组
A123: SD-db051-250105-786931-17 | B123: 2025-01-05 08:45:05 | C123: (家客)潍坊-诸城市-重复投诉投诉督办通知-一级督办15165660006-202501050000099838 | D123: 80+金卡-普通区域-诸城市-阳光河畔-15165660006-1000M-业务受理宽带-次数0-202501050000099838 | E123: 202501050000099838#15165660006客户来电称家里的宽带无法上网，要求核实具体原因。联系人：先生 联系电话：本机 录音流水：2025010508405104320892568 | F123: 潍坊 | G123: 诸城市 | H123: 15165660006 | I123: SD-057-250105-796104-230 | J123: 'SD-057-241229-698547-553' | K123: 是 | L123: =IF(OR(LEFT(G123,2)="高新"),"奎文",IF(LEFT(G123,2)="峡山","坊子",IF(LEFT(G123,2)="滨海","寒亭",LEFT(G123,2)))) -> 诸城 | M123: =TEXT(B123,"mmdd") -> 0105 | N123: =VLOOKUP(I123,累计派单!A:O,15,0) -> dw3_jk_lihaodi | O123: =IF(LEN(J123)<2,0,DATEDIF(DATE(IF(MID(J123,9,2)="23",2023,2024),MID(J123,11,2),MID(J123,13,2)),B123,"d")) -> 7 | P123: =IF(O123=0,"无",IF(O123<8,"7天内",IF(O123<31,"30天内",IF(O123<61,"60天内",IF(O123<91,"90天内"))))) -> 7天内 | Q123: =VLOOKUP(I123,累计派单!A:O,13,0) -> 家客铁通潍坊诸城-兴华西路城区装维组
A124: SD-db051-250105-952607-27 | B124: 2025-01-05 08:57:08 | C124: (家客)潍坊-奎文区-重复投诉投诉督办通知-一级督办18678020483-202501050000111970 | D124: 普通区域-奎文区-奎文区宏伟北区-18678020483-500M-业务受理宽带-次数0-202501050000111970 | E124: 202501050000111970# 宽带账号:18678020483; 联系电话：18678020483，问题类型：此工单为群障修复工单，根据群障全量闭环修复管理要求，为确保客户网络通畅，请装维人员跟进修复网络问题，谢谢！ 群障标题：公告。故障描述：潍坊奎文区奎文区宏伟北区光缆故障，预估24小时恢复，请帮忙拦截,如有需要请联系片区装维师傅朱文杰15706366520主叫号码：13953660016.0;该号码仅供参考，请优先联系宽带账号。 | F124: 潍坊 | G124: 奎文区 | H124: 18678020483 | I124: SD-057-250105-752491-370 | J124: 'SD-057-250104-479513-6872' | K124: 是 | L124: =IF(OR(LEFT(G124,2)="高新"),"奎文",IF(LEFT(G124,2)="峡山","坊子",IF(LEFT(G124,2)="滨海","寒亭",LEFT(G124,2)))) -> 奎文 | M124: =TEXT(B124,"mmdd") -> 0105 | N124: =VLOOKUP(I124,累计派单!A:O,15,0) -> dw3_jk_zhuwenjie | O124: =IF(LEN(J124)<2,0,DATEDIF(DATE(IF(MID(J124,9,2)="23",2023,2024),MID(J124,11,2),MID(J124,13,2)),B124,"d")) -> 367 | P124: =IF(O124=0,"无",IF(O124<8,"7天内",IF(O124<31,"30天内",IF(O124<61,"60天内",IF(O124<91,"90天内"))))) -> FALSE | Q124: =VLOOKUP(I124,累计派单!A:O,13,0) -> 家客铁通潍坊奎文-潍州路城区装维组
A125: SD-db051-250105-270936-30 | B125: 2025-01-05 08:57:41 | C125: (家客)潍坊-青州市-重复投诉投诉督办通知-一级督办15006692995-202501050000113371 | D125: 【调研】-80+银卡-普通区域-青州市-烟厂东宿舍-15006692995-300M-业务受理宽带-次数0-202501050000113371 | E125: 202501050000113371#【已关注中国移动10086微信公众号】 宽带账号:15006692995; 联系电话：15006692995，问题类型：此工单为群障修复工单，根据群障全量闭环修复管理要求，为确保客户网络通畅，请装维人员跟进修复网络问题，谢谢！ 群障标题：公告。故障描述：潍坊青州市烟厂东宿舍光缆故障，预估24小时恢复，请帮忙拦截,如有需要请联系片区装维师傅魏守波15706307630主叫号码：15253695756.0;该号码仅供参考，请优先联系宽带账号。 | F125: 潍坊 | G125: 青州市 | H125: 15006692995 | I125: SD-057-250105-628735-386 | J125: 'SD-057-241129-589641-5993' | K125: 是 | L125: =IF(OR(LEFT(G125,2)="高新"),"奎文",IF(LEFT(G125,2)="峡山","坊子",IF(LEFT(G125,2)="滨海","寒亭",LEFT(G125,2)))) -> 青州 | M125: =TEXT(B125,"mmdd") -> 0105 | N125: =VLOOKUP(I125,累计派单!A:O,15,0) -> dw3_jk_weishoubo | O125: =IF(LEN(J125)<2,0,DATEDIF(DATE(IF(MID(J125,9,2)="23",2023,2024),MID(J125,11,2),MID(J125,13,2)),B125,"d")) -> 37 | P125: =IF(O125=0,"无",IF(O125<8,"7天内",IF(O125<31,"30天内",IF(O125<61,"60天内",IF(O125<91,"90天内"))))) -> 60天内 | Q125: =VLOOKUP(I125,累计派单!A:O,13,0) -> 家客铁通潍坊青州-古城城区装维组
A126: SD-db051-250105-195387-31 | B126: 2025-01-05 08:57:59 | C126: (家客)潍坊-高密市-重复投诉投诉督办通知-一级督办13335250709-202501050000112407 | D126: 【重投】-普通区域-高密市-八里庄-13335250709-200M-宽带上网投诉-次数0-202501050000112407 | E126: 202501050000112407#流程受理流水号：20250105085624133352507091009072 客户号码:13335250709 客户姓名:李** 投诉地市:潍坊 来话流水:2025010508550375420899441 宽带账号:13335250709 宽带账号归属地市:潍坊 宽带账号归属区县:高密市 故障地址:潍坊高密市密水街道八里庄行政村八里庄高密八里庄李严亮36号箱********* 联系电话:13335250709 联系人:先生/女士 工单紧急程度:非常紧急 是否有升级投诉倾向:否 是否重复投诉:否 是否携转意向:否 是否投诉倾向:否 是否智能网关:智能网关 当前是否在线:是 接入方式:FTTH 端到端诊断结果:客户侧设备问题（新增） 是否质差终端:无质差信息 光功率:-18.56 故障大类:宽带/电视 故障细类:网速慢/上网掉线(专席) 携转原因: 故障时间:2025-01-05 08:56:40 具体故障现象:频繁掉线，有提及工信部投诉。 客户其他诉求: ;宽带小区$[八里庄]$ | F126: 潍坊 | G126: 高密市 | H126: 13335250709 | I126: SD-057-250105-519846-388 | J126: 'SD-057-241212-680549-3997' | K126: 是 | L126: =IF(OR(LEFT(G126,2)="高新"),"奎文",IF(LEFT(G126,2)="峡山","坊子",IF(LEFT(G126,2)="滨海","寒亭",LEFT(G126,2)))) -> 高密 | M126: =TEXT(B126,"mmdd") -> 0105 | N126: =VLOOKUP(I126,累计派单!A:O,15,0) -> dw3_jk_liuchaogm | O126: =IF(LEN(J126)<2,0,DATEDIF(DATE(IF(MID(J126,9,2)="23",2023,2024),MID(J126,11,2),MID(J126,13,2)),B126,"d")) -> 24 | P126: =IF(O126=0,"无",IF(O126<8,"7天内",IF(O126<31,"30天内",IF(O126<61,"60天内",IF(O126<91,"90天内"))))) -> 30天内 | Q126: =VLOOKUP(I126,累计派单!A:O,13,0) -> 家客铁通潍坊高密-朝阳城区装维组
A127: SD-db051-250105-918047-74 | B127: 2025-01-05 09:42:34 | C127: (家客)潍坊-奎文区-重复投诉投诉督办通知-一级督办18765103358-202501050000122125 | D127: 【调研】-80+银卡-普通区域-奎文区-东方太阳城-18765103358-300M-魔百和投诉-次数0-202501050000122125 | E127: 202501050000122125#流程受理流水号：20250105090307187651033581011552 客户号码:18765103358 客户姓名:吕** 投诉地市:潍坊 来话流水:2025010508524417120880709 宽带账号:18765103358 宽带账号归属地市:潍坊 宽带账号归属区县:奎文区 故障地址:潍坊奎文区北苑街道虞河路东方太阳城7号楼********* 联系电话:18765103358 联系人:先生/女士 工单紧急程度:一般 是否有升级投诉倾向:否 是否重复投诉:否 是否携转意向:否 是否投诉倾向:否 携转原因: 提单模板:客户来电反映观看移动高清电视时，在有移动高清影视黄金会员时所有VIP节目都无法观看，客户不认可，请协助处理，谢谢。 ;宽带小区$[东方太阳城]$ | F127: 潍坊 | G127: 奎文区 | H127: 18765103358 | I127: SD-057-250105-215948-879 | J127: 'SD-057-241114-976342-1811' | K127: 是 | L127: =IF(OR(LEFT(G127,2)="高新"),"奎文",IF(LEFT(G127,2)="峡山","坊子",IF(LEFT(G127,2)="滨海","寒亭",LEFT(G127,2)))) -> 奎文 | M127: =TEXT(B127,"mmdd") -> 0105 | N127: =VLOOKUP(I127,累计派单!A:O,15,0) -> dw3_jk_renfeng | O127: =IF(LEN(J127)<2,0,DATEDIF(DATE(IF(MID(J127,9,2)="23",2023,2024),MID(J127,11,2),MID(J127,13,2)),B127,"d")) -> 52 | P127: =IF(O127=0,"无",IF(O127<8,"7天内",IF(O127<31,"30天内",IF(O127<61,"60天内",IF(O127<91,"90天内"))))) -> 60天内 | Q127: =VLOOKUP(I127,累计派单!A:O,13,0) -> 家客铁通潍坊奎文-鸢飞路城区装维组
A128: SD-db051-250105-947562-81 | B128: 2025-01-05 09:47:14 | C128: (家客)潍坊-高密市-重复投诉投诉督办通知-一级督办19806246598-20250105094513X513966794 | D128: 普通区域-高密市-尚家庄自然村-19806246598-200M-宽带上网投诉-次数0-20250105094513X513966794 | E128: 【农村网络投诉】流程受理流水号：20250105094200198062465981025972 客户号码:19806246598 客户姓名:杜** 投诉地市:潍坊 来话流水:2025010509401897620863085 宽带账号:19806246598 宽带账号归属地市:潍坊 宽带账号归属区县:高密市 故障地址:潍坊高密市井沟镇南李家村鹏益养殖场********* 联系电话:15066275500 联系人:先生/女士 工单紧急程度:一般 是否有升级投诉倾向:否 是否重复投诉:否 是否携转意向:否 是否投诉倾向:否 是否智能网关:智能网关 当前是否在线:否 接入方式:FTTH 端到端诊断结果:状态正常 是否质差终端:无质差信息 光功率:无 故障大类:宽带/电视 故障细类:宽带无法上网(专席) 携转原因: 故障时间:2025-01-05 09:43:04 具体故障现象:光猫亮红灯， 客户其他诉求: | F128: 潍坊 | G128: 高密市 | H128: 19806246598 | I128: SD-057-250105-130659-924 | J128: 'SD-057-241210-207516-3437' | K128: 是 | L128: =IF(OR(LEFT(G128,2)="高新"),"奎文",IF(LEFT(G128,2)="峡山","坊子",IF(LEFT(G128,2)="滨海","寒亭",LEFT(G128,2)))) -> 高密 | M128: =TEXT(B128,"mmdd") -> 0105 | N128: =VLOOKUP(I128,累计派单!A:O,15,0) -> dw3_jk_liujun1 | O128: =IF(LEN(J128)<2,0,DATEDIF(DATE(IF(MID(J128,9,2)="23",2023,2024),MID(J128,11,2),MID(J128,13,2)),B128,"d")) -> 26 | P128: =IF(O128=0,"无",IF(O128<8,"7天内",IF(O128<31,"30天内",IF(O128<61,"60天内",IF(O128<91,"90天内"))))) -> 30天内 | Q128: =VLOOKUP(I128,累计派单!A:O,13,0) -> 家客铁通潍坊高密-井沟乡镇装维组
A129: SD-db051-250105-593614-83 | B129: 2025-01-05 09:47:25 | C129: (家客)潍坊-坊子区-重复投诉投诉督办通知-一级督办15163613448-20250105094520X520967600 | D129: 80+金卡-FTTR-普通区域-坊子区-坊子临街商铺-后埠头村沿街-15163613448-1000M-宽带上网投诉-次数0-20250105094520X520967600 | E129: 【农村网络投诉】流程受理流水号：20250105094427151636134481026888 客户号码:15163613448 客户姓名:何** 投诉地市:潍坊 来话流水:2025010509434362920801669 宽带账号:15163613448 宽带账号归属地市:潍坊 宽带账号归属区县:坊子区 故障地址:潍坊坊子区坊子老区坊子临街商铺-后埠头村沿街行政村坊子临街商铺-后埠头村沿街坊子临街商铺-后埠头村沿街4号箱********* 联系电话:15163613448 联系人:何女士 工单紧急程度:紧急 是否有升级投诉倾向:否 是否重复投诉:否 是否携转意向:否 是否投诉倾向:否 是否智能网关:智能网关 当前是否在线:是 接入方式:FTTH 端到端诊断结果:客户侧设备问题（新增） 是否质差终端:无质差信息 光功率:-21.93 故障大类:宽带/电视 故障细类:宽带无法上网(专席) 携转原因: 故障时间:2025-01-05 09:44:47 具体故障现象:提示网络无法连接， 客户其他诉求:已自行重启设备也没有恢复，客户非常着急，要求师傅加急给予解决处理，谢谢 | F129: 潍坊 | G129: 坊子区 | H129: 15163613448 | I129: SD-057-250105-987613-927 | J129: 'SD-057-241015-143795-3776' | K129: 是 | L129: =IF(OR(LEFT(G129,2)="高新"),"奎文",IF(LEFT(G129,2)="峡山","坊子",IF(LEFT(G129,2)="滨海","寒亭",LEFT(G129,2)))) -> 坊子 | M129: =TEXT(B129,"mmdd") -> 0105 | N129: =VLOOKUP(I129,累计派单!A:O,15,0) -> dw3_jk_wangshumingfz | O129: =IF(LEN(J129)<2,0,DATEDIF(DATE(IF(MID(J129,9,2)="23",2023,2024),MID(J129,11,2),MID(J129,13,2)),B129,"d")) -> 82 | P129: =IF(O129=0,"无",IF(O129<8,"7天内",IF(O129<31,"30天内",IF(O129<61,"60天内",IF(O129<91,"90天内"))))) -> 90天内 | Q129: =VLOOKUP(I129,累计派单!A:O,13,0) -> 家客铁通潍坊坊子-坊城城区装维组
... A265: SD-db051-250109-796230-176 | B265: 2025-01-09 12:23:11 | C265: (家客)潍坊-奎文区-重复投诉投诉督办通知-一级督办15065616628-20250109122059X459607574 | D265: 80+金卡-普通区域-奎文区-金福苑A区-15065616628-1000M-宽带上网投诉-次数0-20250109122059X459607574 | E265: 流程受理流水号：20250109122014150656166281064420 客户号码:15065616628 客户姓名:徐** 投诉地市:潍坊 来话流水:2025010912192307320853322 宽带账号:15065616628 宽带账号归属地市:潍坊 宽带账号归属区县:高新 故障地址:潍坊高新高新城区福寿街金福苑A区1号楼********* 联系电话:15065616628 联系人:先生/女士 工单紧急程度:非常紧急 是否有升级投诉倾向:否 是否重复投诉:否 是否携转意向:否 是否投诉倾向:否 是否智能网关:智能网关 当前是否在线:是 接入方式:FTTH 端到端诊断结果:客户侧设备问题（新增） 是否质差终端:无质差信息 光功率:-21.36 故障大类:宽带/电视 故障细类:网速慢/上网掉线(专席) 携转原因: 故障时间:2025-01-09 12:22:52 具体故障现象:家庭WiFi信号弱， 客户其他诉求: | F265: 潍坊 | G265: 奎文区 | H265: 15065616628 | I265: SD-057-250109-862759-2191 | J265: 'SD-057-241224-437621-2546' | K265: 否 | L265: =IF(OR(LEFT(G265,2)="高新"),"奎文",IF(LEFT(G265,2)="峡山","坊子",IF(LEFT(G265,2)="滨海","寒亭",LEFT(G265,2)))) -> 奎文 | M265: =TEXT(B265,"mmdd") -> 0109 | N265: =VLOOKUP(I265,累计派单!A:O,15,0) -> dw3_jk_wangxingang | O265: =IF(LEN(J265)<2,0,DATEDIF(DATE(IF(MID(J265,9,2)="23",2023,2024),MID(J265,11,2),MID(J265,13,2)),B265,"d")) -> 16 | P265: =IF(O265=0,"无",IF(O265<8,"7天内",IF(O265<31,"30天内",IF(O265<61,"60天内",IF(O265<91,"90天内"))))) -> 30天内 | Q265: =VLOOKUP(I265,累计派单!A:O,13,0) -> 家客铁通潍坊奎文-北宫街城区装维组
A266: SD-db051-250109-476583-199 | B266: 2025-01-09 12:52:47 | C266: (家客)潍坊--重复投诉投诉督办通知-一级督办13026556766-202501090000317819 | D266: 普通区域--null-13026556766-宽带上网投诉-次数0-202501090000317819 | E266: 202501090000317819#流程受理流水号：20250109125044130265567661070070 客户号码:13026556766 客户姓名:孙** 投诉地市:潍坊 来话流水:2025010912482973420883981 宽带账号:13026556766 账号归属区县:昌邑市北海路信达通讯服务部（社区） 联系电话:13793621967 联系人:先生/女士 宽带地址:潍坊 工单紧急程度:紧急 是否投诉倾向:否 是否重复投诉:否 是否携转意向:否 是否有升级投诉倾向:否 *业务名称:业务融合开机流程宽带 投诉内容:手机号码：13026556766，【问题描述】客户已办理宽带业务，有开通单，要求装维尽快联系上门，请处理，谢谢。联系电话：13793621967，联系人：先生/女士，录音流水号：2025010912482973420883981。受理明细：531920062399999999。 在途开通单信息：536250103792603030，13026556766，2025-01-03 16:31:13，业务融合开机流程宽带，处理中，黄单扩容 是否到厅:否 业务名称:业务融合开机流程宽带 ;宽带小区$[null]$ | F266: 潍坊 | H266: 13026556766 | I266: SD-057-250109-093452-2404 | J266: 'SD-057-250106-268741-2030' | K266: 否 | L266: =IF(OR(LEFT(G266,2)="高新"),"奎文",IF(LEFT(G266,2)="峡山","坊子",IF(LEFT(G266,2)="滨海","寒亭",LEFT(G266,2)))) | M266: =TEXT(B266,"mmdd") -> 0109 | N266: =VLOOKUP(I266,累计派单!A:O,15,0) -> 0 | O266: =IF(LEN(J266)<2,0,DATEDIF(DATE(IF(MID(J266,9,2)="23",2023,2024),MID(J266,11,2),MID(J266,13,2)),B266,"d")) -> 369 | P266: =IF(O266=0,"无",IF(O266<8,"7天内",IF(O266<31,"30天内",IF(O266<61,"60天内",IF(O266<91,"90天内"))))) -> FALSE | Q266: =VLOOKUP(I266,累计派单!A:O,13,0) -> 0
A267: SD-db051-250109-724538-202 | B267: 2025-01-09 12:57:15 | C267: (家客)潍坊-昌邑市-重复投诉投诉督办通知-一级督办15165666265-202501090000320047 | D267: 普通区域-昌邑市-潍水蓝湾-15165666265-300M-业务受理宽带-次数0-202501090000320047 | E267: 202501090000320047# 宽带账号:15165666265; 联系电话：15165666265，问题类型：此工单为群障修复工单，根据群障全量闭环修复管理要求，为确保客户网络通畅，请装维人员跟进修复网络问题，谢谢！ 群障标题：公告。故障描述：潍坊昌邑市潍水蓝湾光缆故障，预估24小时恢复，请帮忙拦截,如有需要请联系片区装维师傅陈建超15706307114主叫号码：13165262283.0;该号码仅供参考，请优先联系宽带账号。 | F267: 潍坊 | G267: 昌邑市 | H267: 15165666265 | I267: SD-057-250109-076154-2445 | J267: 'SD-057-241130-034619-5949' | K267: 否 | L267: =IF(OR(LEFT(G267,2)="高新"),"奎文",IF(LEFT(G267,2)="峡山","坊子",IF(LEFT(G267,2)="滨海","寒亭",LEFT(G267,2)))) -> 昌邑 | M267: =TEXT(B267,"mmdd") -> 0109 | N267: =VLOOKUP(I267,累计派单!A:O,15,0) -> dw3_jk_donghuiqingcy | O267: =IF(LEN(J267)<2,0,DATEDIF(DATE(IF(MID(J267,9,2)="23",2023,2024),MID(J267,11,2),MID(J267,13,2)),B267,"d")) -> 40 | P267: =IF(O267=0,"无",IF(O267<8,"7天内",IF(O267<31,"30天内",IF(O267<61,"60天内",IF(O267<91,"90天内"))))) -> 60天内 | Q267: =VLOOKUP(I267,累计派单!A:O,13,0) -> 家客铁通潍坊昌邑-城北城区装维组
A268: SD-db051-250109-863572-234 | B268: 2025-01-09 13:44:07 | C268: (家客)潍坊-寿光市-重复投诉投诉督办通知-一级督办18815365857-20250109134123X283965744 | D268: 【调研】-80+白金-普通区域-寿光市-经委家属院-18815365857-1000M-宽带上网投诉-次数0-20250109134123X283965744 | E268: 流程受理流水号：20250109133949188153658571078288 客户号码:18815365857 客户姓名:刘* 投诉地市:潍坊 来话流水:2025010913392405420865677 宽带账号:18815365857 宽带账号归属地市:潍坊 宽带账号归属区县:寿光市 故障地址:潍坊寿光市圣城街道公园街经委家属院南楼********* 联系电话:18815365857 联系人:先生/女士 工单紧急程度:非常紧急 是否有升级投诉倾向:否 是否重复投诉:否 是否携转意向:否 是否投诉倾向:否 是否智能网关:智能网关 当前是否在线:否 接入方式:FTTH 端到端诊断结果:状态正常 是否质差终端:无质差信息 光功率:无 故障大类:宽带/电视 故障细类:宽带无法上网 携转原因: 故障时间:2025-01-09 13:41:05 具体故障现象:光猫亮红灯， 客户其他诉求: | F268: 潍坊 | G268: 寿光市 | H268: 18815365857 | I268: SD-057-250109-107629-2772 | J268: 'SD-057-241231-789302-6754' | K268: 否 | L268: =IF(OR(LEFT(G268,2)="高新"),"奎文",IF(LEFT(G268,2)="峡山","坊子",IF(LEFT(G268,2)="滨海","寒亭",LEFT(G268,2)))) -> 寿光 | M268: =TEXT(B268,"mmdd") -> 0109 | N268: =VLOOKUP(I268,累计派单!A:O,15,0) -> dw3_jk_liubing | O268: =IF(LEN(J268)<2,0,DATEDIF(DATE(IF(MID(J268,9,2)="23",2023,2024),MID(J268,11,2),MID(J268,13,2)),B268,"d")) -> 9 | P268: =IF(O268=0,"无",IF(O268<8,"7天内",IF(O268<31,"30天内",IF(O268<61,"60天内",IF(O268<91,"90天内"))))) -> 30天内 | Q268: =VLOOKUP(I268,累计派单!A:O,13,0) -> 家客铁通潍坊寿光-市中城区装维组
A269: SD-db051-250109-826035-250 | B269: 2025-01-09 14:06:32 | C269: (家客)潍坊-青州市-重复投诉投诉督办通知-一级督办15216463133-202501090000357751 | D269: 普通区域-青州市-口埠村-15216463133-300M-宽带上网投诉-次数0-202501090000357751 | E269: 202501090000357751#宽带账号：15216463133；宽带地址：潍坊青州市何官镇口埠村口埠村49号箱（村东路北刘子庆)；客户来电反映移动高清无法正常观看，客户无法配合线上指导，要求师傅上门，请协助处理，谢谢！联系电话：15216463133***；联系人：先生；来电流水：2025010913541866620821589。 | F269: 潍坊 | G269: 青州市 | H269: 15216463133 | I269: SD-057-250109-013269-2982 | J269: 'SD-057-241011-018536-3798' | K269: 否 | L269: =IF(OR(LEFT(G269,2)="高新"),"奎文",IF(LEFT(G269,2)="峡山","坊子",IF(LEFT(G269,2)="滨海","寒亭",LEFT(G269,2)))) -> 青州 | M269: =TEXT(B269,"mmdd") -> 0109 | N269: =VLOOKUP(I269,累计派单!A:O,15,0) -> dw3_jk_dongbaoquan | O269: =IF(LEN(J269)<2,0,DATEDIF(DATE(IF(MID(J269,9,2)="23",2023,2024),MID(J269,11,2),MID(J269,13,2)),B269,"d")) -> 90 | P269: =IF(O269=0,"无",IF(O269<8,"7天内",IF(O269<31,"30天内",IF(O269<61,"60天内",IF(O269<91,"90天内"))))) -> 90天内 | Q269: =VLOOKUP(I269,累计派单!A:O,13,0) -> 家客铁通潍坊青州-何官乡镇装维组
A270: SD-db051-250109-790261-254 | B270: 2025-01-09 14:09:31 | C270: (家客)潍坊-安丘市-重复投诉投诉督办通知-一级督办15906366086-202501090000361660 | D270: 80+普通-普通区域-安丘市-东辛庄村自然村-15906366086-200M-宽带上网投诉-次数0-202501090000361660 | E270: 202501090000361660#流程受理流水号：20250109140814159063660861084527 客户号码:15906366086 客户姓名:宋** 投诉地市:潍坊 来话流水:2025010914075661220882382 宽带账号:15906366086 宽带账号归属地市:潍坊 宽带账号归属区县:安丘市 故障地址:潍坊安丘市临浯镇东辛庄村东辛庄村苑培章0号楼********* 联系电话:15906366086 联系人:先生/女士 工单紧急程度:一般 是否有升级投诉倾向:否 是否重复投诉:否 是否携转意向:否 是否投诉倾向:否 是否智能网关:非智能网关 当前是否在线:是 接入方式:FTTH 端到端诊断结果:客户侧设备问题 是否质差终端:是 光功率:无 故障大类:宽带/电视 故障细类:宽带无法上网 携转原因: 故障时间:2025-01-09 14:08:57 具体故障现象:光猫亮红灯， 客户其他诉求:客户侧为质差终端，要求上门更换终端并一并处理故障问题。 | F270: 潍坊 | G270: 安丘市 | H270: 15906366086 | I270: SD-057-250109-520987-3022 | J270: 'SD-057-241127-897504-4168' | K270: 否 | L270: =IF(OR(LEFT(G270,2)="高新"),"奎文",IF(LEFT(G270,2)="峡山","坊子",IF(LEFT(G270,2)="滨海","寒亭",LEFT(G270,2)))) -> 安丘 | M270: =TEXT(B270,"mmdd") -> 0109 | N270: =VLOOKUP(I270,累计派单!A:O,15,0) -> dw3_jk_daijiaoyunaq | O270: =IF(LEN(J270)<2,0,DATEDIF(DATE(IF(MID(J270,9,2)="23",2023,2024),MID(J270,11,2),MID(J270,13,2)),B270,"d")) -> 43 | P270: =IF(O270=0,"无",IF(O270<8,"7天内",IF(O270<31,"30天内",IF(O270<61,"60天内",IF(O270<91,"90天内"))))) -> 60天内 | Q270: =VLOOKUP(I270,累计派单!A:O,13,0) -> 家客铁通潍坊安丘-景芝乡镇装维组
A271: SD-db051-250109-305972-272 | B271: 2025-01-09 14:41:07 | C271: (家客)潍坊-寿光市-重复投诉投诉督办通知-一级督办13806477559-202501090000388512 | D271: 【调研】-80+白金-普通区域-寿光市-魏家-13806477559-300M-宽带上网投诉-次数0-202501090000388512 | E271: 202501090000388512#流程受理流水号：20250109144017138064775591092195 客户号码:13806477559 客户姓名:魏** 投诉地市:潍坊 来话流水:2025010914393321520813052 宽带账号:13806477559 宽带账号归属地市:潍坊 宽带账号归属区县:寿光市 故障地址:潍坊寿光市纪台镇魏家魏家11号箱********* 联系电话:15166369880 联系人:先生/女士 工单紧急程度:非常紧急 是否有升级投诉倾向:否 是否重复投诉:否 是否携转意向:否 是否投诉倾向:否 是否智能网关:智能网关 当前是否在线:是 接入方式:FTTH 端到端诊断结果:客户侧设备问题 是否质差终端:是 光功率:-15.18 故障大类:宽带/电视 故障细类:移动高清电视故障 携转原因: 故障时间:2025-01-09 14:40:30 魔百和单播/组播:单播 具体故障现象:机顶盒无法开机， 客户其他诉求:客户侧为质差终端，要求上门更换终端并一并处理故障问题。 | F271: 潍坊 | G271: 寿光市 | H271: 13806477559 | I271: SD-057-250109-293761-3260 | J271: 'SD-057-241103-207534-5550' | K271: 否 | L271: =IF(OR(LEFT(G271,2)="高新"),"奎文",IF(LEFT(G271,2)="峡山","坊子",IF(LEFT(G271,2)="滨海","寒亭",LEFT(G271,2)))) -> 寿光 | M271: =TEXT(B271,"mmdd") -> 0109 | N271: =VLOOKUP(I271,累计派单!A:O,15,0) -> dw3_jk_lichuidong | O271: =IF(LEN(J271)<2,0,DATEDIF(DATE(IF(MID(J271,9,2)="23",2023,2024),MID(J271,11,2),MID(J271,13,2)),B271,"d")) -> 67 | P271: =IF(O271=0,"无",IF(O271<8,"7天内",IF(O271<31,"30天内",IF(O271<61,"60天内",IF(O271<91,"90天内"))))) -> 90天内 | Q271: =VLOOKUP(I271,累计派单!A:O,13,0) -> 家客铁通潍坊寿光-纪台乡镇装维组
A272: SD-db051-250109-923815-283 | B272: 2025-01-09 14:56:37 | C272: (家客)潍坊-寒亭区-重复投诉投诉督办通知-一级督办17865998808-202501090000400418 | D272: 普通区域-寒亭区-交界村自然村-17865998808-100M-宽带上网投诉-次数0-202501090000400418 | E272: 202501090000400418#宽带账号：17865998808；宽带地址：潍坊寒亭区河滩镇交界村交界村自然村交界村10号箱*********；客户来电反映宽带无法连网 /客户不配合排障，要求上门，请协助处理，谢谢！来电流水：2025010914531951920812325*，联系电话：15863687444 | F272: 潍坊 | G272: 寒亭区 | H272: 17865998808 | I272: SD-057-250109-269351-3384 | J272: 'SD-057-241124-712863-6675' | K272: 否 | L272: =IF(OR(LEFT(G272,2)="高新"),"奎文",IF(LEFT(G272,2)="峡山","坊子",IF(LEFT(G272,2)="滨海","寒亭",LEFT(G272,2)))) -> 寒亭 | M272: =TEXT(B272,"mmdd") -> 0109 | N272: =VLOOKUP(I272,累计派单!A:O,15,0) -> dw3_jk_yuchengcheng | O272: =IF(LEN(J272)<2,0,DATEDIF(DATE(IF(MID(J272,9,2)="23",2023,2024),MID(J272,11,2),MID(J272,13,2)),B272,"d")) -> 46 | P272: =IF(O272=0,"无",IF(O272<8,"7天内",IF(O272<31,"30天内",IF(O272<61,"60天内",IF(O272<91,"90天内"))))) -> 60天内 | Q272: =VLOOKUP(I272,累计派单!A:O,13,0) -> 家客铁通潍坊寒亭-朱里乡镇装维组
A273: SD-db051-250109-875294-332 | B273: 2025-01-09 16:26:20 | C273: (家客)潍坊-寿光市-重复投诉投诉督办通知-一级督办13854485828-202501090000478524 | D273: 【调研】-80+普通-普通区域-寿光市-牛头-13854485828-1000M-业务受理宽带-次数0-202501090000478524 | E273: 202501090000478524# 宽带账号:13854485828; 联系电话：13854485828，问题类型：此工单为群障修复工单，根据群障全量闭环修复管理要求，为确保客户网络通畅，请装维人员跟进修复网络问题，谢谢！ 群障标题：公告。故障描述：潍坊寿光市牛头光缆故障，预估24小时恢复，请帮忙拦截,如有需要请联系片区装维师傅蔺荣明15706307753主叫号码：13465685708.0;该号码仅供参考，请优先联系宽带账号。 | F273: 潍坊 | G273: 寿光市 | H273: 13854485828 | I273: SD-057-250109-817436-4083 | J273: 'SD-057-250107-053742-5565' | K273: 否 | L273: =IF(OR(LEFT(G273,2)="高新"),"奎文",IF(LEFT(G273,2)="峡山","坊子",IF(LEFT(G273,2)="滨海","寒亭",LEFT(G273,2)))) -> 寿光 | M273: =TEXT(B273,"mmdd") -> 0109 | N273: =VLOOKUP(I273,累计派单!A:O,15,0) -> dw3_jk_linrongming | O273: =IF(LEN(J273)<2,0,DATEDIF(DATE(IF(MID(J273,9,2)="23",2023,2024),MID(J273,11,2),MID(J273,13,2)),B273,"d")) -> 368 | P273: =IF(O273=0,"无",IF(O273<8,"7天内",IF(O273<31,"30天内",IF(O273<61,"60天内",IF(O273<91,"90天内"))))) -> FALSE | Q273: =VLOOKUP(I273,累计派单!A:O,13,0) -> 家客铁通潍坊寿光-台头乡镇装维组
A274: SD-db051-250109-061845-359 | B274: 2025-01-09 17:08:44 | C274: (家客)潍坊-潍城区-重复投诉投诉督办通知-一级督办13455668308-202501090000516558 | D274: 80+白金-普通区域-潍城区-金元观悦府-13455668308-1000M-宽带上网投诉-次数0-202501090000516558 | E274: 202501090000516558#宽带账号13455668308：；宽带地址：潍坊潍城区北关街道卧龙西街金元观悦府13号楼；客户来电反映宽带无法上网，无法配合线上指导，请协助处理，谢谢！联系电话；13455668308联系人：；来电流水2025010917063012420887177：。 | F274: 潍坊 | G274: 潍城区 | H274: 13455668308 | I274: SD-057-250109-067352-4468 | J274: 'SD-057-241223-150249-4716' | K274: 否 | L274: =IF(OR(LEFT(G274,2)="高新"),"奎文",IF(LEFT(G274,2)="峡山","坊子",IF(LEFT(G274,2)="滨海","寒亭",LEFT(G274,2)))) -> 潍城 | M274: =TEXT(B274,"mmdd") -> 0109 | N274: =VLOOKUP(I274,累计派单!A:O,15,0) -> dw3_jk_wczhanglei | O274: =IF(LEN(J274)<2,0,DATEDIF(DATE(IF(MID(J274,9,2)="23",2023,2024),MID(J274,11,2),MID(J274,13,2)),B274,"d")) -> 17 | P274: =IF(O274=0,"无",IF(O274<8,"7天内",IF(O274<31,"30天内",IF(O274<61,"60天内",IF(O274<91,"90天内"))))) -> 30天内 | Q274: =VLOOKUP(I274,累计派单!A:O,13,0) -> 家客铁通潍坊潍城-豪德城区装维组
A275: SD-db051-250109-891670-385 | B275: 2025-01-09 17:46:43 | C275: (家客)潍坊-安丘市-重复投诉投诉督办通知-一级督办13455635311-202501090000546704 | D275: 80+普通-普通区域-安丘市-桑家尧村自然村-13455635311-200M-业务受理宽带-次数0-202501090000546704 | E275: 202501090000546704# 宽带账号:13455635311; 联系电话：13455635311，问题类型：此工单为群障修复工单，根据群障全量闭环修复管理要求，为确保客户网络通畅，请装维人员跟进修复网络问题，谢谢！ 群障标题：公告。故障描述：潍坊安丘市桑家尧村自然村割接故障，预估24小时恢复，请帮忙拦截。主叫号码：13406471838.0;该号码仅供参考，请优先联系宽带账号。 | F275: 潍坊 | G275: 安丘市 | H275: 13455635311 | I275: SD-057-250109-083974-4823 | J275: 'SD-057-250105-073591-4474' | K275: 否 | L275: =IF(OR(LEFT(G275,2)="高新"),"奎文",IF(LEFT(G275,2)="峡山","坊子",IF(LEFT(G275,2)="滨海","寒亭",LEFT(G275,2)))) -> 安丘 | M275: =TEXT(B275,"mmdd") -> 0109 | N275: =VLOOKUP(I275,累计派单!A:O,15,0) -> dw3_jk_yvshubo | O275: =IF(LEN(J275)<2,0,DATEDIF(DATE(IF(MID(J275,9,2)="23",2023,2024),MID(J275,11,2),MID(J275,13,2)),B275,"d")) -> 370 | P275: =IF(O275=0,"无",IF(O275<8,"7天内",IF(O275<31,"30天内",IF(O275<61,"60天内",IF(O275<91,"90天内"))))) -> FALSE | Q275: =VLOOKUP(I275,累计派单!A:O,13,0) -> 家客铁通潍坊安丘-刘家尧乡镇装维组
A276: SD-db051-250109-769135-409 | B276: 2025-01-09 18:12:54 | C276: (家客)潍坊-寿光市-重复投诉投诉督办通知-一级督办15154463386-202501090000565085 | D276: 80+普通-普通区域-寿光市-胡营沿街-15154463386-1000M-宽带上网投诉-次数0-202501090000565085 | E276: 202501090000565085#【已关注中国移动10086微信公众号】流程受理流水号：20250109181040151544633861144102 客户号码:15154463386 客户姓名:王** 投诉地市:潍坊 来话流水:2025010918090064720895470 宽带账号:15154463386 宽带账号归属地市:潍坊 宽带账号归属区县:寿光市 故障地址:潍坊寿光市胡营胡一村胡一村自然村胡一村35号箱********* 联系电话:15154463386 联系人:先生/ 工单紧急程度:非常紧急 是否有升级投诉倾向:否 是否重复投诉:否 是否携转意向:否 是否投诉倾向:否 是否智能网关:智能网关 当前是否在线:是 接入方式:FTTH 端到端诊断结果:客户侧设备问题（新增） 是否质差终端:无质差信息 光功率:-17.93 故障大类:宽带/电视 故障细类:宽带网速慢/卡顿 携转原因: 故障时间:2025-01-09 18:11:25 具体故障现象:网速慢卡顿， 客户其他诉求:要求师傅上门测网速 ;宽带小区$[胡营沿街]$ | F276: 潍坊 | G276: 寿光市 | H276: 15154463386 | I276: SD-057-250109-164853-5097 | J276: 'SD-057-250107-021738-4698' | K276: 否 | L276: =IF(OR(LEFT(G276,2)="高新"),"奎文",IF(LEFT(G276,2)="峡山","坊子",IF(LEFT(G276,2)="滨海","寒亭",LEFT(G276,2)))) -> 寿光 | M276: =TEXT(B276,"mmdd") -> 0109 | N276: =VLOOKUP(I276,累计派单!A:O,15,0) -> dw3_jk_sunxindong | O276: =IF(LEN(J276)<2,0,DATEDIF(DATE(IF(MID(J276,9,2)="23",2023,2024),MID(J276,11,2),MID(J276,13,2)),B276,"d")) -> 368 | P276: =IF(O276=0,"无",IF(O276<8,"7天内",IF(O276<31,"30天内",IF(O276<61,"60天内",IF(O276<91,"90天内"))))) -> FALSE | Q276: =VLOOKUP(I276,累计派单!A:O,13,0) -> 家客铁通潍坊寿光-孙集乡镇装维组
A277: SD-db051-250109-630814-425 | B277: 2025-01-09 18:35:07 | C277: (家客)潍坊-滨海-重复投诉投诉督办通知-一级督办13666361207-20250109183225X745750328 | D277: 【调研】-80+银卡-普通区域-滨海-职工家园-13666361207-200M-宽带上网投诉-次数0-20250109183225X745750328 | E277: 流程受理流水号：20250109183026136663612071147785 客户号码:13666361207 客户姓名:王** 投诉地市:潍坊 来话流水:2025010918300867820865655 宽带账号:13666361207 宽带账号归属地市:潍坊 宽带账号归属区县:滨海 故障地址:潍坊滨海央子街道北海路中央郡中央郡1号楼********* 联系电话:13666361207 联系人:先生/女士 工单紧急程度:一般 是否有升级投诉倾向:否 是否重复投诉:否 是否携转意向:否 是否投诉倾向:否 是否智能网关:智能网关 当前是否在线:否 接入方式:FTTH 端到端诊断结果:状态正常 是否质差终端:无质差信息 光功率:无 故障大类:宽带/电视 故障细类:宽带无法上网 携转原因: 故障时间:2025-01-09 18:27:01 具体故障现象:光猫亮红灯， 客户其他诉求:光猫亮红灯， | F277: 潍坊 | G277: 滨海 | H277: 13666361207 | I277: SD-057-250109-367481-5314 | J277: 'SD-057-241102-086241-3664' | K277: 否 | L277: =IF(OR(LEFT(G277,2)="高新"),"奎文",IF(LEFT(G277,2)="峡山","坊子",IF(LEFT(G277,2)="滨海","寒亭",LEFT(G277,2)))) -> 寒亭 | M277: =TEXT(B277,"mmdd") -> 0109 | N277: =VLOOKUP(I277,累计派单!A:O,15,0) -> dw3_jk_wangwenkang1 | O277: =IF(LEN(J277)<2,0,DATEDIF(DATE(IF(MID(J277,9,2)="23",2023,2024),MID(J277,11,2),MID(J277,13,2)),B277,"d")) -> 68 | P277: =IF(O277=0,"无",IF(O277<8,"7天内",IF(O277<31,"30天内",IF(O277<61,"60天内",IF(O277<91,"90天内"))))) -> 90天内 | Q277: =VLOOKUP(I277,累计派单!A:O,13,0) -> 家客铁通潍坊滨海-央子乡镇装维组
A278: SD-db051-250109-302418-426 | B278: 2025-01-09 18:35:20 | C278: (家客)潍坊-寿光市-重复投诉投诉督办通知-一级督办13573644545-20250109183331X811281197 | D278: 80+银卡-普通区域-寿光市-丰一-13573644545-300M-宽带上网投诉-次数0-20250109183331X811281197 | E278: 【农村网络投诉】流程受理流水号：20250109183249135736445451148234 客户号码:13573644545 客户姓名:张** 投诉地市:潍坊 来话流水:2025010918314732120878048 宽带账号:13573644545 宽带账号归属地市:潍坊 宽带账号归属区县:寿光市 故障地址:潍坊寿光市丰城镇丰一丰一丰一村3箱（张金旺外墙）********* 联系电话:15064438931 联系人:先生/女士 工单紧急程度:一般 是否有升级投诉倾向:否 是否重复投诉:否 是否携转意向:否 是否投诉倾向:否 是否智能网关:智能网关 当前是否在线:否 接入方式:FTTH 端到端诊断结果:状态正常 是否质差终端:无质差信息 光功率:无 故障大类:宽带/电视 故障细类:宽带无法上网 携转原因: 故障时间:2025-01-09 18:33:03 具体故障现象:光猫亮红灯， 客户其他诉求: | F278: 潍坊 | G278: 寿光市 | H278: 13573644545 | I278: SD-057-250109-108237-5316 | J278: 'SD-057-250103-265908-5651' | K278: 否 | L278: =IF(OR(LEFT(G278,2)="高新"),"奎文",IF(LEFT(G278,2)="峡山","坊子",IF(LEFT(G278,2)="滨海","寒亭",LEFT(G278,2)))) -> 寿光 | M278: =TEXT(B278,"mmdd") -> 0109 | N278: =VLOOKUP(I278,累计派单!A:O,15,0) -> dw3_jk_sunxiangxin | O278: =IF(LEN(J278)<2,0,DATEDIF(DATE(IF(MID(J278,9,2)="23",2023,2024),MID(J278,11,2),MID(J278,13,2)),B278,"d")) -> 372 | P278: =IF(O278=0,"无",IF(O278<8,"7天内",IF(O278<31,"30天内",IF(O278<61,"60天内",IF(O278<91,"90天内"))))) -> FALSE | Q278: =VLOOKUP(I278,累计派单!A:O,13,0) -> 家客铁通潍坊寿光-台头乡镇装维组
... A558: SD-db051-250118-437802-35 | B558: 2025-01-18 09:06:09 | C558: (家客)潍坊-潍城区-重复投诉投诉督办通知-一级督办18264616291-202501180000112897 | D558: 普通区域-潍城区-潍城向阳小区-18264616291-300M-业务受理宽带-次数0-202501180000112897 | E558: 202501180000112897# 宽带账号:18264616291; 联系电话：18264616291，问题类型：此工单为群障修复工单，根据群障全量闭环修复管理要求，为确保客户网络通畅，请装维人员跟进修复网络问题，谢谢！ 群障标题：公告。故障描述：潍坊潍城区潍城向阳小区光缆故障，预估24小时恢复，请帮忙拦截,如有需要请联系片区装维师傅张传阳15706307885主叫号码：18264616291.0;该号码仅供参考，请优先联系宽带账号。 | F558: 潍坊 | G558: 潍城区 | H558: 18264616291 | I558: SD-057-250118-796538-477 | J558: 'SD-057-250116-859326-4107' | K558: 否 | L558: =IF(OR(LEFT(G558,2)="高新"),"奎文",IF(LEFT(G558,2)="峡山","坊子",IF(LEFT(G558,2)="滨海","寒亭",LEFT(G558,2)))) -> 潍城 | M558: =TEXT(B558,"mmdd") -> 0118 | N558: =VLOOKUP(I558,累计派单!A:O,15,0) -> dw3_jk_wcdudesheng | O558: =IF(LEN(J558)<2,0,DATEDIF(DATE(IF(MID(J558,9,2)="23",2023,2024),MID(J558,11,2),MID(J558,13,2)),B558,"d")) -> 368 | P558: =IF(O558=0,"无",IF(O558<8,"7天内",IF(O558<31,"30天内",IF(O558<61,"60天内",IF(O558<91,"90天内"))))) -> FALSE | Q558: =VLOOKUP(I558,累计派单!A:O,13,0) -> 家客铁通潍坊潍城-胜利街城区装维组
A559: SD-db051-250118-712865-42 | B559: 2025-01-18 09:12:11 | C559: (家客)潍坊--重复投诉投诉督办通知-一级督办13562609182-202501180000118010 | D559: 普通区域--null-13562609182-宽带上网投诉-次数0-202501180000118010 | E559: 202501180000118010#流程受理流水号：20250118091059135626091821010619 客户号码:13562609182 客户姓名:魏** 投诉地市:潍坊 来话流水:2025011809103922320884312 宽带账号:13562609182 账号归属区县:寿光新兴街营业厅 联系电话:13562609182 联系人:先生/女士 宽带地址:潍坊 工单紧急程度:一般 是否投诉倾向:否 是否重复投诉:否 是否携转意向:否 是否有升级投诉倾向:否 *业务名称:业务融合开机流程小微宽带 投诉内容:手机号码：13562609182，【问题描述】客户已办理宽带业务，有开通单，要求装维尽快联系上门，请处理，谢谢。联系电话：13562609182，联系人：先生/女士，录音流水号：2025011809103922320884312。受理明细：531920062399999999。 在途开通单信息：536250114358560894，13562609182，2025-01-14 18:35:18，业务融合开机流程小微宽带，处理中，装维选址，需要回电 是否到厅:否 业务名称:业务融合开机流程小微宽带 ;宽带小区$[null]$ | F559: 潍坊 | H559: 13562609182 | I559: SD-057-250118-169482-552 | J559: 'SD-057-250114-049735-5282' | K559: 是 | L559: =IF(OR(LEFT(G559,2)="高新"),"奎文",IF(LEFT(G559,2)="峡山","坊子",IF(LEFT(G559,2)="滨海","寒亭",LEFT(G559,2)))) | M559: =TEXT(B559,"mmdd") -> 0118 | N559: =VLOOKUP(I559,累计派单!A:O,15,0) -> wangkunwf | O559: =IF(LEN(J559)<2,0,DATEDIF(DATE(IF(MID(J559,9,2)="23",2023,2024),MID(J559,11,2),MID(J559,13,2)),B559,"d")) -> 370 | P559: =IF(O559=0,"无",IF(O559<8,"7天内",IF(O559<31,"30天内",IF(O559<61,"60天内",IF(O559<91,"90天内"))))) -> FALSE | Q559: =VLOOKUP(I559,累计派单!A:O,13,0)
A560: SD-db051-250118-897302-49 | B560: 2025-01-18 09:17:04 | C560: (家客)潍坊-奎文区-重复投诉投诉督办通知-一级督办18663669989-20250118091418X858497466 | D560: 普通区域-奎文区-金都时代新城-18663669989-300M-宽带上网投诉-次数0-20250118091418X858497466 | E560: 流程受理流水号：20250118091324186636699891011246 客户号码:18663669989 客户姓名:冷** 投诉地市:潍坊 来话流水:2025011809074533220854590 宽带账号:18663669989 宽带账号归属地市:潍坊 宽带账号归属区县:奎文区 故障地址:潍坊奎文区北苑街道北宫街金都时代新城15号楼********* 联系电话:18663669989 联系人:先生/女士 工单紧急程度:非常紧急 是否有升级投诉倾向:是 是否重复投诉:否 是否携转意向:否 是否投诉倾向:否 是否智能网关:智能网关 当前是否在线:是 接入方式:FTTH 端到端诊断结果:客户侧设备问题（新增） 是否质差终端:无质差信息 光功率:-21.19 故障大类:宽带/电视 故障细类:宽带无法上网(专席) 携转原因: 故障时间:2025-01-18 09:18:30 具体故障现象:打不开网页， 客户其他诉求: | F560: 潍坊 | G560: 奎文区 | H560: 18663669989 | I560: SD-057-250118-326891-605 | J560: 'SD-057-250117-675349-1260' | K560: 是 | L560: =IF(OR(LEFT(G560,2)="高新"),"奎文",IF(LEFT(G560,2)="峡山","坊子",IF(LEFT(G560,2)="滨海","寒亭",LEFT(G560,2)))) -> 奎文 | M560: =TEXT(B560,"mmdd") -> 0118 | N560: =VLOOKUP(I560,累计派单!A:O,15,0) -> dw3_jk_yangmingxin | O560: =IF(LEN(J560)<2,0,DATEDIF(DATE(IF(MID(J560,9,2)="23",2023,2024),MID(J560,11,2),MID(J560,13,2)),B560,"d")) -> 367 | P560: =IF(O560=0,"无",IF(O560<8,"7天内",IF(O560<31,"30天内",IF(O560<61,"60天内",IF(O560<91,"90天内"))))) -> FALSE | Q560: =VLOOKUP(I560,累计派单!A:O,13,0) -> 家客铁通潍坊奎文-鸢飞路城区装维组
A561: SD-db051-250118-867941-71 | B561: 2025-01-18 09:44:40 | C561: (家客)潍坊-昌邑市-重复投诉投诉督办通知-一级督办13053673814-20250118094329X609421151 | D561: 普通区域-昌邑市-金台西南村自然村-13053673814-1000M-宽带上网投诉-次数0-20250118094329X609421151 | E561: 【农村网络投诉】流程受理流水号：20250118094226130536738141019044 客户号码:13053673814 客户姓名:李** 投诉地市:潍坊 来话流水:2025011809414496620837260 宽带账号:13053673814 宽带账号归属地市:潍坊 宽带账号归属区县:昌邑市 故障地址:潍坊昌邑市石埠镇金台西南村金台西南村自然村38号箱********* 联系电话:15762635775 联系人:先生/女士 工单紧急程度:一般 是否有升级投诉倾向:否 是否重复投诉:否 是否携转意向:否 是否投诉倾向:否 是否智能网关:智能网关 当前是否在线:是 接入方式:FTTH 端到端诊断结果:客户侧设备问题（新增） 是否质差终端:无质差信息 光功率:-16.34 故障大类:宽带/电视 故障细类:网速慢/上网掉线(专席) 携转原因: 故障时间:2025-01-18 09:39:10 具体故障现象:网速慢 千兆路由器 摆在开阔的位置 未测速 已按顺序重启未恢复 客户其他诉求: | F561: 潍坊 | G561: 昌邑市 | H561: 13053673814 | I561: SD-057-250118-310892-914 | J561: 'SD-057-241028-598264-6687' | K561: 是 | L561: =IF(OR(LEFT(G561,2)="高新"),"奎文",IF(LEFT(G561,2)="峡山","坊子",IF(LEFT(G561,2)="滨海","寒亭",LEFT(G561,2)))) -> 昌邑 | M561: =TEXT(B561,"mmdd") -> 0118 | N561: =VLOOKUP(I561,累计派单!A:O,15,0) -> dw3_jk_zhaixuhui | O561: =IF(LEN(J561)<2,0,DATEDIF(DATE(IF(MID(J561,9,2)="23",2023,2024),MID(J561,11,2),MID(J561,13,2)),B561,"d")) -> 82 | P561: =IF(O561=0,"无",IF(O561<8,"7天内",IF(O561<31,"30天内",IF(O561<61,"60天内",IF(O561<91,"90天内"))))) -> 90天内 | Q561: =VLOOKUP(I561,累计派单!A:O,13,0) -> 家客铁通潍坊昌邑-饮马乡镇装维组
A562: SD-db051-250118-598340-78 | B562: 2025-01-18 09:56:30 | C562: (家客)潍坊-高密市-重复投诉投诉督办通知-一级督办15963619446-202501180000151039 | D562: 普通区域-高密市-水岸东方-15963619446-300M-业务受理宽带-次数0-202501180000151039 | E562: 202501180000151039#【已关注中国移动10086微信公众号】 宽带账号:15963619446; 联系电话：15963619446，问题类型：此工单为群障修复工单，根据群障全量闭环修复管理要求，为确保客户网络通畅，请装维人员跟进修复网络问题，谢谢！ 群障标题：公告。故障描述：潍坊高密市水岸东方主缆故障，预估24小时恢复，请帮忙拦截。主叫号码：18253645931.0;该号码仅供参考，请优先联系宽带账号。 | F562: 潍坊 | G562: 高密市 | H562: 15963619446 | I562: SD-057-250118-082769-1038 | J562: 'SD-057-250106-240387-6205' | K562: 是 | L562: =IF(OR(LEFT(G562,2)="高新"),"奎文",IF(LEFT(G562,2)="峡山","坊子",IF(LEFT(G562,2)="滨海","寒亭",LEFT(G562,2)))) -> 高密 | M562: =TEXT(B562,"mmdd") -> 0118 | N562: =VLOOKUP(I562,累计派单!A:O,15,0) -> dw3_jk_zhangjinlei | O562: =IF(LEN(J562)<2,0,DATEDIF(DATE(IF(MID(J562,9,2)="23",2023,2024),MID(J562,11,2),MID(J562,13,2)),B562,"d")) -> 378 | P562: =IF(O562=0,"无",IF(O562<8,"7天内",IF(O562<31,"30天内",IF(O562<61,"60天内",IF(O562<91,"90天内"))))) -> FALSE | Q562: =VLOOKUP(I562,累计派单!A:O,13,0) -> 家客铁通潍坊高密-朝阳城区装维组
A563: SD-db051-250118-698143-97 | B563: 2025-01-18 10:16:04 | C563: (家客)潍坊-寿光市-重复投诉投诉督办通知-一级督办13054751006-202501180000165800 | D563: 普通区域-寿光市-清华名园-13054751006-300M-业务受理宽带-次数0-202501180000165800 | E563: 202501180000165800#【已关注中国移动10086微信公众号】 宽带账号:13054751006; 联系电话：13054751006，问题类型：此工单为群障修复工单，根据群障全量闭环修复管理要求，为确保客户网络通畅，请装维人员跟进修复网络问题，谢谢！ 群障标题：公告。故障描述：清华名园主叫号码：13054751006.0;该号码仅供参考，请优先联系宽带账号。 | F563: 潍坊 | G563: 寿光市 | H563: 13054751006 | I563: SD-057-250118-398526-1225 | J563: 'SD-057-241116-906481-7821' | K563: 否 | L563: =IF(OR(LEFT(G563,2)="高新"),"奎文",IF(LEFT(G563,2)="峡山","坊子",IF(LEFT(G563,2)="滨海","寒亭",LEFT(G563,2)))) -> 寿光 | M563: =TEXT(B563,"mmdd") -> 0118 | N563: =VLOOKUP(I563,累计派单!A:O,15,0) -> dw3_jk_liuyingjun | O563: =IF(LEN(J563)<2,0,DATEDIF(DATE(IF(MID(J563,9,2)="23",2023,2024),MID(J563,11,2),MID(J563,13,2)),B563,"d")) -> 63 | P563: =IF(O563=0,"无",IF(O563<8,"7天内",IF(O563<31,"30天内",IF(O563<61,"60天内",IF(O563<91,"90天内"))))) -> 90天内 | Q563: =VLOOKUP(I563,累计派单!A:O,13,0) -> 家客铁通潍坊寿光-文家乡镇装维组
A564: SD-db051-250118-178596-98 | B564: 2025-01-18 10:16:29 | C564: (家客)潍坊-昌邑市-重复投诉投诉督办通知-一级督办19853636877-202501180000166790 | D564: 普通区域-昌邑市-政亨小区1-19853636877-300M-业务受理宽带-次数0-202501180000166790 | E564: 202501180000166790# 宽带账号:19853636877; 联系电话：19853636877，问题类型：此工单为群障修复工单，根据群障全量闭环修复管理要求，为确保客户网络通畅，请装维人员跟进修复网络问题，谢谢！ 群障标题：公告。故障描述：政亨小区1主叫号码：19853636877.0;该号码仅供参考，请优先联系宽带账号。 | F564: 潍坊 | G564: 昌邑市 | H564: 19853636877 | I564: SD-057-250118-859320-1236 | J564: 'SD-057-250117-175839-5744' | K564: 是 | L564: =IF(OR(LEFT(G564,2)="高新"),"奎文",IF(LEFT(G564,2)="峡山","坊子",IF(LEFT(G564,2)="滨海","寒亭",LEFT(G564,2)))) -> 昌邑 | M564: =TEXT(B564,"mmdd") -> 0118 | N564: =VLOOKUP(I564,累计派单!A:O,15,0) -> dw3_jk_xuruipeng | O564: =IF(LEN(J564)<2,0,DATEDIF(DATE(IF(MID(J564,9,2)="23",2023,2024),MID(J564,11,2),MID(J564,13,2)),B564,"d")) -> 367 | P564: =IF(O564=0,"无",IF(O564<8,"7天内",IF(O564<31,"30天内",IF(O564<61,"60天内",IF(O564<91,"90天内"))))) -> FALSE | Q564: =VLOOKUP(I564,累计派单!A:O,13,0) -> 家客铁通潍坊昌邑-柳疃乡镇装维组
A565: SD-db051-250118-138056-100 | B565: 2025-01-18 10:16:49 | C565: (家客)潍坊-寿光市-重复投诉投诉督办通知-一级督办13793636315-202501180000167072 | D565: 普通区域-寿光市-北单-13793636315-300M-宽带上网投诉-次数0-202501180000167072 | E565: 202501180000167072#宽带账号：13793636315；宽带地址：潍坊寿光市营里镇北单北单北单村；客户来电反映移动高清无法使用，客户不配合排障，要求上门，请协助处理，谢谢！联系电话：13793636315；联系人：女士；来电流水：2025011810134033420820017 | F565: 潍坊 | G565: 寿光市 | H565: 13793636315 | I565: SD-057-250118-678503-1245 | J565: 'SD-057-250115-791436-5820' | K565: 是 | L565: =IF(OR(LEFT(G565,2)="高新"),"奎文",IF(LEFT(G565,2)="峡山","坊子",IF(LEFT(G565,2)="滨海","寒亭",LEFT(G565,2)))) -> 寿光 | M565: =TEXT(B565,"mmdd") -> 0118 | N565: =VLOOKUP(I565,累计派单!A:O,15,0) -> dw3_jk_suijiangong | O565: =IF(LEN(J565)<2,0,DATEDIF(DATE(IF(MID(J565,9,2)="23",2023,2024),MID(J565,11,2),MID(J565,13,2)),B565,"d")) -> 369 | P565: =IF(O565=0,"无",IF(O565<8,"7天内",IF(O565<31,"30天内",IF(O565<61,"60天内",IF(O565<91,"90天内"))))) -> FALSE | Q565: =VLOOKUP(I565,累计派单!A:O,13,0) -> 家客铁通潍坊寿光-营里乡镇装维组
A566: SD-db051-250118-235019-104 | B566: 2025-01-18 10:20:04 | C566: (家客)潍坊-寒亭区-重复投诉投诉督办通知-一级督办15065656837-20250118101732X652384489 | D566: 【调研】-80+普通-普通区域-寒亭区-富郭庄二村自然村-15065656837-1000M-魔百和投诉-次数0-20250118101732X652384489 | E566: 【农村网络投诉】流程受理流水号：20250118101643150656568371028457 客户号码:15065656837 客户姓名:孙* 投诉地市:潍坊 来话流水:2025011810122889020805313 宽带账号:15065656837 宽带账号归属地市:潍坊 宽带账号归属区县:寒亭区 故障地址:潍坊寒亭区朱里镇富郭庄二村富郭庄二村自然村朱里镇富郭庄二村20号箱********* 联系电话:15054452315 联系人:先生/女士 工单紧急程度:非常紧急 是否有升级投诉倾向:否 是否重复投诉:否 是否携转意向:否 是否投诉倾向:否 是否智能网关:智能网关 当前是否在线:是 接入方式:FTTH 端到端诊断结果:客户侧设备问题 是否质差终端:是 光功率:无 故障大类:宽带/电视 故障细类:移动高清电视故障(专席) 携转原因: 故障时间:2025-01-18 10:15:34 魔百和单播/组播:组播 具体故障现象:电视提示网络类错误， 客户其他诉求: 魔百和单/组播：组播 | F566: 潍坊 | G566: 寒亭区 | H566: 15065656837 | I566: SD-057-250118-184296-1268 | J566: 'SD-057-241026-873219-6398' | K566: 是 | L566: =IF(OR(LEFT(G566,2)="高新"),"奎文",IF(LEFT(G566,2)="峡山","坊子",IF(LEFT(G566,2)="滨海","寒亭",LEFT(G566,2)))) -> 寒亭 | M566: =TEXT(B566,"mmdd") -> 0118 | N566: =VLOOKUP(I566,累计派单!A:O,15,0) -> dw3_jk_lilianqun | O566: =IF(LEN(J566)<2,0,DATEDIF(DATE(IF(MID(J566,9,2)="23",2023,2024),MID(J566,11,2),MID(J566,13,2)),B566,"d")) -> 84 | P566: =IF(O566=0,"无",IF(O566<8,"7天内",IF(O566<31,"30天内",IF(O566<61,"60天内",IF(O566<91,"90天内"))))) -> 90天内 | Q566: =VLOOKUP(I566,累计派单!A:O,13,0) -> 家客铁通潍坊寒亭-朱里乡镇装维组
A567: SD-db051-250118-179365-120 | B567: 2025-01-18 10:36:28 | C567: (家客)潍坊-寿光市-重复投诉投诉督办通知-一级督办17685909925-202501180000181388 | D567: 普通区域-寿光市-南范村-17685909925-300M-宽带上网投诉-次数0-202501180000181388 | E567: 202501180000181388#流程受理流水号：20250118103550176859099251033744 客户号码:17685909925 客户姓名:王* 投诉地市:潍坊 来话流水:2025011810345068320879786 宽带账号:17685909925 宽带账号归属地市:潍坊 宽带账号归属区县:寿光市 故障地址:潍坊寿光市洛城街道南范村南范村扩容23号箱********* 联系电话:17685909925 联系人:先生 工单紧急程度:一般 是否有升级投诉倾向:否 是否重复投诉:否 是否携转意向:否 是否投诉倾向:否 是否智能网关:智能网关 当前是否在线:否 接入方式:FTTH 端到端诊断结果:大面积故障 是否质差终端:无质差信息 光功率:无 故障大类:宽带/电视 故障细类:宽带无法上网 携转原因: 故障时间:2025-01-18 10:36:03 具体故障现象:打不开网页， 客户其他诉求: ;宽带小区$[南范村]$ | F567: 潍坊 | G567: 寿光市 | H567: 17685909925 | I567: SD-057-250118-761902-1424 | J567: 'SD-057-241124-910648-1578' | K567: 是 | L567: =IF(OR(LEFT(G567,2)="高新"),"奎文",IF(LEFT(G567,2)="峡山","坊子",IF(LEFT(G567,2)="滨海","寒亭",LEFT(G567,2)))) -> 寿光 | M567: =TEXT(B567,"mmdd") -> 0118 | N567: =VLOOKUP(I567,累计派单!A:O,15,0) -> dw3_jk_liubin | O567: =IF(LEN(J567)<2,0,DATEDIF(DATE(IF(MID(J567,9,2)="23",2023,2024),MID(J567,11,2),MID(J567,13,2)),B567,"d")) -> 55 | P567: =IF(O567=0,"无",IF(O567<8,"7天内",IF(O567<31,"30天内",IF(O567<61,"60天内",IF(O567<91,"90天内"))))) -> 60天内 | Q567: =VLOOKUP(I567,累计派单!A:O,13,0) -> 家客铁通潍坊寿光-洛城乡镇装维组
A568: SD-db051-250118-873419-144 | B568: 2025-01-18 10:59:56 | C568: (家客)潍坊-安丘市-重复投诉投诉督办通知-一级督办15165679699-202501180000203020 | D568: 【调研】-80+银卡-普通区域-安丘市-东南街村、环卫局家属院-15165679699-200M-宽带上网投诉-次数0-202501180000203020 | E568: 202501180000203020#流程受理流水号：20250118105900151656796991040036 客户号码:15165679699 客户姓名:白** 投诉地市:潍坊 来话流水:2025011810564488820853410 宽带账号:15165679699 宽带账号归属地市:潍坊 宽带账号归属区县:安丘市 故障地址:潍坊安丘市兴安街道健康街东南街村环卫局家属院沿街楼********* 联系电话:15165679699 联系人:先生/女士 工单紧急程度:一般 是否有升级投诉倾向:否 是否重复投诉:否 是否携转意向:否 是否投诉倾向:否 是否智能网关:智能网关 当前是否在线:是 接入方式:FTTH 端到端诊断结果:客户侧设备问题（新增） 是否质差终端:无质差信息 光功率:-21.48 故障大类:宽带/电视 故障细类:网速慢/上网掉线(专席) 携转原因: 故障时间:2025-01-18 10:59:12 具体故障现象:路由器年限未超过，位置开阔，重启未恢复 客户其他诉求: ;宽带小区$[东南街村、环卫局家属院]$ | F568: 潍坊 | G568: 安丘市 | H568: 15165679699 | I568: SD-057-250118-972430-1694 | J568: 'SD-057-241024-307162-3530' | K568: 是 | L568: =IF(OR(LEFT(G568,2)="高新"),"奎文",IF(LEFT(G568,2)="峡山","坊子",IF(LEFT(G568,2)="滨海","寒亭",LEFT(G568,2)))) -> 安丘 | M568: =TEXT(B568,"mmdd") -> 0118 | N568: =VLOOKUP(I568,累计派单!A:O,15,0) -> dw3_jk_lichangming | O568: =IF(LEN(J568)<2,0,DATEDIF(DATE(IF(MID(J568,9,2)="23",2023,2024),MID(J568,11,2),MID(J568,13,2)),B568,"d")) -> 86 | P568: =IF(O568=0,"无",IF(O568<8,"7天内",IF(O568<31,"30天内",IF(O568<61,"60天内",IF(O568<91,"90天内"))))) -> 90天内 | Q568: =VLOOKUP(I568,累计派单!A:O,13,0) -> 家客铁通潍坊安丘-永安路城区装维组
A569: SD-db051-250118-619573-204 | B569: 2025-01-18 12:32:45 | C569: (家客)潍坊-寒亭区-重复投诉投诉督办通知-一级督办18764730300-202501180000261894 | D569: 80+金卡-普通区域-寒亭区-冯家花园村自然村-18764730300-1000M-宽带上网投诉-次数0-202501180000261894 | E569: 202501180000261894#【已关注中国移动10086微信公众号】流程受理流水号：20250118123208187647303001061953 客户号码:18764730300 客户姓名:冯** 投诉地市:潍坊 来话流水:2025011812314000120847587 宽带账号:18764730300 宽带账号归属地市:潍坊 宽带账号归属区县:寒亭区 故障地址:潍坊寒亭区高里镇冯家花园村冯家花园村自然村高里镇冯家花园村28号箱********* 联系电话:18764730300 联系人:先生/女士 工单紧急程度:一般 是否有升级投诉倾向:否 是否重复投诉:否 是否携转意向:否 是否投诉倾向:否 是否智能网关:智能网关 当前是否在线:是 接入方式:FTTH 端到端诊断结果:客户侧设备问题 是否质差终端:是 光功率: 故障大类:宽带/电视 故障细类:宽带无法上网 携转原因: 故障时间:2025-01-18 12:37:31 具体故障现象:打不开网页， 客户其他诉求:客户侧为质差终端，要求上门更换终端并一并处理故障问题。 | F569: 潍坊 | G569: 寒亭区 | H569: 18764730300 | I569: SD-057-250118-140786-2668 | J569: 'SD-057-241112-289314-2250' | K569: 否 | L569: =IF(OR(LEFT(G569,2)="高新"),"奎文",IF(LEFT(G569,2)="峡山","坊子",IF(LEFT(G569,2)="滨海","寒亭",LEFT(G569,2)))) -> 寒亭 | M569: =TEXT(B569,"mmdd") -> 0118 | N569: =VLOOKUP(I569,累计派单!A:O,15,0) -> dw3_jk_lifawei | O569: =IF(LEN(J569)<2,0,DATEDIF(DATE(IF(MID(J569,9,2)="23",2023,2024),MID(J569,11,2),MID(J569,13,2)),B569,"d")) -> 67 | P569: =IF(O569=0,"无",IF(O569<8,"7天内",IF(O569<31,"30天内",IF(O569<61,"60天内",IF(O569<91,"90天内"))))) -> 90天内 | Q569: =VLOOKUP(I569,累计派单!A:O,13,0) -> 家客铁通潍坊寒亭-固高乡镇装维组
A570: SD-db051-250118-275840-211 | B570: 2025-01-18 12:41:10 | C570: (家客)潍坊-昌乐县-重复投诉投诉督办通知-一级督办15065620250-202501180000264308 | D570: 【调研】-80+银卡-普通区域-昌乐县-福荣世家-15065620250-300M-宽带上网投诉-次数0-202501180000264308 | E570: 202501180000264308#流程受理流水号：20250118123951150656202501063381 客户号码:15065620250 客户姓名:蔡** 投诉地市:潍坊 来话流水:2025011812393064920800264 宽带账号:15065620250 账号归属区县:昌乐 联系电话:15065620250 联系人:先生/女士 宽带地址:潍坊 工单紧急程度:非常紧急 是否投诉倾向:否 是否重复投诉:否 是否携转意向:否 是否有升级投诉倾向:否 *业务名称:业务融合移机流程宽带 投诉内容:手机号码：15065620250，【问题描述】客户已办理宽带业务，有开通单，要求装维尽快联系上门，请处理，谢谢。联系电话：15065620250，联系人：先生/女士，录音流水号：2025011812393064920800264。受理明细：531920062399999999。 在途开通单信息：536250117035838670，15065620250，2025-01-17 14:06:29，业务融合移机流程宽带，处理中，手写判断和地址录入 是否到厅:否 业务名称:业务融合移机流程宽带 ;宽带小区$[福荣世家]$ | F570: 潍坊 | G570: 昌乐县 | H570: 15065620250 | I570: SD-057-250118-356142-2745 | J570: 'SD-057-250107-028534-4386' | K570: 否 | L570: =IF(OR(LEFT(G570,2)="高新"),"奎文",IF(LEFT(G570,2)="峡山","坊子",IF(LEFT(G570,2)="滨海","寒亭",LEFT(G570,2)))) -> 昌乐 | M570: =TEXT(B570,"mmdd") -> 0118 | N570: =VLOOKUP(I570,累计派单!A:O,15,0) -> dw3_jk_liruiqing | O570: =IF(LEN(J570)<2,0,DATEDIF(DATE(IF(MID(J570,9,2)="23",2023,2024),MID(J570,11,2),MID(J570,13,2)),B570,"d")) -> 377 | P570: =IF(O570=0,"无",IF(O570<8,"7天内",IF(O570<31,"30天内",IF(O570<61,"60天内",IF(O570<91,"90天内"))))) -> FALSE | Q570: =VLOOKUP(I570,累计派单!A:O,13,0) -> 家客铁通潍坊昌乐-方山路城区装维组
A571: SD-db051-250118-197285-223 | B571: 2025-01-18 12:51:27 | C571: (家客)潍坊-奎文区-重复投诉投诉督办通知-一级督办15063679849-202501180000271802 | D571: 80+金卡-普通区域-奎文区-武家涧头自然村-15063679849-300M-宽带上网投诉-次数0-202501180000271802 | E571: 202501180000271802#流程受理流水号：20250118125030150636798491065358 客户号码:15063679849 客户姓名:王** 投诉地市:潍坊 来话流水:2025011812494702020868430 宽带账号:15063679849 宽带账号归属地市:潍坊 宽带账号归属区县:奎文区 故障地址:潍坊奎文区廿里堡街道武家涧头武家涧头自然村武家南起6排二列2#********* 联系电话:13475699776 联系人:先生/女士 工单紧急程度:紧急 是否有升级投诉倾向:否 是否重复投诉:否 是否携转意向:否 是否投诉倾向:否 是否智能网关:智能网关 当前是否在线:是 接入方式:FTTH 端到端诊断结果:客户侧设备问题（新增） 是否质差终端:无质差信息 光功率:-30 故障大类:宽带/电视 故障细类:网速慢/上网掉线(专席) 携转原因: 故障时间:2025-01-18 12:47:03 具体故障现象:家庭WiFi信号弱，光功率弱，请协助，谢谢！ 客户其他诉求: ;宽带小区$[武家涧头自然村]$ | F571: 潍坊 | G571: 奎文区 | H571: 15063679849 | I571: SD-057-250118-370651-2848 | J571: 'SD-057-241117-508176-6392' | K571: 否 | L571: =IF(OR(LEFT(G571,2)="高新"),"奎文",IF(LEFT(G571,2)="峡山","坊子",IF(LEFT(G571,2)="滨海","寒亭",LEFT(G571,2)))) -> 奎文 | M571: =TEXT(B571,"mmdd") -> 0118 | N571: =VLOOKUP(I571,累计派单!A:O,15,0) -> dw3_jk_liuzuqikw | O571: =IF(LEN(J571)<2,0,DATEDIF(DATE(IF(MID(J571,9,2)="23",2023,2024),MID(J571,11,2),MID(J571,13,2)),B571,"d")) -> 62 | P571: =IF(O571=0,"无",IF(O571<8,"7天内",IF(O571<31,"30天内",IF(O571<61,"60天内",IF(O571<91,"90天内"))))) -> 90天内 | Q571: =VLOOKUP(I571,累计派单!A:O,13,0) -> 家客铁通潍坊奎文-潍州路城区装维组
... A587: SD-db051-250118-514708-567 | B587: 2025-01-18 23:18:20 | C587: (家客)潍坊-滨海-重复投诉投诉督办通知-一级督办15069690881-202501180000545051 | D587: 普通区域-滨海-华润世家-15069690881-300M-宽带上网投诉-次数0-202501180000545051 | E587: 202501180000545051#【已关注中国移动10086微信公众号】流程受理流水号：20250118231721150696908811165302 客户号码:15069690881 客户姓名:司** 投诉地市:潍坊 来话流水:2025011823170656920836751 宽带账号:15069690881 宽带账号归属地市:潍坊 宽带账号归属区县:滨海 故障地址:潍坊滨海央子街道北海路红旗家园小区北西4号楼********* 联系电话:15069690881 联系人:先生/女士 工单紧急程度:一般 是否有升级投诉倾向:否 是否重复投诉:否 是否携转意向:否 是否投诉倾向:否 是否智能网关:智能网关 当前是否在线:是 接入方式:FTTH 端到端诊断结果:客户侧设备问题 是否质差终端:是 光功率:-16.16 故障大类:宽带/电视 故障细类:宽带无法上网 携转原因: 故障时间:2025-01-18 23:17:39 具体故障现象:打不开网页， 客户其他诉求:客户侧为质差终端，要求上门更换终端并一并处理故障问题。 | F587: 潍坊 | G587: 滨海 | H587: 15069690881 | I587: SD-057-250118-064725-7769 | J587: 'SD-057-241215-632071-4903' | K587: 否 | L587: =IF(OR(LEFT(G587,2)="高新"),"奎文",IF(LEFT(G587,2)="峡山","坊子",IF(LEFT(G587,2)="滨海","寒亭",LEFT(G587,2)))) -> 寒亭 | M587: =TEXT(B587,"mmdd") -> 0118 | N587: =VLOOKUP(I587,累计派单!A:O,15,0) -> dw3_jk_wangwenkang1 | O587: =IF(LEN(J587)<2,0,DATEDIF(DATE(IF(MID(J587,9,2)="23",2023,2024),MID(J587,11,2),MID(J587,13,2)),B587,"d")) -> 34 | P587: =IF(O587=0,"无",IF(O587<8,"7天内",IF(O587<31,"30天内",IF(O587<61,"60天内",IF(O587<91,"90天内"))))) -> 60天内 | Q587: =VLOOKUP(I587,累计派单!A:O,13,0) -> 家客铁通潍坊滨海-央子乡镇装维组

Sheet 累计派单
A1: 工单号 | B1: 派单时间 | C1: 地市 | D1: 主题 | E1: 处理时限 | F1: 客服侧工单流水号 | G1: 故障现象 | H1: T1受理时间 | I1: 投诉细类 | J1: T1处理人 | K1: T1处理人电话 | L1: 新小区名称 | M1: 装维所属网格 | N1: t3环节处理措施 | O1: 装维处理人账号 | P1: 首次响应成功时间 | Q1: 关联装移机单号 | R1: =IF(OR(LEFT(L1,2)="高新"),"奎文",IF(LEFT(L1,2)="峡山","坊子",IF(LEFT(L1,2)="滨海","寒亭",LEFT(L1,2)))) -> 新小 | S1: =TEXT(B1,"mmdd") -> 派单时间
A2: SD-057-250101-435892-443 | B2: 2025-01-01 09:02:46 | C2: 潍坊 | D2: 普通区域-奎文区-樱园东区-15864560786-1000M-魔百和投诉-次数0-202501010000118335 | E2: 2025-01-02 08:00:00 | F2: 202501010000118335 | G2: 202501010000118335#【已关注中国移动10086微信公众号】流程受理流水号：20250101090115158645607861011362 客户号码:15864560786 客户姓名:张** 投诉地市:潍坊 来话流水:2025010109001607220892535 宽带账号:15864560786 宽带账号归属地市:潍坊 宽带账号归属区县:奎文区 故障地址:潍坊奎文区梨园街道樱前街樱园东区19号楼1单元402 联系电话:15269604152 联系人:先生/女士 工单紧急程度:非常紧急 是否有升级投诉倾向:否 是否重复投诉:否 是否携转意向:否 是否投诉倾向:否 是否智能网关:智能网关 当前是否在线:是 接入方式:FTTH 端到端诊断结果:客户侧设备问题（新增） 是否质差终端:无质差信息 光功率:-16.03 故障大类:宽带/电视 故障细类:移动高清电视故障(专席) 携转原因: 故障时间:2025-01-01 09:02:03 魔百和单播/组播:单播 具体故障现象:机顶盒自动重启 客户其他诉求: 魔百和单/组播：单播;宽带小区$[樱园东区]$ | H2: 2025-01-01 09:03:49 | I2: 家庭咨询->产品质量->互联网电视(移动高清)->全局流转->功能使用->无法进入播放界面->全局流转 | J2: 李三志 | K2: 15706366501 | L2: 奎文区 | M2: 家客铁通潍坊奎文-樱前街城区装维组 | N2: 重启或检修后恢复 | O2: dw3_jk_lisanzhi | P2: 2025-01-01 09:04:03 | Q2: SD-851-268393-24496-25616 | R2: =IF(OR(LEFT(L2,2)="高新"),"奎文",IF(LEFT(L2,2)="峡山","坊子",IF(LEFT(L2,2)="滨海","寒亭",LEFT(L2,2)))) -> 奎文 | S2: =TEXT(B2,"mmdd") -> 0101
A3: SD-057-250101-805763-511 | B3: 2025-01-01 09:08:37 | C3: 潍坊 | D3: 【调研】-80+银卡-普通区域-潍城区-福安家园-18765155279-1000M-宽带上网投诉-次数0-20250101090720X640117956 | E3: 2025-01-02 08:00:00 | F3: 20250101090720X640117956 | G3: 流程受理流水号：20250101090630187651552791013223 客户号码:18765155279 客户姓名:周** 投诉地市:潍坊 来话流水:2025010109055454420855467 宽带账号:18765155279 宽带账号归属地市:潍坊 宽带账号归属区县:潍城区 故障地址:潍坊潍城区北关街道福寿西街福安家园8号楼********* 联系电话:18765155279 联系人:先生/女士 工单紧急程度:非常紧急 是否有升级投诉倾向:否 是否重复 | H3: 2025-01-01 09:10:02 | I3: 家宽业务->网络质量->家庭宽带->全局流转->功能使用->网络无法连接->全局流转 | J3: 张乐华 | K3: 15706307858 | L3: 潍城区 | M3: 家客铁通潍坊潍城-东风街城区装维组 | N3: 重新熔接皮线 | O3: dw3_jk_wczhanglehua | P3: 2025-01-01 09:10:28 | Q3: SD-851-250897-27494-8338 | R3: =IF(OR(LEFT(L3,2)="高新"),"奎文",IF(LEFT(L3,2)="峡山","坊子",IF(LEFT(L3,2)="滨海","寒亭",LEFT(L3,2)))) -> 潍城 | S3: =TEXT(B3,"mmdd") -> 0101
A4: SD-057-250101-346702-6988 | B4: 2025-01-01 22:14:02 | C4: 潍坊 | D4: 普通区域-临朐县-富华家园-13884702599-1000M-宽带上网投诉-次数0-20250101221111X671905871 | E4: 2025-01-02 18:00:00 | F4: 20250101221111X671905871 | G4: 检测结果：1、手机账号余额检测：手机账户余额正常；2、宽带速率检测：宽带速率正常；3、宽带账号登录状态检测：账号登录状态正常；4、宽带状态检测：宽带状态正常；5、群体故障检测：无大面积群障；6、线路检测：线路状态正常；7、光猫在线检测：光猫在线；故障类型：网络连接掉线。故障描述：家 | H4: 2025-01-02 07:03:53 | I4: 家宽业务->网络质量->家庭宽 | J4: 韩崇 | K4: 15706307608 | L4: 临朐县 | M4: 家客铁通潍坊临朐-城关城区装维组 | O4: dw3_jk_hanchong | P4: 2025-01-02 07:04:17 | Q4: SD-851-281698-27550-25617 | R4: =IF(OR(LEFT(L4,2)="高新"),"奎文",IF(LEFT(L4,2)="峡山","坊子",IF(LEFT(L4,2)="滨海","寒亭",LEFT(L4,2)))) -> 临朐 | S4: =TEXT(B4,"mmdd") -> 0101
A5: SD-057-250101-726805-503 | B5: 2025-01-01 09:08:09 | C5: 潍坊 | D5: 【调研】-80+金卡-FTTR-普通区域-青州市-益青园-13562669900-1000M-宽带上网投诉-次数0-20250101090531X531924625 | E5: 2025-01-02 08:00:00 | F5: 20250101090531X531924625 | G5: 流程受理流水号：20250101090321135626699001012126 客户号码:13562669900 客户姓名:王** 投诉地市:潍坊 来话流水:2025010109021397020814190 宽带账号:13562669900 宽带账号归属地市:潍坊 宽带账号归属区县:青州市 故障地址:潍坊青州市王府街道玲珑山南路益青园8号楼********* 联系电话:13562669900 联系人:先生/女士 工单紧急程度:非常紧急 是否有升级投诉倾向:否 是否重复投诉:否 是否携转意向:否 是否投诉倾向:否 是否智能网关:智能网关 当前是否在线:否 接入方式:FTTH 端到端诊断结果:设备告警 是否质差终端:无质差信息 光功率:无 故障大类:宽带/电视 故障细类:宽带无法上网 携转原因: 故障时间:2025-01-01 09:05:11 具体故障现象:光猫亮红灯， 客户其他诉求: | H5: 2025-01-01 09:11:10 | I5: 家宽业务->网络质量->家庭宽带->全局流转->功能使用->LOS红灯，无法上网->全局流转 | J5: 魏守波 | K5: 15706307630 | L5: 青州市 | M5: 家客铁通潍坊青州-古城城区装维组 | N5: 更换尾纤 | O5: dw3_jk_weishoubo | P5: 2025-01-01 09:11:53 | Q5: SD-851-255666-29671-17918 | R5: =IF(OR(LEFT(L5,2)="高新"),"奎文",IF(LEFT(L5,2)="峡山","坊子",IF(LEFT(L5,2)="滨海","寒亭",LEFT(L5,2)))) -> 青州 | S5: =TEXT(B5,"mmdd") -> 0101
A6: SD-057-250101-785269-451 | B6: 2025-01-01 09:03:43 | C6: 潍坊 | D6: 80+银卡-普通区域-高密市-海建宿舍-13589198860-200M-宽带上网投诉-次数0-202501010000119670 | E6: 2025-01-02 10:04:00 | F6: 202501010000119670 | G6: 202501010000119670#【已关注中国移动10086微信公众号】流程受理流水号：20250101090217135891988601011753 客户号码:13589198860 客户姓名:范** 投诉地市:潍坊 来话流水:2025010109012784520805710 宽带账号:13589198860 宽带账号归属地市:潍坊 宽带账号归属区县:高密市 故障地址:潍坊高密市密水街道立新街海建宿舍立新小区1号楼********* 联系电话:13589198860 联系人:先生/女士 工单紧急程度:一般 是否有 | H6: 2025-01-01 09:07:03 | I6: 家庭咨询->网络质量->家庭宽带->全局流转->功能使用->光猫设备故障->线上义诊 | J6: 贾鑫 | K6: 15706307327 | L6: 高密市 | M6: 家客铁通潍坊高密-醴泉城区装维组 | N6: 营业厅重新办理业务 | O6: dw3_jk_jiaxin | P6: 2025-01-01 09:07:29 | R6: =IF(OR(LEFT(L6,2)="高新"),"奎文",IF(LEFT(L6,2)="峡山","坊子",IF(LEFT(L6,2)="滨海","寒亭",LEFT(L6,2)))) -> 高密 | S6: =TEXT(B6,"mmdd") -> 0101
A7: SD-057-250101-396875-2363 | B7: 2025-01-01 12:38:17 | C7: 潍坊 | D7: 【调研】-80+银卡-普通区域-安丘市-钢材市场-15853611557-500M-宽带上网投诉-次数0-20250101123745X265183383 | E7: 2025-01-02 08:00:00 | F7: 20250101123745X265183383 | G7: 流程受理流水号：20250101123655158536115571076564 客户号码:15853611557 客户姓名:李** 投诉地市:潍坊 来话流水:2025010112355614320839233 宽带账号:15853611557 宽带账号归属地市:潍坊 宽带账号归属区县:安丘市 故障地址:潍坊安丘市兴安街道建安路华苑家园5号楼 联系电话:15853611557 联系人:先生 工单紧急程度:非常紧急 是否有升级投诉倾向:否 是否重复投诉:否 是否携转意向:否 是否投诉倾向:否 是否智能网关:智能网关 当前是否在线:是 接入方式:FTTH 端到端诊断结果:客户侧设备问题 是否质差终端:是 光功率:-26.38 故障大类:宽带/电视 故障细类:网速慢/上网掉线(专席) 携转原因: 故障时间:2025-01-01 12:37:46 具体故障现象:光猫灯正常但电脑手机无法上网， 客户其他诉求: | H7: 2025-01-01 12:40:29 | I7: 家宽业务->网络质量->家庭宽带->全局流转->功能使用->频繁出现故障、网速慢->全局流转 | J7: 董策策 | K7: 15706307039 | L7: 安丘市 | M7: 家客铁通潍坊安丘-潍安路城区装维组 | N7: 建议用户更换路由器 | O7: dw3_jk_dongcece | P7: 2025-01-01 12:40:46 | R7: =IF(OR(LEFT(L7,2)="高新"),"奎文",IF(LEFT(L7,2)="峡山","坊子",IF(LEFT(L7,2)="滨海","寒亭",LEFT(L7,2)))) -> 安丘 | S7: =TEXT(B7,"mmdd") -> 0101
A8: SD-057-250101-072469-452 | B8: 2025-01-01 09:03:49 | C8: 潍坊 | D8: 【调研】-普通区域-青州市-东坝新村-13668669581-200M-宽带上网投诉-次数0-202501010000116152 一级督办 | E8: 2025-01-02 10:04:00 | F8: 202501010000116152 | G8: 202501010000116152#13668669581客户来电反映宽带无法使用/客户不配合操作/，要求维修人员上门维修，请尽快协助处理，谢谢 联系人：女士 联系电 | H8: 2025-01-01 09:06:49 | I8: 家庭咨询->网络质量->家庭宽带->全局流转->功能使用->客户要求装维上门服务->全局流转 | J8: 王振海 | K8: 15706307675 | L8: 青州市 | M8: 家客铁通潍坊青州-黄楼乡镇装维组 | N8: 更换光猫 | O8: dw3_jk_wangzhenhai | P8: 2025-01-01 09:08:23 | R8: =IF(OR(LEFT(L8,2)="高新"),"奎文",IF(LEFT(L8,2)="峡山","坊子",IF(LEFT(L8,2)="滨海","寒亭",LEFT(L8,2)))) -> 青州 | S8: =TEXT(B8,"mmdd") -> 0101
A9: SD-057-250101-689713-510 | B9: 2025-01-01 09:08:33 | C9: 潍坊 | D9: 80+普通-普通区域-潍城区-杏埠镇沿街J-13505360207-100M-宽带上网投诉-次数0-20250101090652X612212326 | E9: 2025-01-02 10:09:00 | F9: 20250101090652X612212326 | G9: 流程受理流水号：20250101085703135053602071009960 客户号码:13505360207 客户姓名:吴** 投诉地市:潍坊 来话流水:2025010108563499320853366 宽带账号:13505360207 宽带账号归属地市:潍坊 宽带账号归属区县:潍城区 故障地址:潍坊潍城区后大岗丸 联系电话:13505360207 联系人:先生 工单紧急程度:一般 是否有升级投诉倾向:否 是否重复投诉:否 是否携转意向:否 是否投诉倾向:否 是否智能网关:智能网关 当前是否在线:否 接入方式:FTTH 端到端诊断结果:状态正常 是否质差终端:无质差信息 光功率:无 故障大类:宽带 故障细类:宽带无法上网(专席) 携转原因: 故障时间:2025-01-01 08:58:29 具体故障现象:客户来电反映宽带无法上网，注册灯闪烁，将光纤线插紧，捋直，重启未恢复，请协助谢谢 客户其他诉求: | H9: 2025-01-01 09:17:34 | I9: 家宽业务->网络质量->家庭宽带->全局流转->功能使用->网络无法连接->全局流转 | J9: 王绪友 | K9: 15706307892 | L9: 潍城区 | M9: 家客铁通潍坊潍城-豪德城区装维组 | N9: 城域网割接调整 | O9: dw3_jk_wangxuyou | P9: 2025-01-01 09:18:00 | R9: =IF(OR(LEFT(L9,2)="高新"),"奎文",IF(LEFT(L9,2)="峡山","坊子",IF(LEFT(L9,2)="滨海","寒亭",LEFT(L9,2)))) -> 潍城 | S9: =TEXT(B9,"mmdd") -> 0101
A10: SD-057-250101-840263-463 | B10: 2025-01-01 09:05:18 | C10: 潍坊 | D10: 【调研】-普通区域-潍城区-贵和苑小区-13964697509-100M-魔百和投诉-次数0-202501010000121263 | E10: 2025-01-02 10:06:00 | F10: 202501010000121263 | G10: 202501010000121263#流程受理流水号：20250101090348139646975091012272 客户号码:13964697509 客户姓名:王** 投诉地市:潍坊 来话流水:2025010109032099020826545 宽带账号:13964697509 宽带账号归属地市:潍坊 宽带账号归属区县:潍城区 故障地址:潍坊潍城区经济开发区管理委员会东风西街贵和苑小区 联系电话:18863656267 联系人:女士 工单紧急程度:一般 是否有升级投诉倾向:否 是否重复投诉:否 是否携转意向:否 是否投诉倾向:否 是否智能网关:智能网关 当前是否在线:是 接入方式:FTTH 端到端诊断结果:客户侧设备问题（新增） 是否质差终端:无质差信息 光功率:-19.74 故障大类:宽带/电视 故障细类:移动高清电视故障(专席) 携转原因: 故障时间:2025-01-01 09:09:03 魔百和单播/组播:单播 具体故障现象:电视提示网络类错误 客户其他诉求: 魔百和单/组播：单播;宽带小区$[贵和苑小区]$ | H10: 2025-01-01 09:10:06 | I10: 家庭咨询->产品质量->互联网电视(移动高清)->全局流转->功能使用->无法进入播放界面->全局流转 | J10: 孙廷强 | K10: 15706307850 | L10: 潍城区 | M10: 家客铁通潍坊潍城-豪德城区装维组 | N10: 更换网线或接头 | O10: dw3_jk_wcsuntingqiang | P10: 2025-01-01 09:10:37 | R10: =IF(OR(LEFT(L10,2)="高新"),"奎文",IF(LEFT(L10,2)="峡山","坊子",IF(LEFT(L10,2)="滨海","寒亭",LEFT(L10,2)))) -> 潍城 | S10: =TEXT(B10,"mmdd") -> 0101
A11: SD-057-250101-784593-2313 | B11: 2025-01-01 12:32:20 | C11: 潍坊 | D11: 80+白金-普通区域-青州市-苏桥新居-15063632588-1000M-宽带上网投诉-次数0-202501010000301319 | E11: 2025-01-02 08:00:00 | F11: 202501010000301319 | G11: 202501010000301319#【已关注中国移动10086微信公众号】流程受理流水号：20250101122920150636325881074752 客户号码:15063632588 客户姓名:郑* 投诉地市:潍坊 来话流水:2025010112283779420871704 宽带账号:15063632588 宽带账号归属地市:潍坊 宽带账号归属区县:青州市 故障地址:潍坊青州市云门山街道范公亭东路苏桥新居东区北2号楼********* 联系电话:15063632588 联系人:女士 工单紧急程度:一般 是否有升级投诉倾向:否 是否重复投诉:否 是否携转意向:否 是否投诉倾向:否 是否智能网关:智能网关 当前是否在线:是 接入方式:FTTH 端到端诊断结果:客户侧设备问题 是否质差终端:是 光功率:-22.21 故障大类:宽带/电视 故障细类:移动高清电视故障 携转原因: 故障时间:2025-01-01 12:30:07 魔百和单播/组播:组播 具体故障现象:内容页面无法载入图片， 客户其他诉求:客户侧为质差终端，要求尽快上门处理故障问题。 | H11: 2025-01-01 12:34:55 | I11: 家庭咨询->网络质量->家庭宽带->全局流转->功能使用->光猫设备故障->线上义诊 | J11: 孙光超 | K11: 15706307651 | L11: 青州市 | M11: 家客铁通潍坊青州-黄楼乡镇装维组 | N11: 指导用户重新连接线缆 | O11: dw3_jk_sunguangchao | P11: 2025-01-01 12:35:19 | Q11: SD-851-269196-5116-16328 | R11: =IF(OR(LEFT(L11,2)="高新"),"奎文",IF(LEFT(L11,2)="峡山","坊子",IF(LEFT(L11,2)="滨海","寒亭",LEFT(L11,2)))) -> 青州 | S11: =TEXT(B11,"mmdd") -> 0101
A12: SD-057-250101-041537-4031 | B12: 2025-01-01 15:47:04 | C12: 潍坊 | D12: 普通区域-奎文区-中百大厦谷德广场店（扩容）-13869692393-1000M-宽带上网投诉-次数0-202501010000446908 | E12: 2025-01-02 08:00:00 | F12: 202501010000446908 | G12: 202501010000446908#宽带账号：13869692393**；宽带地址：**潍坊奎文区新城街道福寿街中百大厦谷德广场**；客户来电反映宽带不能连网，要求上门，请协助处理，谢谢！联系电话：*13869692393*；联系人：***；来电流水：2025010115424925220876163 | H12: 2025-01-01 15:49:09 | I12: 家庭咨询->网络质量->家庭宽带->全局流转->功能使用->客户要求装维上门服务->全局流转 | J12: 倪苹伟 | K12: 15706366536 | L12: 奎文区 | M12: 家客铁通潍坊奎文-北宫街城区装维组 | N12: 室内重新布线 | O12: dw3_jk_nipingwei | P12: 2025-01-01 15:49:45 | Q12: SD-851-323329-30301-4719 | R12: =IF(OR(LEFT(L12,2)="高新"),"奎文",IF(LEFT(L12,2)="峡山","坊子",IF(LEFT(L12,2)="滨海","寒亭",LEFT(L12,2)))) -> 奎文 | S12: =TEXT(B12,"mmdd") -> 0101
A13: SD-057-250101-809267-2332 | B13: 2025-01-01 12:35:22 | C13: 潍坊 | D13: 80+普通-普通区域-高密市-周阳平安大道小尹村沿街（小微）-15094984627-200M-宽带上网投诉-次数0-20250101123231X951165408 | E13: 2025-01-02 13:00:00 | F13: 20250101123231X951165408 | G13: 【农村网络投诉】流程受理流水号：20250101123050150949846271075104 客户号码:15094984627 客户姓名:刘* 投诉地市:潍坊 来话流水:2025010112301648220887191 宽带账号:15094984627 宽带账号归属地市:潍坊 宽带账号归属区县:高密市 故障地址:潍坊高密市密水街道平安大道周阳平安大道小尹村沿街（小微）高密周阳平安大道小尹村沿街（小微）5号箱********* 联系 | H13: 2025-01-01 12:41:52 | I13: 家宽业务->网络质量->家庭宽带->全局流转->功能使用->LOS红灯，无法上网->全局流转 | J13: 冷光朋 | K13: 15706307276 | L13: 高密市 | M13: 家客铁通潍坊高密-密水城区装维组 | N13: 重新施工布放光缆 | O13: dw3_jk_lengguangpeng | P13: 2025-01-01 12:42:11 | R13: =IF(OR(LEFT(L13,2)="高新"),"奎文",IF(LEFT(L13,2)="峡山","坊子",IF(LEFT(L13,2)="滨海","寒亭",LEFT(L13,2)))) -> 高密 | S13: =TEXT(B13,"mmdd") -> 0101
A14: SD-057-250101-152693-3991 | B14: 2025-01-01 15:44:18 | C14: 潍坊 | D14: 普通区域-诸城市-利群小区-15066368962-200M-魔百和投诉-次数0-20250101154356X436057481 | E14: 2025-01-02 16:45:00 | F14: 20250101154356X436057481 | G14: 检测结果：1、宽带是否在线：宽带在线；2、电视账号状态检测：电视账号状态异常；3、电视片源检测：电视片源正常；4、机顶盒性能检测：机顶盒性能正常；5、机顶盒设备检测：未检测到；6、电视播放流畅度检测：电视播放流畅；7、电视连接方式检测：未检测到；故障类型：电视无法观看。故障描述：机顶盒能开机但不能看电视频道节目。联系人：15066368962。联系电话：15066368962。 | H14: 2025-01-01 15:45:59 | I14: 家庭业务->产品质量->互联网电视(移动高清)->全局流转->功能使用->栏目点播、电视看点、电视[直播]无法观看->全局流转 | J14: 张伟华 | K14: 15706307949 | L14: 诸城市 | M14: 家客铁通潍坊诸城-兴华东路城区装维组 | N14: 选择正确信号源 | O14: dw3_jk_zhangweihua | P14: 2025-01-01 15:47:08 | Q14: SD-851-320726-7139-12186 | R14: =IF(OR(LEFT(L14,2)="高新"),"奎文",IF(LEFT(L14,2)="峡山","坊子",IF(LEFT(L14,2)="滨海","寒亭",LEFT(L14,2)))) -> 诸城 | S14: =TEXT(B14,"mmdd") -> 0101
A15: SD-057-250101-354829-478 | B15: 2025-01-01 09:06:19 | C15: 潍坊 | D15: 普通区域-寿光市-岳寺李-15105363210-300M-魔百和投诉-次数0-202501010000122440 | E15: 2025-01-02 08:00:00 | F15: 202501010000122440 | G15: 202501010000122440#【已关注中国移动10086微信公众号】流程受理流水号：20250101090506151053632101012728 客户号码:15105363210 客户姓名:朱** 投诉地市:潍坊 来话流水:2025010109010963220802338 宽带账号:15105363210 宽带账号归属地市:潍坊 宽带账号归属区县:寿光市 故障地址:潍坊寿光市孙家集街道岳寺李村岳寺李26号箱********* 联系电话:15095151583 联系人:先生/女士 工单紧急程度:紧急 是否有升级投诉倾向:否 是否重复投诉:否 是否携转意向:否 是否投诉倾向:否 是否智能网关:智能网关 当前是否在线:是 接入方式:FTTH 端到端诊断结果:客户侧设备问题（新增） 是否质差终端:无质差信息 光功率:-22.83 故障大类:宽带/电视 故障细类:移动高清电视故障(专席) 携转原因: 故障时间:2025-01-01 09:05:35 魔百和单播/组播:单播 具体故障现象:电视直播或点播无法观看， 客户其他诉求:谢谢 魔百和单/组播：单播;宽带小区$[岳寺李]$ | H15: 2025-01-01 09:11:25 | I15: 家庭咨询->产品质量->互联网电视(移动高清)->全局流转->功能使用->无法进入播放界面->全局流转 | J15: 孙新东 | K15: 15706307818 | L15: 寿光市 | M15: 家客铁通潍坊寿光-孙集乡镇装维组 | N15: 更换机顶盒 | O15: dw3_jk_sunxindong | P15: 2025-01-01 09:11:43 | R15: =IF(OR(LEFT(L15,2)="高新"),"奎文",IF(LEFT(L15,2)="峡山","坊子",IF(LEFT(L15,2)="滨海","寒亭",LEFT(L15,2)))) -> 寿光 | S15: =TEXT(B15,"mmdd") -> 0101
A16: SD-057-250101-368219-445 | B16: 2025-01-01 09:03:02 | C16: 潍坊 | D16: FTTR-普通区域-安丘市-大盛金湖社区（吴家院庄）-15698252312-1000M-宽带上网投诉-次数0-202501010000119327 | E16: 2025-01-02 08:00:00 | F16: 202501010000119327 | G16: 202501010000119327#流程受理流水号：20250101090158156982523121011624 客户号码:15698252312 客户姓名:韩** 投诉地市:潍坊 来话流水:2025010109000774020891021 宽带账号:15698252312 账号归属区县:安丘市锦祥通讯店 联系电话:15698252312 联系人:先生/女士 宽带地址:潍坊 工单紧急程度:非常紧急 是否投诉倾向:否 是否重复投诉:否 是否携转意向:否 是否有升级投诉倾向:否 *业务名称:业务融合移机流程宽带 投诉内容:手机号码：15698252312，【问题描述】客户已办理宽带业务，有开通单，要求装维尽快联系上门，请处理，谢谢。联系电话：15698252312，联系人：先生/女士，录音流水号：2025010109000774020891021。受理明细：531920062399999999。 在途开通单信息：536241102795333136，15698252312，2024-11-02 09:51:11，业务融合移机流程宽带，处理中，手写判断和地址录入 是否到厅:否 业务名称:业务融合移机流程宽带 ;宽带小区$[大盛金湖社区（吴家院庄）]$ | H16: 2025-01-01 09:07:00 | I16: 家庭咨询->服务触点->装维人员->全局流转->售后服务->装维人员未及时联系客户->全局流转 | J16: 王龙斌 | K16: 15706307057 | L16: 安丘市 | M16: 家客铁通潍坊安丘-吾山乡镇装维组 | N16: 已上报建设部门建设 | O16: dw3_jk_wanglongbin | P16: 2025-01-01 09:18:19 | Q16: SD-852-265126-381-28686 | R16: =IF(OR(LEFT(L16,2)="高新"),"奎文",IF(LEFT(L16,2)="峡山","坊子",IF(LEFT(L16,2)="滨海","寒亭",LEFT(L16,2)))) -> 安丘 | S16: =TEXT(B16,"mmdd") -> 0101
A17: SD-057-250101-145290-512 | B17: 2025-01-01 09:08:50 | C17: 潍坊 | D17: 80+银卡-普通区域-潍城区-恒大翡翠华庭-13205360790-1000M-宽带上网投诉-次数0-202501010000123471 | E17: 2025-01-02 08:00:00 | F17: 202501010000123471 | G17: 202501010000123471#宽带账号：13205360790；宽带地址：潍坊潍城区西关街道福寿西街恒大翡翠华庭2号楼；客户来电反映宽带网慢，客户不配合排障，要求师傅上门，请协助处理，谢谢！联系电话：13205360790；联系人：女士；来电流水：2025010109073871920875062。 | H17: 2025-01-01 09:17:23 | I17: 家庭咨询->网络质量->家庭宽带->全局流转->功能使用->客户要求装维上门服务->全局流转 | J17: 周富超 | K17: 15706307864 | L17: 潍城区 | M17: 家客铁通潍坊潍城-和平路城区装维组 | N17: 用户感觉网速慢，但测速达标 | P17: 2025-01-01 09:17:50 | R17: =IF(OR(LEFT(L17,2)="高新"),"奎文",IF(LEFT(L17,2)="峡山","坊子",IF(LEFT(L17,2)="滨海","寒亭",LEFT(L17,2)))) -> 潍城 | S17: =TEXT(B17,"mmdd") -> 0101
A18: SD-057-250101-560147-483 | B18: 2025-01-01 09:06:51 | C18: 潍坊 | D18: 【调研】-80+银卡-普通区域-潍城区-壹里阳光-18264449111-300M-宽带上网投诉-次数0-202501010000123236 | E18: 2025-01-02 08:00:00 | F18: 202501010000123236 | G18: 202501010000123236#流程受理流水号：20250101090519182644491111012809 客户号码:18264449111 客户姓名:宋** 投诉地市:潍坊 来话流水:2025010109013817420807665 宽带账号:18264449111 宽带账号归属地市:潍坊 宽带账号归属区县:潍城区 故障地址:潍坊潍城区西关街道长松路壹里阳光壹里阳光二期11号楼********* 联系电话:15964302878 联系人:先生/女士 工单紧急程度:一般 是否有升级投诉倾向:否 是否重复投诉:否 是否携转意向:否 是否投诉倾向:否 是否智能网关:智能网关 当前是否在线:是 接入方式:FTTH 端到端诊断结果:客户侧设备问题（新增） 是否质差终端:无质差信息 光功率:-24.55 故障大类:宽带/电视 故障细类:电脑上网出现故障(专席) 携转原因: 故障时间:2025-01-01 08:59:31 具体故障现象:电脑无法上网，拔插网线，更换网口，未恢复，请协助处理，谢谢 客户其他诉求: ;宽带小区$[壹里阳光]$ | H18: 2025-01-01 09:10:27 | I18: 家宽咨询->网络质量->家庭宽带->全局流转->功能使用->远程计算机无法响应->全局流转 | J18: 孙宗来 | K18: 15706307854 | L18: 潍城区 | M18: 家客铁通潍坊潍城-和平路城区装维组 | N18: 重启终端 | O18: dw3_jk_wcsunzonglai | P18: 2025-01-01 09:10:42 | R18: =IF(OR(LEFT(L18,2)="高新"),"奎文",IF(LEFT(L18,2)="峡山","坊子",IF(LEFT(L18,2)="滨海","寒亭",LEFT(L18,2)))) -> 潍城 | S18: =TEXT(B18,"mmdd") -> 0101
A19: SD-057-250101-869231-2307 | B19: 2025-01-01 12:32:04 | C19: 潍坊 | D19: 【追1】80+普通-普通区域-诸城市-四季美林二期-18364695606-200M-宽带上网投诉-次数0-20250101122925X765567918 | E19: 2025-01-02 13:00:00 | F19: 20250101122925X765567918 | G19: 流程受理流水号：20250101122832183646956061074578 客户号码:18364695606 客户姓名:张** 投诉地市:潍坊 来话流水:2025010112250468120836969 宽带账号:18364695606 宽带账号归属地市:潍坊 宽带账号归属区县:诸城市 故障地址:潍坊诸城市龙都街道张择端路四季美林二期2号楼********* 联系电话:18364695606 联系人:先生/女士 工单紧急程度:紧急 是否有升级投诉倾向:否 是否重复投诉:否 是否携转意向:否 是否投诉倾向:否 是否智能网关:智能网关 当前是否在线:是 接入方式:FTTH 端到端诊断结果:客户侧设备问题（新增） 是否质差终端:无质差信息 光功率:-16.84 故障大类:宽带/电视 故障细类:网速慢/上网掉线(专席) 携转原因: 故障时间:2025-01-01 12:25:36 具体故障现象:网速慢卡顿，路由器位置开阔，指导重启未恢复，请协助，谢谢 客户其他诉求: | H19: 2025-01-01 12:47:59 | I19: 家宽业务->网络质量->家庭宽带->全局流转->功能使用->频繁出现故障、网速慢->全局流转 | J19: 丁正 | K19: 15706307374 | L19: 诸城市 | M19: 家客铁通潍坊诸城-兴华西路城区装维组 | N19: 用户感觉网速慢，但测速达标 | O19: dw3_jk_dingzheng | P19: 2025-01-01 12:49:11 | R19: =IF(OR(LEFT(L19,2)="高新"),"奎文",IF(LEFT(L19,2)="峡山","坊子",IF(LEFT(L19,2)="滨海","寒亭",LEFT(L19,2)))) -> 诸城 | S19: =TEXT(B19,"mmdd") -> 0101
A20: SD-057-250101-145679-3989 | B20: 2025-01-01 15:44:10 | C20: 潍坊 | D20: (目标)普通区域-潍城区-巨力新村-15165601317-300M-宽带上网投诉-次数0-20250101154348X428693845 | E20: 2025-01-02 08:00:00 | F20: 20250101154348X428693845 | G20: 【农村网络投诉】流程受理流水号：20250101154243151656013171128498 客户号码:15165601317 客户姓名:张* 投诉地市:潍坊 来话流水:2025010115421311920868961 宽带账号:15165601317 宽带账号归属地市:潍坊 宽带账号归属区县:潍城区 故障地址:潍坊潍城区西关街道长松路巨力新村东1号楼********* 联系电话:15165601317 联系人:先生/女士 工单紧急程度:一般 是否有升级投诉倾向:否 是否重复投诉:否 是否携转意向:否 是否投诉倾向:否 是否智能网关:智能网关 当前是否在线:否 接入方式:FTTH 端到端诊断结果:状态正常 是否质差终端:无质差信息 光功率:无 故障大类:宽带/电视 故障细类:宽带无法上网 携转原因: 故障时间:2025-01-01 15:43:01 具体故障现象:光猫灯正常但电脑手机无法上网， 客户其他诉求: | H20: 2025-01-01 15:45:52 | I20: 家宽业务->网络质量->家庭宽带->全局流转->功能使用->网络无法连接->全局流转 | J20: 曹会武 | K20: 15706307855 | L20: 潍城区 | M20: 家客铁通潍坊潍城-东风街城区装维组 | N20: 更换端口 | O20: dw3_jk_caohuiwu | P20: 2025-01-01 15:46:36 | R20: =IF(OR(LEFT(L20,2)="高新"),"奎文",IF(LEFT(L20,2)="峡山","坊子",IF(LEFT(L20,2)="滨海","寒亭",LEFT(L20,2)))) -> 潍城 | S20: =TEXT(B20,"mmdd") -> 0101
A21: SD-057-250101-042653-2324 | B21: 2025-01-01 12:34:15 | C21: 潍坊 | D21: 普通区域-青州市-西马兰村-15288825072-100M-宽带上网投诉-次数0-202501010000302244 | E21: 2025-01-02 13:00:00 | F21: 202501010000302244 | G21: 202501010000302244#流程受理流水号：20250101123324152888250721075730 客户号码:15288825072 客户姓名:黄** 投诉地市:潍坊 来话流水:2025010112324435920810176 宽带账号:15288825072 宽带账号归属地市:潍坊 宽带账号归属区县:青州市 故障地址:潍坊青州市高柳镇西马兰村西马兰村29号箱(村南邢天宫）********* 联系电话:19805362768 联系人:先生/女士 工单紧急程度:非常紧急 是否有升级投诉倾向:否 是否重复投诉:否 是否携转意向:否 是否投诉倾向:否 是否智能网关:非智能网关 当前是否在线:是 接入方式:FTTH 端到端诊断结果:客户侧设备问题 是否质差终端:是 光功率:无 故障大类:宽带/电视 故障细类:移动高清电视故障 携转原因: 故障时间:2025-01-01 12:33:38 魔百和单播/组播:单播 具体故障现象:电视直播或点播无法观看， 客户其他诉求:客户侧为质差终端，要求上门更换终端并一并处理故障问题。 | H21: 2025-01-01 12:37:17 | I21: 家庭咨询->网络质量->家庭宽带->全局流转->功能使用->光猫设备故障->线上义诊 | J21: 李超 | K21: 15706307648 | L21: 青州市 | M21: 家客铁通潍坊青州-高柳乡镇装维组 | N21: 改为有线接入 | O21: dw3_jk_lichao | P21: 2025-01-01 12:37:44 | R21: =IF(OR(LEFT(L21,2)="高新"),"奎文",IF(LEFT(L21,2)="峡山","坊子",IF(LEFT(L21,2)="滨海","寒亭",LEFT(L21,2)))) -> 青州 | S21: =TEXT(B21,"mmdd") -> 0101
A22: SD-057-250101-712584-1429 | B22: 2025-01-01 10:53:14 | C22: 潍坊 | D22: 【调研】-(目标)普通区域-寿光市-鸿正领寓-15963605751-100M-宽带上网投诉-次数0-20250101105239X959757435 | E22: 2025-01-02 11:54:00 | F22: 20250101105239X959757435 | G22: 检测结果：1、宽带账号登录状态检测：账号登录状态正常；2、手机账号余额检测：手机账户余额正常；3、宽带速率检测：宽带速率正常；4、宽带状态检测：宽带状态正常；5、群体故障检测：无大面积群障；6、线路检测：线路状态正常；7、光猫在线检测：光猫在线；故障类型：频繁出现故障、网速慢。故障描述：频繁断网连接失败手机电视都不行。联系人：15963605751。联系电话：15963605751。。 | H22: 2025-01-01 10:55:10 | I22: 家宽业务->网络质量->家庭宽带->全局流转->功能使用->频繁出现故障、网速慢->全局流转 | J22: 刘冰 | K22: 15706307742 | L22: 寿光市 | M22: 家客铁通潍坊寿光-市中城区装维组 | N22: 重新连接机顶盒网络 | O22: dw3_jk_liubing | P22: 2025-01-01 10:55:38 | R22: =IF(OR(LEFT(L22,2)="高新"),"奎文",IF(LEFT(L22,2)="峡山","坊子",IF(LEFT(L22,2)="滨海","寒亭",LEFT(L22,2)))) -> 寿光 | S22: =TEXT(B22,"mmdd") -> 0101
A23: SD-057-250101-429307-5678 | B23: 2025-01-01 18:37:10 | C23: 潍坊 | D23: 普通区域-安丘市-三合村自然村-18263632618-100M-宽带上网投诉-次数0-202501010000592388 | E23: 2025-01-02 19:00:00 | F23: 202501010000592388 | G23: 202501010000592388#受理号码 : 18263632618客户姓名 : 李**号码归属地 : 潍坊安丘 － 安丘市金冢子镇诺基亚手机超市-李小惠（社区）用户品牌 : 神州行 客户来电反映：跨带无法连接摄像头，客户要求上门，请求协助处理，谢谢！ 联系电话：18263693362 联系人：先生 宽带地址：潍坊安丘市金冢子镇三合村 来电流水：2025010118315152320888950 | H23: 2025-01-01 18:40:05 | I23: 家庭咨询->网络质量->家庭宽带->全局流转->功能使用->客户要求装维上门服务->全局流转 | J23: 王炳龙 | K23: 15706307018 | L23: 安丘市 | M23: 家客铁通潍坊安丘-景芝乡镇装维组 | N23: 【退单】无延伸服务工单 | O23: dw3_jk_wangbinglong | P23: 2025-01-01 18:41:04 | R23: =IF(OR(LEFT(L23,2)="高新"),"奎文",IF(LEFT(L23,2)="峡山","坊子",IF(LEFT(L23,2)="滨海","寒亭",LEFT(L23,2)))) -> 安丘 | S23: =TEXT(B23,"mmdd") -> 0101
A24: SD-057-250101-528674-1492 | B24: 2025-01-01 10:59:14 | C24: 潍坊 | D24: 【调研】-80+普通-普通区域-安丘市-西南庄村自然村-15553626586-1000M-宽带上网投诉-次数0-202501010000220555 | E24: 2025-01-02 08:00:00 | F24: 202501010000220555 | G24: 202501010000220555#流程受理流水号：20250101105818155536265861048561 客户号码:15553626586 客户姓名:刘* 投诉地市:潍坊 来话流水:2025010110575005620886934 宽带账号:15553626586 宽带账号归属地市:潍坊 宽带账号归属区县:安丘市 故障地址:潍坊安丘市白芬子镇西南庄村西南庄村自然村西南庄村10号箱东南2刘新强********* 联系电话:15553626586 联系人:先生/女士 工单紧急程度:非常紧急 是否有升级投诉倾向:否 是否重复投诉:否 是否携转意向:否 是否投诉倾向:否 是否智能网关:智能网关 当前是否在线:否 接入方式:FTTH 端到端诊断结果:大面积故障 是否质差终端:无质差信息 光功率:无 故障大类:宽带/电视 故障细类:宽带无法上网(专席) 携转原因: 故障时间:2025-01-01 10:55:36 具体故障现象:网线断开 客户其他诉求: ;宽带小区$[西南庄村自然村]$ | H24: 2025-01-01 11:02:01 | I24: 家宽咨询->网络质量->家庭宽带->全局流转->功能使用->网络无法连接->全局流转 | J24: 徐中华 | K24: 15706307040 | L24: 安丘市 | M24: 家客铁通潍坊安丘-官庄乡镇装维组 | N24: 更换皮线或网线 | O24: dw3_jk_xuzhonghua | P24: 2025-01-01 11:02:22 | Q24: SD-851-336841-4233-18985 | R24: =IF(OR(LEFT(L24,2)="高新"),"奎文",IF(LEFT(L24,2)="峡山","坊子",IF(LEFT(L24,2)="滨海","寒亭",LEFT(L24,2)))) -> 安丘 | S24: =TEXT(B24,"mmdd") -> 0101
A25: SD-057-250101-823091-1436 | B25: 2025-01-01 10:54:08 | C25: 潍坊 | D25: 【调研】-80+银卡-(目标)普通区域-诸城市-祥和小区-15153695395-300M-魔百和投诉-次数0-202501010000217506 | E25: 2025-01-02 08:00:00 | F25: 202501010000217506 | G25: 202501010000217506#【已关注中国移动10086微信公众号】流程受理流水号：20250101105113151536953951046269 客户号码:15153695395 客户姓名:郭** 投诉地市:潍坊 来话流水:2025010110522002920813441 宽带账号:15153695395 宽带账号归属地市:潍坊 宽带账号归属区县:诸城市 故障地址:潍坊诸城市密州街道人民东路祥和小区7号楼********* 联系电话:18263609951 联系人:先生 工单紧急程度:一般 是否有升级投诉倾向:否 是否重复投诉:否 是否携转意向:否 是否投诉倾向:否 是否智能网关:智能网关 当前是否在线:是 接入方式:FTTH 端到端诊断结果:客户侧设备问题（新增） 是否质差终端:无质差信息 光功率:-21.87 故障大类:宽带/电视 故障细类:移动高清电视故障(专席) 携转原因: 故障时间:2025-01-01 10:57:22 魔百和单播/组播:单播 具体故障现象:视频播放出现花屏， 客户其他诉求: 魔百和单/组播：单播;宽带小区$[祥和小区]$ | H25: 2025-01-01 11:00:55 | I25: 家庭咨询->产品质量->互联网电视(移动高清)->全局流转->功能使用->栏目点播、电视看点、电视[直播]无法观看->全局流转 | J25: 石震 | K25: 15706307950 | L25: 诸城市 | M25: 家客铁通潍坊诸城-兴华东路城区装维组 | N25: 重新调试终端 | O25: dw3_jk_shizhen | P25: 2025-01-01 11:01:20 | Q25: SD-851-268091-10195-708 | R25: =IF(OR(LEFT(L25,2)="高新"),"奎文",IF(LEFT(L25,2)="峡山","坊子",IF(LEFT(L25,2)="滨海","寒亭",LEFT(L25,2)))) -> 诸城 | S25: =TEXT(B25,"mmdd") -> 0101
A26: SD-057-250101-173964-6608 | B26: 2025-01-01 20:32:20 | C26: 潍坊 | D26: 普通区域-诸城市-奥韵花园-18369652188-300M-宽带上网投诉-次数0-202501010000646135 | E26: 2025-01-02 18:00:00 | F26: 202501010000646135 | G26: 202501010000646135#宽带账号：18369652188；宽带地址：潍坊诸城市密州街道东坡街奥韵花园30号楼*********；客户来电反映移动高清无法观看，客户不在现场，无法配合线上指导/客户不配合排障，要求上门，请协助处理，谢谢！！来电流水：2025010120244771520848167，联系电话：18369652188 | H26: 2025-01-01 20:39:01 | I26: 家庭咨询->网络质量->家庭宽带->全局流转->功能使用->客户要求装维上门服务->全局流转 | J26: 石震 | K26: 15706307950 | L26: 诸城市 | M26: 家客铁通潍坊诸城-兴华东路城区装维组 | O26: dw3_jk_shizhen | P26: 2025-01-01 20:41:25 | Q26: SD-851-316721-10438-26100 | R26: =IF(OR(LEFT(L26,2)="高新"),"奎文",IF(LEFT(L26,2)="峡山","坊子",IF(LEFT(L26,2)="滨海","寒亭",LEFT(L26,2)))) -> 诸城 | S26: =TEXT(B26,"mmdd") -> 0101
A27: SD-057-250101-647352-6600 | B27: 2025-01-01 20:30:28 | C27: 潍坊 | D27: 80+普通-FTTR-普通区域-寿光市-文盛家园-18754402777-1000M-宽带上网投诉-次数0-202501010000642464 | E27: 2025-01-02 18:00:00 | F27: 202501010000642464 | G27: 202501010000642464#宽带账号：18754402777，宽带地址：潍坊寿光市文家街道黄海路文盛家园，客户办理移动高清业务，电视无法观看，机顶盒不通电，客户不方便线上排障要求上门维修，请处理，联系电话：14768449444或18754402777，联系人：本人，谢谢，来电流水：2025010120223057520836127 | H27: 2025-01-01 20:38:00 | I27: 家庭咨询->网络质量->家庭宽带->全局流转->功能使用->客户要求装维上门服务->全局流转 | J27: 王松强 | K27: 15706307773 | L27: 寿光市 | M27: 家客铁通潍坊寿光-文家乡镇装维组 | O27: dw3_jk_wangsongqiang | Q27: SD-851-275454-12649-15260 | R27: =IF(OR(LEFT(L27,2)="高新"),"奎文",IF(LEFT(L27,2)="峡山","坊子",IF(LEFT(L27,2)="滨海","寒亭",LEFT(L27,2)))) -> 寿光 | S27: =TEXT(B27,"mmdd") -> 0101
A28: SD-057-250101-503642-1409 | B28: 2025-01-01 10:50:28 | C28: 潍坊 | D28: 80+银卡-普通区域-坊子区-营子花园-18764639188-1000M-魔百和投诉-次数0-20250101104807X687351747 一级督办 | E28: 2025-01-02 08:00:00 | F28: 20250101104807X687351747 | G28: 【农村网络投诉】【预处理派单】宽带账号：18764639188，宽带地址： 潍坊坊子区坊子新区辛李家村营子花园坊子营子花园3号楼*********，故障现象：，故障现象类型：，客户诉求：客户来点反应有部分频道缺失，操作了恢复出厂设置，没有恢复，请协助处理，谢谢，联系电话：18764639188，通话流水：2025010110395658720845521。接入方式：，当前是否在线：，端到端诊断结果：，是否智能网关：，光功率。,单组播状态:组播 | H28: 2025-01-01 10:54:35 | I28: 家庭业务->产品质量->互联网电视(移动高清)->全局流转->功能使用->观看内容缺失->全局流转 | J28: 王富峰 | K28: 15706307267 | L28: 坊子区 | M28: 家客铁通潍坊坊子-凤凰城区装维组 | N28: 用户感觉网速慢，但测速达标 | O28: dw3_jk_wangfufeng | P28: 2025-01-01 10:56:12 | Q28: SD-851-225950-16241-2875 | R28: =IF(OR(LEFT(L28,2)="高新"),"奎文",IF(LEFT(L28,2)="峡山","坊子",IF(LEFT(L28,2)="滨海","寒亭",LEFT(L28,2)))) -> 坊子 | S28: =TEXT(B28,"mmdd") -> 0101
A29: SD-057-250101-923057-2848 | B29: 2025-01-01 13:40:13 | C29: 潍坊 | D29: 80+银卡-普通区域-青州市-牛角-13780812668-1000M-宽带上网投诉-次数0-202501010000341455 | E29: 2025-01-02 08:00:00 | F29: 202501010000341455 | G29: 202501010000341455#宽带账号13780812668；宽带地址：潍坊青州市王府街道史店村；客户来电反映宽带，经查询客户侧为质差终端，请协助上门更换终端并一并处理故障问题，谢谢！联系电话：13780812668；联系人：先生；来电流水：2025010113352279220862569 | H29: 2025-01-01 13:42:42 | I29: 家庭咨询->网络质量->家庭宽带->全局流转->功能使用->客户要求装维上门服务->全局流转 | J29: 盛国伟 | K29: 15706307697 | L29: 青州市 | M29: 家客铁通潍坊青州-王府乡镇装维组 | N29: 重新熔缆 | O29: dw3_jk_shengguowei | P29: 2025-01-01 13:43:06 | Q29: SD-851-315706-12281-5540 | R29: =IF(OR(LEFT(L29,2)="高新"),"奎文",IF(LEFT(L29,2)="峡山","坊子",IF(LEFT(L29,2)="滨海","寒亭",LEFT(L29,2)))) -> 青州 | S29: =TEXT(B29,"mmdd") -> 0101
A30: SD-057-250101-931286-2862 | B30: 2025-01-01 13:41:51 | C30: 潍坊 | D30: 普通区域--null-18706502091-宽带上网投诉-次数0-202501010000343079 | E30: 2025-01-02 13:00:00 | F30: 202501010000343079 | G30: 202501010000343079#【已关注中国移动10086微信公众号】流程受理流水号：20250101134111187065020911092362 客户号码:18706502091 客户姓名:潘** 投诉地市:潍坊 来话流水:2025010113391432120898133 宽带账号:18706502091 账号归属区县:高密-高密市辰鑫手机通讯经营部 联系电话:18706502091 联系人:先生 宽带地址:潍坊 工单紧急程度:一般 是否投诉倾向:否 是否重复投诉:否 是否携转意向:否 是否有升级投诉倾向:否 *业务名称:业务融合开机流程宽带 投诉内容:手机号码：18706502091，【问题描述】客户已办理宽带业务，有开通单，要求装维尽快联系上门，请处理，谢谢。联系电话：18706502091，联系人：先生，录音流水号：2025010113391432120898133。受理明细：531920062399999999。 在途开通单信息：536250101487470208，18706502091，2025-01-01 10:36:16，业务融合开机流程宽带，处理中，黄单扩容 是否到厅:否 业务名称:业务融合开机流程宽带 ;宽带小区$[null]$ | H30: 2025-01-01 17:43:32 | I30: 家庭咨询->服务触点->装维人员->全局流转->售后服务->装维人员未及时联系客户->全局流转 | J30: 王坤 | K30: 15706307002 | N30: 营业厅重新办理业务 | O30: wangkunwf | R30: =IF(OR(LEFT(L30,2)="高新"),"奎文",IF(LEFT(L30,2)="峡山","坊子",IF(LEFT(L30,2)="滨海","寒亭",LEFT(L30,2)))) | S30: =TEXT(B30,"mmdd") -> 0101
A31: SD-057-250101-136407-6609 | B31: 2025-01-01 20:32:46 | C31: 潍坊 | D31: 【调研】-80+银卡-普通区域-寿光市-三座楼小区-18453632389-1000M-宽带上网投诉-次数0-202501010000646234 | E31: 2025-01-02 18:00:00 | F31: 202501010000646234 | G31: 202501010000646234#宽带账号：18453632389；宽带地址：潍坊寿光市台头镇三座楼村；客户来电反映宽带上网慢，客户已将光猫路由器断电并按顺序重启后仍未恢复，要求上门，请协助处理，谢谢！联系电话：15253695493；联系人：先生；来电流水：2025010120260355420854735。 | H31: 2025-01-01 20:50:05 | I31: 家庭咨询->网络质量->家庭宽带->全局流转->功能使用->客户要求装维上门服务->全局流转 | J31: 刘鑫平 | K31: 15706307754 | L31: 寿光市 | M31: 家客铁通潍坊寿光-台头乡镇装维组 | O31: dw3_jk_liuxinping | P31: 2025-01-01 20:50:27 | Q31: SD-851-269961-14656-25145 | R31: =IF(OR(LEFT(L31,2)="高新"),"奎文",IF(LEFT(L31,2)="峡山","坊子",IF(LEFT(L31,2)="滨海","寒亭",LEFT(L31,2)))) -> 寿光 | S31: =TEXT(B31,"mmdd") -> 0101
A32: SD-057-250101-734905-5651 | B32: 2025-01-01 18:35:23 | C32: 潍坊 | D32: 【调研】-80+银卡-普通区域-临朐县-王家西圈自然村-18264639998-300M-宽带上网投诉-次数0-202501010000591373 | E32: 2025-01-02 19:00:00 | F32: 202501010000591373 | G32: 202501010000591373#宽带账号：18265368660；宽带地址：潍坊临朐县辛寨镇王家西圈；客户来电反映宽带无法上网，要求师傅上门，请协助处理，谢谢！联系电话：18265368660；联系人：先生；来电流水：2025010118293263120869786。 | H32: 2025-01-01 18:36:48 | I32: 家庭咨询->网络质量->家庭宽带->全局流转->功能使用->客户要求装维上门服务->全局流转 | J32: 王海城 | K32: 15706307564 | L32: 临朐县 | M32: 家客铁通潍坊临朐-辛寨乡镇装维组 | N32: 选择正确信号源 | O32: dw3_jk_wanghaicheng | P32: 2025-01-01 18:37:09 | Q32: SD-851-282514-14740-24592 | R32: =IF(OR(LEFT(L32,2)="高新"),"奎文",IF(LEFT(L32,2)="峡山","坊子",IF(LEFT(L32,2)="滨海","寒亭",LEFT(L32,2)))) -> 临朐 | S32: =TEXT(B32,"mmdd") -> 0101
A33: SD-057-250101-509627-6649 | B33: 2025-01-01 20:39:13 | C33: 潍坊 | D33: 普通区域-潍城区-陈家油坊-18866369055-1000M-宽带上网投诉-次数0-202501010000647779 | E33: 2025-01-02 18:00:00 | F33: 202501010000647779 | G33: 202501010000647779#宽带账号：18866369055*；宽带地址：潍坊潍城区城关街道向阳路陈家油坊**；客户来电反映宽带搜不到无线网信号，重启未恢复，要求上门，请协助处理，谢谢！联系电话：*13969880997*；联系人：***；来电流水：2025010120310872120881268 | H33: 2025-01-01 20:41:40 | I33: 家庭咨询->网络质量->家庭宽带->全局流转->功能使用->客户要求装维上门服务->全局流转 | J33: 张广顺 | K33: 15305366017 | L33: 潍城区 | M33: 家客铁通潍坊潍城-和平路城区装维组 | O33: dw3_jk_wczhangguangshun | P33: 2025-01-01 20:41:59 | Q33: SD-851-274427-8671-215 | R33: =IF(OR(LEFT(L33,2)="高新"),"奎文",IF(LEFT(L33,2)="峡山","坊子",IF(LEFT(L33,2)="滨海","寒亭",LEFT(L33,2)))) -> 潍城 | S33: =TEXT(B33,"mmdd") -> 0101
A34: SD-057-250101-619702-6639 | B34: 2025-01-01 20:37:57 | C34: 潍坊 | D34: 普通区域-高密市-海怡东方花园-13864683552-300M-宽带上网投诉-次数0-202501010000647922 | E34: 2025-01-02 18:00:00 | F34: 202501010000647922 | G34: 202501010000647922#流程受理流水号：20250101203717138646835521201715 客户号码:13864683552 客户姓名:王** 投诉地市:潍坊 来话流水:2025010120365954520810823 宽带账号:13864683552 宽带账号归属地市:潍坊 宽带账号归属区县:高密市 故障地址:潍坊高密市密水街道创业街千树海小区13号楼********* 联系电话:13864683552 联系人:先生/女士 工单紧急程度:一般 是否有升级投诉倾向:否 是否重复投诉:否 是否携转意向:否 是否投诉倾向:否 是否智能网关:智能网关 当前是否在线:是 接入方式:FTTH 端到端诊断结果:客户侧设备问题 是否质差终端:是 光功率:无 故障大类:宽带/电视 故障细类:宽带无法上网 携转原因: 故障时间:2025-01-01 20:37:29 具体故障现象:网速慢卡顿， 客户其他诉求:客户侧为质差终端，要求上门更换终端并一并处理故障问题。 | H34: 2025-01-01 20:41:37 | I34: 家庭咨询->网络质量->家庭宽带->全局流转->功能使用->光猫设备故障->线上义诊 | J34: 贾鑫 | K34: 15706307327 | L34: 高密市 | M34: 家客铁通潍坊高密-醴泉城区装维组 | O34: dw3_jk_jiaxin | P34: 2025-01-01 20:42:02 | R34: =IF(OR(LEFT(L34,2)="高新"),"奎文",IF(LEFT(L34,2)="峡山","坊子",IF(LEFT(L34,2)="滨海","寒亭",LEFT(L34,2)))) -> 高密 | S34: =TEXT(B34,"mmdd") -> 0101
A35: SD-057-250101-041582-6947 | B35: 2025-01-01 21:50:05 | C35: 潍坊 | D35: 【调研】-普通区域-寿光市-环翠花园-18863650682-500M-魔百和投诉-次数0-20250101214744X264263726 | E35: 2025-01-02 18:00:00 | F35: 20250101214744X264263726 | G35: 检测结果：1、宽带是否在线：宽带在线；2、电视账号状态检测：电视账号状态正常；3、电视片源检测：电视片源正常；4、机顶盒性能检测：机顶盒性能正常；5、机顶盒设备检测：机顶盒设备正常；6、电视播放流畅度检测：电视播放流畅；7、电视连接方式检测：未检测到；故障类型：视频卡顿、声画不同步。故障描述：电视卡顿、网络不流畅，网络不好，重启机顶盒无用。联系人：李建文。联系电话：18863650682。 | H35: 2025-01-02 07:03:21 | I35: 家庭业务->网络质量->互联网电视(移动高清)->全局流转->功能使用->点播和直播观看都出现卡顿、缓冲、声画不同步->全局流转 | J35: 李永伟 | K35: 15706307736 | L35: 寿光市 | M35: 家客铁通潍坊寿光-东城城区装维组 | O35: dw3_jk_liyongwei | R35: =IF(OR(LEFT(L35,2)="高新"),"奎文",IF(LEFT(L35,2)="峡山","坊子",IF(LEFT(L35,2)="滨海","寒亭",LEFT(L35,2)))) -> 寿光 | S35: =TEXT(B35,"mmdd") -> 0101
A36: SD-057-250101-845370-2952 | B36: 2025-01-01 13:47:36 | C36: 潍坊 | D36: 80+银卡-普通区域-潍城区-乔铁村-18369650345-1000M-宽带上网投诉-次数0-202501010000349334 | E36: 2025-01-02 08:00:00 | F36: 202501010000349334 | G36: 202501010000349334#宽带账号：18369650345；宽带地址：潍坊潍城区乐埠山生态经济发展区乔铁村；客户来电反映移动宽带无法使用，经查询客户侧为质差路由器，请协助上门更换设备并一并处理故障问题，谢谢！联系电话：13573666706；联系人：先生；来电流水：2025010113422376320827521 | H36: 2025-01-01 13:48:31 | I36: 家庭咨询->网络质量->家庭宽带->全局流转->功能使用->路由器质差->全局流转 | J36: 杜桂超 | K36: 15706307902 | L36: 潍城区 | M36: 家客铁通潍坊潍城-豪德城区装维组 | N36: 更换皮线或网线 | O36: dw3_jk_duguichaowc | P36: 2025-01-01 13:49:09 | R36: =IF(OR(LEFT(L36,2)="高新"),"奎文",IF(LEFT(L36,2)="峡山","坊子",IF(LEFT(L36,2)="滨海","寒亭",LEFT(L36,2)))) -> 潍城 | S36: =TEXT(B36,"mmdd") -> 0101
A37: SD-057-250101-734506-1483 | B37: 2025-01-01 10:58:25 | C37: 潍坊 | D37: 80+普通-普通区域-寿光市-新华园小区-15864331200-1000M-宽带上网投诉-次数0-202501010000222041 | E37: 2025-01-02 08:00:00 | F37: 202501010000222041 | G37: 202501010000222041#【已关注中国移动10086微信公众号】流程受理流水号：20250101105731158643312001048313 客户号码:15864331200 客户姓名:高** 投诉地市:潍坊 来话流水:2025010110540034720836005 宽带账号:15864331200 宽带账号归属地市:潍坊 宽带账号归属区县:-- 故障地址:潍坊寿光市圣城街道石马路新华园小区3号楼********* 联系电话:15318932161 联系人:先生 工单紧急程度:一般 是否有升级投诉倾向:否 是否重复投诉:否 是否携转意向:否 是否投诉倾向:否 是否智能网关:智能网关 当前是否在线:是 接入方式:FTTH 端到端诊断结果:客户侧设备问题（新增） 是否质差终端:无质差信息 光功率:-18.72 故障大类:宽带 故障细类:宽带无法上网(专席) 携转原因: 故障时间:2025-01-01 10:57:20 具体故障现象:打不开网页， 客户其他诉求:网口指示灯正常，网线连接正确，外接路由器，未操作恢复出厂或者换新，指导断电重启设备无效，请协助处理，谢谢。 ;宽带小区$[新华园小区]$ | H37: 2025-01-01 11:15:35 | I37: 家宽咨询->网络质量->家庭宽带->全局流转->功能使用->网络无法连接->全局流转 | J37: 孙新程 | K37: 15706307815 | L37: 寿光市 | M37: 家客铁通潍坊寿光-西城城区装维组 | N37: 指导用户输入正确宽带账号密码 | O37: dw3_jk_sunxincheng | P37: 2025-01-01 11:15:59 | Q37: SD-851-290100-16732-25949 | R37: =IF(OR(LEFT(L37,2)="高新"),"奎文",IF(LEFT(L37,2)="峡山","坊子",IF(LEFT(L37,2)="滨海","寒亭",LEFT(L37,2)))) -> 寿光 | S37: =TEXT(B37,"mmdd") -> 0101
A38: SD-057-250101-180327-1642 | B38: 2025-01-01 11:14:45 | C38: 潍坊 | D38: 【调研】-普通区域-昌乐县-月亮湾-18706539857-300M-宽带上网投诉-次数0-202501010000235227 | E38: 2025-01-02 08:00:00 | F38: 202501010000235227 | G38: 202501010000235227#宽带账号：18706539857；宽带地址：潍坊昌乐县城关街道新昌路月亮湾18号楼*********；客户来电反映移动高清电视观看直播时全屏后屏幕很小，客户不会操作，无法配合线上指导，要求上门，请协助处理，谢谢！联系电话：本机；联系人：先生/女士；来电流水：2025010111094569220845654。 | H38: 2025-01-01 11:24:09 | I38: 家庭咨询->网络质量->家庭宽带->全局流转->功能使用->客户要求装维上门服务->全局流转 | J38: 赵海磊 | K38: 15706307129 | L38: 昌乐县 | M38: 家客铁通潍坊昌乐-方山路城区装维组 | N38: 指导用户正确使用遥控器 | O38: dw3_jk_zhaohailei | P38: 2025-01-01 11:24:40 | Q38: SD-851-288007-32061-7311 | R38: =IF(OR(LEFT(L38,2)="高新"),"奎文",IF(LEFT(L38,2)="峡山","坊子",IF(LEFT(L38,2)="滨海","寒亭",LEFT(L38,2)))) -> 昌乐 | S38: =TEXT(B38,"mmdd") -> 0101
A39: SD-057-250101-975430-5639 | B39: 2025-01-01 18:32:29 | C39: 潍坊 | D39: 80+普通-普通区域-寿光市-杨庄小区二期-18366352028-1000M-宽带上网投诉-次数0-202501010000589783 | E39: 2025-01-02 19:00:00 | F39: 202501010000589783 | G39: 202501010000589783#宽带账号：18366352028；宽带地址：潍坊寿光市杨庄杨庄村杨庄小区二期2号楼*********；客户来电反映电视看不了，经查询客户侧为质差机顶盒，请协助上门更换终端并一并处理故障问题，谢谢！联系电话：18366352028；联系人：杨**；来电流水：2025010118242188920825612。 | H39: 2025-01-01 18:34:04 | I39: 家庭咨询->网络质量->家庭宽带->全局流转->功能使用->质差机顶盒->全局流转 | J39: 刘春瑞 | K39: 15706307347 | L39: 寿光市 | M39: 家客铁通潍坊寿光-营里乡镇装维组 | N39: 选择正确信号源 | O39: dw3_jk_liuchunrui | P39: 2025-01-01 18:35:04 | Q39: SD-851-276436-10034-10871 | R39: =IF(OR(LEFT(L39,2)="高新"),"奎文",IF(LEFT(L39,2)="峡山","坊子",IF(LEFT(L39,2)="滨海","寒亭",LEFT(L39,2)))) -> 寿光 | S39: =TEXT(B39,"mmdd") -> 0101
A40: SD-057-250101-872164-2891 | B40: 2025-01-01 13:44:24 | C40: 潍坊 | D40: 【调研】-(目标)普通区域-青州市-化肥街-13863697217-100M-宽带上网投诉-次数0-20250101134132X926229530 | E40: 2025-01-02 13:00:00 | F40: 20250101134132X926229530 | G40: 流程受理流水号：20250101133955138636972171092059 客户号码:13863697217 客户姓名:魏** 投诉地市:潍坊 来话流水:2025010113391287120897912 宽带账号:13863697217 宽带账号归属地市:潍坊 宽带账号归属区县:青州市 故障地址:潍坊青州市益都街道明祖山西路化肥街外运宿舍1号楼********* 联系电话:15165683392 联系人:先生/女士 工单紧急程度:一般 是否有升级投诉倾向:否 是否重复投诉:否 是否携转意向:否 是否投诉倾向:否 是否智能网关:智能网关 当前是否在线:否 接入方式:-- 端到端诊断结果:大面积故障 是否质差终端:无质差信息 光功率:无 故障大类:宽带/电视 故障细类:宽带无法上网 携转原因: 故障时间:2025-01-01 13:53:51 具体故障现象:频繁掉线， 客户其他诉求: | H40: 2025-01-01 13:46:00 | I40: 家宽业务->网络质量->家庭宽带->全局流转->功能使用->LOS红灯，无法上网->全局流转 | J40: 关松 | K40: 15706307680 | L40: 青州市 | M40: 家客铁通潍坊青州-益都乡镇装维组 | N40: 重新施工布放光缆 | O40: dw3_jk_guansong | P40: 2025-01-01 13:46:17 | Q40: SD-851-313837-953-9446 | R40: =IF(OR(LEFT(L40,2)="高新"),"奎文",IF(LEFT(L40,2)="峡山","坊子",IF(LEFT(L40,2)="滨海","寒亭",LEFT(L40,2)))) -> 青州 | S40: =TEXT(B40,"mmdd") -> 0101
A41: SD-057-250101-486972-1456 | B41: 2025-01-01 10:56:27 | C41: 潍坊 | D41: 普通区域-潍城区-潍城向阳小区-17865990056-1000M-宽带上网投诉-次数0-202501010000219204 二级督办 | E41: 2025-01-02 08:00:00 | F41: 202501010000219204 | G41: 202501010000219204#？ 宽带账号：17865990056；联系电话：18863669269宽带地址：潍坊潍城区南关街道向阳路向阳小区17号楼客户来电反映宽带网速慢卡顿，线上指导无法配合操作，要求上门处理, 来电流水：2025010110515557020807876 | H41: 2025-01-01 11:01:20 | I41: 家庭咨询->网络质量->家庭宽带->全局流转->功能使用->客户要求装维上门服务->全局流转 | J41: 杜德生 | K41: 15706307862 | L41: 潍城区 | M41: 家客铁通潍坊潍城-胜利街城区装维组 | N41: 重启机顶盒 | O41: dw3_jk_wcdudesheng | P41: 2025-01-01 11:01:39 | Q41: SD-851-290525-1964-15203 | R41: =IF(OR(LEFT(L41,2)="高新"),"奎文",IF(LEFT(L41,2)="峡山","坊子",IF(LEFT(L41,2)="滨海","寒亭",LEFT(L41,2)))) -> 潍城 | S41: =TEXT(B41,"mmdd") -> 0101
A42: SD-057-250101-560248-2861 | B42: 2025-01-01 13:41:50 | C42: 潍坊 | D42: 80+银卡-普通区域-青州市-辛家村-18753617797-1000M-宽带上网投诉-次数0-202501010000344593 | E42: 2025-01-02 08:00:00 | F42: 202501010000344593 | G42: 202501010000344593#流程受理流水号：20250101133816187536177971091623 客户号码:18753617797 客户姓名:杨** 投诉地市:潍坊 来话流水:2025010113353823620864868 宽带账号:18753617797 宽带账号归属地市:潍坊 宽带账号归属区县:青州市 故障地址:潍坊青州市何官镇辛家村辛家村扩容4号箱杨福铸********* 联系电话:18753617797 联系人:先生/女士 工单紧急程度:一般 是否有升级投诉倾向:否 是否重复投诉:否 是否携转意向:否 是否投诉倾向:否 是否智能网关:智能网关 当前是否在线:是 接入方式:FTTH 端到端诊断结果:客户侧设备问题 是否质差终端:是 光功率:-20.31 故障大类:宽带/电视 故障细类:宽带无法上网 携转原因: 故障时间:2025-01-01 13:38:41 具体故障现象:频繁掉线， 客户其他诉求:客户侧为质差终端，要求上门更换终端并一并处理故障问题。要求取消宽带并退还费用， | H42: 2025-01-01 13:43:35 | I42: 家庭咨询->网络质量->家庭宽带->全局流转->功能使用->光猫设备故障->线上义诊 | J42: 董宝泉 | K42: 15706307660 | L42: 青州市 | M42: 家客铁通潍坊青州-何官乡镇装维组 | N42: 更换皮线或网线 | O42: dw3_jk_dongbaoquan | P42: 2025-01-01 13:43:56 | Q42: SD-851-298176-1450-3000 | R42: =IF(OR(LEFT(L42,2)="高新"),"奎文",IF(LEFT(L42,2)="峡山","坊子",IF(LEFT(L42,2)="滨海","寒亭",LEFT(L42,2)))) -> 青州 | S42: =TEXT(B42,"mmdd") -> 0101
A43: SD-057-250101-905462-1640 | B43: 2025-01-01 11:14:33 | C43: 潍坊 | D43: 普通区域-寒亭区-韩家朱马村自然村-13455648275-300M-宽带上网投诉-次数0-20250101111332X212657500 | E43: 2025-01-02 08:00:00 | F43: 20250101111332X212657500 | G43: 【农村网络投诉】流程受理流水号：20250101111144134556482751052724 客户号码:13455648275 客户姓名:韩** 投诉地市:潍坊 来话流水:2025010111111312520865099 宽带账号:13455648275 宽带账号归属地市:潍坊 宽带账号归属区县:寒亭区 故障地址:潍坊寒亭区高里镇韩家朱马村韩家朱马村自然村韩家朱马村10号箱********* 联系电话:13455648275 联系人:先生/女士 工单紧急程度:紧急 是否有升级投诉倾向:否 是否重复投诉:否 是否携转意向:否 是否投诉倾向:否 是否智能网关:智能网关 当前是否在线:否 接入方式:FTTH 端到端诊断结果:状态正常 是否质差终端:无质差信息 光功率:无 故障大类:宽带/电视 故障细类:宽带无法上网(专席) 携转原因: 故障时间:2025-01-01 11:08:02 具体故障现象:光猫灯正常但电脑手机无法上网，请协助谢谢 客户其他诉求: | H43: 2025-01-01 11:19:07 | I43: 家宽业务->网络质量->家庭宽带->全局流转->功能使用->网络无法连接->全局流转 | J43: 权怀磊 | K43: 17865660038 | L43: 寒亭区 | M43: 家客铁通潍坊寒亭-固高乡镇装维组 | N43: 更换热缩管 | O43: dw3_jk_quanhuailei | P43: 2025-01-01 11:21:49 | R43: =IF(OR(LEFT(L43,2)="高新"),"奎文",IF(LEFT(L43,2)="峡山","坊子",IF(LEFT(L43,2)="滨海","寒亭",LEFT(L43,2)))) -> 寒亭 | S43: =TEXT(B43,"mmdd") -> 0101
A44: SD-057-250101-831476-1618 | B44: 2025-01-01 11:11:29 | C44: 潍坊 | D44: 【调研】-(目标)普通区域-青州市-云门山花园樱园-18366518756-300M-宽带上网投诉-次数0-20250101111041X416311690 | E44: 2025-01-02 08:00:00 | F44: 20250101111041X416311690 | G44: 流程受理流水号：20250101110858183665187561051907 客户号码:18366518756 客户姓名:李** 投诉地市:潍坊 来话流水:2025010111071731420812345 宽带账号:18366518756 宽带账号归属地市:潍坊 宽带账号归属区县:青州市 故障地址:潍坊青州市云门山街樱园17号楼********道云门山路云门山花园* 联系电话:18366518756 联系人:先生 工单紧急程度:紧急 是否有升级投诉倾向:否 是否重复投诉:否 是否携转意向:否 是否投诉倾向:否 是否智能网关:智能网关 当前是否在线:是 接入方式:FTTH 端到端诊断结果:客户侧设备问题（新增） 是否质差终端:无质差信息 光功率:-24.43 故障大类:宽带/电视 故障细类:宽带无法上网 携转原因: 故障时间:2025-01-01 11:10:27 具体故障现象:光猫灯正常但电脑手机无法上网， 客户其他诉求: | H44: 2025-01-01 11:22:50 | I44: 家宽业务->网络质量->家庭宽带->全局流转->功能使用->网络连接掉线->全局流转 | J44: 李明辉 | K44: 15706307632 | L44: 青州市 | M44: 家客铁通潍坊青州-古城城区装维组 | N44: 建议用户更换路由器 | O44: dw3_jk_liminghui | Q44: SD-851-252847-28574-29327 | R44: =IF(OR(LEFT(L44,2)="高新"),"奎文",IF(LEFT(L44,2)="峡山","坊子",IF(LEFT(L44,2)="滨海","寒亭",LEFT(L44,2)))) -> 青州 | S44: =TEXT(B44,"mmdd") -> 0101
A45: SD-057-250101-208376-5661 | B45: 2025-01-01 18:36:27 | C45: 潍坊 | D45: 普通区域-临朐县-沈洪自然村-18253642059-300M-宽带上网投诉-次数0-202501010000590513 | E45: 2025-01-02 19:00:00 | F45: 202501010000590513 | G45: 202501010000590513#宽带账号：18253642059；联系电话：18253642059；宽带地址：潍坊临朐县寺头镇人民政府沈洪沈洪自然村沈洪2号箱杨本志；客户来电反映：电视，监控网络不稳定，不配合排障，线上指导无法配合操作，要求上门处理, 来电流水：2025010118311078220883398 | H45: 2025-01-01 18:41:47 | I45: 家庭咨询->网络质量->家庭宽带->全局流转->功能使用->客户要求装维上门服务->全局流转 | J45: 韩东 | K45: 15706307548 | L45: 临朐县 | M45: 家客铁通潍坊临朐-五井乡镇装维组 | N45: 建议用户联系终端厂商处理 | O45: dw3_jk_handong | P45: 2025-01-01 18:42:09 | R45: =IF(OR(LEFT(L45,2)="高新"),"奎文",IF(LEFT(L45,2)="峡山","坊子",IF(LEFT(L45,2)="滨海","寒亭",LEFT(L45,2)))) -> 临朐 | S45: =TEXT(B45,"mmdd") -> 0101
A46: SD-057-250101-028691-5704 | B46: 2025-01-01 18:38:57 | C46: 潍坊 | D46: 【调研】-普通区域-奎文区-九龙山庄-18553627603-1000M-宽带上网投诉-次数0-202501010000592990 | E46: 2025-01-02 19:00:00 | F46: 202501010000592990 | G46: 202501010000592990#宽带账号18553627603；联系电话：18553627603宽带地址：潍坊高新高新城区樱前街九龙山庄紫云苑15号楼*********；客户来电反映宽带网速慢，线上指导无法配合操作，要求上门处理, 来电流水：2025010118325178320897277 | H46: 2025-01-01 18:39:58 | I46: 家庭咨询->网络质量->家庭宽带->全局流转->功能使用->客户要求装维上门服务->全局流转 | J46: 曹明超 | K46: 15706307420 | L46: 奎文区 | M46: 家客铁通潍坊奎文-樱前街城区装维组 | O46: dw3_jk_caomingchaogx | P46: 2025-01-01 18:40:18 | Q46: SD-851-320752-1613-11899 | R46: =IF(OR(LEFT(L46,2)="高新"),"奎文",IF(LEFT(L46,2)="峡山","坊子",IF(LEFT(L46,2)="滨海","寒亭",LEFT(L46,2)))) -> 奎文 | S46: =TEXT(B46,"mmdd") -> 0101
A47: SD-057-250101-685432-5652 | B47: 2025-01-01 18:35:27 | C47: 潍坊 | D47: 【调研】-普通区域-昌邑市-民丰村自然村-15154495079-300M-宽带上网投诉-次数0-20250101183402X642961789 | E47: 2025-01-02 18:00:00 | F47: 20250101183402X642961789 | G47: 【农村网络投诉】流程受理流水号：20250101183214151544950791179013 客户号码:15154495079 客户姓名:王** 投诉地市:潍坊 来话流水:2025010118240985020823895 宽带账号:15154495079 宽带账号归属地市:潍坊 宽带账号归属区县:昌邑市 故障地址:潍坊昌邑市仓街镇民丰村民丰村自然村36号箱********* 联系电话:15154495079 联系人:先生 工单紧急程度:紧急 是否有升级投诉倾向:否 是否重复投诉:否 是否携转意向:否 是否投诉倾向:否 是否智能网关:智能网关 当前是否在线:否 接入方式:FTTH 端到端诊断结果:大面积故障 是否质差终端:无质差信息 光功率:无 故障大类:宽带/电视 故障细类:宽带无法上网 携转原因: 故障时间:2025-01-01 18:32:34 具体故障现象:提示网络无法连接， 客户其他诉求:用户来电反映家里宽带近一星期都无法使用了，坚持要求师傅上门服务，有投诉倾向，请尽快处理 | H47: 2025-01-01 18:47:03 | I47: 家宽业务->网络质量->家庭宽带->全局流转->功能使用->LOS红灯，无法上网->全局流转 | J47: 姜军辉 | K47: 15706307200 | L47: 昌邑市 | M47: 家客铁通潍坊昌邑-围子乡镇装维组 | O47: dw3_jk_jiangjunhui | P47: 2025-01-01 18:48:03 | R47: =IF(OR(LEFT(L47,2)="高新"),"奎文",IF(LEFT(L47,2)="峡山","坊子",IF(LEFT(L47,2)="滨海","寒亭",LEFT(L47,2)))) -> 昌邑 | S47: =TEXT(B47,"mmdd") -> 0101
A48: SD-057-250101-624138-5689 | B48: 2025-01-01 18:38:02 | C48: 潍坊 | D48: 80+银卡-普通区域-昌乐县-鄌郚镇张家庄-13854432895-1000M-魔百和投诉-次数0-20250101183500X700832602 | E48: 2025-01-02 19:00:00 | F48: 20250101183500X700832602 | G48: 流程受理流水号：20250101183412138544328951179467 客户号码:13854432895 客户姓名:张** 投诉地市:潍坊 来话流水:2025010118314787720888425 宽带账号:13854432895 宽带账号归属地市:潍坊 宽带账号归属区县:昌乐县 故障地址:潍坊昌乐县鄌郚镇鄌郚镇张家庄鄌郚镇张家庄K2号箱********* 联系电话:13854432895 联系人:先生 工单紧急程度:非常紧急 是否有升级投诉倾向:否 是否重复投诉:否 是否携转意向:否 是否投诉倾向:否 是否智能网关:智能网关 当前是否在线:是 接入方式:FTTH 端到端诊断结果:客户侧设备问题（新增） 是否质差终端:无质差信息 光功率:-21.54 故障大类:宽带/电视 故障细类:移动高清电视故障(专席) 携转原因: 故障时间:2025-01-01 18:38:18 魔百和单播/组播:组播 具体故障现象:登录超时 客户其他诉求: 魔百和单/组播：组播 | H48: 2025-01-01 18:40:40 | I48: 家庭业务->产品质量->互联网电视(移动高清)->全局流转->功能使用->无法进入播放界面->全局流转 | J48: 刘志诚 | K48: 15706307122 | L48: 昌乐县 | M48: 家客铁通潍坊昌乐-唐吾乡镇装维组 | N48: 更换网线或接头 | O48: dw3_jk_liuzhicheng | P48: 2025-01-01 18:42:00 | Q48: SD-851-281153-12731-915 | R48: =IF(OR(LEFT(L48,2)="高新"),"奎文",IF(LEFT(L48,2)="峡山","坊子",IF(LEFT(L48,2)="滨海","寒亭",LEFT(L48,2)))) -> 昌乐 | S48: =TEXT(B48,"mmdd") -> 0101
A49: SD-057-250101-509642-5647 | B49: 2025-01-01 18:34:34 | C49: 潍坊 | D49: 【调研】-普通区域-昌乐县-东山旺沿街（含东山旺、牙山、龙王河、冯家沟、孟家峪）-15265636223-100M-宽带上网投诉-次数0-202501010000590778 | E49: 2025-01-02 19:00:00 | F49: 202501010000590778 | G49: 202501010000590778#宽带账号：15265636223 宽带地址：潍坊昌乐县鄌郚镇东山旺东山旺沿街牙山村 客户来电反映宽带无法使用 客户不配合排障，要求上门，请协助处理，谢谢！联系电话：13406465556 联系人：先生；来电流水：2025010118302363620876865 | H49: 2025-01-01 18:41:35 | I49: 家庭咨询->网络质量->家庭宽带->全局流转->功能使用->客户要求装维上门服务->全局流转 | J49: 肖鹏 | K49: 15706307127 | L49: 昌乐县 | M49: 家客铁通潍坊昌乐-唐吾乡镇装维组 | N49: 指导用户正确使用遥控器 | O49: dw3_jk_xiaopengcl | P49: 2025-01-01 18:42:06 | R49: =IF(OR(LEFT(L49,2)="高新"),"奎文",IF(LEFT(L49,2)="峡山","坊子",IF(LEFT(L49,2)="滨海","寒亭",LEFT(L49,2)))) -> 昌乐 | S49: =TEXT(B49,"mmdd") -> 0101
A50: SD-057-250101-847192-1636 | B50: 2025-01-01 11:14:19 | C50: 潍坊 | D50: 80+银卡-普通区域-诸城市-西安自然村-15065624145-200M-宽带上网投诉-次数0-20250101111213X133751875 | E50: 2025-01-02 12:15:00 | F50: 20250101111213X133751875 | G50: 【农村网络投诉】流程受理流水号：20250101111113150656241451052584 客户号码:15065624145 客户姓名:张** 投诉地市:潍坊 来话流水:2025010111093023920842296 宽带账号:15065624145 宽带账号归属地市:潍坊 宽带账号归属区县:诸城市 故障地址:潍坊诸城市枳沟镇西安西安自然村西安村1号箱（王贵凯）********* 联系电话:15264447577 联系人:先生/女士 工单紧急程度:一般 是否有升级投诉倾向:否 是否重复投诉:否 是否携转意向:否 是否投诉倾向:否 是否智能网关:智能网关 当前是否在线:是 接入方式:FTTH 端到端诊断结果:客户侧设备问题（新增） 是否质差终端:无质差信息 光功率:-17.39 故障大类:宽带/电视 故障细类:宽带无法上网(专席) 携转原因: 故障时间:2025-01-01 11:10:17 具体故障现象:客户网络在线，已正常排查，电源注册光信号，网口灯均正常，为客户刷新网络，未恢复 客户其他诉求: | H50: 2025-01-01 11:17:20 | I50: 家宽业务->网络质量->家庭宽带->全局流转->功能使用->网络无法连接->全局流转 | J50: 王海 | K50: 15706307956 | L50: 诸城市 | M50: 家客铁通潍坊诸城-枳沟乡镇装维组 | N50: 建议用户更换路由器 | O50: dw3_jk_wanghai | P50: 2025-01-01 11:20:24 | R50: =IF(OR(LEFT(L50,2)="高新"),"奎文",IF(LEFT(L50,2)="峡山","坊子",IF(LEFT(L50,2)="滨海","寒亭",LEFT(L50,2)))) -> 诸城 | S50: =TEXT(B50,"mmdd") -> 0101
A51: SD-057-250101-834056-5624 | B51: 2025-01-01 18:30:37 | C51: 潍坊 | D51: 【调研】-普通区域-诸城市-皇家半岛小区-18366537345-1000M-宽带上网投诉-次数0-202501010000585538 | E51: 2025-01-02 19:00:00 | F51: 202501010000585538 | G51: 202501010000585538#宽带账号：18366537345；联系电话：18366537345；宽带地址：潍坊诸城市龙都街道沿河路皇家半岛10号楼501；客户来电反映：网速卡顿，麻烦尽快联系客户，客户有投诉倾向。麻烦尽快联系。线上指导无法配合操作，要求上门处理, 来电流水：2025010118240179220822635 | H51: 2025-01-01 18:38:31 | I51: 家庭咨询->网络质量->家庭宽带->全局流转->功能使用->客户要求装维上门服务->全局流转 | J51: 李宇 | K51: 15706307948 | L51: 诸城市 | M51: 家客铁通潍坊诸城-繁荣路城区装维组 | N51: 用户感觉网速慢，但测速达标 | O51: dw3_jk_liyu | P51: 2025-01-01 18:38:53 | Q51: SD-851-256760-2206-15181 | R51: =IF(OR(LEFT(L51,2)="高新"),"奎文",IF(LEFT(L51,2)="峡山","坊子",IF(LEFT(L51,2)="滨海","寒亭",LEFT(L51,2)))) -> 诸城 | S51: =TEXT(B51,"mmdd") -> 0101
A52: SD-057-250101-810463-6890 | B52: 2025-01-01 21:26:13 | C52: 潍坊 | D52: 80+银卡-FTTR-普通区域-寿光市-稻田昌大路以南东侧-13780802088-1000M-宽带上网投诉-次数0-20250101212455X895983846 | E52: 2025-01-02 18:00:00 | F52: 20250101212455X895983846 | G52: 【农村网络投诉】流程受理流水号：20250101212220137808020881206826 客户号码:13780802088 客户姓名:李** 投诉地市:潍坊 来话流水:2025010121211975120801574 宽带账号:13780802088 宽带账号归属地市:潍坊 宽带账号归属区县:寿光市 故障地址:潍坊寿光市稻田镇梁武赵村梁武赵村自然村梁武赵村扩容26号箱********* 联系电话:13780802088 联系人:先生/女士 工单紧急程度:非常紧急 是否有升级投诉倾向:否 是否重复投诉:否 是否携转意向:否 是否投诉倾向:否 是否智能网关:智能网关 当前是否在线:否 接入方式:FTTH 端到端诊断结果:状态正常 是否质差终端:无质差信息 光功率:无 故障大类:宽带/电视 故障细类:宽带无法上网(专席) 携转原因: 故障时间:2025-01-01 21:18:14 具体故障现象:Pon闪烁：引导客户将光纤线插紧，将弯折的位置捋直后重启无效 客户其他诉求: | H52: 2025-01-01 21:30:42 | I52: 家宽业务->网络质量->家庭宽带->全局流转->功能使用->网络无法连接->全局流转 | J52: 宋玉杰 | K52: 15706307816 | L52: 寿光市 | M52: 家客铁通潍坊寿光-稻田乡镇装维组 | O52: dw3_jk_songyujie | P52: 2025-01-01 21:34:03 | Q52: SD-851-292916-831-6642 | R52: =IF(OR(LEFT(L52,2)="高新"),"奎文",IF(LEFT(L52,2)="峡山","坊子",IF(LEFT(L52,2)="滨海","寒亭",LEFT(L52,2)))) -> 寿光 | S52: =TEXT(B52,"mmdd") -> 0101
A53: SD-057-250101-541732-5233 | B53: 2025-01-01 17:54:58 | C53: 潍坊 | D53: 普通区域--null--宽带上网投诉-次数0-202412310000762813 | E53: 2025-01-02 18:55:00 | F53: 202412310000762813 | G53: 202412310000762813#15864321596客户办理新装宽带但师傅说没有端口无法安装，经解释，客户不认可，请协助处理，谢谢 联系人：女士 联系电话：18365609363流水号：2024123118413766620864770 | H53: 2025-01-01 19:29:40 | I53: 家庭咨询->基础服务->家庭宽带->全局流转->办理规范->宽带未覆盖无法办理->全局流转 | J53: 王坤 | K53: 15706307002 | N53: 营业厅重新办理业务 | O53: wangkunwf | R53: =IF(OR(LEFT(L53,2)="高新"),"奎文",IF(LEFT(L53,2)="峡山","坊子",IF(LEFT(L53,2)="滨海","寒亭",LEFT(L53,2)))) | S53: =TEXT(B53,"mmdd") -> 0101
A54: SD-057-250101-497036-5204 | B54: 2025-01-01 17:51:47 | C54: 潍坊 | D54: 【调研】-80+普通-普通区域-奎文区-奎文自来水宿舍一-15064662813-1000M-宽带上网投诉-次数0-202501010000558860 | E54: 2025-01-02 18:52:00 | F54: 202501010000558860 | G54: 202501010000558860#宽带账号：15064662813；宽带地址：潍坊奎文区广文街道院校街自来水宿舍如家酒店对面自来水宿舍楼****；客户来电反映宽带无法上网，注册闪，插紧捋顺光纤线重启还是闪，要求上门，请协助处理，谢谢！ 联系电话：15064662813；联系人：女士；来电流水：2025010117494217220898541 | H54: 2025-01-01 17:59:42 | I54: 家庭咨询->网络质量->家庭宽带->全局流转->功能使用->客户要求装维上门服务->全局流转 | J54: 张万里 | K54: 15706307485 | L54: 奎文区 | M54: 家客铁通潍坊奎文-樱前街城区装维组 | N54: 更换端口 | O54: dw3_jk_zhangwanli | P54: 2025-01-01 17:59:59 | Q54: SD-851-271357-8188-11170 | R54: =IF(OR(LEFT(L54,2)="高新"),"奎文",IF(LEFT(L54,2)="峡山","坊子",IF(LEFT(L54,2)="滨海","寒亭",LEFT(L54,2)))) -> 奎文 | S54: =TEXT(B54,"mmdd") -> 0101
A55: SD-057-250101-026739-5274 | B55: 2025-01-01 17:57:45 | C55: 潍坊 | D55: 80+金卡-普通区域-昌邑市-马家村庄社区-15963670778-200M-魔百和投诉-次数0-202501010000562633 | E55: 2025-01-02 18:58:00 | F55: 202501010000562633 | G55: 202501010000562633#流程受理流水号：20250101175357159636707781169299 客户号码:15963670778 客户姓名:马** 投诉地市:潍坊 来话流水:2025010117515524620820700 宽带账号:15963670778 宽带账号归属地市:潍坊 宽带账号归属区县:昌邑市 故障地址:潍坊昌邑市城区利民街马家村庄社区B2号楼********* 联系电话:15263666667 联系人:先生 工单紧急程度:一般 是否有升级投诉倾向:否 是否重复投诉:否 是否携转意向:否 是否投诉倾向:否 是否智能网关:智能网关 当前是否在线:是 接入方式:FTTH 端到端诊断结果:客户侧设备问题（新增） 是否质差终端:无质差信息 光功率:-15.75 故障大类:宽带/电视 故障细类:移动高清电视故障(专席) 携转原因: 故障时间:2025-01-01 17:59:11 魔百和单播/组播: 具体故障现象:电视机提示无信号 客户其他诉求: ;宽带小区$[马家村庄社区]$ | H55: 2025-01-01 18:00:31 | I55: 家庭咨询->产品质量->互联网电视(移动高清)->全局流转->售后服务->电视机提示“无信号”->全局流转 | J55: 邓艺浩 | K55: 15706307216 | L55: 昌邑市 | M55: 家客铁通潍坊昌邑-城西城区装维组 | N55: 重新连接机顶盒网络 | O55: dw3_jk_dengyihao | P55: 2025-01-01 18:01:47 | R55: =IF(OR(LEFT(L55,2)="高新"),"奎文",IF(LEFT(L55,2)="峡山","坊子",IF(LEFT(L55,2)="滨海","寒亭",LEFT(L55,2)))) -> 昌邑 | S55: =TEXT(B55,"mmdd") -> 0101
A56: SD-057-250101-846375-5224 | B56: 2025-01-01 17:54:20 | C56: 潍坊 | D56: 【调研】-80+普通-普通区域-奎文区-健康八号-15963469817-300M-宽带上网投诉-次数0-202501010000559929 | E56: 2025-01-02 18:55:00 | F56: 202501010000559929 | G56: 202501010000559929#流程受理流水号：20250101175316159634698171169088 客户号码:15963469817 客户姓名:张** 投诉地市:潍坊 来话流水:2025010117520787320822836 宽带账号:15963469817 宽带账号归属地市:潍坊 宽带账号归属区县:高新 故障地址:潍坊高新清池东南段村东南段村自然村扩容11号分线箱********* 联系电话:13561637770 联系人:/女士 工单紧急程度:一般 是否有升级投诉倾向:否 是否重复投诉:否 是否携转意向:否 是否投诉倾向:否 是否智能网关:智能网关 当前是否在线:是 接入方式:FTTH 端到端诊断结果:客户侧设备问题 是否质差终端:是 光功率:-23.27 故障大类:宽带/电视 故障细类:移动高清电视故障 携转原因: 故障时间:2025-01-01 17:54:05 魔百和单播/组播:组播 具体故障现象:机顶盒无法开机， 客户其他诉求:客户侧为质差终端，要求上门更换终端并一并处理故障问题。 | H56: 2025-01-01 17:58:11 | I56: 家庭咨询->网络质量->家庭宽带->全局流转->功能使用->光猫设备故障->线上义诊 | J56: 郝林朋 | K56: 15706307422 | L56: 奎文区 | M56: 家客铁通潍坊奎文-健康街城区装维组 | N56: 【退单】非宽带网络问题 | O56: dw3_jk_haolinpeng | P56: 2025-01-01 18:00:45 | Q56: SD-852-281830-164-29433 | R56: =IF(OR(LEFT(L56,2)="高新"),"奎文",IF(LEFT(L56,2)="峡山","坊子",IF(LEFT(L56,2)="滨海","寒亭",LEFT(L56,2)))) -> 奎文 | S56: =TEXT(B56,"mmdd") -> 0101
A57: SD-057-250101-683275-5206 | B57: 2025-01-01 17:52:02 | C57: 潍坊 | D57: 【调研】-80+普通-(目标)普通区域-诸城市-臧家铁沟自然村-15094970945-300M-宽带上网投诉-次数0-202501010000556702 | E57: 2025-01-02 18:53:00 | F57: 202501010000556702 | G57: 202501010000556702#流程受理流水号：20250101175136150949709451168597 客户号码:15094970945 客户姓名:许** 投诉地市:潍坊 来话流水:2025010117504663220809252 宽带账号:15094970945 宽带账号归属地市:潍坊 宽带账号归属区县:诸城市 故障地址:潍坊诸城市密州街道臧家铁沟臧家铁沟自然村臧家铁沟村粮油超市东南7号箱********* 联系电话:15094970945 联系人:先生/女士 工单紧急程度:一般 是否有升级投诉倾向:否 是否重复投诉:否 是否携转意向:否 是否投诉倾向:否 是否智能网关:非智能网关 当前是否在线:是 接入方式:FTTH 端到端诊断结果:客户侧设备问题 是否质差终端:是 光功率:无 故障大类:宽带/电视 故障细类:移动高清电视故障 携转原因: 故障时间:2025-01-01 17:51:43 魔百和单播/组播:组播 具体故障现象:电视直播或点播无法观看， 客户其他诉求:客户侧为质差终端，要求上门更换终端并一并处理故障问题。 | H57: 2025-01-01 18:11:43 | I57: 家庭咨询->网络质量->家庭宽带->全局流转->功能使用->光猫设备故障->线上义诊 | J57: 刘国栋 | K57: 15169670180 | L57: 诸城市 | M57: 家客铁通潍坊诸城-兴华东路城区装维组 | N57: 更换网线或接头 | O57: dw3_jk_liuguodongzc | P57: 2025-01-01 18:12:13 | R57: =IF(OR(LEFT(L57,2)="高新"),"奎文",IF(LEFT(L57,2)="峡山","坊子",IF(LEFT(L57,2)="滨海","寒亭",LEFT(L57,2)))) -> 诸城 | S57: =TEXT(B57,"mmdd") -> 0101
A58: SD-057-250101-765432-1163 | B58: 2025-01-01 10:24:41 | C58: 潍坊 | D58: 80+银卡-普通区域-奎文区-富华新村-13563682905-300M-魔百和投诉-次数0-202501010000189725 | E58: 2025-01-02 08:00:00 | F58: 202501010000189725 | G58: 202501010000189725#流程受理流水号：20250101102259135636829051037045 客户号码:13563682905 客户姓名:孙** 投诉地市:潍坊 来话流水:2025010110211094620893570 宽带账号:13563682905 宽带账号归属地市:潍坊 宽带账号归属区县:-- 故障地址:潍坊高新高新城区东方路富华新村29号楼********* 联系电话:13563682905 联系人:先生/女士 工单紧急程度:紧急 是否有升级投诉倾向:否 是否重复投诉:否 是否携转意向:否 是否投诉倾向:否 是否智能网关:智能网关 当前是否在线:是 接入方式:FTTH 端到端诊断结果:客户侧设备问题（新增） 是否质差终端:无质差信息 光功率:-20 故障大类:宽带/电视 故障细类:移动高清电视故障 携转原因: 故障时间:2025-01-01 10:24:41 魔百和单播/组播:组播 具体故障现象:点播和直播观看都出现卡顿缓冲， 客户其他诉求:用户要求上门修理，请协助处理谢谢 魔百和单/组播：组播;宽带小区$[富华新村]$ | H58: 2025-01-01 10:28:00 | I58: 家庭咨询->产品质量->互联网电视(移动高清)->全局流转->功能使用->栏目点播、电视看点、电视[直播]无法观看->全局流转 | J58: 倪苹伟 | K58: 15706366536 | L58: 奎文区 | M58: 家客铁通潍坊奎文-北宫街城区装维组 | N58: 更换网线或接头 | O58: dw3_jk_nipingwei | P58: 2025-01-01 10:28:19 | R58: =IF(OR(LEFT(L58,2)="高新"),"奎文",IF(LEFT(L58,2)="峡山","坊子",IF(LEFT(L58,2)="滨海","寒亭",LEFT(L58,2)))) -> 奎文 | S58: =TEXT(B58,"mmdd") -> 0101
A59: SD-057-250101-708562-1215 | B59: 2025-01-01 10:29:13 | C59: 潍坊 | D59: 【调研】-普通区域-潍城区-王家官庄自然村-13964654686-300M-宽带上网投诉-次数0-20250101102801X481184195 | E59: 2025-01-02 08:00:00 | F59: 20250101102801X481184195 | G59: 【农村网络投诉】流程受理流水号：20250101102653139646546861038306 客户号码:13964654686 客户姓名:郝** 投诉地市:潍坊 来话流水:2025010110231145720820380 宽带账号:13964654686 宽带账号归属地市:潍坊 宽带账号归属区县:潍城区 故障地址:潍坊潍城区军埠口综合项目区张家官庄村张家官庄村自然村卫生室路西二条街北300米15#********* 联系电话:13964654686 联系人:先生/女士 工单紧急程度:一般 是否有升级投诉倾向:否 是否重复投诉:否 是否携转意向:否 是否投诉倾向:否 是否智能网关:智能网关 当前是否在线:否 接入方式:FTTH 端到端诊断结果:状态正常 是否质差终端:无质差信息 光功率:无 故障大类:宽带/电视 故障细类:宽带无法上网(专席) 携转原因: 故障时间:2025-01-01 10:24:11 具体故障现象:无法上网 客户其他诉求: | H59: 2025-01-01 10:31:54 | I59: 家宽业务->网络质量->家庭宽带->全局流转->功能使用->网络无法连接->全局流转 | J59: 宋九龙 | K59: 15706307876 | L59: 潍城区 | M59: 家客铁通潍坊潍城-胜利街城区装维组 | N59: 恢复出厂 | O59: dw3_jk_songjiulongwc | P59: 2025-01-01 10:32:39 | Q59: SD-851-268450-2933-23667 | R59: =IF(OR(LEFT(L59,2)="高新"),"奎文",IF(LEFT(L59,2)="峡山","坊子",IF(LEFT(L59,2)="滨海","寒亭",LEFT(L59,2)))) -> 潍城 | S59: =TEXT(B59,"mmdd") -> 0101
A60: SD-057-250101-013724-6870 | B60: 2025-01-01 21:20:07 | C60: 潍坊 | D60: 80+普通-普通区域-安丘市-马家楼小区-15253615862-300M-宽带上网投诉-次数0-20250101211903X543308588 | E60: 2025-01-02 18:00:00 | F60: 20250101211903X543308588 | G60: 流程受理流水号：20250101211741152536158621206418 客户号码:15253615862 客户姓名:李** 投诉地市:潍坊 来话流水:2025010121161075320881921 宽带账号:15253615862 宽带账号归属地市:潍坊 宽带账号归属区县:安丘市 故障地址:潍坊安丘市兴安街道和平路马家楼小区3号楼********* 联系电话:15253615862 联系人:先生 工单紧急程度:一般 是否有升级投诉倾向:否 是否重复投诉:否 是否携转意向:否 是否投诉倾向:否 是否智能网关:智能网关 当前是否在线:是 接入方式:FTTH 端到端诊断结果:客户侧设备问题（新增） 是否质差终端:无质差信息 光功率:-22.92 故障大类:宽带/电视 故障细类:网速慢/上网掉线(专席) 携转原因: 故障时间:2025-01-01 21:15:40 具体故障现象:网速慢卡顿， 客户其他诉求: | H60: 2025-01-01 21:22:07 | I60: 家宽业务->网络质量->家庭宽带->全局流转->功能使用->部分网页打不开->全局流转 | J60: 刘树强 | K60: 15706307030 | L60: 安丘市 | M60: 家客铁通潍坊安丘-潍安路城区装维组 | O60: dw3_jk_liushuqiangaq | P60: 2025-01-01 21:22:27 | R60: =IF(OR(LEFT(L60,2)="高新"),"奎文",IF(LEFT(L60,2)="峡山","坊子",IF(LEFT(L60,2)="滨海","寒亭",LEFT(L60,2)))) -> 安丘 | S60: =TEXT(B60,"mmdd") -> 0101
A61: SD-057-250101-476985-1964 | B61: 2025-01-01 11:48:22 | C61: 潍坊 | D61: 【调研】-普通区域-坊子区-虞河花园-18366230526-200M-宽带上网投诉-次数0-202501010000266685 | E61: 2025-01-02 12:49:00 | F61: 202501010000266685 | G61: 202501010000266685#宽带账号18366230526；宽带地址：潍坊坊子区坊子新区凤凰大街虞河花园24号楼***；客户来电反映宽带上网慢*****，光猫自带无线功能，要求师傅上门，请协助处理，谢谢！联系电话：本机；联系人先生；来电流水：2025010111441580820892417 | H61: 2025-01-01 11:57:16 | I61: 家庭咨询->网络质量->家庭宽带->全局流转->功能使用->客户要求装维上门服务->全局流转 | J61: 王春宁 | K61: 15706307258 | L61: 坊子区 | M61: 家客铁通潍坊坊子-凤凰城区装维组 | N61: 用户感觉网速慢，但测速达标 | O61: dw3_jk_wangchunning | P61: 2025-01-01 11:57:35 | Q61: SD-852-308878-559-166 | R61: =IF(OR(LEFT(L61,2)="高新"),"奎文",IF(LEFT(L61,2)="峡山","坊子",IF(LEFT(L61,2)="滨海","寒亭",LEFT(L61,2)))) -> 坊子 | S61: =TEXT(B61,"mmdd") -> 0101
A62: SD-057-250101-758139-1207 | B62: 2025-01-01 10:28:22 | C62: 潍坊 | D62: 【调研】-(目标)普通区域-高密市-龙都花园-15964321261-300M-宽带上网投诉-次数0-202501010000191285 | E62: 2025-01-02 08:00:00 | F62: 202501010000191285 | G62: 202501010000191285#流程受理流水号：20250101102721159643212611038461 客户号码:15964321261 客户姓名:任** 投诉地市:潍坊 来话流水:2025010110264746220868595 宽带账号:15964321261 宽带账号归属地市:潍坊 宽带账号归属区县:高密市 故障地址:潍坊高密市朝阳街道月潭路龙都花园龙都花园6号楼********* 联系电话:15964321261 联系人:先生 工单紧急程度:一般 是否有升级投诉倾向:否 是否重复投诉:否 是否携转意向:否 是否投诉倾向:否 是否智能网关:智能网关 当前是否在线:是 接入方式:FTTH 端到端诊断结果:客户侧设备问题 是否质差终端:是 光功率:-25.37 故障大类:宽带/电视 故障细类:宽带网速慢/卡顿 携转原因: 故障时间:2025-01-01 10:27:41 具体故障现象:网速慢卡顿， 客户其他诉求:客户侧为质差终端，要求上门更换终端并一并处理故障问题。 | H62: 2025-01-01 10:33:16 | I62: 家庭咨询->网络质量->家庭宽带->全局流转->功能使用->光猫设备故障->线上义诊 | J62: 赵祉边 | K62: 15706307357 | L62: 高密市 | M62: 家客铁通潍坊高密-朝阳城区装维组 | N62: 重启路由器 | O62: dw3_jk_zhaozhibian | P62: 2025-01-01 10:33:40 | R62: =IF(OR(LEFT(L62,2)="高新"),"奎文",IF(LEFT(L62,2)="峡山","坊子",IF(LEFT(L62,2)="滨海","寒亭",LEFT(L62,2)))) -> 高密 | S62: =TEXT(B62,"mmdd") -> 0101
A63: SD-057-250101-164520-5190 | B63: 2025-01-01 17:50:28 | C63: 潍坊 | D63: 普通区域-昌邑市-长胡同村自然村-13791643448-300M-宽带上网投诉-次数0-20250101174745X865301517 | E63: 2025-01-02 18:51:00 | F63: 20250101174745X865301517 | G63: 【农村网络投诉】流程受理流水号：20250101174658137916434481167223 客户号码:13791643448 客户姓名:姜** 投诉地市:潍坊 来话流水:2025010117442226120845225 宽带账号:13791643448 宽带账号归属地市:潍坊 宽带账号归属区县:昌邑市 故障地址:潍坊昌邑市柳疃镇长胡同村长胡同村自然村6号箱姜言信********* 联系电话:13791643448 联系人:先生/女士 工单紧急程度:一般 是否有升级投诉倾向:否 是否重复投诉:否 是否携转意向:否 是否投诉倾向:否 是否智能网关:智能网关 当前是否在线:否 接入方式:FTTH 端到端诊断结果:光猫掉电 是否质差终端:无质差信息 光功率:无 故障大类:宽带/电视 故障细类:宽带无法上网(专席) 携转原因: 故障时间:2025-01-01 17:38:40 具体故障现象:提示网络无法连接，光猫只亮电源灯，重启很久就只亮一个灯，要求处理，谢谢 客户其他诉求: | H63: 2025-01-01 17:58:39 | I63: 家宽业务->网络质量->家庭宽带->全局流转->功能使用->网络无法连接->全局流转 | J63: 徐瑞鹏 | K63: 15706307210 | L63: 昌邑市 | M63: 家客铁通潍坊昌邑-柳疃乡镇装维组 | N63: 更换皮线或网线 | O63: dw3_jk_xuruipeng | P63: 2025-01-01 17:59:12 | Q63: SD-851-244637-715-16930 | R63: =IF(OR(LEFT(L63,2)="高新"),"奎文",IF(LEFT(L63,2)="峡山","坊子",IF(LEFT(L63,2)="滨海","寒亭",LEFT(L63,2)))) -> 昌邑 | S63: =TEXT(B63,"mmdd") -> 0101
A64: SD-057-250101-340891-6876 | B64: 2025-01-01 21:22:31 | C64: 潍坊 | D64: 【重投】-普通区域-奎文区-美丽华小区-15169693535-300M-宽带上网投诉-次数0-202501010000653774 | E64: 2025-01-02 18:00:00 | F64: 202501010000653774 | G64: 202501010000653774#宽带账号：15169693535；宽带地址：潍坊高新高新城区北海路居易家园1号楼（东楼）；客户来电反映移动高清无法观看，客户无法配合线上指导/客户不配合排障，要求去家里，请协助处理，谢谢！联系电话：13678662326；联系人：先生；来电流水：2025010120591063120812887。 | H64: 2025-01-01 21:36:20 | I64: 家庭咨询->网络质量->家庭宽带->全局流转->功能使用->客户要求装维上门服务->全局流转 | J64: 扈培富 | K64: 15706366508 | L64: 奎文区 | M64: 家客铁通潍坊奎文-鸢飞路城区装维组 | O64: dw3_jk_hupeifu | P64: 2025-01-01 21:38:29 | R64: =IF(OR(LEFT(L64,2)="高新"),"奎文",IF(LEFT(L64,2)="峡山","坊子",IF(LEFT(L64,2)="滨海","寒亭",LEFT(L64,2)))) -> 奎文 | S64: =TEXT(B64,"mmdd") -> 0101
A65: SD-057-250101-291564-5290 | B65: 2025-01-01 17:59:29 | C65: 潍坊 | D65: 【调研】-(目标)普通区域-潍城区-远西村自然村-13455666395-100M-宽带上网投诉-次数0-20250101175842X522117785 | E65: 2025-01-02 19:00:00 | F65: 20250101175842X522117785 | G65: 【农村网络投诉】流程受理流水号：20250101175749134556663951170402 客户号码:13455666395 客户姓名:于** 投诉地市:潍坊 来话流水:2025010117560770820862437 宽带账号:13455666395 宽带账号归属地市:潍坊 宽带账号归属区县:潍城区 故障地址:潍坊潍城区于河街道远西村远西村自然村远西村东数2条街路西中间北4排7#箱********* 联系电话:13455666395 联系人:先生/女士 工单紧急程度:一般 是否有升级投诉倾向:否 是否重复投诉:否 是否携转意向:否 是否投诉倾向:否 是否智能网关:智能网关 当前是否在线:否 接入方式:FTTH 端到端诊断结果:状态正常 是否质差终端:无质差信息 光功率:无 故障大类:宽带/电视 故障细类:宽带无法上网(专席) 携转原因: 故障时间:2025-01-01 18:00:35 具体故障现象:光信号亮红灯：拔插捋直光纤线未恢复，请协助处理，谢谢。 客户其他诉求: | H65: 2025-01-01 18:02:29 | I65: 家宽业务->网络质量->家庭宽带->全局流转->功能使用->网络无法连接->全局流转 | J65: 季道宽 | K65: 15706307907 | L65: 潍城区 | M65: 家客铁通潍坊潍城-豪德城区装维组 | N65: 更换皮线或网线 | O65: dw3_jk_jidaokuan | P65: 2025-01-01 18:02:52 | Q65: SD-851-294730-63981-8439 | R65: =IF(OR(LEFT(L65,2)="高新"),"奎文",IF(LEFT(L65,2)="峡山","坊子",IF(LEFT(L65,2)="滨海","寒亭",LEFT(L65,2)))) -> 潍城 | S65: =TEXT(B65,"mmdd") -> 0101
A66: SD-057-250101-584203-5196 | B66: 2025-01-01 17:50:48 | C66: 潍坊 | D66: 80+金卡-普通区域-寿光市-巨能嘉园-15006569456-1000M-宽带上网投诉-次数0-202501010000546803 | E66: 2025-01-02 18:51:00 | F66: 202501010000546803 | G66: 202501010000546803#宽带账号：15006569456；宽带地址：潍坊寿光市圣城街道北环路巨能嘉园北区7号楼 1单元403，具体现象：客户反映宽带不能上网，要求尽快处理回复！来电流水： 2025010117360935120861558，联系电话： 15006569456 | H66: 2025-01-01 18:06:27 | I66: 家庭咨询->网络质量->家庭宽带->全局流转->功能使用->客户要求装维上门服务->全局流转 | J66: 张锡森 | K66: 15706307741 | L66: 寿光市 | M66: 家客铁通潍坊寿光-东城城区装维组 | N66: 重新调试终端 | O66: dw3_jk_zhangxisen | P66: 2025-01-01 18:06:58 | R66: =IF(OR(LEFT(L66,2)="高新"),"奎文",IF(LEFT(L66,2)="峡山","坊子",IF(LEFT(L66,2)="滨海","寒亭",LEFT(L66,2)))) -> 寿光 | S66: =TEXT(B66,"mmdd") -> 0101
A67: SD-057-250101-905861-1921 | B67: 2025-01-01 11:46:23 | C67: 潍坊 | D67: 【调研】-80+普通-普通区域-寿光市-北魏社区-18253692228-300M-宽带上网投诉-次数0-202501010000268170 | E67: 2025-01-02 08:00:00 | F67: 202501010000268170 | G67: 202501010000268170#【已关注中国移动10086微信公众号】流程受理流水号：20250101114411182536922281062873 客户号码:18253692228 客户姓名:魏** 投诉地市:潍坊 来话流水:2025010111435599720888549 宽带账号:18253692228 宽带账号归属地市:潍坊 宽带账号归属区县:-- 故障地址:潍坊寿光市圣城街道健康街北魏社区1号楼********* 联系电话:18253692228 联系人:先生/女士 工单紧急程度:一般 是否有升级投诉倾向:否 是否重复投诉:否 是否携转意向:否 是否投诉倾向:否 是否智能网关:智能网关 当前是否在线:否 接入方式:FTTH 端到端诊断结果:状态正常 是否质差终端:无质差信息 光功率:无 故障大类:宽带/电视 故障细类:宽带无法上网 携转原因: 故障时间:2025-01-01 11:45:37 具体故障现象:光猫亮红灯， 客户其他诉求: ;宽带小区$[北魏社区]$ | H67: 2025-01-01 11:56:50 | I67: 家宽咨询->网络质量->家庭宽带->全局流转->功能使用->LOS红灯，无法上网->全局流转 | J67: 赵一武 | K67: 15706307728 | L67: 寿光市 | M67: 家客铁通潍坊寿光-市中城区装维组 | N67: 重新熔缆 | O67: dw3_jk_zhaoyiwu | P67: 2025-01-01 11:57:05 | Q67: SD-851-275399-21678-15449 | R67: =IF(OR(LEFT(L67,2)="高新"),"奎文",IF(LEFT(L67,2)="峡山","坊子",IF(LEFT(L67,2)="滨海","寒亭",LEFT(L67,2)))) -> 寿光 | S67: =TEXT(B67,"mmdd") -> 0101
A68: SD-057-250101-476910-1880 | B68: 2025-01-01 11:40:11 | C68: 潍坊 | D68: 80+银卡-普通区域-青州市-代楼-15094985877-1000M-宽带上网投诉-次数0-202501010000260662 | E68: 2025-01-02 08:00:00 | F68: 202501010000260662 | G68: 202501010000260662#宽带账号：15094985877；宽带地址：潍坊青州市何官镇代楼代楼29号箱（村中心街东北代全之）****；客户来电反映宽带上网慢卡顿，经查询客户为质差路由器，请协助上门更换终端并一并处理故障问题，谢谢！ 联系电话：15094985877；联系人：女士；来电流水：2025010111363406420897102 | H68: 2025-01-01 11:48:54 | I68: 家庭咨询->网络质量->家庭宽带->全局流转->功能使用->路由器质差->全局流转 | J68: 董宝泉 | K68: 15706307660 | L68: 青州市 | M68: 家客铁通潍坊青州-何官乡镇装维组 | N68: 室内重新布线 | O68: dw3_jk_dongbaoquan | P68: 2025-01-01 11:49:33 | R68: =IF(OR(LEFT(L68,2)="高新"),"奎文",IF(LEFT(L68,2)="峡山","坊子",IF(LEFT(L68,2)="滨海","寒亭",LEFT(L68,2)))) -> 青州 | S68: =TEXT(B68,"mmdd") -> 0101
A69: SD-057-250101-230541-6901 | B69: 2025-01-01 21:28:17 | C69: 潍坊 | D69: 【调研】-80+银卡-普通区域-潍城区-傅家村自然村-13906368978-1000M-宽带上网投诉-次数0-202501010000660407 | E69: 2025-01-02 19:00:00 | F69: 202501010000660407 | G69: 202501010000660407#流程受理流水号：20250101212620139063689781207159 客户号码:13906368978 客户姓名:任** 投诉地市:潍坊 来话流水:2025010121255093820818171 宽带账号:13906368978 宽带账号归属地市:潍坊 宽带账号归属区县:潍城区 故障地址:潍坊潍城区望留街道傅家村傅家村自然村3#西面第一条胡同从北数11排东户********* 联系电话:13906368978 联系人:先生 工单紧急程度:非常紧急 是否有升级投诉倾向:否 是否重复投诉:否 是否携转意向:否 是否投诉倾向:否 是否智能网关:智能网关 当前是否在线:是 接入方式:FTTH 端到端诊断结果:客户侧设备问题（新增） 是否质差终端:无质差信息 光功率:-17.42 故障大类:宽带/电视 故障细类:网速慢/上网掉线(专席) 携转原因: 故障时间:2025-01-01 21:29:56 具体故障现象:网速慢卡顿， 客户其他诉求: ;宽带小区$[傅家村自然村]$ | H69: 2025-01-01 21:31:47 | I69: 家宽咨询->网络质量->家庭宽带->全局流转->功能使用->频繁出现故障、网速慢->全局流转 | J69: 刘得胜 | K69: 15706307856 | L69: 潍城区 | M69: 家客铁通潍坊潍城-东风街城区装维组 | O69: dw3_jk_wcliudesheng | P69: 2025-01-01 21:32:08 | Q69: SD-851-289289-7906-9568 | R69: =IF(OR(LEFT(L69,2)="高新"),"奎文",IF(LEFT(L69,2)="峡山","坊子",IF(LEFT(L69,2)="滨海","寒亭",LEFT(L69,2)))) -> 潍城 | S69: =TEXT(B69,"mmdd") -> 0101
A70: SD-057-250101-301956-6907 | B70: 2025-01-01 21:29:41 | C70: 潍坊 | D70: 【调研】-普通区域-潍城区-乔铁村-18363692933-300M-宽带上网投诉-次数0-202501010000661521 一级督办 | E70: 2025-01-02 18:00:00 | F70: 202501010000661521 | G70: 202501010000661521#宽带账号：18363692933；宽带地址：潍坊潍城区乐埠山生态经济发展区乔铁村乔铁村路东往北3列6排东山1#分纤箱*********；客户来电反映宽带故障，客户不配合排障，要求上门，请协助处理，谢谢！联系电话：本机；联系人：先生；来电流水：2025010121254863420818015 | H70: 2025-01-01 21:34:08 | I70: 家庭咨询->网络质量->家庭宽带->全局流转->功能使用->客户要求装维上门服务->全局流转 | J70: 杜桂超 | K70: 15706307902 | L70: 潍城区 | M70: 家客铁通潍坊潍城-豪德城区装维组 | O70: dw3_jk_duguichaowc | P70: 2025-01-01 21:35:18 | R70: =IF(OR(LEFT(L70,2)="高新"),"奎文",IF(LEFT(L70,2)="峡山","坊子",IF(LEFT(L70,2)="滨海","寒亭",LEFT(L70,2)))) -> 潍城 | S70: =TEXT(B70,"mmdd") -> 0101
A71: SD-057-250101-138529-5243 | B71: 2025-01-01 17:56:23 | C71: 潍坊 | D71: 【调研】-80+银卡-普通区域-寒亭区-苏杭花园小区-18678022851-1000M-宽带上网投诉-次数0-202501010000563423 | E71: 2025-01-02 18:57:00 | F71: 202501010000563423 | G71: 202501010000563423#流程受理流水号：20250101175530186780228511169707 客户号码:18678022851 客户姓名:冷** 投诉地市:潍坊 来话流水:2025010117531807820834418 宽带账号:18678022851 宽带账号归属地市:潍坊 宽带账号归属区县:寒亭区 故障地址:潍坊寒亭区经济开发区月河路苏杭花园小区14号楼********* 联系电话:18678022851 联系人:女士 工单紧急程度:非常紧急 是否有升级投诉倾向:否 是否重复投诉:否 是否携转意向:否 是否投诉倾向:否 是否智能网关:智能网关 当前是否在线:是 接入方式:FTTH 端到端诊断结果:客户侧设备问题（新增） 是否质差终端:无质差信息 光功率:无 故障大类:宽带/电视 故障细类:网速慢/上网掉线(专席) 携转原因: 故障时间:2025-01-01 17:50:41 具体故障现象:网速慢卡顿，线上排障不认可 谢谢！ 客户其他诉求: ;宽带小区$[苏杭花园小区]$ | H71: 2025-01-01 18:04:27 | I71: 家宽咨询->网络质量->家庭宽带->全局流转->功能使用->频繁出现故障、网速慢->全局流转 | J71: 李源 | K71: 17853670973 | L71: 寒亭区 | M71: 家客铁通潍坊寒亭-开发区乡镇装维组 | N71: 重启路由器 | O71: dw3_jk_liyuan | P71: 2025-01-01 18:05:06 | Q71: SD-851-290020-10385-27358 | R71: =IF(OR(LEFT(L71,2)="高新"),"奎文",IF(LEFT(L71,2)="峡山","坊子",IF(LEFT(L71,2)="滨海","寒亭",LEFT(L71,2)))) -> 寒亭 | S71: =TEXT(B71,"mmdd") -> 0101
A72: SD-057-250101-092617-5288 | B72: 2025-01-01 17:59:21 | C72: 潍坊 | D72: 普通区域-诸城市-王庄自然村-15165651088-300M-宽带上网投诉-次数0-20250101175744X464371148 | E72: 2025-01-02 19:00:00 | F72: 20250101175744X464371148 | G72: 【农村网络投诉】流程受理流水号：20250101175556151656510881169842 客户号码:15165651088 客户姓名:冯** 投诉地市:潍坊 来话流水:2025010117523019120826550 宽带账号:15165651088 宽带账号归属地市:潍坊 宽带账号归属区县:诸城市 故障地址:潍坊诸城市贾悦镇王庄王庄自然村王庄西南区19#箱********* 联系电话:15165651088 联系人:先生 工单紧急程度:一般 是否有升级投诉倾向:否 是否重复投诉:否 是否携转意向:否 是否投诉倾向:否 是否智能网关:智能网关 当前是否在线:否 接入方式:FTTH 端到端诊断结果:状态正常 是否质差终端:无质差信息 光功率:无 故障大类:宽带/电视 故障细类:宽带无法上网(专席) 携转原因: 故障时间:2025-01-01 17:56:04 具体故障现象:光猫亮红灯，客户来电反映光信号亮红灯，引导插紧光纤线，捋直未恢复，请协助处理 客户其他诉求: | H72: 2025-01-01 18:00:58 | I72: 家宽业务->网络质量->家庭宽带->全局流转->功能使用->网络无法连接->全局流转 | J72: 王海 | K72: 15706307956 | L72: 诸城市 | M72: 家客铁通潍坊诸城-枳沟乡镇装维组 | O72: dw3_jk_wanghai | P72: 2025-01-01 18:01:30 | R72: =IF(OR(LEFT(L72,2)="高新"),"奎文",IF(LEFT(L72,2)="峡山","坊子",IF(LEFT(L72,2)="滨海","寒亭",LEFT(L72,2)))) -> 诸城 | S72: =TEXT(B72,"mmdd") -> 0101
A73: SD-057-250101-839567-1214 | B73: 2025-01-01 10:29:10 | C73: 潍坊 | D73: 【调研】-80+普通-普通区域-昌邑市-北孟圣泽苑-15965059680-1000M-宽带上网投诉-次数0-20250101102712X432574171 | E73: 2025-01-02 08:00:00 | F73: 20250101102712X432574171 | G73: 流程受理流水号：20250101102501159650596801037715 客户号码:15965059680 客户姓名:刘** 投诉地市:潍坊 来话流水:2025010110224316220813921 宽带账号:15965059680 宽带账号归属地市:潍坊 宽带账号归属区县:昌邑市 故障地址:潍坊昌邑市北孟镇北孟街北孟圣泽苑小区3号楼********* 联系电话:15965059680 联系人:先生/女士 工单紧急程度:非常紧急 是否有升级投诉倾向:否 是否重复投诉:否 是否携转意向:否 是否投诉倾向:否 是否智能网关:智能网关 当前是否在线:是 接入方式:FTTH 端到端诊断结果:客户侧设备问题（新增） 是否质差终端:无质差信息 光功率:-19.35 故障大类:宽带/电视 故障细类:宽带无法上网(专席) 携转原因: 故障时间:2025-01-01 10:24:36 具体故障现象:提示网络无法连接，光猫正常后台刷新重启设备还是无法连接网络 客户其他诉求: | H73: 2025-01-01 10:31:03 | I73: 家宽业务->网络质量->家庭宽带->全局流转->功能使用->网络无法连接->全局流转 | J73: 李勇 | K73: 15706307207 | L73: 昌邑市 | M73: 家客铁通潍坊昌邑-北孟乡镇装维组 | N73: 重新熔接皮线 | O73: dw3_jk_liyong | P73: 2025-01-01 10:31:34 | Q73: SD-851-317450-16896-14323 | R73: =IF(OR(LEFT(L73,2)="高新"),"奎文",IF(LEFT(L73,2)="峡山","坊子",IF(LEFT(L73,2)="滨海","寒亭",LEFT(L73,2)))) -> 昌邑 | S73: =TEXT(B73,"mmdd") -> 0101
A74: SD-057-250101-261304-5231 | B74: 2025-01-01 17:54:42 | C74: 潍坊 | D74: 80+普通-普通区域--null--魔百和投诉-次数0-20250101163258X378692767 | E74: 2025-01-02 17:55:00 | F74: 20250101163258X378692767 | G74: 客户表示 自己 订购的 黄金会员 现在 不能 看 要求 尽快 回电 解决 流水号2025010116292535320821748 联系电话18205361155 | I74: 家庭业务->业务营销->互联网电视(移动高清)->全局流转->业务规则->叠加消费不认可->全局流转 | R74: =IF(OR(LEFT(L74,2)="高新"),"奎文",IF(LEFT(L74,2)="峡山","坊子",IF(LEFT(L74,2)="滨海","寒亭",LEFT(L74,2)))) | S74: =TEXT(B74,"mmdd") -> 0101
A75: SD-057-250101-873506-4425 | B75: 2025-01-01 16:30:55 | C75: 潍坊 | D75: 普通区域-寒亭区-田东村自然村-19861342098-1000M-魔百和投诉-次数0-202501010000485918 | E75: 2025-01-02 17:31:00 | F75: 202501010000485918 | G75: 202501010000485918#流程受理流水号：20250101162934198613420981142893 客户号码:19861342098 客户姓名:苏** 投诉地市:潍坊 来话流水:2025010116282785120810703 宽带账号:19861342098 宽带账号归属地市:潍坊 宽带账号归属区县:寒亭区 故障地址:潍坊寒亭区经济开发区田东村田东村自然村寒亭区经济开发区田东村12号箱********* 联系电话:19861342098 联系人:女士 工单紧急程度:非常紧急 是否有升级投诉倾向:否 是否重复投诉:否 是否携转意向:否 是否投诉倾向:否 是否智能网关:智能网关 当前是否在线:是 接入方式:FTTH 端到端诊断结果:客户侧设备问题（新增） 是否质差终端:无质差信息 光功率:-19.24 故障大类:宽带/电视 故障细类:移动高清电视故障(专席) 携转原因: 故障时间:2025-01-01 16:29:47 魔百和单播/组播:单播 具体故障现象:卡在开机页面，按遥控器没反应 客户其他诉求:请处理，谢谢 魔百和单/组播：单播;宽带小区$[田东村自然村]$ | H75: 2025-01-01 16:35:29 | I75: 家庭咨询->产品质量->互联网电视(移动高清)->全局流转->功能使用->无法进入播放界面->全局流转 | J75: 王春锦 | K75: 15706307445 | L75: 寒亭区 | M75: 家客铁通潍坊寒亭-开发区乡镇装维组 | N75: 重新配置数据 | O75: dw3_jk_wangchunjin | P75: 2025-01-01 16:35:58 | Q75: SD-851-312697-29989-20459 | R75: =IF(OR(LEFT(L75,2)="高新"),"奎文",IF(LEFT(L75,2)="峡山","坊子",IF(LEFT(L75,2)="滨海","寒亭",LEFT(L75,2)))) -> 寒亭 | S75: =TEXT(B75,"mmdd") -> 0101
A76: SD-057-250101-915307-2099 | B76: 2025-01-01 12:07:02 | C76: 潍坊 | D76: 普通区域-诸城市-东武古城南区-13153613297-300M-宽带上网投诉-次数0-202501010000283554 | E76: 2025-01-02 08:00:00 | F76: 202501010000283554 | G76: 202501010000283554#受理号码 : 13153613297客户姓名 : 李**号码归属地 : 潍坊诸城 － 诸城市宏晨电讯服务部（社区）用户品牌 : 全球通 客户来电反映，家里电视无法使用，出现无信号，按流程排查未恢复，请协助处理，谢谢！ 联系人：先生 联系电话：13153613297 宽带地址：潍坊诸城市密州街道东武街东武古城南区40号楼********* 电话流水：2025010112034022620820030 | H76: 2025-01-01 12:11:22 | I76: 家庭咨询->网络质量->家庭宽带->全局流转->功能使用->客户要求装维上门服务->全局流转 | J76: 石震 | K76: 15706307950 | L76: 诸城市 | M76: 家客铁通潍坊诸城-兴华东路城区装维组 | N76: 重新连接机顶盒网络 | O76: dw3_jk_shizhen | P76: 2025-01-01 12:15:59 | R76: =IF(OR(LEFT(L76,2)="高新"),"奎文",IF(LEFT(L76,2)="峡山","坊子",IF(LEFT(L76,2)="滨海","寒亭",LEFT(L76,2)))) -> 诸城 | S76: =TEXT(B76,"mmdd") -> 0101
A77: SD-057-250101-098372-5810 | B77: 2025-01-01 18:50:21 | C77: 潍坊 | D77: 普通区域-寿光市-怡和苑小区-13573656607-300M-宽带上网投诉-次数0-20250101184737X457806615 | E77: 2025-01-02 19:00:00 | F77: 20250101184737X457806615 | G77: 流程受理流水号：20250101184416135736566071181619 客户号码:13573656607 客户姓名:王** 投诉地市:潍坊 来话流水:2025010118435544820883152 宽带账号:13573656607 宽带账号归属地市:潍坊 宽带账号归属区县:寿光市 故障地址:潍坊寿光市北洛镇特钢路怡和苑小区4号楼********* 联系电话:13573656607 联系人:先生/女士 工单紧急程度:紧急 是否有升级投诉倾向:否 是否重复投诉:否 是否携转意向:否 是否投诉倾向:否 是否智能网关:智能网关 当前是否在线:否 接入方式:FTTH 端到端诊断结果:大面积故障 是否质差终端:无质差信息 光功率:无 故障大类:宽带/电视 故障细类:宽带无法上网 携转原因: 故障时间:2025-01-01 18:16:22 具体故障现象:打不开网页， 客户其他诉求: | H77: 2025-01-01 18:54:38 | I77: 家宽业务->网络质量->家庭宽带->全局流转->功能使用->LOS红灯，无法上网->全局流转 | J77: 赵坤 | K77: 15706307757 | L77: 寿光市 | M77: 家客铁通潍坊寿光-古城乡镇装维组 | N77: 更换皮线或网线 | O77: dw3_jk_zhaokun | P77: 2025-01-01 19:02:21 | R77: =IF(OR(LEFT(L77,2)="高新"),"奎文",IF(LEFT(L77,2)="峡山","坊子",IF(LEFT(L77,2)="滨海","寒亭",LEFT(L77,2)))) -> 寿光 | S77: =TEXT(B77,"mmdd") -> 0101
A78: SD-057-250101-381562-183 | B78: 2025-01-01 08:38:24 | C78: 潍坊 | D78: 普通区域-安丘市-尚水名邸-13869650617-300M-魔百和投诉-次数0-20250101083704X824857207 | E78: 2025-01-02 08:00:00 | F78: 20250101083704X824857207 | G78: 流程受理流水号：20250101083556138696506171003062 客户号码:13869650617 客户姓名:高** 投诉地市:潍坊 来话流水:2025010108331776320840556 宽带账号:13869650617 宽带账号归属地市:潍坊 宽带账号归属区县:安丘市 故障地址:潍坊安丘市兴安街道世贸大街尚水名邸尚水名邸38号楼********* 联系电话:13869650617 联系人:先生/女士 工单紧急程度:一般 是否有升级投诉倾向:否 是否重复投诉:否 是否携转意向:否 是否投诉倾向:否 是否智能网关:智能网关 当前是否在线:是 接入方式:FTTH 端到端诊断结果:客户侧设备问题（新增） 是否质差终端:无质差信息 光功率:-18.38 故障大类:宽带/电视 故障细类:移动高清电视故障(专席) 携转原因: 故障时间:2025-01-01 08:35:17 魔百和单播/组播:组播 具体故障现象:电视提示网络类错误， 插拔网线 重新设置网络不恢复 客户其他诉求: 魔百和单/组播：组播 | H78: 2025-01-01 08:42:21 | I78: 家庭业务->产品质量->互联网电视(移动高清)->全局流转->功能使用->无法进入播放界面->全局流转 | J78: 陈玉君 | K78: 15706307059 | L78: 安丘市 | M78: 家客铁通潍坊安丘-贾戈乡镇装维组 | N78: 改为有线接入 | O78: dw3_jk_chenyujun | P78: 2025-01-01 08:42:49 | R78: =IF(OR(LEFT(L78,2)="高新"),"奎文",IF(LEFT(L78,2)="峡山","坊子",IF(LEFT(L78,2)="滨海","寒亭",LEFT(L78,2)))) -> 安丘 | S78: =TEXT(B78,"mmdd") -> 0101
A79: SD-057-250101-163582-176 | B79: 2025-01-01 08:38:05 | C79: 潍坊 | D79: 普通区域-高密市-凤城丽景二期-17663608560-500M-宽带上网投诉-次数0-20250101083527X727096763 | E79: 2025-01-02 08:00:00 | F79: 20250101083527X727096763 | G79: 流程受理流水号：20250101083403176636085601002451 客户号码:17663608560 客户姓名:宿** 投诉地市:潍坊 来话流水:2025010108285750720810119 宽带账号:17663608560 宽带账号归属地市:潍坊 宽带账号归属区县:高密市 故障地址:潍坊高密市朝阳街道康成大街凤城丽景二期77号楼********* 联系电话:18353612096 联系人:先生/女士 工单紧急程度:一般 是否有升级投诉倾向:否 是否重复投诉:否 是否携转意向:否 是否投诉倾向:否 是否智能网关:智能网关 当前是否在线:否 接入方式:FTTH 端到端诊断结果:光猫掉电 是否质差终端:无质差信息 光功率:无 故障大类:宽带/电视 故障细类:宽带无法上网 携转原因: 故障时间:2025-01-01 08:33:20 具体故障现象:光猫亮红灯， 客户其他诉求: | H79: 2025-01-01 08:49:25 | I79: 家宽业务->网络质量->家庭宽带->全局流转->功能使用->LOS红灯，无法上网->全局流转 | J79: 郭涛 | K79: 15706307290 | L79: 高密市 | M79: 家客铁通潍坊高密-朝阳城区装维组 | N79: 更换网线或接头 | O79: dw3_jk_guotao | P79: 2025-01-01 08:50:33 | R79: =IF(OR(LEFT(L79,2)="高新"),"奎文",IF(LEFT(L79,2)="峡山","坊子",IF(LEFT(L79,2)="滨海","寒亭",LEFT(L79,2)))) -> 高密 | S79: =TEXT(B79,"mmdd") -> 0101
A80: SD-057-250101-863705-4451 | B80: 2025-01-01 16:34:59 | C80: 潍坊 | D80: 【调研】-普通区域-奎文区-奎文粮食局宿舍2-13854454918-200M-宽带上网投诉-次数0-202501010000489737 | E80: 2025-01-02 17:35:00 | F80: 202501010000489737 | G80: 202501010000489737#要求装维上门服务：宽带账号：13854454918；宽带地址：潍坊奎文区大虞街道鸢飞路粮食局宿舍南楼*；客户来电反映移动高清电视不能看，客户不配合排障，要求上门，请协助处理，谢谢！联系电话：13854454918；联系人：先生；来电流水：2025010116311071220842142 | H80: 2025-01-01 16:40:51 | I80: 家庭咨询->网络质量->家庭宽带->全局流转->功能使用->客户要求装维上门服务->全局流转 | J80: 张越 | K80: 15706307483 | L80: 奎文区 | M80: 家客铁通潍坊奎文-鸢飞路城区装维组 | N80: 重新调试终端 | O80: dw3_jk_zhangyue | P80: 2025-01-01 16:44:09 | Q80: SD-851-287219-20808-1675 | R80: =IF(OR(LEFT(L80,2)="高新"),"奎文",IF(LEFT(L80,2)="峡山","坊子",IF(LEFT(L80,2)="滨海","寒亭",LEFT(L80,2)))) -> 奎文 | S80: =TEXT(B80,"mmdd") -> 0101
A81: SD-057-250101-590178-2053 | B81: 2025-01-01 12:01:46 | C81: 潍坊 | D81: 普通区域-安丘市-王家营村-18764607722-300M-魔百和投诉-次数0-202501010000281110 | E81: 2025-01-02 08:00:00 | F81: 202501010000281110 | G81: 202501010000281110#流程受理流水号：20250101115733187646077221066901 客户号码:18764607722 客户姓名:刘** 投诉地市:潍坊 来话流水:2025010111570112420846207 宽带账号:18764607722 宽带账号归属地市:潍坊 宽带账号归属区县:安丘市 故障地址:潍坊安丘市凌河镇王家营王家营村安丘凌河王家营村李树良-7号箱********* 联系电话:18764607722 联系人:先生 工单紧急程度:一般 是否有升级投诉倾向:否 是否重复投诉:否 是否携转意向:否 是否投诉倾向:否 是否智能网关:智能网关 当前是否在线:是 接入方式:FTTH 端到端诊断结果:客户侧设备问题（新增） 是否质差终端:无质差信息 光功率:-22.36 故障大类:宽带/电视 故障细类:移动高清电视故障(专席) 携转原因: 故障时间:2025-01-01 12:03:42 魔百和单播/组播:组播 具体故障现象:22002 客户其他诉求: 魔百和单/组播：组播;宽带小区$[王家营村]$ | H81: 2025-01-01 12:06:28 | I81: 家庭咨询->产品质量->互联网电视(移动高清)->全局流转->功能使用->无法进入播放界面->全局流转 | J81: 王振华 | K81: 18863682356 | L81: 安丘市 | M81: 家客铁通潍坊安丘-凌河乡镇装维组 | N81: 指导用户正确使用遥控器 | O81: dw3_jk_wangzhenhua | P81: 2025-01-01 12:07:04 | R81: =IF(OR(LEFT(L81,2)="高新"),"奎文",IF(LEFT(L81,2)="峡山","坊子",IF(LEFT(L81,2)="滨海","寒亭",LEFT(L81,2)))) -> 安丘 | S81: =TEXT(B81,"mmdd") -> 0101
A82: SD-057-250101-368197-5834 | B82: 2025-01-01 18:53:35 | C82: 潍坊 | D82: 普通区域-奎文区-祥瑞家园-15006696759-500M-宽带上网投诉-次数0-202501010000599285 | E82: 2025-01-02 19:00:00 | F82: 202501010000599285 | G82: 202501010000599285#受理号码 : 15006696759客户姓名 : 于**号码归属地 : 潍坊奎文 － 潍坊-奎文-北苑网格-潍坊经济开发区新新营业厅用户品牌 : 全球通 客户来电反映，宽带上网慢，按流程排查未恢复，请协助处理，谢谢！ 联系人：先生 联系电话：15006696758 宽带地址：潍坊奎文区北苑街道玄武街祥瑞家园7号楼********* 电话流水：2025010118491986720823676 | H82: 2025-01-01 18:54:48 | I82: 家庭咨询->网络质量->家庭宽带->全局流转->功能使用->客户要求装维上门服务->全局流转 | J82: 扈培富 | K82: 15706366508 | L82: 奎文区 | M82: 家客铁通潍坊奎文-鸢飞路城区装维组 | N82: 建议用户更换路由器 | O82: dw3_jk_hupeifu | P82: 2025-01-01 18:59:22 | Q82: SD-851-265198-27237-14510 | R82: =IF(OR(LEFT(L82,2)="高新"),"奎文",IF(LEFT(L82,2)="峡山","坊子",IF(LEFT(L82,2)="滨海","寒亭",LEFT(L82,2)))) -> 奎文 | S82: =TEXT(B82,"mmdd") -> 0101
A83: SD-057-250101-729483-141 | B83: 2025-01-01 08:35:25 | C83: 潍坊 | D83: 80+银卡-普通区域-奎文区-加州世纪尊品二期-13791887378-300M-宽带上网投诉-次数0-20250101083412X652726346 | E83: 2025-01-02 08:00:00 | F83: 20250101083412X652726346 | G83: 流程受理流水号：20250101083341137918873781002334 客户号码:13791887378 客户姓名:田** 投诉地市:潍坊 来话流水:2025010108325837020837815 宽带账号:13791887378 宽带账号归属地市:潍坊 宽带账号归属区县:高新 故障地址:潍坊高新高新城区健康街加州世纪尊品二期19号楼********* 联系电话:13791887378 联系人:先生 工单紧急程度:一般 是否有升级投诉倾向:否 是否重复投诉:否 是否携转意向:否 是否投诉倾向:否 是否智能网关:智能网关 当前是否在线:是 接入方式:FTTH 端到端诊断结果:客户侧设备问题（新增） 是否质差终端:无质差信息 光功率:-19.24 故障大类:宽带/电视 故障细类:宽带无法上网(专席) 携转原因: 故障时间:2025-01-01 08:31:47 具体故障现象:光猫亮红灯， 客户其他诉求: | H83: 2025-01-01 08:47:39 | I83: 家宽业务->网络质量->家庭宽带->全局流转->功能使用->网络无法连接->全局流转 | J83: 曹明超 | K83: 15706307420 | L83: 奎文区 | M83: 家客铁通潍坊奎文-樱前街城区装维组 | N83: 重新放缆 | O83: dw3_jk_caomingchaogx | P83: 2025-01-01 08:51:04 | R83: =IF(OR(LEFT(L83,2)="高新"),"奎文",IF(LEFT(L83,2)="峡山","坊子",IF(LEFT(L83,2)="滨海","寒亭",LEFT(L83,2)))) -> 奎文 | S83: =TEXT(B83,"mmdd") -> 0101
A84: SD-057-250101-462017-5814 | B84: 2025-01-01 18:50:29 | C84: 潍坊 | D84: 【调研】-80+银卡-普通区域-安丘市-大华名府-13696361318-1000M-宽带上网投诉-次数0-202501010000599704 | E84: 2025-01-02 18:00:00 | F84: 202501010000599704 | G84: 202501010000599704#宽带账号：13696361318；宽带地址：潍坊安丘市兴安街道商场路大华名府大华名府10号楼*；客户来电反映移动高清不好用，客户不配合排障，要求上门，请协助处理，谢谢！联系电话：13696361318；联系人：孙**；来电流水：2025010118480219320814060 | H84: 2025-01-01 18:52:29 | I84: 家庭咨询->网络质量->家庭宽带->全局流转->功能使用->客户要求装维上门服务->全局流转 | J84: 王国龙 | K84: 15706307029 | L84: 安丘市 | M84: 家客铁通潍坊安丘-永安路城区装维组 | O84: dw3_jk_wangguolong | P84: 2025-01-01 18:52:45 | Q84: SD-851-248013-22229-18467 | R84: =IF(OR(LEFT(L84,2)="高新"),"奎文",IF(LEFT(L84,2)="峡山","坊子",IF(LEFT(L84,2)="滨海","寒亭",LEFT(L84,2)))) -> 安丘 | S84: =TEXT(B84,"mmdd") -> 0101
A85: SD-057-250101-785106-4479 | B85: 2025-01-01 16:37:29 | C85: 潍坊 | D85: 80+银卡-普通区域-青州市-陈仁马村-15864320856-100M-宽带上网投诉-次数0-202501010000494517 | E85: 2025-01-02 17:38:00 | F85: 202501010000494517 | G85: 202501010000494517#导航立单,客户通过语音导航反馈宽带故障问题,经诊断光猫设备性能不佳,要求装维回访处理,请协助.联系电话：15864320856 | H85: 2025-01-01 16:40:04 | I85: 家庭咨询->网络质量->家庭宽带->全局流转->功能使用->光猫设备故障->线上义诊 | J85: 赵坤 | K85: 15706307617 | L85: 青州市 | M85: 家客铁通潍坊青州-邵庄乡镇装维组 | N85: 重新配置数据 | O85: dw3_jk_zhaokunqz | P85: 2025-01-01 16:40:21 | R85: =IF(OR(LEFT(L85,2)="高新"),"奎文",IF(LEFT(L85,2)="峡山","坊子",IF(LEFT(L85,2)="滨海","寒亭",LEFT(L85,2)))) -> 青州 | S85: =TEXT(B85,"mmdd") -> 0101
A86: SD-057-250101-907186-4470 | B86: 2025-01-01 16:36:36 | C86: 潍坊 | D86: 普通区域-临朐县-弥南安置楼-18765617277-300M-宽带上网投诉-次数0-202501010000491513 | E86: 2025-01-02 17:37:00 | F86: 202501010000491513 | G86: 202501010000491513#客户来电反映宽带无法使用，频繁掉线，线上排障不认可，要求维修人员上门维修，请尽快协助处理，谢谢 联系人：先生 联系电话：13361577677 流水：2025010116332863120868741 | H86: 2025-01-01 16:51:01 | I86: 家庭咨询->网络质量->家庭宽带->全局流转->功能使用->客户要求装维上门服务->全局流转 | J86: 郇雨 | K86: 15706307607 | L86: 临朐县 | M86: 家客铁通潍坊临朐-东城城区装维组 | N86: 用户感觉网速慢，但测速达标 | O86: dw3_jk_huanyu | P86: 2025-01-01 16:51:40 | Q86: SD-851-323814-4851-1137 | R86: =IF(OR(LEFT(L86,2)="高新"),"奎文",IF(LEFT(L86,2)="峡山","坊子",IF(LEFT(L86,2)="滨海","寒亭",LEFT(L86,2)))) -> 临朐 | S86: =TEXT(B86,"mmdd") -> 0101
A87: SD-057-250101-736419-2055 | B87: 2025-01-01 12:02:02 | C87: 潍坊 | D87: 【调研】-80+普通-(目标)普通区域-昌邑市-东金台村自然村-13515361814-1000M-宽带上网投诉-次数0-20250101115905X945414360 | E87: 2025-01-02 08:00:00 | F87: 20250101115905X945414360 | G87: 【农村网络投诉】流程受理流水号：20250101115821135153618141067150 客户号码:13515361814 客户姓名:李** 投诉地市:潍坊 来话流水:2025010111564363720842822 宽带账号:13515361814 宽带账号归属地市:潍坊 宽带账号归属区县:昌邑市 故障地址:潍坊昌邑市石埠镇东金台村东金台村自然村昌邑石埠东金台村4号箱李天先pos001-1:8********* 联系电话:13515361814 联系人:先生/女士 工单紧急程度:非常紧急 是否有升级投诉倾向:否 是否重复投诉:否 是否携转意向:否 是否投诉倾向:否 工单内容:客户来电反映室内网线断了，请协助处理，谢谢 | H87: 2025-01-01 12:08:52 | I87: 家宽业务->网络质量->家庭宽带->全局流转->功能使用->网络无法连接->全局流转 | J87: 翟旭辉 | K87: 15706307193 | L87: 昌邑市 | M87: 家客铁通潍坊昌邑-饮马乡镇装维组 | N87: 更换皮线或网线 | O87: dw3_jk_zhaixuhui | P87: 2025-01-01 12:10:27 | Q87: SD-851-282533-9969-13325 | R87: =IF(OR(LEFT(L87,2)="高新"),"奎文",IF(LEFT(L87,2)="峡山","坊子",IF(LEFT(L87,2)="滨海","寒亭",LEFT(L87,2)))) -> 昌邑 | S87: =TEXT(B87,"mmdd") -> 0101
A88: SD-057-250101-804213-175 | B88: 2025-01-01 08:38:01 | C88: 潍坊 | D88: 【调研】-(目标)普通区域-安丘市-青云府-15095237752-300M-宽带上网投诉-次数0-20250101083523X723371333 | E88: 2025-01-02 08:00:00 | F88: 20250101083523X723371333 | G88: 流程受理流水号：20250101083327150952377521002248 客户号码:15095237752 客户姓名:曹** 投诉地市:潍坊 来话流水:2025010108315094720829108 宽带账号:15095237752 宽带账号归属地市:潍坊 宽带账号归属区县:安丘市 故障地址:潍坊安丘市新安街道学府街青云府15--301 联系电话:15095237752 联系人:女士 工单紧急程度:一般 是否有升级投诉倾向:否 是否重复投诉:否 是否携转意向:否 是否投诉倾向:否 是否智能网关:智能网关 当前是否在线:是 接入方式:FTTH 端到端诊断结果:客户侧设备问题（新增） 是否质差终端:无质差信息 光功率:-19.24 故障大类:宽带/电视 故障细类:宽带无法上网(专席) 携转原因: 故障时间:2025-01-01 08:33:52 具体故障现象:打不开网页， 客户其他诉求: | H88: 2025-01-01 08:57:51 | I88: 家宽业务->网络质量->家庭宽带->全局流转->功能使用->网络无法连接->全局流转 | J88: 何成庆 | K88: 15706307023 | L88: 安丘市 | M88: 家客铁通潍坊安丘-刘家尧乡镇装维组 | N88: 重启终端 | O88: dw3_jk_hechengqing | P88: 2025-01-01 09:00:25 | Q88: SD-851-270933-9120-14217 | R88: =IF(OR(LEFT(L88,2)="高新"),"奎文",IF(LEFT(L88,2)="峡山","坊子",IF(LEFT(L88,2)="滨海","寒亭",LEFT(L88,2)))) -> 安丘 | S88: =TEXT(B88,"mmdd") -> 0101
A89: SD-057-250101-045968-2069 | B89: 2025-01-01 12:03:47 | C89: 潍坊 | D89: 【调研】-80+普通-普通区域-寿光市-西岔河一村自然村-15064439811-300M-宽带上网投诉-次数0-202501010000279268 | E89: 2025-01-02 08:00:00 | F89: 202501010000279268 | G89: 202501010000279268#客户来电反映宽带无法使用，线上排障不认可，要求维修人员上门维修，请尽快协助处理，谢谢 联系人：女士 联系电话：本机 流水：2025010112010570720892241 | H89: 2025-01-01 12:09:49 | I89: 家庭咨询->网络质量->家庭宽带->全局流转->功能使用->客户要求装维上门服务->全局流转 | J89: 李培杰 | K89: 15706307761 | L89: 寿光市 | M89: 家客铁通潍坊寿光-侯镇乡镇装维组 | N89: 更换网线或接头 | O89: dw3_jk_lipeijie | P89: 2025-01-01 12:10:22 | R89: =IF(OR(LEFT(L89,2)="高新"),"奎文",IF(LEFT(L89,2)="峡山","坊子",IF(LEFT(L89,2)="滨海","寒亭",LEFT(L89,2)))) -> 寿光 | S89: =TEXT(B89,"mmdd") -> 0101
A90: SD-057-250101-241876-2096 | B90: 2025-01-01 12:06:42 | C90: 潍坊 | D90: 80+银卡-普通区域-寿光市-北关西沿街-15963690539-1000M-宽带上网投诉-次数0-202501010000283283 | E90: 2025-01-02 08:00:00 | F90: 202501010000283283 | G90: 202501010000283283#【已关注中国移动10086微信公众号】流程受理流水号：20250101120615159636905391069211 客户号码:15963690539 客户姓名:刘** 投诉地市:潍坊 来话流水:2025010112060640820845968 宽带账号:15963690539 宽带账号归属地市:潍坊 宽带账号归属区县:寿光市 故障地址:潍坊寿光市圣城街道渤海路北关西沿街2号箱沿街********* 联系电话:15963690539 联系人:先生/女士 工单紧急程度:一般 是否有升级投诉倾向:否 是否重复投诉:否 是否携转意向:否 是否投诉倾向:否 是否智能网关:智能网关 当前是否在线:是 接入方式:FTTH 端到端诊断结果:客户侧设备问题 是否质差终端:是 光功率:-22.75 故障大类:宽带/电视 故障细类:移动高清电视故障 携转原因: 故障时间:2025-01-01 12:06:26 魔百和单播/组播:单播 具体故障现象:机顶盒无法开机， 客户其他诉求:客户侧为质差终端，要求上门更换终端并一并处理故障问题。 | H90: 2025-01-01 12:15:27 | I90: 家庭咨询->网络质量->家庭宽带->全局流转->功能使用->光猫设备故障->线上义诊 | J90: 王晓宁 | K90: 15706307783 | L90: 寿光市 | M90: 家客铁通潍坊寿光-西城城区装维组 | N90: 选择正确信号源 | O90: dw3_jk_wangxiaoning | P90: 2025-01-01 12:15:54 | Q90: SD-851-259533-5847-15192 | R90: =IF(OR(LEFT(L90,2)="高新"),"奎文",IF(LEFT(L90,2)="峡山","坊子",IF(LEFT(L90,2)="滨海","寒亭",LEFT(L90,2)))) -> 寿光 | S90: =TEXT(B90,"mmdd") -> 0101
A91: SD-057-250101-382067-2065 | B91: 2025-01-01 12:03:24 | C91: 潍坊 | D91: 普通区域-昌乐县-大清沟-13656467428-200M-魔百和投诉-次数0-202501010000281742 | E91: 2025-01-02 13:00:00 | F91: 202501010000281742 | G91: 202501010000281742#流程受理流水号：20250101120202136564674281068206 客户号码:13656467428 客户姓名:王** 投诉地市:潍坊 来话流水:2025010111580955120859218 宽带账号:13656467428 宽带账号归属地市:潍坊 宽带账号归属区县:昌乐县 故障地址:潍坊昌乐县乔官镇大清沟大清沟大清沟村6#********* 联系电话:13656467428 联系人:先生/女士 工单紧急程度:一般 是否有升级投诉倾向:否 是否重复投诉:否 是否携转意向:否 是否投诉倾向:否 是否智能网关:智能网关 当前是否在线:是 接入方式:FTTH 端到端诊断结果:客户侧设备问题（新增） 是否质差终端:无质差信息 光功率:-16.67 故障大类:宽带/电视 故障细类:移动高清电视故障(专席) 携转原因: 故障时间:2025-01-01 12:02:28 魔百和单播/组播:组播 具体故障现象:电视提示网络类错误，客户来电反映电视无法观看，我处排障未恢复，请协助处理谢谢 客户其他诉求: 魔百和单/组播：组播;宽带小区$[大清沟]$ | H91: 2025-01-01 12:06:51 | I91: 家庭咨询->产品质量->互联网电视(移动高清)->全局流转->售后服务->电视机提示“无信号”->全局流转 | J91: 岳作涛 | K91: 15706307176 | L91: 昌乐县 | M91: 家客铁通潍坊昌乐-乔官乡镇装维组 | N91: 选择正确信号源 | O91: dw3_jk_yuezuotao | P91: 2025-01-01 12:07:28 | Q91: SD-851-248985-8136-18859 | R91: =IF(OR(LEFT(L91,2)="高新"),"奎文",IF(LEFT(L91,2)="峡山","坊子",IF(LEFT(L91,2)="滨海","寒亭",LEFT(L91,2)))) -> 昌乐 | S91: =TEXT(B91,"mmdd") -> 0101
A92: SD-057-250101-378510-189 | B92: 2025-01-01 08:39:06 | C92: 潍坊 | D92: 80+金卡-普通区域-安丘市-领世新城南区-13721951866-1000M-宽带上网投诉-次数0-202501010000097169 | E92: 2025-01-02 08:00:00 | F92: 202501010000097169 | G92: 202501010000097169#马**13721951866 号码归属地潍坊安丘 － 安丘永安路营业厅 客户来电反映 潍坊安丘市新安街道学府街领世新城南区219号楼***** 宽带无法上网，电视无法观看，自己不会操作，请协助处理，谢谢联系电话15963610638 2025010108322797020833855 | H92: 2025-01-01 08:57:35 | I92: 家庭咨询->网络质量->家庭宽带->全局流转->功能使用->客户要求装维上门服务->全局流转 | J92: 何成庆 | K92: 15706307023 | L92: 安丘市 | M92: 家客铁通潍坊安丘-刘家尧乡镇装维组 | N92: 指导用户加固线缆 | O92: dw3_jk_hechengqing | P92: 2025-01-01 08:58:33 | Q92: SD-851-326859-52594-13506 | R92: =IF(OR(LEFT(L92,2)="高新"),"奎文",IF(LEFT(L92,2)="峡山","坊子",IF(LEFT(L92,2)="滨海","寒亭",LEFT(L92,2)))) -> 安丘 | S92: =TEXT(B92,"mmdd") -> 0101
A93: SD-057-250101-806217-695 | B93: 2025-01-01 09:29:30 | C93: 潍坊 | D93: 80+银卡-普通区域-临朐县-燕子崖农场沿街（小微）-15169558639-300M-宽带上网投诉-次数0-20250101092837X917779971 | E93: 2025-01-02 08:00:00 | F93: 20250101092837X917779971 | G93: 【农村网络投诉】流程受理流水号：20250101092716151695586391019895 客户号码:15169558639 客户姓名:马** 投诉地市:潍坊 来话流水:2025010109263591920896289 宽带账号:15169558639 宽带账号归属地市:潍坊 宽带账号归属区县:临朐县 故障地址:潍坊临朐县冶源镇人民政府燕子崖村燕子崖农场沿街（小微）1号箱燕子崖羊肉馆（外墙）********* 联系电话:15169558639 联系人:女士 工单紧急程度:紧急 是否有升级投诉倾向:否 是否重复投诉:否 是否携转意向:否 是否投诉倾向:否 是否智能网关:智能网关 当前是否在线:否 接入方式:FTTH 端到端诊断结果:状态正常 是否质差终端:无质差信息 光功率:无 故障大类:宽带/电视 故障细类:宽带无法上网 携转原因: 故障时间:2025-01-01 09:28:17 具体故障现象:光猫亮红灯， 客户其他诉求: | H93: 2025-01-01 09:32:40 | I93: 家宽业务->网络质量->家庭宽带->全局流转->功能使用->网络无法连接->全局流转 | J93: 马宝全 | K93: 15706307576 | L93: 临朐县 | M93: 家客铁通潍坊临朐-冶源乡镇装维组 | N93: 更换光猫 | O93: dw3_jk_mabaoquan | P93: 2025-01-01 09:34:59 | R93: =IF(OR(LEFT(L93,2)="高新"),"奎文",IF(LEFT(L93,2)="峡山","坊子",IF(LEFT(L93,2)="滨海","寒亭",LEFT(L93,2)))) -> 临朐 | S93: =TEXT(B93,"mmdd") -> 0101
A94: SD-057-250101-985103-46 | B94: 2025-01-01 07:52:04 | C94: 潍坊 | D94: 80+银卡-普通区域-诸城市-东河崖自然村-13963642253-300M-宽带上网投诉-次数0-202501010000091065 | E94: 2025-01-01 19:00:00 | F94: 202501010000091065 | G94: 202501010000091065#流程受理流水号：20250101075035139636422531000564 客户号码:13963642253 客户姓名:隋** 投诉地市:潍坊 来话流水:2025010107501658620870669 宽带账号:13963642253 宽带账号归属地市:潍坊 宽带账号归属区县:诸城市 故障地址:潍坊诸城市昌城镇东河崖东河崖自然村东河崖村26号箱********* 联系电话:13963642253 联系人:先生/女士 工单紧急程度:紧急 是否有升级投诉倾向:否 是否重复投诉:否 是否携转意向:否 是否投诉倾向:否 是否智能网关:智能网关 当前是否在线:是 接入方式:FTTH 端到端诊断结果:客户侧设备问题（新增） 是否质差终端:无质差信息 光功率:-20.26 故障大类:宽带/电视 故障细类:宽带无法上网 携转原因: 故障时间:2025-01-01 07:51:42 具体故障现象:打不开网页， 客户其他诉求: ;宽带小区$[东河崖自然村]$ | H94: 2025-01-01 07:55:27 | I94: 家宽咨询->网络质量->家庭宽带->全局流转->功能使用->网络连接掉线->全局流转 | J94: 姜健 | K94: 15706307954 | L94: 诸城市 | M94: 家客铁通潍坊诸城-昌城乡镇装维组 | N94: 重启路由器 | O94: dw3_jk_jiangjian1 | P94: 2025-01-01 07:55:53 | R94: =IF(OR(LEFT(L94,2)="高新"),"奎文",IF(LEFT(L94,2)="峡山","坊子",IF(LEFT(L94,2)="滨海","寒亭",LEFT(L94,2)))) -> 诸城 | S94: =TEXT(B94,"mmdd") -> 0101
A95: SD-057-250101-716084-693 | B95: 2025-01-01 09:29:26 | C95: 潍坊 | D95: 【调研】-80+银卡-普通区域-寿光市-龙胜家园-15253629916-200M-魔百和投诉-次数0-20250101092830X910709608 | E95: 2025-01-02 10:30:00 | F95: 20250101092830X910709608 | G95: 流程受理流水号：20250101092715152536299161019886 客户号码:15253629916 客户姓名:柴* 投诉地市:潍坊 来话流水:2025010109194711320815179 宽带账号:15253629916 宽带账号归属地市:潍坊 宽带账号归属区县:寿光市 故障地址:潍坊寿光市化龙镇政府路龙胜家园6号楼东单元402 联系电话:18253629558 联系人:先生 工单紧急程度:一般 是否有升级投诉倾向:否 是否重复投诉:否 是否携转意向:否 是否投诉倾向:否 是否智能网关:智能网关 当前是否在线:是 接入方式:FTTH 端到端诊断结果:客户侧设备问题（新增） 是否质差终端:无质差信息 光功率:-20 故障大类:宽带/电视 故障细类:移动高清电视故障(专席) 携转原因: 故障时间:2025-01-01 09:27:31 魔百和单播/组播:组播 具体故障现象:电视机提示无信号，拔插高清线，调整信号源无效。 客户其他诉求: 魔百和单/组播：组播 | H95: 2025-01-01 09:31:35 | I95: 家庭业务->产品质量->互联网电视(移动高清)->全局流转->售后服务->电视机提示“无信号”->全局流转 | J95: 刘鑫平 | K95: 15706307754 | L95: 寿光市 | M95: 家客铁通潍坊寿光-台头乡镇装维组 | N95: 选择正确信号源 | O95: dw3_jk_liuxinping | P95: 2025-01-01 09:32:03 | R95: =IF(OR(LEFT(L95,2)="高新"),"奎文",IF(LEFT(L95,2)="峡山","坊子",IF(LEFT(L95,2)="滨海","寒亭",LEFT(L95,2)))) -> 寿光 | S95: =TEXT(B95,"mmdd") -> 0101
A96: SD-057-250101-140892-1360 | B96: 2025-01-01 10:46:28 | C96: 潍坊 | D96: 80+金卡-普通区域-寿光市-西岔河二-15163655170-300M-宽带上网投诉-次数0-202501010000210309 | E96: 2025-01-02 08:00:00 | F96: 202501010000210309 | G96: 202501010000210309#流程受理流水号：20250101104527151636551701044378 客户号码:15163655170 客户姓名:宋** 投诉地市:潍坊 来话流水:2025010110430405120887400 宽带账号:15163655170 宽带账号归属地市:潍坊 宽带账号归属区县:-- 故障地址:潍坊寿光市侯镇西岔河二村西岔河二西岔河二村34号箱宋世亮外墙********* 联系电话:15163655170 联系人:先生/女士 工单紧急程度:非常紧急 是否有升级投诉倾向:否 是否重复投诉:否 是否携转意向:否 是否投诉倾向:否 是否智能网关:智能网关 当前是否在线:否 接入方式:FTTH 端到端诊断结果:大面积故障 是否质差终端:无质差信息 光功率:无 故障大类:宽带/电视 故障细类:宽带无法上网 携转原因: 故障时间:2025-01-01 10:50:16 具体故障现象:提示网络无法连接， 客户其他诉求:15163655170客户来电 宽带无法使用 已按口径解释 要求上报 请协助处理谢谢 ;宽带小区$[西岔河二]$ | H96: 2025-01-01 11:02:59 | I96: 家宽咨询->网络质量->家庭宽带->全局流转->功能使用->LOS红灯，无法上网->全局流转 | J96: 李培杰 | K96: 15706307761 | L96: 寿光市 | M96: 家客铁通潍坊寿光-侯镇乡镇装维组 | N96: 【退单】非宽带网络问题 | O96: dw3_jk_wangshuaisg | P96: 2025-01-01 11:04:21 | R96: =IF(OR(LEFT(L96,2)="高新"),"奎文",IF(LEFT(L96,2)="峡山","坊子",IF(LEFT(L96,2)="滨海","寒亭",LEFT(L96,2)))) -> 寿光 | S96: =TEXT(B96,"mmdd") -> 0101
A97: SD-057-250101-420358-1341 | B97: 2025-01-01 10:44:19 | C97: 潍坊 | D97: 普通区域-诸城市-大潘旺自然村-15098170271-100M-宽带上网投诉-次数0-20250101104256X376522840 | E97: 2025-01-02 11:45:00 | F97: 20250101104256X376522840 | G97: 【农村网络投诉】流程受理流水号：20250101104208150981702711043323 客户号码:15098170271 客户姓名:王** 投诉地市:潍坊 来话流水:2025010110383274420826631 宽带账号:15098170271 宽带账号归属地市:潍坊 宽带账号归属区县:诸城市 故障地址:潍坊诸城市密州街道朱解大潘旺大潘旺自然村大潘旺村南5号箱（王树全）********* 联系电话:15098170271 联系人:先生/女士 工单紧急程度:一般 是否有升级投诉倾向:否 是否重复投诉:否 是否携转意向:否 是否投诉倾向:否 是否智能网关:智能网关 当前是否在线:否 接入方式:FTTH 端到端诊断结果:状态正常 是否质差终端:无质差信息 光功率:无 故障大类:宽带/电视 故障细类:宽带无法上网(专席) 携转原因: 故障时间:2025-01-01 10:39:25 具体故障现象:光猫不亮灯，已指导更换插牌未恢复 客户其他诉求: | H97: 2025-01-01 10:49:09 | I97: 家宽业务->网络质量->家庭宽带->全局流转->功能使用->网络无法连接->全局流转 | J97: 胡伟 | K97: 15706307936 | L97: 诸城市 | M97: 家客铁通潍坊诸城-辛兴乡镇装维组 | N97: 指导用户重新连接线缆 | O97: dw3_jk_huweizc | P97: 2025-01-01 10:49:26 | R97: =IF(OR(LEFT(L97,2)="高新"),"奎文",IF(LEFT(L97,2)="峡山","坊子",IF(LEFT(L97,2)="滨海","寒亭",LEFT(L97,2)))) -> 诸城 | S97: =TEXT(B97,"mmdd") -> 0101
A98: SD-057-250101-487916-1363 | B98: 2025-01-01 10:46:31 | C98: 潍坊 | D98: 【调研】-80+普通-普通区域-潍城区-鲁发名城东区-15165603295-500M-宽带上网投诉-次数0-202501010000208799 | E98: 2025-01-02 08:00:00 | F98: 202501010000208799 | G98: 202501010000208799#宽带账号：15165603295；宽带地址：潍坊潍城区西关街道长松路鲁发名城东区A区31号楼，客户来电反映魔百和无法使用，经查询客户侧为质差机顶盒，请协助上门更换终端并一并处理故障问题，谢谢！联系电话：15165603295；联系人：；来电流水：2025010110431407620889561。 | H98: 2025-01-01 10:48:34 | I98: 家庭咨询->网络质量->家庭宽带->全局流转->功能使用->质差机顶盒->全局流转 | J98: 姚国强 | K98: 15706307905 | L98: 潍城区 | M98: 家客铁通潍坊潍城-东风街城区装维组 | N98: 重启机顶盒 | O98: dw3_jk_yaoguoqiang | P98: 2025-01-01 10:48:55 | Q98: SD-851-309327-19885-27721 | R98: =IF(OR(LEFT(L98,2)="高新"),"奎文",IF(LEFT(L98,2)="峡山","坊子",IF(LEFT(L98,2)="滨海","寒亭",LEFT(L98,2)))) -> 潍城 | S98: =TEXT(B98,"mmdd") -> 0101
