Workbook

Sheet 通报
A1: =N6&"日10086投诉一级督办单占比通报" -> 17日10086投诉一级督办单占比通报
A2: 序号 | B2: 区县 | C2: =TEXT(NOW()-1,"dd")&"日新增" -> 17日新增 | J2: 累计一级督办单 | K2: 累计一级督办单占比 | L2: 区县 | U2: =_xlfn.TEXTJOIN(",",,X3:X14) | X2: 前3 | Z2: =_xlfn.TEXTJOIN(",",,AC3:AC14) | AC2: 前3
C3: 重复投诉时间段 | H3: 一级督办单新增 | I3: 一级督办单占比新增 | X3: =VLOOKUP(1,$U$6:$V$17,2,0) | Y3: 1 | AC3: =VLOOKUP(1,$Z$6:$AA$17,2,0) | AD3: 1
C4: 无重复投诉（网课、重点客户） | D4: 7天内重复投诉 | E4: 7-30天以内重复投诉 | F4: 30-60天以内重复投诉 | G4: 60-90天以内重复投诉 | X4: =VLOOKUP(2,$U$6:$V$17,2,0) | Y4: 2 | AC4: =VLOOKUP(2,$Z$6:$AA$17,2,0) | AD4: 2
O5: 对比列 | P5: =VLOOKUP(1,O6:P17,2,0)&","&VLOOKUP(2,O6:P17,2,0)&","&VLOOKUP(3,O6:P17,2,0) -> 昌邑(5.5%),安丘(4.83%),潍城(4.57%) | Q5: 对比列 | R5: =VLOOKUP(1,Q6:R17,2,0)&","&VLOOKUP(2,Q6:R17,2,0)&","&VLOOKUP(3,Q6:R17,2,0) -> #N/A | T5: =VLOOKUP(1,S6:T17,2,0)&","&VLOOKUP(2,S6:T17,2,0)&","&VLOOKUP(3,S6:T17,2,0) -> 昌邑0件,安丘0件,潍城0件 | X5: =VLOOKUP(3,$U$6:$V$17,2,0) | Y5: 3 | AC5: =VLOOKUP(3,$Z$6:$AA$17,2,0) | AD5: 3
A6: 1 | B6: 昌邑 | C6: =COUNTIFS(督办单!L:L,B:B,督办单!M:M,$M$6,督办单!P:P,"无",督办单!C:C,"*一级*") -> 0 | D6: =COUNTIFS(督办单!L:L,B:B,督办单!M:M,$M$6,督办单!P:P,"7天内",督办单!C:C,"*一级*") -> 0 | E6: =COUNTIFS(督办单!L:L,B:B,督办单!M:M,$M$6,督办单!P:P,"30天内",督办单!C:C,"*一级*") -> 0 | F6: =COUNTIFS(督办单!L:L,B:B,督办单!M:M,$M$6,督办单!P:P,"60天内",督办单!C:C,"*一级*") -> 0 | G6: =COUNTIFS(督办单!L:L,B:B,督办单!M:M,$M$6,督办单!P:P,"90天内",督办单!C:C,"*一级*") -> 0 | H6: =COUNTIFS(督办单!L:L,B:B,督办单!C:C,"*一级*",督办单!M:M,$M$6) -> 0 | I6: =COUNTIFS(督办单!L:L,B:B,督办单!C:C,"*一级*",督办单!M:M,$M$6)/(COUNTIFS(累计派单!R:R,B:B,累计派单!S:S,$M$6)-COUNTIFS(累计派单!R:R,B:B,累计派单!I:I,"*业务受理*",累计派单!S:S,$M$6)) -> #DIV/0! | J6: =COUNTIFS(督办单!L:L,B:B,督办单!C:C,"*一级*") -> 23 | K6: =J6/(COUNTIFS(累计派单!R:R,B:B)-COUNTIFS(累计派单!R:R,B:B,累计派单!I:I,"*业务受理*")-COUNTIFS(累计派单!I:I,"*客户咨询*")) -> 0.055023923 | L6: 昌邑 | M6: =TEXT(TODAY()-1,"mmdd") -> 0717 | N6: =TEXT(M6,"dd") -> 17 | O6: =_xlfn.RANK.AVG(K6,$K$6:$K$17) -> 1 | P6: =B6&"("&ROUND(K6*100,2)&"%)" -> 昌邑(5.5%) | Q6: =_xlfn.RANK.AVG(I6,$I$6:$I$17) -> #DIV/0! | R6: =B6&"("&ROUND(I6*100,2)&"%)" -> #DIV/0! | S6: =_xlfn.RANK.EQ(H6,$H$6:$H$17,0)+COUNTIF($H$6:$H6,H6)-1 -> 1 | T6: =B6&H6&"件" -> 昌邑0件 | U6: =_xlfn.RANK.EQ(D6,$D$6:$D$17,0)+COUNTIF($D$6:$D6,D6)-1 -> 1 | V6: =IF(W6=0,"",B6&D6&"件") | W6: =D6 -> 0 | X6: =IF(VLOOKUP(Y5,$U$6:$W$17,3,0)=VLOOKUP(Y6,$U$6:$W$17,3,0),VLOOKUP(Y6,$U$6:$W$17,2,0),"") | Y6: 4 | Z6: =_xlfn.RANK.EQ(E6,$E$6:$E$17,0)+COUNTIF($E$6:$E6,E6)-1 -> 1 | AA6: =IF(AB6=0,"",B6&E6&"件") | AB6: =E6 -> 0 | AC6: =IF(VLOOKUP(AD5,$Z$6:$AB$17,3,0)=VLOOKUP(AD6,$Z$6:$AB$17,3,0),VLOOKUP(AD6,$Z$6:$AB$17,2,0),"") | AD6: 4
A7: 2 | B7: 安丘 | C7: =COUNTIFS(督办单!L:L,B:B,督办单!M:M,$M$6,督办单!P:P,"无",督办单!C:C,"*一级*") -> 0 | D7: =COUNTIFS(督办单!L:L,B:B,督办单!M:M,$M$6,督办单!P:P,"7天内",督办单!C:C,"*一级*") -> 0 | E7: =COUNTIFS(督办单!L:L,B:B,督办单!M:M,$M$6,督办单!P:P,"30天内",督办单!C:C,"*一级*") -> 0 | F7: =COUNTIFS(督办单!L:L,B:B,督办单!M:M,$M$6,督办单!P:P,"60天内",督办单!C:C,"*一级*") -> 0 | G7: =COUNTIFS(督办单!L:L,B:B,督办单!M:M,$M$6,督办单!P:P,"90天内",督办单!C:C,"*一级*") -> 0 | H7: =COUNTIFS(督办单!L:L,B:B,督办单!C:C,"*一级*",督办单!M:M,$M$6) -> 0 | I7: =COUNTIFS(督办单!L:L,B:B,督办单!C:C,"*一级*",督办单!M:M,$M$6)/(COUNTIFS(累计派单!R:R,B:B,累计派单!S:S,$M$6)-COUNTIFS(累计派单!R:R,B:B,累计派单!I:I,"*业务受理*",累计派单!S:S,$M$6)) -> #DIV/0! | J7: =COUNTIFS(督办单!L:L,B:B,督办单!C:C,"*一级*") -> 36 | K7: =J7/(COUNTIFS(累计派单!R:R,B:B)-COUNTIFS(累计派单!R:R,B:B,累计派单!I:I,"*业务受理*")-COUNTIFS(累计派单!I:I,"*客户咨询*")) -> 0.048322148 | L7: 安丘 | O7: =_xlfn.RANK.AVG(K7,$K$6:$K$17) -> 2 | P7: =B7&"("&ROUND(K7*100,2)&"%)" -> 安丘(4.83%) | Q7: =_xlfn.RANK.AVG(I7,$I$6:$I$17) -> #DIV/0! | R7: =B7&"("&ROUND(I7*100,2)&"%)" -> #DIV/0! | S7: =_xlfn.RANK.EQ(H7,$H$6:$H$17,0)+COUNTIF($H$6:$H7,H7)-1 -> 2 | T7: =B7&H7&"件" -> 安丘0件 | U7: =_xlfn.RANK.EQ(D7,$D$6:$D$17,0)+COUNTIF($D$6:$D7,D7)-1 -> 2 | V7: =IF(W7=0,"",B7&D7&"件") | W7: =D7 -> 0 | X7: =IF(VLOOKUP(Y6,$U$6:$W$17,3,0)=VLOOKUP(Y7,$U$6:$W$17,3,0),VLOOKUP(Y7,$U$6:$W$17,2,0),"") | Y7: 5 | Z7: =_xlfn.RANK.EQ(E7,$E$6:$E$17,0)+COUNTIF($E$6:$E7,E7)-1 -> 2 | AA7: =IF(AB7=0,"",B7&E7&"件") | AB7: =E7 -> 0 | AC7: =IF(VLOOKUP(AD6,$Z$6:$AB$17,3,0)=VLOOKUP(AD7,$Z$6:$AB$17,3,0),VLOOKUP(AD7,$Z$6:$AB$17,2,0),"") | AD7: 5
A8: 3 | B8: 潍城 | C8: =COUNTIFS(督办单!L:L,B:B,督办单!M:M,$M$6,督办单!P:P,"无",督办单!C:C,"*一级*") -> 0 | D8: =COUNTIFS(督办单!L:L,B:B,督办单!M:M,$M$6,督办单!P:P,"7天内",督办单!C:C,"*一级*") -> 0 | E8: =COUNTIFS(督办单!L:L,B:B,督办单!M:M,$M$6,督办单!P:P,"30天内",督办单!C:C,"*一级*") -> 0 | F8: =COUNTIFS(督办单!L:L,B:B,督办单!M:M,$M$6,督办单!P:P,"60天内",督办单!C:C,"*一级*") -> 0 | G8: =COUNTIFS(督办单!L:L,B:B,督办单!M:M,$M$6,督办单!P:P,"90天内",督办单!C:C,"*一级*") -> 0 | H8: =COUNTIFS(督办单!L:L,B:B,督办单!C:C,"*一级*",督办单!M:M,$M$6) -> 0 | I8: =COUNTIFS(督办单!L:L,B:B,督办单!C:C,"*一级*",督办单!M:M,$M$6)/(COUNTIFS(累计派单!R:R,B:B,累计派单!S:S,$M$6)-COUNTIFS(累计派单!R:R,B:B,累计派单!I:I,"*业务受理*",累计派单!S:S,$M$6)) -> #DIV/0! | J8: =COUNTIFS(督办单!L:L,B:B,督办单!C:C,"*一级*") -> 27 | K8: =J8/(COUNTIFS(累计派单!R:R,B:B)-COUNTIFS(累计派单!R:R,B:B,累计派单!I:I,"*业务受理*")-COUNTIFS(累计派单!I:I,"*客户咨询*")) -> 0.045685279 | L8: 潍城 | O8: =_xlfn.RANK.AVG(K8,$K$6:$K$17) -> 3 | P8: =B8&"("&ROUND(K8*100,2)&"%)" -> 潍城(4.57%) | Q8: =_xlfn.RANK.AVG(I8,$I$6:$I$17) -> #DIV/0! | R8: =B8&"("&ROUND(I8*100,2)&"%)" -> #DIV/0! | S8: =_xlfn.RANK.EQ(H8,$H$6:$H$17,0)+COUNTIF($H$6:$H8,H8)-1 -> 3 | T8: =B8&H8&"件" -> 潍城0件 | U8: =_xlfn.RANK.EQ(D8,$D$6:$D$17,0)+COUNTIF($D$6:$D8,D8)-1 -> 3 | V8: =IF(W8=0,"",B8&D8&"件") | W8: =D8 -> 0 | X8: =IF(VLOOKUP(Y7,$U$6:$W$17,3,0)=VLOOKUP(Y8,$U$6:$W$17,3,0),VLOOKUP(Y8,$U$6:$W$17,2,0),"") | Y8: 6 | Z8: =_xlfn.RANK.EQ(E8,$E$6:$E$17,0)+COUNTIF($E$6:$E8,E8)-1 -> 3 | AA8: =IF(AB8=0,"",B8&E8&"件") | AB8: =E8 -> 0 | AC8: =IF(VLOOKUP(AD7,$Z$6:$AB$17,3,0)=VLOOKUP(AD8,$Z$6:$AB$17,3,0),VLOOKUP(AD8,$Z$6:$AB$17,2,0),"") | AD8: 6
A9: 4 | B9: 寒亭 | C9: =COUNTIFS(督办单!L:L,B:B,督办单!M:M,$M$6,督办单!P:P,"无",督办单!C:C,"*一级*") -> 0 | D9: =COUNTIFS(督办单!L:L,B:B,督办单!M:M,$M$6,督办单!P:P,"7天内",督办单!C:C,"*一级*") -> 0 | E9: =COUNTIFS(督办单!L:L,B:B,督办单!M:M,$M$6,督办单!P:P,"30天内",督办单!C:C,"*一级*") -> 0 | F9: =COUNTIFS(督办单!L:L,B:B,督办单!M:M,$M$6,督办单!P:P,"60天内",督办单!C:C,"*一级*") -> 0 | G9: =COUNTIFS(督办单!L:L,B:B,督办单!M:M,$M$6,督办单!P:P,"90天内",督办单!C:C,"*一级*") -> 0 | H9: =COUNTIFS(督办单!L:L,B:B,督办单!C:C,"*一级*",督办单!M:M,$M$6) -> 0 | I9: =COUNTIFS(督办单!L:L,B:B,督办单!C:C,"*一级*",督办单!M:M,$M$6)/(COUNTIFS(累计派单!R:R,B:B,累计派单!S:S,$M$6)-COUNTIFS(累计派单!R:R,B:B,累计派单!I:I,"*业务受理*",累计派单!S:S,$M$6)) -> #DIV/0! | J9: =COUNTIFS(督办单!L:L,B:B,督办单!C:C,"*一级*") -> 19 | K9: =J9/(COUNTIFS(累计派单!R:R,B:B)-COUNTIFS(累计派单!R:R,B:B,累计派单!I:I,"*业务受理*")-COUNTIFS(累计派单!I:I,"*客户咨询*")) -> 0.045673077 | L9: 寒亭 | O9: =_xlfn.RANK.AVG(K9,$K$6:$K$17) -> 4 | P9: =B9&"("&ROUND(K9*100,2)&"%)" -> 寒亭(4.57%) | Q9: =_xlfn.RANK.AVG(I9,$I$6:$I$17) -> #DIV/0! | R9: =B9&"("&ROUND(I9*100,2)&"%)" -> #DIV/0! | S9: =_xlfn.RANK.EQ(H9,$H$6:$H$17,0)+COUNTIF($H$6:$H9,H9)-1 -> 4 | T9: =B9&H9&"件" -> 寒亭0件 | U9: =_xlfn.RANK.EQ(D9,$D$6:$D$17,0)+COUNTIF($D$6:$D9,D9)-1 -> 4 | V9: =IF(W9=0,"",B9&D9&"件") | W9: =D9 -> 0 | X9: =IF(VLOOKUP(Y8,$U$6:$W$17,3,0)=VLOOKUP(Y9,$U$6:$W$17,3,0),VLOOKUP(Y9,$U$6:$W$17,2,0),"") | Y9: 7 | Z9: =_xlfn.RANK.EQ(E9,$E$6:$E$17,0)+COUNTIF($E$6:$E9,E9)-1 -> 4 | AA9: =IF(AB9=0,"",B9&E9&"件") | AB9: =E9 -> 0 | AC9: =IF(VLOOKUP(AD8,$Z$6:$AB$17,3,0)=VLOOKUP(AD9,$Z$6:$AB$17,3,0),VLOOKUP(AD9,$Z$6:$AB$17,2,0),"") | AD9: 7
A10: 5 | B10: 奎文 | C10: =COUNTIFS(督办单!L:L,B:B,督办单!M:M,$M$6,督办单!P:P,"无",督办单!C:C,"*一级*") -> 0 | D10: =COUNTIFS(督办单!L:L,B:B,督办单!M:M,$M$6,督办单!P:P,"7天内",督办单!C:C,"*一级*") -> 0 | E10: =COUNTIFS(督办单!L:L,B:B,督办单!M:M,$M$6,督办单!P:P,"30天内",督办单!C:C,"*一级*") -> 0 | F10: =COUNTIFS(督办单!L:L,B:B,督办单!M:M,$M$6,督办单!P:P,"60天内",督办单!C:C,"*一级*") -> 0 | G10: =COUNTIFS(督办单!L:L,B:B,督办单!M:M,$M$6,督办单!P:P,"90天内",督办单!C:C,"*一级*") -> 0 | H10: =COUNTIFS(督办单!L:L,B:B,督办单!C:C,"*一级*",督办单!M:M,$M$6) -> 0 | I10: =COUNTIFS(督办单!L:L,B:B,督办单!C:C,"*一级*",督办单!M:M,$M$6)/(COUNTIFS(累计派单!R:R,B:B,累计派单!S:S,$M$6)-COUNTIFS(累计派单!R:R,B:B,累计派单!I:I,"*业务受理*",累计派单!S:S,$M$6)) -> #DIV/0! | J10: =COUNTIFS(督办单!L:L,B:B,督办单!C:C,"*一级*") -> 41 | K10: =J10/(COUNTIFS(累计派单!R:R,B:B)-COUNTIFS(累计派单!R:R,B:B,累计派单!I:I,"*业务受理*")-COUNTIFS(累计派单!I:I,"*客户咨询*")) -> 0.039347409 | L10: 奎文 | O10: =_xlfn.RANK.AVG(K10,$K$6:$K$17) -> 7 | P10: =B10&"("&ROUND(K10*100,2)&"%)" -> 奎文(3.93%) | Q10: =_xlfn.RANK.AVG(I10,$I$6:$I$17) -> #DIV/0! | R10: =B10&"("&ROUND(I10*100,2)&"%)" -> #DIV/0! | S10: =_xlfn.RANK.EQ(H10,$H$6:$H$17,0)+COUNTIF($H$6:$H10,H10)-1 -> 5 | T10: =B10&H10&"件" -> 奎文0件 | U10: =_xlfn.RANK.EQ(D10,$D$6:$D$17,0)+COUNTIF($D$6:$D10,D10)-1 -> 5 | V10: =IF(W10=0,"",B10&D10&"件") | W10: =D10 -> 0 | X10: =IF(VLOOKUP(Y9,$U$6:$W$17,3,0)=VLOOKUP(Y10,$U$6:$W$17,3,0),VLOOKUP(Y10,$U$6:$W$17,2,0),"") | Y10: 8 | Z10: =_xlfn.RANK.EQ(E10,$E$6:$E$17,0)+COUNTIF($E$6:$E10,E10)-1 -> 5 | AA10: =IF(AB10=0,"",B10&E10&"件") | AB10: =E10 -> 0 | AC10: =IF(VLOOKUP(AD9,$Z$6:$AB$17,3,0)=VLOOKUP(AD10,$Z$6:$AB$17,3,0),VLOOKUP(AD10,$Z$6:$AB$17,2,0),"") | AD10: 8
A11: 6 | B11: 临朐 | C11: =COUNTIFS(督办单!L:L,B:B,督办单!M:M,$M$6,督办单!P:P,"无",督办单!C:C,"*一级*") -> 0 | D11: =COUNTIFS(督办单!L:L,B:B,督办单!M:M,$M$6,督办单!P:P,"7天内",督办单!C:C,"*一级*") -> 0 | E11: =COUNTIFS(督办单!L:L,B:B,督办单!M:M,$M$6,督办单!P:P,"30天内",督办单!C:C,"*一级*") -> 0 | F11: =COUNTIFS(督办单!L:L,B:B,督办单!M:M,$M$6,督办单!P:P,"60天内",督办单!C:C,"*一级*") -> 0 | G11: =COUNTIFS(督办单!L:L,B:B,督办单!M:M,$M$6,督办单!P:P,"90天内",督办单!C:C,"*一级*") -> 0 | H11: =COUNTIFS(督办单!L:L,B:B,督办单!C:C,"*一级*",督办单!M:M,$M$6) -> 0 | I11: =COUNTIFS(督办单!L:L,B:B,督办单!C:C,"*一级*",督办单!M:M,$M$6)/(COUNTIFS(累计派单!R:R,B:B,累计派单!S:S,$M$6)-COUNTIFS(累计派单!R:R,B:B,累计派单!I:I,"*业务受理*",累计派单!S:S,$M$6)) -> #DIV/0! | J11: =COUNTIFS(督办单!L:L,B:B,督办单!C:C,"*一级*") -> 20 | K11: =J11/(COUNTIFS(累计派单!R:R,B:B)-COUNTIFS(累计派单!R:R,B:B,累计派单!I:I,"*业务受理*")-COUNTIFS(累计派单!I:I,"*客户咨询*")) -> 0.043859649 | L11: 临朐 | O11: =_xlfn.RANK.AVG(K11,$K$6:$K$17) -> 5 | P11: =B11&"("&ROUND(K11*100,2)&"%)" -> 临朐(4.39%) | Q11: =_xlfn.RANK.AVG(I11,$I$6:$I$17) -> #DIV/0! | R11: =B11&"("&ROUND(I11*100,2)&"%)" -> #DIV/0! | S11: =_xlfn.RANK.EQ(H11,$H$6:$H$17,0)+COUNTIF($H$6:$H11,H11)-1 -> 6 | T11: =B11&H11&"件" -> 临朐0件 | U11: =_xlfn.RANK.EQ(D11,$D$6:$D$17,0)+COUNTIF($D$6:$D11,D11)-1 -> 6 | V11: =IF(W11=0,"",B11&D11&"件") | W11: =D11 -> 0 | X11: =IF(VLOOKUP(Y10,$U$6:$W$17,3,0)=VLOOKUP(Y11,$U$6:$W$17,3,0),VLOOKUP(Y11,$U$6:$W$17,2,0),"") | Y11: 9 | Z11: =_xlfn.RANK.EQ(E11,$E$6:$E$17,0)+COUNTIF($E$6:$E11,E11)-1 -> 6 | AA11: =IF(AB11=0,"",B11&E11&"件") | AB11: =E11 -> 0 | AC11: =IF(VLOOKUP(AD10,$Z$6:$AB$17,3,0)=VLOOKUP(AD11,$Z$6:$AB$17,3,0),VLOOKUP(AD11,$Z$6:$AB$17,2,0),"") | AD11: 9
A12: 7 | B12: 坊子 | C12: =COUNTIFS(督办单!L:L,B:B,督办单!M:M,$M$6,督办单!P:P,"无",督办单!C:C,"*一级*") -> 0 | D12: =COUNTIFS(督办单!L:L,B:B,督办单!M:M,$M$6,督办单!P:P,"7天内",督办单!C:C,"*一级*") -> 0 | E12: =COUNTIFS(督办单!L:L,B:B,督办单!M:M,$M$6,督办单!P:P,"30天内",督办单!C:C,"*一级*") -> 0 | F12: =COUNTIFS(督办单!L:L,B:B,督办单!M:M,$M$6,督办单!P:P,"60天内",督办单!C:C,"*一级*") -> 0 | G12: =COUNTIFS(督办单!L:L,B:B,督办单!M:M,$M$6,督办单!P:P,"90天内",督办单!C:C,"*一级*") -> 0 | H12: =COUNTIFS(督办单!L:L,B:B,督办单!C:C,"*一级*",督办单!M:M,$M$6) -> 0 | I12: =COUNTIFS(督办单!L:L,B:B,督办单!C:C,"*一级*",督办单!M:M,$M$6)/(COUNTIFS(累计派单!R:R,B:B,累计派单!S:S,$M$6)-COUNTIFS(累计派单!R:R,B:B,累计派单!I:I,"*业务受理*",累计派单!S:S,$M$6)) -> #DIV/0! | J12: =COUNTIFS(督办单!L:L,B:B,督办单!C:C,"*一级*") -> 14 | K12: =J12/(COUNTIFS(累计派单!R:R,B:B)-COUNTIFS(累计派单!R:R,B:B,累计派单!I:I,"*业务受理*")-COUNTIFS(累计派单!I:I,"*客户咨询*")) -> 0.042168675 | L12: 坊子 | O12: =_xlfn.RANK.AVG(K12,$K$6:$K$17) -> 6 | P12: =B12&"("&ROUND(K12*100,2)&"%)" -> 坊子(4.22%) | Q12: =_xlfn.RANK.AVG(I12,$I$6:$I$17) -> #DIV/0! | R12: =B12&"("&ROUND(I12*100,2)&"%)" -> #DIV/0! | S12: =_xlfn.RANK.EQ(H12,$H$6:$H$17,0)+COUNTIF($H$6:$H12,H12)-1 -> 7 | T12: =B12&H12&"件" -> 坊子0件 | U12: =_xlfn.RANK.EQ(D12,$D$6:$D$17,0)+COUNTIF($D$6:$D12,D12)-1 -> 7 | V12: =IF(W12=0,"",B12&D12&"件") | W12: =D12 -> 0 | X12: =IF(VLOOKUP(Y11,$U$6:$W$17,3,0)=VLOOKUP(Y12,$U$6:$W$17,3,0),VLOOKUP(Y12,$U$6:$W$17,2,0),"") | Y12: 10 | Z12: =_xlfn.RANK.EQ(E12,$E$6:$E$17,0)+COUNTIF($E$6:$E12,E12)-1 -> 7 | AA12: =IF(AB12=0,"",B12&E12&"件") | AB12: =E12 -> 0 | AC12: =IF(VLOOKUP(AD11,$Z$6:$AB$17,3,0)=VLOOKUP(AD12,$Z$6:$AB$17,3,0),VLOOKUP(AD12,$Z$6:$AB$17,2,0),"") | AD12: 10
A13: 8 | B13: 寿光 | C13: =COUNTIFS(督办单!L:L,B:B,督办单!M:M,$M$6,督办单!P:P,"无",督办单!C:C,"*一级*") -> 0 | D13: =COUNTIFS(督办单!L:L,B:B,督办单!M:M,$M$6,督办单!P:P,"7天内",督办单!C:C,"*一级*") -> 0 | E13: =COUNTIFS(督办单!L:L,B:B,督办单!M:M,$M$6,督办单!P:P,"30天内",督办单!C:C,"*一级*") -> 0 | F13: =COUNTIFS(督办单!L:L,B:B,督办单!M:M,$M$6,督办单!P:P,"60天内",督办单!C:C,"*一级*") -> 0 | G13: =COUNTIFS(督办单!L:L,B:B,督办单!M:M,$M$6,督办单!P:P,"90天内",督办单!C:C,"*一级*") -> 0 | H13: =COUNTIFS(督办单!L:L,B:B,督办单!C:C,"*一级*",督办单!M:M,$M$6) -> 0 | I13: =COUNTIFS(督办单!L:L,B:B,督办单!C:C,"*一级*",督办单!M:M,$M$6)/(COUNTIFS(累计派单!R:R,B:B,累计派单!S:S,$M$6)-COUNTIFS(累计派单!R:R,B:B,累计派单!I:I,"*业务受理*",累计派单!S:S,$M$6)) -> #DIV/0! | J13: =COUNTIFS(督办单!L:L,B:B,督办单!C:C,"*一级*") -> 37 | K13: =J13/(COUNTIFS(累计派单!R:R,B:B)-COUNTIFS(累计派单!R:R,B:B,累计派单!I:I,"*业务受理*")-COUNTIFS(累计派单!I:I,"*客户咨询*")) -> 0.032656664 | L13: 寿光 | O13: =_xlfn.RANK.AVG(K13,$K$6:$K$17) -> 8 | P13: =B13&"("&ROUND(K13*100,2)&"%)" -> 寿光(3.27%) | Q13: =_xlfn.RANK.AVG(I13,$I$6:$I$17) -> #DIV/0! | R13: =B13&"("&ROUND(I13*100,2)&"%)" -> #DIV/0! | S13: =_xlfn.RANK.EQ(H13,$H$6:$H$17,0)+COUNTIF($H$6:$H13,H13)-1 -> 8 | T13: =B13&H13&"件" -> 寿光0件 | U13: =_xlfn.RANK.EQ(D13,$D$6:$D$17,0)+COUNTIF($D$6:$D13,D13)-1 -> 8 | V13: =IF(W13=0,"",B13&D13&"件") | W13: =D13 -> 0 | X13: =IF(VLOOKUP(Y12,$U$6:$W$17,3,0)=VLOOKUP(Y13,$U$6:$W$17,3,0),VLOOKUP(Y13,$U$6:$W$17,2,0),"") | Y13: 11 | Z13: =_xlfn.RANK.EQ(E13,$E$6:$E$17,0)+COUNTIF($E$6:$E13,E13)-1 -> 8 | AA13: =IF(AB13=0,"",B13&E13&"件") | AB13: =E13 -> 0 | AC13: =IF(VLOOKUP(AD12,$Z$6:$AB$17,3,0)=VLOOKUP(AD13,$Z$6:$AB$17,3,0),VLOOKUP(AD13,$Z$6:$AB$17,2,0),"") | AD13: 11
A14: 9 | B14: 高密 | C14: =COUNTIFS(督办单!L:L,B:B,督办单!M:M,$M$6,督办单!P:P,"无",督办单!C:C,"*一级*") -> 0 | D14: =COUNTIFS(督办单!L:L,B:B,督办单!M:M,$M$6,督办单!P:P,"7天内",督办单!C:C,"*一级*") -> 0 | E14: =COUNTIFS(督办单!L:L,B:B,督办单!M:M,$M$6,督办单!P:P,"30天内",督办单!C:C,"*一级*") -> 0 | F14: =COUNTIFS(督办单!L:L,B:B,督办单!M:M,$M$6,督办单!P:P,"60天内",督办单!C:C,"*一级*") -> 0 | G14: =COUNTIFS(督办单!L:L,B:B,督办单!M:M,$M$6,督办单!P:P,"90天内",督办单!C:C,"*一级*") -> 0 | H14: =COUNTIFS(督办单!L:L,B:B,督办单!C:C,"*一级*",督办单!M:M,$M$6) -> 0 | I14: =COUNTIFS(督办单!L:L,B:B,督办单!C:C,"*一级*",督办单!M:M,$M$6)/(COUNTIFS(累计派单!R:R,B:B,累计派单!S:S,$M$6)-COUNTIFS(累计派单!R:R,B:B,累计派单!I:I,"*业务受理*",累计派单!S:S,$M$6)) -> #DIV/0! | J14: =COUNTIFS(督办单!L:L,B:B,督办单!C:C,"*一级*") -> 20 | K14: =J14/(COUNTIFS(累计派单!R:R,B:B)-COUNTIFS(累计派单!R:R,B:B,累计派单!I:I,"*业务受理*")-COUNTIFS(累计派单!I:I,"*客户咨询*")) -> 0.028653295 | L14: 高密 | O14: =_xlfn.RANK.AVG(K14,$K$6:$K$17) -> 9 | P14: =B14&"("&ROUND(K14*100,2)&"%)" -> 高密(2.87%) | Q14: =_xlfn.RANK.AVG(I14,$I$6:$I$17) -> #DIV/0! | R14: =B14&"("&ROUND(I14*100,2)&"%)" -> #DIV/0! | S14: =_xlfn.RANK.EQ(H14,$H$6:$H$17,0)+COUNTIF($H$6:$H14,H14)-1 -> 9 | T14: =B14&H14&"件" -> 高密0件 | U14: =_xlfn.RANK.EQ(D14,$D$6:$D$17,0)+COUNTIF($D$6:$D14,D14)-1 -> 9 | V14: =IF(W14=0,"",B14&D14&"件") | W14: =D14 -> 0 | X14: =IF(VLOOKUP(Y13,$U$6:$W$17,3,0)=VLOOKUP(Y14,$U$6:$W$17,3,0),VLOOKUP(Y14,$U$6:$W$17,2,0),"") | Y14: 12 | Z14: =_xlfn.RANK.EQ(E14,$E$6:$E$17,0)+COUNTIF($E$6:$E14,E14)-1 -> 9 | AA14: =IF(AB14=0,"",B14&E14&"件") | AB14: =E14 -> 0 | AC14: =IF(VLOOKUP(AD13,$Z$6:$AB$17,3,0)=VLOOKUP(AD14,$Z$6:$AB$17,3,0),VLOOKUP(AD14,$Z$6:$AB$17,2,0),"") | AD14: 12
A15: 10 | B15: 青州 | C15: =COUNTIFS(督办单!L:L,B:B,督办单!M:M,$M$6,督办单!P:P,"无",督办单!C:C,"*一级*") -> 0 | D15: =COUNTIFS(督办单!L:L,B:B,督办单!M:M,$M$6,督办单!P:P,"7天内",督办单!C:C,"*一级*") -> 0 | E15: =COUNTIFS(督办单!L:L,B:B,督办单!M:M,$M$6,督办单!P:P,"30天内",督办单!C:C,"*一级*") -> 0 | F15: =COUNTIFS(督办单!L:L,B:B,督办单!M:M,$M$6,督办单!P:P,"60天内",督办单!C:C,"*一级*") -> 0 | G15: =COUNTIFS(督办单!L:L,B:B,督办单!M:M,$M$6,督办单!P:P,"90天内",督办单!C:C,"*一级*") -> 0 | H15: =COUNTIFS(督办单!L:L,B:B,督办单!C:C,"*一级*",督办单!M:M,$M$6) -> 0 | I15: =COUNTIFS(督办单!L:L,B:B,督办单!C:C,"*一级*",督办单!M:M,$M$6)/(COUNTIFS(累计派单!R:R,B:B,累计派单!S:S,$M$6)-COUNTIFS(累计派单!R:R,B:B,累计派单!I:I,"*业务受理*",累计派单!S:S,$M$6)) -> #DIV/0! | J15: =COUNTIFS(督办单!L:L,B:B,督办单!C:C,"*一级*") -> 24 | K15: =J15/(COUNTIFS(累计派单!R:R,B:B)-COUNTIFS(累计派单!R:R,B:B,累计派单!I:I,"*业务受理*")-COUNTIFS(累计派单!I:I,"*客户咨询*")) -> 0.02690583 | L15: 青州 | O15: =_xlfn.RANK.AVG(K15,$K$6:$K$17) -> 10 | P15: =B15&"("&ROUND(K15*100,2)&"%)" -> 青州(2.69%) | Q15: =_xlfn.RANK.AVG(I15,$I$6:$I$17) -> #DIV/0! | R15: =B15&"("&ROUND(I15*100,2)&"%)" -> #DIV/0! | S15: =_xlfn.RANK.EQ(H15,$H$6:$H$17,0)+COUNTIF($H$6:$H15,H15)-1 -> 10 | T15: =B15&H15&"件" -> 青州0件 | U15: =_xlfn.RANK.EQ(D15,$D$6:$D$17,0)+COUNTIF($D$6:$D15,D15)-1 -> 10 | V15: =IF(W15=0,"",B15&D15&"件") | W15: =D15 -> 0 | Z15: =_xlfn.RANK.EQ(E15,$E$6:$E$17,0)+COUNTIF($E$6:$E15,E15)-1 -> 10 | AA15: =IF(AB15=0,"",B15&E15&"件") | AB15: =E15 -> 0
A16: 11 | B16: 诸城 | C16: =COUNTIFS(督办单!L:L,B:B,督办单!M:M,$M$6,督办单!P:P,"无",督办单!C:C,"*一级*") -> 0 | D16: =COUNTIFS(督办单!L:L,B:B,督办单!M:M,$M$6,督办单!P:P,"7天内",督办单!C:C,"*一级*") -> 0 | E16: =COUNTIFS(督办单!L:L,B:B,督办单!M:M,$M$6,督办单!P:P,"30天内",督办单!C:C,"*一级*") -> 0 | F16: =COUNTIFS(督办单!L:L,B:B,督办单!M:M,$M$6,督办单!P:P,"60天内",督办单!C:C,"*一级*") -> 0 | G16: =COUNTIFS(督办单!L:L,B:B,督办单!M:M,$M$6,督办单!P:P,"90天内",督办单!C:C,"*一级*") -> 0 | H16: =COUNTIFS(督办单!L:L,B:B,督办单!C:C,"*一级*",督办单!M:M,$M$6) -> 0 | I16: =COUNTIFS(督办单!L:L,B:B,督办单!C:C,"*一级*",督办单!M:M,$M$6)/(COUNTIFS(累计派单!R:R,B:B,累计派单!S:S,$M$6)-COUNTIFS(累计派单!R:R,B:B,累计派单!I:I,"*业务受理*",累计派单!S:S,$M$6)) -> #DIV/0! | J16: =COUNTIFS(督办单!L:L,B:B,督办单!C:C,"*一级*") -> 16 | K16: =J16/(COUNTIFS(累计派单!R:R,B:B)-COUNTIFS(累计派单!R:R,B:B,累计派单!I:I,"*业务受理*")-COUNTIFS(累计派单!I:I,"*客户咨询*")) -> 0.022191401 | L16: 诸城 | O16: =_xlfn.RANK.AVG(K16,$K$6:$K$17) -> 11 | P16: =B16&"("&ROUND(K16*100,2)&"%)" -> 诸城(2.22%) | Q16: =_xlfn.RANK.AVG(I16,$I$6:$I$17) -> #DIV/0! | R16: =B16&"("&ROUND(I16*100,2)&"%)" -> #DIV/0! | S16: =_xlfn.RANK.EQ(H16,$H$6:$H$17,0)+COUNTIF($H$6:$H16,H16)-1 -> 11 | T16: =B16&H16&"件" -> 诸城0件 | U16: =_xlfn.RANK.EQ(D16,$D$6:$D$17,0)+COUNTIF($D$6:$D16,D16)-1 -> 11 | V16: =IF(W16=0,"",B16&D16&"件") | W16: =D16 -> 0 | Z16: =_xlfn.RANK.EQ(E16,$E$6:$E$17,0)+COUNTIF($E$6:$E16,E16)-1 -> 11 | AA16: =IF(AB16=0,"",B16&E16&"件") | AB16: =E16 -> 0
A17: 12 | B17: 昌乐 | C17: =COUNTIFS(督办单!L:L,B:B,督办单!M:M,$M$6,督办单!P:P,"无",督办单!C:C,"*一级*") -> 0 | D17: =COUNTIFS(督办单!L:L,B:B,督办单!M:M,$M$6,督办单!P:P,"7天内",督办单!C:C,"*一级*") -> 0 | E17: =COUNTIFS(督办单!L:L,B:B,督办单!M:M,$M$6,督办单!P:P,"30天内",督办单!C:C,"*一级*") -> 0 | F17: =COUNTIFS(督办单!L:L,B:B,督办单!M:M,$M$6,督办单!P:P,"60天内",督办单!C:C,"*一级*") -> 0 | G17: =COUNTIFS(督办单!L:L,B:B,督办单!M:M,$M$6,督办单!P:P,"90天内",督办单!C:C,"*一级*") -> 0 | H17: =COUNTIFS(督办单!L:L,B:B,督办单!C:C,"*一级*",督办单!M:M,$M$6) -> 0 | I17: =COUNTIFS(督办单!L:L,B:B,督办单!C:C,"*一级*",督办单!M:M,$M$6)/(COUNTIFS(累计派单!R:R,B:B,累计派单!S:S,$M$6)-COUNTIFS(累计派单!R:R,B:B,累计派单!I:I,"*业务受理*",累计派单!S:S,$M$6)) -> #DIV/0! | J17: =COUNTIFS(督办单!L:L,B:B,督办单!C:C,"*一级*") -> 5 | K17: =J17/(COUNTIFS(累计派单!R:R,B:B)-COUNTIFS(累计派单!R:R,B:B,累计派单!I:I,"*业务受理*")-COUNTIFS(累计派单!I:I,"*客户咨询*")) -> 0.021551724 | L17: 昌乐 | O17: =_xlfn.RANK.AVG(K17,$K$6:$K$17) -> 12 | P17: =B17&"("&ROUND(K17*100,2)&"%)" -> 昌乐(2.16%) | Q17: =_xlfn.RANK.AVG(I17,$I$6:$I$17) -> #DIV/0! | R17: =B17&"("&ROUND(I17*100,2)&"%)" -> #DIV/0! | S17: =_xlfn.RANK.EQ(H17,$H$6:$H$17,0)+COUNTIF($H$6:$H17,H17)-1 -> 12 | T17: =B17&H17&"件" -> 昌乐0件 | U17: =_xlfn.RANK.EQ(D17,$D$6:$D$17,0)+COUNTIF($D$6:$D17,D17)-1 -> 12 | V17: =IF(W17=0,"",B17&D17&"件") | W17: =D17 -> 0 | Z17: =_xlfn.RANK.EQ(E17,$E$6:$E$17,0)+COUNTIF($E$6:$E17,E17)-1 -> 12 | AA17: =IF(AB17=0,"",B17&E17&"件") | AB17: =E17 -> 0
A18: 合计 | C18: =SUM(C6:C17) -> 0 | D18: =SUM(D6:D17) -> 0 | E18: =SUM(E6:E17) -> 0 | F18: =SUM(F6:F17) -> 0 | G18: =SUM(G6:G17) -> 0 | H18: =SUM(H6:H17) -> 0 | I18: =H18/(COUNTIFS(累计派单!S:S,$M$6)-COUNTIFS(累计派单!I:I,"*业务受理*",累计派单!S:S,$M$6)-COUNTIFS(累计派单!I:I,"*修复*",累计派单!S:S,$M$6)-COUNTIFS(累计派单!I:I,"*客户咨询*",累计派单!S:S,$M$6)) -> #DIV/0! | J18: =SUM(J6:J17) -> 282 | K18: =J18/(COUNTIFS(累计派单!C:C,"潍坊")-COUNTIFS(累计派单!I:I,"*业务受理*")-COUNTIFS(累计派单!I:I,"*客户咨询*")) -> 0.036270096 | L18: 合计
C20: ="关于10086投诉一级督办占比的通报-截止"&N6&"日 一、整体情况： 1、截止"&N6&"日，累计产生一级督办单"&J18&"件，一级督办单占比"&ROUND(K18*100,2)&"%。 2、一级督办单累计增长："&P5&"较高。 二、单日情况： 1、"&R5&"较多。 2、"&N6&"日新增"&H18&"件："&T5&"较多。 三、分析情况： 1、无重复投诉（重点客户、网课）："&C18&"件。 2、7天内重复投诉"&D18&"件："&U2&"。 3、大于7天小于30天"&E18&"件："&Z2&"。" -> #N/A

Sheet 督办单
A1: 督办工单号 | B1: 督办工单发起时间 | C1: 督办单主题 | D1: 投诉主题 | E1: 投诉内容 | F1: 投诉地市 | G1: 投诉区县 | H1: 投诉电话 | I1: 投诉工单号 | J1: 重复投诉工单号 | K1: 是否处理 | L1: =IF(OR(LEFT(G1,2)="高新"),"奎文",IF(LEFT(G1,2)="峡山","坊子",IF(LEFT(G1,2)="滨海","寒亭",LEFT(G1,2)))) -> 投诉 | M1: =TEXT(B1,"yyyymmdd") -> 督办工单发起时间 | N1: 工号 | O1: 时间段 | P1: 时间段 | Q1: 网格
A2: SD-db051-240703-735269-5 | B2: 2024-07-03 07:28:06 | C2: (家客)潍坊-诸城市-重复投诉投诉督办通知-一级督办18805365378-202407030000090931 | D2: 【调研】-普通区域-诸城市-山钢碧桂园·翡翠城-18805365378-200M-宽带上网投诉-次数0-202407030000090931 | E2: 202407030000090931#流程受理流水号：20240703072721188053653781000254 客户号码:18805365378 客户姓名:郭** 投诉地市:潍坊 来话流水:2024070307224877020852549 宽带账号:18805365378 宽带账号归属地市:潍坊 宽带账号归属区县:诸城市 故障地址:潍坊诸城市密州街道南外环山钢碧桂园·翡翠城27号楼********* 联系电话:18353631333 联系人:先生 工单紧急程度:一般 是否有升级投诉倾向:否 是否重复投诉:否 是否携转意向:否 是否投诉倾向:否 是否智 | F2: 潍坊 | G2: 诸城市 | H2: 18805365378 | I2: SD-057-240703-451762-61 | J2: 'SD-057-240501-762354-6441' | K2: 是 | L2: =IF(OR(LEFT(G2,2)="高新"),"奎文",IF(LEFT(G2,2)="峡山","坊子",IF(LEFT(G2,2)="滨海","寒亭",LEFT(G2,2)))) -> 诸城 | M2: =TEXT(B2,"mmdd") -> 0703 | N2: =VLOOKUP(I2,累计派单!A:O,15,0) -> dw3_jk_liuyong | O2: =IF(LEN(J2)<2,0,DATEDIF(DATE(IF(MID(J2,9,2)="23",2023,2024),MID(J2,11,2),MID(J2,13,2)),B2,"d")) -> 63 | P2: =IF(O2=0,"无",IF(O2<8,"7天内",IF(O2<31,"30天内",IF(O2<61,"60天内",IF(O2<91,"90天内"))))) -> 90天内 | Q2: =VLOOKUP(I:I,累计派单!A:M,13,0) -> 家客铁通潍坊诸城-兴华东路城区装维组
A3: SD-db051-240703-137465-22 | B3: 2024-07-03 08:50:08 | C3: (家客)潍坊-安丘市-重复投诉投诉督办通知-一级督办15762672444-20240703084737X657898290 | D3: 普通区域-安丘市-于家营子居民楼-15762672444-300M-宽带上网投诉-次数0-20240703084737X657898290 | E3: 【农村网络投诉】流程受理流水号：20240703084706157626724441006608 客户号码:15762672444 客户姓名:曹** 投诉地市:潍坊 来话流水:2024070308454173720834966 宽带账号:15762672444 宽带账号归属地市:潍坊 宽带账号归属区县:安丘市 故障地址:潍坊安丘市刘家尧镇于家营子村于家营子居民楼北楼********* 联系电话:18764651666 联系人:先生 工单紧急程度:一般 是否有升级投诉倾向:否 是否重复投诉:否 是 | F3: 潍坊 | G3: 安丘市 | H3: 15762672444 | I3: SD-057-240703-354692-421 | J3: 'SD-057-240518-847215-6881' | K3: 否 | L3: =IF(OR(LEFT(G3,2)="高新"),"奎文",IF(LEFT(G3,2)="峡山","坊子",IF(LEFT(G3,2)="滨海","寒亭",LEFT(G3,2)))) -> 安丘 | M3: =TEXT(B3,"mmdd") -> 0703 | N3: =VLOOKUP(I3,累计派单!A:O,15,0) -> dw3_jk_yvshubo | O3: =IF(LEN(J3)<2,0,DATEDIF(DATE(IF(MID(J3,9,2)="23",2023,2024),MID(J3,11,2),MID(J3,13,2)),B3,"d")) -> 46 | P3: =IF(O3=0,"无",IF(O3<8,"7天内",IF(O3<31,"30天内",IF(O3<61,"60天内",IF(O3<91,"90天内"))))) -> 60天内 | Q3: =VLOOKUP(I:I,累计派单!A:M,13,0) -> 家客铁通潍坊安丘-刘家尧乡镇装维组
A4: SD-db051-240703-439850-115 | B4: 2024-07-03 10:55:41 | C4: (家客)潍坊-昌邑市-重复投诉投诉督办通知-一级督办13963626484-202407030000237758 | D4: 普通区域-昌邑市-昌邑北海花园-13963626484-300M-宽带上网投诉-次数0-202407030000237758 | E4: 202407030000237758#流程受理流水号：20240703105501139636264841052844 客户号码:13963626484 客户姓名:马** 投诉地市:潍坊 来话流水:2024070310544538220815984 宽带账号:13963626484 宽带账号归属地市:潍坊 宽带账号归属区县:昌邑市 故障地址:潍坊昌邑市城区天水路北海花园5号楼********* 联系电话:13963626484 联系人:先生/女士 工单紧急程度:一般 是否有升级投诉倾向:否 是否重复投诉:否 是否携转意向:否 是否投诉倾向:否 是否智能网关 | F4: 潍坊 | G4: 昌邑市 | H4: 13963626484 | I4: SD-057-240703-621375-1808 | J4: 'SD-057-240414-134857-6898' | K4: 是 | L4: =IF(OR(LEFT(G4,2)="高新"),"奎文",IF(LEFT(G4,2)="峡山","坊子",IF(LEFT(G4,2)="滨海","寒亭",LEFT(G4,2)))) -> 昌邑 | M4: =TEXT(B4,"mmdd") -> 0703 | N4: =VLOOKUP(I4,累计派单!A:O,15,0) -> dw3_jk_wangsongliang | O4: =IF(LEN(J4)<2,0,DATEDIF(DATE(IF(MID(J4,9,2)="23",2023,2024),MID(J4,11,2),MID(J4,13,2)),B4,"d")) -> 80 | P4: =IF(O4=0,"无",IF(O4<8,"7天内",IF(O4<31,"30天内",IF(O4<61,"60天内",IF(O4<91,"90天内"))))) -> 90天内 | Q4: =VLOOKUP(I:I,累计派单!A:M,13,0) -> 家客铁通潍坊昌邑-城北城区装维组
A5: SD-db051-240703-375482-116 | B5: 2024-07-03 10:56:15 | C5: (家客)潍坊-奎文区-重复投诉投诉督办通知-一级督办15953670982-20240703105429X269466225 | D5: 普通区域-奎文区-苇湾社区-15953670982-300M-宽带上网投诉-次数0-20240703105429X269466225 | E5: 流程受理流水号：20240703105319159536709821052260 客户号码:15953670982 客户姓名:何* 投诉地市:潍坊 来话流水:2024070310504465120857181 宽带账号:15953670982 宽带账号归属地市:潍坊 宽带账号归属区县:奎文区 故障地址:潍坊奎文区东关街道东风街四平路苇湾社区31号楼********* 联系电话:15253676293 联系人:先生 工单紧急程度:一般 是否有升级投诉倾向:否 是否重复投诉:否 是否携转意向:否 是否投诉倾向:否 是否智能网关:智能网关 当前是否在线:是 接入方式:FTTH 端到端诊断结果:客户侧设备问题（新增） 是否质差终端:无质差信息 光功率:-19.70 故障大类:宽带/电视 故障细类:宽带无法上网(专席) 携转原因: 故障时间:2024-07-03 10:54:46 具体故障现象:宽带不能上网，排障之后没有恢复 客户其他诉求: | F5: 潍坊 | G5: 奎文区 | H5: 15953670982 | I5: SD-057-240703-192637-1814 | J5: 'SD-057-240622-159832-2435' | K5: 是 | L5: =IF(OR(LEFT(G5,2)="高新"),"奎文",IF(LEFT(G5,2)="峡山","坊子",IF(LEFT(G5,2)="滨海","寒亭",LEFT(G5,2)))) -> 奎文 | M5: =TEXT(B5,"mmdd") -> 0703 | N5: =VLOOKUP(I5,累计派单!A:O,15,0) -> dw3_ji_liguolei | O5: =IF(LEN(J5)<2,0,DATEDIF(DATE(IF(MID(J5,9,2)="23",2023,2024),MID(J5,11,2),MID(J5,13,2)),B5,"d")) -> 11 | P5: =IF(O5=0,"无",IF(O5<8,"7天内",IF(O5<31,"30天内",IF(O5<61,"60天内",IF(O5<91,"90天内"))))) -> 30天内 | Q5: =VLOOKUP(I:I,累计派单!A:M,13,0) -> 家客铁通潍坊奎文-鸢飞路城区装维组
A6: SD-db051-240703-186530-134 | B6: 2024-07-03 11:20:47 | C6: (家客)潍坊-昌邑市-重复投诉投诉督办通知-一级督办15863416817-20240703111910X750915355 | D6: 【调研】-普通区域-昌邑市-南苏村自然村-15863416817-300M-宽带上网投诉-次数0-20240703111910X750915355 | E6: 【农村网络投诉】流程受理流水号：20240703111707158634168171060001 客户号码:15863416817 客户姓名:苏** 投诉地市:潍坊 来话流水:2024070311161618120826646 宽带账号:15863416817 宽带账号归属地市:潍坊 宽带账号归属区县:昌邑市 故障地址:潍坊昌邑市围子镇南苏村南苏村自然村5号箱苏海波********* 联系电话:15863416817 联系人:先生 工单紧急程度:非常紧急 是否有升级投诉倾向:否 是否重复投诉:否 是否携转意向:否 是否投诉倾向:否 是否智能网关:智能网关 当前是否在线:否 接入方式:FTTH 端到端诊断结果:状态正常 是否质差终端:无质差信息 光功率:无 故障大类:宽带/电视 故障细类:宽带无法上网 携转原因: 故障时间:2024-07-03 11:25:28 具体故障现象:光猫亮红灯 客户其他诉求: | F6: 潍坊 | G6: 昌邑市 | H6: 15863416817 | I6: SD-057-240703-425139-2137 | J6: 'SD-057-240630-560193-65' | K6: 否 | L6: =IF(OR(LEFT(G6,2)="高新"),"奎文",IF(LEFT(G6,2)="峡山","坊子",IF(LEFT(G6,2)="滨海","寒亭",LEFT(G6,2)))) -> 昌邑 | M6: =TEXT(B6,"mmdd") -> 0703 | N6: =VLOOKUP(I6,累计派单!A:O,15,0) -> dw3_jk_dongwenqi | O6: =IF(LEN(J6)<2,0,DATEDIF(DATE(IF(MID(J6,9,2)="23",2023,2024),MID(J6,11,2),MID(J6,13,2)),B6,"d")) -> 3 | P6: =IF(O6=0,"无",IF(O6<8,"7天内",IF(O6<31,"30天内",IF(O6<61,"60天内",IF(O6<91,"90天内"))))) -> 7天内 | Q6: =VLOOKUP(I:I,累计派单!A:M,13,0) -> 家客铁通潍坊昌邑-围子乡镇装维组
A7: SD-db051-240703-786035-151 | B7: 2024-07-03 11:56:56 | C7: (家客)潍坊-安丘市-重复投诉投诉督办通知-一级督办15244405552-202407030000298786 | D7: 【调研】-普通区域-安丘市-金地太阳城(含小庄子安置楼)-15244405552-1000M-宽带上网投诉-次数0-202407030000298786 | E7: 202407030000298786#15244405552客户来电反映对前期工单处理结果不认可，要求回电处理，前期工单流水：202405270000201921，本次通话流水：2024070311485682820866598，联系人：先生，联系电话：15244405552，请协助处理，谢谢 | F7: 潍坊 | G7: 安丘市 | H7: 15244405552 | I7: SD-057-240703-136847-2442 | J7: 'SD-057-240527-579816-1712' | K7: 是 | L7: =IF(OR(LEFT(G7,2)="高新"),"奎文",IF(LEFT(G7,2)="峡山","坊子",IF(LEFT(G7,2)="滨海","寒亭",LEFT(G7,2)))) -> 安丘 | M7: =TEXT(B7,"mmdd") -> 0703 | N7: =VLOOKUP(I7,累计派单!A:O,15,0) -> dw3_jk_sunhao | O7: =IF(LEN(J7)<2,0,DATEDIF(DATE(IF(MID(J7,9,2)="23",2023,2024),MID(J7,11,2),MID(J7,13,2)),B7,"d")) -> 37 | P7: =IF(O7=0,"无",IF(O7<8,"7天内",IF(O7<31,"30天内",IF(O7<61,"60天内",IF(O7<91,"90天内"))))) -> 60天内 | Q7: =VLOOKUP(I:I,累计派单!A:M,13,0) -> 家客铁通潍坊安丘-潍安路城区装维组
A8: SD-db051-240703-628401-156 | B8: 2024-07-03 12:05:28 | C8: (家客)潍坊-潍城区-重复投诉投诉督办通知-一级督办15953692822-20240703120359X439850191 | D8: 【调研】-80+白金-普通区域-潍城区-恒信玫瑰公馆二期-15953692822-1000M-宽带上网投诉-次数0-20240703120359X439850191 | E8: 流程受理流水号：20240703120102159536928221073605 客户号码:15953692822 客户姓名:杨** 投诉地市:潍坊 来话流水:2024070311591672620893501 宽带账号:15953692822 宽带账号归属地市:潍坊 宽带账号归属区县:潍城区 故障地址:潍坊潍城区北关街道永安路恒信玫瑰公馆二期13号楼********* 联系电话:15953692822 联系人:先生/女士 工单紧急程度:非常紧急 是否有升级投诉倾向:否 是否重复投诉:否 是否携转意向:否 是否投诉倾向:否 是否智能网关:智能网关 当前是否在线:是 接入方式:FTTH 端到端诊断结果:客户侧设备问题（新增） 是否质差终端:无质差信息 光功率:-22.67 故障大类:宽带/电视 故障细类:网速慢/上网掉线(专席) 携转原因: 故障时间:2024-07-03 12:01:03 具体故障现象:光猫频繁掉线，重启设备未恢复，客户要求换工作人员处理，客户要求换光猫设备，解释不认可，请核实处理谢谢 客户其他诉求: | F8: 潍坊 | G8: 潍城区 | H8: 15953692822 | I8: SD-057-240703-735402-2504 | J8: 'SD-057-240619-967481-6759' | K8: 否 | L8: =IF(OR(LEFT(G8,2)="高新"),"奎文",IF(LEFT(G8,2)="峡山","坊子",IF(LEFT(G8,2)="滨海","寒亭",LEFT(G8,2)))) -> 潍城 | M8: =TEXT(B8,"mmdd") -> 0703 | N8: =VLOOKUP(I8,累计派单!A:O,15,0) -> dw3_jk_wcfuguangjie | O8: =IF(LEN(J8)<2,0,DATEDIF(DATE(IF(MID(J8,9,2)="23",2023,2024),MID(J8,11,2),MID(J8,13,2)),B8,"d")) -> 14 | P8: =IF(O8=0,"无",IF(O8<8,"7天内",IF(O8<31,"30天内",IF(O8<61,"60天内",IF(O8<91,"90天内"))))) -> 30天内 | Q8: =VLOOKUP(I:I,累计派单!A:M,13,0) -> 家客铁通潍坊潍城-和平路城区装维组
A9: SD-db051-240703-469150-205 | B9: 2024-07-03 14:02:31 | C9: (家客)潍坊-高密市-重复投诉投诉督办通知-一级督办18366317111-20240703140136X496524849 | D9: 80+金卡-普通区域-高密市-十里堡自然村-18366317111-1000M-宽带上网投诉-次数0-20240703140136X496524849 | E9: 【农村网络投诉】流程受理流水号：20240703140116183663171111100489 客户号码:18366317111 客户姓名:葛** 投诉地市:潍坊 来话流水:2024070314004669020825575 宽带账号:18366317111 宽带账号归属地市:潍坊 宽带账号归属区县:高密市 故障地址:潍坊高密市夏庄镇十里堡十里堡自然村新村张先荣西屋山K18号********* 联系电话:18366317111 联系人:先生/女士 工单紧急程度:非常紧急 是否有升级投诉倾向:否 是否重复投诉:否 是否携转意向:否 是否投诉倾向:否 是否智能网关:智能网关 当前是否在线:否 接入方式:FTTH 端到端诊断结果:状态正常 是否质差终端:无质差信息 光功率:无 故障大类:宽带/电视 故障细类:宽带无法上网(专席) 携转原因: 故障时间:2024-07-03 14:03:38 具体故障现象:打不开网页， 客户其他诉求: | F9: 潍坊 | G9: 高密市 | H9: 18366317111 | I9: SD-057-240703-152489-3592 | J9: 'SD-057-240503-375284-3143' | K9: 是 | L9: =IF(OR(LEFT(G9,2)="高新"),"奎文",IF(LEFT(G9,2)="峡山","坊子",IF(LEFT(G9,2)="滨海","寒亭",LEFT(G9,2)))) -> 高密 | M9: =TEXT(B9,"mmdd") -> 0703 | N9: =VLOOKUP(I9,累计派单!A:O,15,0) -> dw3_jk_gaoqiang | O9: =IF(LEN(J9)<2,0,DATEDIF(DATE(IF(MID(J9,9,2)="23",2023,2024),MID(J9,11,2),MID(J9,13,2)),B9,"d")) -> 61 | P9: =IF(O9=0,"无",IF(O9<8,"7天内",IF(O9<31,"30天内",IF(O9<61,"60天内",IF(O9<91,"90天内"))))) -> 90天内 | Q9: =VLOOKUP(I:I,累计派单!A:M,13,0) -> 家客铁通潍坊高密-夏庄乡镇装维组
A10: SD-db051-240703-791634-281 | B10: 2024-07-03 16:56:40 | C10: (家客)潍坊-寒亭区-重复投诉投诉督办通知-一级督办15163615099-202407030000552400 | D10: 普通区域-寒亭区-元和新城-15163615099-300M-宽带上网投诉-次数0-202407030000552400 | E10: 202407030000552400#流程受理流水号：20240703165457151636150991150667 客户号码:15163615099 客户姓名:董** 投诉地市:潍坊 来话流水:2024070316524804320850494 宽带账号:15163615099 宽带账号归属地市:潍坊 宽带账号归属区县:寒亭区 故障地址:潍坊寒亭区寒亭街道益新街元和新城29号楼********* 联系电话:15163615099 联系人:先生/女士 工单紧急程度:非常紧急 是否有升级投诉倾向:否 是否重复投诉:否 是否携转意向:否 是否投诉倾向:否 是否智能网关:智能网关 当前是否在线:是 接入方式:FTTH 端到端诊断结果:客户侧设备问题 是否质差终端:是 光功率:-18.96 故障大类:宽带/电视 故障细类:宽带无法上网 携转原因: 故障时间:2024-07-03 16:54:46 具体故障现象:网速慢卡顿， 客户其他诉求:客户侧为质差终端，要求上门更换终端并一并处理故障问题。 | F10: 潍坊 | G10: 寒亭区 | H10: 15163615099 | I10: SD-057-240703-237615-5158 | J10: 'SD-057-240406-873246-6570' | K10: 是 | L10: =IF(OR(LEFT(G10,2)="高新"),"奎文",IF(LEFT(G10,2)="峡山","坊子",IF(LEFT(G10,2)="滨海","寒亭",LEFT(G10,2)))) -> 寒亭 | M10: =TEXT(B10,"mmdd") -> 0703 | N10: =VLOOKUP(I10,累计派单!A:O,15,0) -> dw3_jk_liuxingtao | O10: =IF(LEN(J10)<2,0,DATEDIF(DATE(IF(MID(J10,9,2)="23",2023,2024),MID(J10,11,2),MID(J10,13,2)),B10,"d")) -> 88 | P10: =IF(O10=0,"无",IF(O10<8,"7天内",IF(O10<31,"30天内",IF(O10<61,"60天内",IF(O10<91,"90天内"))))) -> 90天内 | Q10: =VLOOKUP(I:I,累计派单!A:M,13,0) -> 家客铁通潍坊寒亭-城东城区装维组
A11: SD-db051-240703-456791-314 | B11: 2024-07-03 18:10:07 | C11: (家客)潍坊-寿光市-重复投诉投诉督办通知-一级督办18253639999-202407030000614989 | D11: 80+普通-普通区域-寿光市-西丹河村-18253639999-1000M-宽带 | E11: 202407030000614989#18253639999客户来电反应前期处理不满，前期工单 202407010000431538，要求再次反馈处理并回复电话，联系电话本机，流水 2024070317555677320842113 | F11: 潍坊 | G11: 寿光市 | H11: 18253639999 | I11: SD-057-240703-976382-5904 | J11: 'SD-057-240701-293764-5373' | K11: 否 | L11: =IF(OR(LEFT(G11,2)="高新"),"奎文",IF(LEFT(G11,2)="峡山","坊子",IF(LEFT(G11,2)="滨海","寒亭",LEFT(G11,2)))) -> 寿光 | M11: =TEXT(B11,"mmdd") -> 0703 | N11: =VLOOKUP(I11,累计派单!A:O,15,0) -> dw3_jk_songyujie | O11: =IF(LEN(J11)<2,0,DATEDIF(DATE(IF(MID(J11,9,2)="23",2023,2024),MID(J11,11,2),MID(J11,13,2)),B11,"d")) -> 2 | P11: =IF(O11=0,"无",IF(O11<8,"7天内",IF(O11<31,"30天内",IF(O11<61,"60天内",IF(O11<91,"90天内"))))) -> 7天内 | Q11: =VLOOKUP(I:I,累计派单!A:M,13,0) -> 家客铁通潍坊寿光-稻田乡镇装维组
A12: SD-db051-240703-780253-383 | B12: 2024-07-03 20:05:15 | C12: (家客)潍坊-青州市-重复投诉投诉督办通知-一级督办13863640425-20240703200329X209594402 | D12: 普通区域-青州市-黄家里双-13863640425-300M-宽带上网投诉-次数0-20240703200329X209594402 | E12: 【农村网络投诉】流程受理流水号：20240703200153138636404251193536 客户号码:13863640425 客户姓名:王** 投诉地市:潍坊 来话流水:2024070320010989920884106 宽带账号:13863640425 宽带账号归属地市:潍坊 宽带账号归属区县:青州市 故障地址:潍坊青州市何官镇黄家里双村黄家里双28号箱#刘君#********* 联系电话:15006611390 联系人:先生 工单紧急程度:一般 是否有升级投诉倾向:否 是否重复投诉:否 是否携转意向:否 是否投诉倾向:否 是否智能网关:智能网关 当前是否在线:否 接入方式:FTTH 端到端诊断结果:状态正常 是否质差终端:无质差信息 光功率:无 故障大类:宽带/电视 故障细类:宽带无法上网 携转原因: 故障时间:2024-07-03 20:03:05 具体故障现象:光猫亮红灯， 客户其他诉求: | F12: 潍坊 | G12: 青州市 | H12: 13863640425 | I12: SD-057-240703-962174-7212 | J12: 'SD-057-240630-638107-6013' | K12: 是 | L12: =IF(OR(LEFT(G12,2)="高新"),"奎文",IF(LEFT(G12,2)="峡山","坊子",IF(LEFT(G12,2)="滨海","寒亭",LEFT(G12,2)))) -> 青州 | M12: =TEXT(B12,"mmdd") -> 0703 | N12: =VLOOKUP(I12,累计派单!A:O,15,0) -> dw3_jk_liuqunbo | O12: =IF(LEN(J12)<2,0,DATEDIF(DATE(IF(MID(J12,9,2)="23",2023,2024),MID(J12,11,2),MID(J12,13,2)),B12,"d")) -> 3 | P12: =IF(O12=0,"无",IF(O12<8,"7天内",IF(O12<31,"30天内",IF(O12<61,"60天内",IF(O12<91,"90天内"))))) -> 7天内 | Q12: =VLOOKUP(I:I,累计派单!A:M,13,0) -> 家客铁通潍坊青州-何官乡镇装维组
A13: SD-db051-240703-374582-403 | B13: 2024-07-03 21:04:25 | C13: (家客)潍坊-临朐县-重复投诉投诉督办通知-一级督办15153663187-202407030000720174 | D13: 普通区域-临朐县-高家庄-15153663187-1000M-宽带上网投诉-次数0-202407030000720174 | E13: 202407030000720174#宽带账号：15153663187；宽带地址：潍坊临朐县寺头镇人民政府高家庄村高家庄高家庄3号箱张长忠（；客户来电反映宽带连不上网，经查询客户侧为质差路由器导致宽带使用不畅，请参考处理，谢谢！联系电话：15153663187；来电流水：2024070320595888720878369 | F13: 潍坊 | G13: 临朐县 | H13: 15153663187 | I13: SD-057-240703-496531-7815 | J13: 'SD-057-240501-065924-6120' | K13: 是 | L13: =IF(OR(LEFT(G13,2)="高新"),"奎文",IF(LEFT(G13,2)="峡山","坊子",IF(LEFT(G13,2)="滨海","寒亭",LEFT(G13,2)))) -> 临朐 | M13: =TEXT(B13,"mmdd") -> 0703 | N13: =VLOOKUP(I13,累计派单!A:O,15,0) -> dw3_jk_zhangjin | O13: =IF(LEN(J13)<2,0,DATEDIF(DATE(IF(MID(J13,9,2)="23",2023,2024),MID(J13,11,2),MID(J13,13,2)),B13,"d")) -> 63 | P13: =IF(O13=0,"无",IF(O13<8,"7天内",IF(O13<31,"30天内",IF(O13<61,"60天内",IF(O13<91,"90天内"))))) -> 90天内 | Q13: =VLOOKUP(I:I,累计派单!A:M,13,0) -> 家客铁通潍坊临朐-五井乡镇装维组
... A283: SD-db051-240716-392475-434 | B283: 2024-07-16 21:11:17 | C283: (家客)潍坊-奎文区-重复投诉投诉督办通知-一级督办15269624455-202407160000611545 | D283: 80+金卡-普通区域-奎文区-四方家和-15269624455-500M-宽带上网投诉-次数0-202407160000611545 | E283: 202407160000611545#宽带账号：15269624455；宽带地址：**潍坊奎文区北苑街道玄武街四方家和3号楼客户来电反映宽带网速慢，客户要求师傅上门，请协助处理，谢谢！联系电话18763607766联系人张***；来电流水：*2024071621070873720835070 | F283: 潍坊 | G283: 奎文区 | H283: 15269624455 | I283: SD-057-240716-037658-7509 | J283: 'SD-057-240507-816537-990' | K283: 否 | L283: =IF(OR(LEFT(G283,2)="高新"),"奎文",IF(LEFT(G283,2)="峡山","坊子",IF(LEFT(G283,2)="滨海","寒亭",LEFT(G283,2)))) -> 奎文 | M283: =TEXT(B283,"mmdd") -> 0716 | N283: =VLOOKUP(I283,累计派单!A:O,15,0) -> dw3_jk_wangxiao | O283: =IF(LEN(J283)<2,0,DATEDIF(DATE(IF(MID(J283,9,2)="23",2023,2024),MID(J283,11,2),MID(J283,13,2)),B283,"d")) -> 70 | P283: =IF(O283=0,"无",IF(O283<8,"7天内",IF(O283<31,"30天内",IF(O283<61,"60天内",IF(O283<91,"90天内"))))) -> 90天内 | Q283: =VLOOKUP(I:I,累计派单!A:M,13,0) -> 家客铁通潍坊奎文-鸢飞路城区装维组

Sheet 累计派单
A1: 工单号 | B1: 派单时间 | C1: 地市 | D1: 主题 | E1: 处理时限 | F1: 客服侧工单流水号 | G1: 故障现象 | H1: T1受理时间 | I1: 投诉细类 | J1: T1处理人 | K1: T1处理人电话 | L1: 新小区名称 | M1: 装维所属网格 | N1: t3环节处理措施 | O1: 装维处理人账号 | P1: 首次响应成功时间 | Q1: 关联装移机单号 | R1: =IF(OR(LEFT(L1,2)="高新"),"奎文",IF(LEFT(L1,2)="峡山","坊子",IF(LEFT(L1,2)="滨海","寒亭",LEFT(L1,2)))) -> 新小 | S1: =TEXT(B1,"mmdd") -> 派单时间
A2: SD-057-240703-759214-7766 | B2: 2024-07-03 20:56:25 | C2: 潍坊 | D2: 普通区域-青州市-代楼-15095195694-200M-业务受理宽带-次数0-202407030000717621 | E2: 2024-07-04 18:00:00 | F2: 202407030000717621 | G2: 202407030000717621#导航立单,用户所在位置有群障,已向客户播报,客户要求装维回访.此工单为群障修复工单,根据群障全量闭环管理要求,为确保客户网络通畅,请装维人员跟进修复网络问题,谢谢.联系电话：15095195694 | H2: 2024-07-03 21:06:12 | I2: 业务受理->线上义诊->家庭业务->全局流转->功能使用->群障弹窗->全局流转 | J2: 王迪 | K2: 15706307660 | L2: 青州市 | M2: 家客铁通潍坊青州-何官乡镇装维组 | N2: 用户感觉网速慢，但测速达标 | O2: dw3_jk_wangdi | P2: 2024-07-03 21:07:02 | R2: =IF(OR(LEFT(L2,2)="高新"),"奎文",IF(LEFT(L2,2)="峡山","坊子",IF(LEFT(L2,2)="滨海","寒亭",LEFT(L2,2)))) -> 青州 | S2: =TEXT(B2,"mmdd") -> 0703
A3: SD-057-240703-817504-3357 | B3: 2024-07-03 13:26:20 | C3: 潍坊 | D3: 【重投】-(目标)普通区域-安丘市-景阳小区(含景中路沿街)-13793676927-200M-宽带上网投诉-次数0-20240703132345X225357224 | E3: 2024-07-04 13:00:00 | F3: 20240703132345X225357224 | G3: 流程受理流水号：20240703132216137936769271091549 客户号码:13793676927 客户姓名:张** 投诉地市:潍坊 来话流水:2024070313203096320855956 宽带账号:13793676927 宽带账号归属地市:潍坊 宽带账号归属区县:安丘市 故障地址:潍坊安丘市景芝镇景中路景阳小区景阳小区3号楼********* 联系电话:13963687477 联系人:先生/女士 工单紧急程度:一般 是否有升级投诉倾向:否 是否重复投诉:否 是否携转意向:否 是否投诉倾向:否 是否智能网关:智能网关 当前是否在线:否 接入方式:FTTH 端到端诊断结果:状态正常 是否质差终端:无质差信息 光功率:无 故障大类:宽带/电视 故障细类:宽带无法上网(专席) 携转原因: 故障时间:2024-07-03 13:21:49 具体故障现象:光猫灯不亮 插排有电 拔插电源线 换插头位置 按开光 未恢复 谢谢 客户其他诉求: | H3: 2024-07-03 13:29:55 | I3: 家宽业务->网络质量->家庭宽带->全局流转->功能使用->网络无法连接->全局流转 | J3: 刘彤彤 | K3: 15706307065 | L3: 安丘市 | M3: 家客铁通潍坊安丘-景芝乡镇装维组 | N3: 更换尾纤 | O3: dw3_jk_liutongtong | P3: 2024-07-03 13:30:41 | R3: =IF(OR(LEFT(L3,2)="高新"),"奎文",IF(LEFT(L3,2)="峡山","坊子",IF(LEFT(L3,2)="滨海","寒亭",LEFT(L3,2)))) -> 安丘 | S3: =TEXT(B3,"mmdd") -> 0703
A4: SD-057-240703-826105-4583 | B4: 2024-07-03 15:45:01 | C4: 潍坊 | D4: 普通区域-安丘市-育英家园-18364666990-300M-宽带上网投诉-次数0-202407030000480165 | E4: 2024-07-04 08:00:00 | F4: 202407030000480165 | G4: 202407030000480165#宽带账号：18364666990；宽带地址：潍坊安丘市兴安街道南苑路育英家园迁2号楼*****；客户来电反映无法上网，客户不在现场，无法配合线上指导，要求上门，请协助处理，谢谢！联系电话：18364666990；联系人：先生；来电流水：2024070315400866320855840 | H4: 2024-07-03 15:52:38 | I4: 家庭咨询->网络质量->家庭宽带->全局流转->功能使用->客户要求装维上门服务->全局流转 | J4: 周龙涛 | K4: 15706307025 | L4: 安丘市 | M4: 家客铁通潍坊安丘-潍安路城区装维组 | N4: 重新连接机顶盒网络 | O4: dw3_jk_zhoulongtao | P4: 2024-07-03 15:53:12 | Q4: SD-851-247561-5815-25557 | R4: =IF(OR(LEFT(L4,2)="高新"),"奎文",IF(LEFT(L4,2)="峡山","坊子",IF(LEFT(L4,2)="滨海","寒亭",LEFT(L4,2)))) -> 安丘 | S4: =TEXT(B4,"mmdd") -> 0703
A5: SD-057-240703-857319-4593 | B5: 2024-07-03 15:47:12 | C5: 潍坊 | D5: 【调研】-(目标)普通区域-高密市-苗家屯自然村-13406603097-300M-宽带上网投诉-次数0-20240703154557X757357681 | E5: 2024-07-04 08:00:00 | F5: 20240703154557X757357681 | G5: 【农村网络投诉】【预处理派单】宽带账号：13406603097，宽带地址： 潍坊高密市密水街道苗家屯，故障现象：无法连接，故障现象类型：手机或笔记本电脑，客户诉求：客户来电反映宽带无法上网，注册灯熄灭，将光纤线插紧捋直、重启光猫后未恢复，请协助谢谢，联系电话：17662431408，通话流水：2024070315354658220895151。接入方式：FTTH，当前是否在线：不在线，端到端诊断结果：状态正常，是否智能网关：是，光功率。 | H5: 2024-07-03 15:51:03 | I5: 家宽业务->网络质量->家庭宽带->全局流转->功能使用->LOS红灯，无法上网->全局流转 | J5: 冷光朋 | K5: 15706307276 | L5: 高密市 | M5: 家客铁通潍坊高密-密水城区装维组 | N5: 更换光猫 | O5: dw3_jk_lengguangpeng | P5: 2024-07-03 15:56:44 | R5: =IF(OR(LEFT(L5,2)="高新"),"奎文",IF(LEFT(L5,2)="峡山","坊子",IF(LEFT(L5,2)="滨海","寒亭",LEFT(L5,2)))) -> 高密 | S5: =TEXT(B5,"mmdd") -> 0703
A6: SD-057-240703-308549-29 | B6: 2024-07-03 07:03:07 | C6: 潍坊 | D6: 80+普通-普通区域-青州市-董家庄村自然村-15069657728-1000M-宽带上网投诉-次数0-202407030000092937 | E6: 2024-07-03 19:00:00 | F6: 202407030000092937 | G6: 202407030000092937#流程受理流水号：20240703070140150696577281000138 客户号码:15069657728 客户姓名:徐** 投诉地市:潍坊 来话流水:2024070307011938120846658 宽带账号:15069657728 宽带账号归属地市:潍坊 宽带账号归属区县:青州市 故障地址:潍坊青州市黄楼街道董家庄村董家庄村自然村二次扩容7号箱（董福华）********* 联系电话:15069657728 联系人:先生/女士 工单紧急程度:非常紧急 是否有升级投诉倾向:否 是否重复投诉:否 是否携转意向:否 是否投诉倾向:否 是否智能网关:智能网关 当前是否在线:否 接入方式:FTTH 端到端诊断结果:光猫掉电 是否质差终端:无质差信息 光功率:无 故障大类:宽带/电视 故障细类:宽带无法上网 携转原因: 故障时间:2024-07-03 07:02:42 具体故障现象:光猫亮红灯， 客户其他诉求: ;宽带小区$[董家庄村自然村]$ | H6: 2024-07-03 07:07:25 | I6: 家宽咨询->网络质量->家庭宽带->全局流转->功能使用->LOS红灯，无法上网->全局流转 | J6: 李明辉 | K6: 15706307719 | L6: 青州市 | M6: 家客铁通潍坊青州-开发区城区装维组 | N6: 重新配置光猫 | O6: dw3_jk_liminghui | P6: 2024-07-03 07:09:17 | Q6: SD-851-273959-379-23823 | R6: =IF(OR(LEFT(L6,2)="高新"),"奎文",IF(LEFT(L6,2)="峡山","坊子",IF(LEFT(L6,2)="滨海","寒亭",LEFT(L6,2)))) -> 青州 | S6: =TEXT(B6,"mmdd") -> 0703
A7: SD-057-240703-805142-3354 | B7: 2024-07-03 13:26:09 | C7: 潍坊 | D7: 【调研】-80+金卡-普通区域-奎文区-阳光100二期-18263663731-1000M-宽带上网投诉-次数0-20240703132329X209361728 | E7: 2024-07-04 08:00:00 | F7: 20240703132329X209361728 | G7: 流程受理流水号：20240703132151182636637311091469 客户号码:18263663731 客户姓名:陈** 投诉地市:潍坊 来话流水:2024070313195415120851352 宽带账号:18263663731 宽带账号归属地市:潍坊 宽带账号归属区县:奎文区 故障地址:潍坊奎文区广文街道胜利街阳光100二期7号楼********* 联系电话:13280706363 联系人:先生/女士 工单紧急程度:非常紧急 是否有升级投诉倾向:否 是否重复投诉:否 是否携转意向:否 是否投诉倾向:否 是否智能网关:智能网关 当前是否在线:否 接入方式:FTTH 端到端诊断结果:状态正常 是否质差终端:无质差信息 光功率:无 故障大类:宽带/电视 故障细类:宽带无法上网(专席) 携转原因: 故障时间:2024-07-03 13:18:45 具体故障现象:注册闪烁：引导客户将光纤线插紧，将弯折的位置捋直后重启无效 客户其他诉求: | H7: 2024-07-03 13:27:32 | I7: 家宽业务->网络质量->家庭宽带->全局流转->功能使用->网络无法连接->全局流转 | J7: 孙晓波 | K7: 15706366530 | L7: 奎文区 | M7: 家客铁通潍坊奎文-樱前街城区装维组 | N7: 重新配置光猫 | O7: dw3_jk_sunxiaobo | P7: 2024-07-03 13:27:48 | Q7: SD-851-278690-7493-19981 | R7: =IF(OR(LEFT(L7,2)="高新"),"奎文",IF(LEFT(L7,2)="峡山","坊子",IF(LEFT(L7,2)="滨海","寒亭",LEFT(L7,2)))) -> 奎文 | S7: =TEXT(B7,"mmdd") -> 0703
A8: SD-057-240703-023865-113 | B8: 2024-07-03 08:00:06 | C8: 潍坊 | D8: 80+普通-普通区域-临朐县-后楼安置楼-15966101741-300M-宽带上网投诉-次数0-202407030000093591 | E8: 2024-07-03 19:00:00 | F8: 202407030000093591 | G8: 202407030000093591#流程受理流水号：20240703075752159661017411000514 客户号码:15966101741 客户姓名:聂** 投诉地市:潍坊 来话流水:2024070307571144220866176 宽带账号:15966101741 宽带账号归属地市:潍坊 宽带账号归属区县:临朐县 故障地址:潍坊临朐县城关街道龙泉路后楼安置楼恒信首府6号楼********* 联系电话:15966101741 联系人:先生/女士 工单紧急程度:非常紧急 是否有升级投诉倾向:否 是否重复投诉:否 是否携转意向:否 是否投诉倾向:否 是否智能网关:智能网关 当前是否在线:否 接入方式:FTTH 端到端诊断结果:状态正常 是否质差终端:无质差信息 光功率:无 故障大类:宽带/电视 故障细类:宽带无法上网 携转原因: 故障时间:2024-07-03 07:59:05 具体故障现象:光猫亮红灯 客户其他诉求:客户要求尽快处理。 ;宽带小区$[后楼安置楼]$ | H8: 2024-07-03 08:07:52 | I8: 家宽咨询->网络质量->家庭宽带->全局流转->功能使用->LOS红灯，无法上网->全局流转 | J8: 邓兆然 | K8: 15706307539 | L8: 临朐县 | M8: 家客铁通潍坊临朐-城关城区装维组 | N8: 重新熔接皮线 | O8: dw3_jk_dengzhaoran | P8: 2024-07-03 08:08:20 | R8: =IF(OR(LEFT(L8,2)="高新"),"奎文",IF(LEFT(L8,2)="峡山","坊子",IF(LEFT(L8,2)="滨海","寒亭",LEFT(L8,2)))) -> 临朐 | S8: =TEXT(B8,"mmdd") -> 0703
A9: SD-057-240703-987615-138 | B9: 2024-07-03 08:07:05 | C9: 潍坊 | D9: 80+普通-普通区域-安丘市-关王村自然村-13465361792-200M-业务受理宽带-次数0-202407030000090351 | E9: 2024-07-04 08:08:00 | F9: 202407030000090351 | G9: 202407030000090351# 宽带账号:13465361792; 联系电话：13465361792，问题类型：此工单为群障修复工单，根据群障全量闭环修复管理要求，为确保客户网络通畅，请装维人员跟进修复网络问题，谢谢！ 群障标题：公告。故障描述：分支光纤断或OLT检测不到ONT的预期的光信号(LOSi/LOBi)主叫号码：13465361792.0;该号码仅供参考，请优先联系宽带账号。 | H9: 2024-07-03 08:13:58 | I9: 业务受理->线上义诊->家庭业务->全局流转->功能使用->群障弹窗->全局流转 | J9: 宋龙海 | K9: 15706307016 | L9: 安丘市 | M9: 家客铁通潍坊安丘-刘家尧乡镇装维组 | N9: 重新熔接皮线 | O9: dw3_jk_songlonghai | P9: 2024-07-03 08:16:20 | R9: =IF(OR(LEFT(L9,2)="高新"),"奎文",IF(LEFT(L9,2)="峡山","坊子",IF(LEFT(L9,2)="滨海","寒亭",LEFT(L9,2)))) -> 安丘 | S9: =TEXT(B9,"mmdd") -> 0703
A10: SD-057-240703-368195-4577 | B10: 2024-07-03 15:44:30 | C10: 潍坊 | D10: FTTR-普通区域-临朐县-大成新文华苑一期-15953628966-1000M-宽带上网投诉-次数0-202407030000479491 | E10: 2024-07-04 08:00:00 | F10: 202407030000479491 | G10: 202407030000479491#宽带账号：15953628966；宽带地址：潍坊临朐县城关街道秦池路大成新文华苑一期1号楼；客户来电反映宽带使用不畅，客户不在现场，无法配合线上指导，要求上门，请协助处理，谢谢！联系电话：本机；联系人：先生；来电流水2024070315422624620886980 | H10: 2024-07-03 15:52:38 | I10: 家庭咨询->网络质量->家庭宽带->全局流转->功能使用->客户要求装维上门服务->全局流转 | J10: 韩崇 | K10: 15706307608 | L10: 临朐县 | M10: 家客铁通潍坊临朐-城关城区装维组 | N10: 重新连接机顶盒网络 | O10: dw3_jk_hanchong | P10: 2024-07-03 15:53:09 | Q10: SD-851-258399-6579-23200 | R10: =IF(OR(LEFT(L10,2)="高新"),"奎文",IF(LEFT(L10,2)="峡山","坊子",IF(LEFT(L10,2)="滨海","寒亭",LEFT(L10,2)))) -> 临朐 | S10: =TEXT(B10,"mmdd") -> 0703
A11: SD-057-240703-451762-61 | B11: 2024-07-03 07:28:05 | C11: 潍坊 | D11: 【调研】-普通区域-诸城市-山钢碧桂园·翡翠城-18805365378-200M-宽带上网投诉-次数0-202407030000090931 一级督办 | E11: 2024-07-03 19:00:00 | F11: 202407030000090931 | G11: 202407030000090931#流程受理流水号：20240703072721188053653781000254 客户号码:18805365378 客户姓名:郭** 投诉地市:潍坊 来话流水:2024070307224877020852549 宽带账号:18805365378 宽带账号归属地市:潍坊 宽带账号归属区县:诸城市 故障地址:潍坊诸城市密州街道南外环山钢碧桂园·翡翠城27号楼********* 联系电话:18353631333 联系人:先生 工单紧急程度:一般 是否有升级投诉倾向:否 是否重复投诉:否 是否携转意向:否 是否投诉倾向:否 是否智能网关:智能网关 当前是否在线:是 接入方式:FTTH 端到端诊断结果:客户侧设备问题（新增） 是否质差终端:无质差信息 光功率:-19.82 故障大类:宽带/电视 故障细类:宽带无法上网 携转原因: 故障时间:2024-07-03 07:27:36 具体故障现象:打不开网页， 客户其他诉求: ;宽带小区$[山钢碧桂园·翡翠城]$ | H11: 2024-07-03 07:35:11 | I11: 家宽咨询->网络质量->家庭宽带->全局流转->功能使用->网络连接掉线->全局流转 | J11: 刘永 | K11: 15706307953 | L11: 诸城市 | M11: 家客铁通潍坊诸城-兴华东路城区装维组 | N11: 机顶盒重新升级 | O11: dw3_jk_liuyong | P11: 2024-07-03 07:35:31 | Q11: SD-851-253327-20031-7246 | R11: =IF(OR(LEFT(L11,2)="高新"),"奎文",IF(LEFT(L11,2)="峡山","坊子",IF(LEFT(L11,2)="滨海","寒亭",LEFT(L11,2)))) -> 诸城 | S11: =TEXT(B11,"mmdd") -> 0703
A12: SD-057-240703-748950-4581 | B12: 2024-07-03 15:44:36 | C12: 潍坊 | D12: FTTR-普通区域-坊子区-下小路沿街-15726054555-1000M-宽带上网投诉-次数0-20240703154343X623753968 一级督办 | E12: 2024-07-04 08:00:00 | F12: 20240703154343X623753968 | G12: 流程受理流水号：20240703154145157260545551128630 客户号码:15726054555 客户姓名:郭** 投诉地市:潍坊 来话流水:2024070315355941720898098 宽带账号:15726054555 宽带账号归属地市:潍坊 宽带账号归属区县:坊子区 故障地址:潍坊坊子区岞山街道岞山大街下小路沿街神州姜窖2号箱李鑫灏外墙 联系电话:15726054555 联系人:先生/女士 工单紧急程度:非常紧急 是否有升级投诉倾向:是 是否重复投诉:否 是否携转意向:否 是否投诉倾向:是 是否智能网关:智能网关 当前是否在线:是 接入方式:FTTH 端到端诊断结果:客户侧设备问题（新增） 是否质差终端:无质差信息 光功率:-14.93 故障大类:宽带/电视 故障细类:网速慢/上网掉线(专席) 携转原因: 故障时间:2024-07-03 15:41:57 具体故障现象:网速慢卡顿，客户称为移动公司线上恶意限速了，在线时间不就，设备支持带宽无损耗，通话中提及12300投诉，请协助，谢谢。 客户其他诉求: | H12: 2024-07-03 15:49:49 | I12: 家宽业务->网络质量->家庭宽带->全局流转->功能使用->频繁出现故障、网速慢->全局流转 | J12: 王其治 | K12: 15706307917 | L12: 坊子区 | M12: 家客铁通潍坊坊子-太保庄乡镇装维组 | O12: dw3_jk_wangqizhi | P12: 2024-07-03 15:50:29 | Q12: SD-851-320940-17145-7584 | R12: =IF(OR(LEFT(L12,2)="高新"),"奎文",IF(LEFT(L12,2)="峡山","坊子",IF(LEFT(L12,2)="滨海","寒亭",LEFT(L12,2)))) -> 坊子 | S12: =TEXT(B12,"mmdd") -> 0703
A13: SD-057-240703-986172-4598 | B13: 2024-07-03 15:47:30 | C13: 潍坊 | D13: 普通区域-临朐县-石门小区-17888364612-300M-宽带上网投诉-次数0-202407030000483603 | E13: 2024-07-04 08:00:00 | F13: 202407030000483603 | G13: 202407030000483603#宽带账号：17888364612；宽带地址：潍坊临朐县城关街道弥河路石门小区15号楼**；客户来电反映宽带上网慢，客户不配合排障，要求上门，请协助处理，谢谢！联系电话：17888364612；联系人：先生；来电流水：2024070315434160620804339。 | H13: 2024-07-03 15:52:06 | I13: 家庭咨询->网络质量->家庭宽带->全局流转->功能使用->客户要求装维上门服务->全局流转 | J13: 尹筱 | K13: 15706307601 | L13: 临朐县 | M13: 家客铁通潍坊临朐-城关城区装维组 | N13: 重启路由器 | O13: dw3_jk_yinxiao | P13: 2024-07-03 15:55:14 | Q13: SD-852-276576-789-28795 | R13: =IF(OR(LEFT(L13,2)="高新"),"奎文",IF(LEFT(L13,2)="峡山","坊子",IF(LEFT(L13,2)="滨海","寒亭",LEFT(L13,2)))) -> 临朐 | S13: =TEXT(B13,"mmdd") -> 0703
A14: SD-057-240703-341876-3374 | B14: 2024-07-03 13:28:33 | C14: 潍坊 | D14: 普通区域-安丘市-江山一品-18706691699-500M-宽带上网投诉-次数0-202407030000343694 | E14: 2024-07-04 08:00:00 | F14: 202407030000343694 | G14: 202407030000343694# 宽带账号：18706691699；宽带地址：潍坊安丘市兴安街道金融街江山一品江山一品14号楼*****客户来电反映 移动高清 不能看/客户不配合排障，要求上门，请协助处理，谢谢！联系电话：***；联系人：18706691699；来电流水：2024070313234194320879800。 | H14: 2024-07-03 13:31:14 | I14: 家庭咨询->网络质量->家庭宽带->全局流转->功能使用->客户要求装维上门服务->全局流转 | J14: 杨晓龙 | K14: 15706307058 | L14: 安丘市 | M14: 家客铁通潍坊安丘-永安路城区装维组 | N14: 重新连接机顶盒网络 | O14: dw3_jk_yangxiaolong | P14: 2024-07-03 13:31:48 | Q14: SD-851-232227-6269-4730 | R14: =IF(OR(LEFT(L14,2)="高新"),"奎文",IF(LEFT(L14,2)="峡山","坊子",IF(LEFT(L14,2)="滨海","寒亭",LEFT(L14,2)))) -> 安丘 | S14: =TEXT(B14,"mmdd") -> 0703
A15: SD-057-240703-829145-7733 | B15: 2024-07-03 20:51:15 | C15: 潍坊 | D15: 【调研】-80+银卡-普通区域-临朐县-御景花园-15054846650-100M-宽带上网投诉-次数0-202407030000715830 | E15: 2024-07-04 19:00:00 | F15: 202407030000715830 | G15: 202407030000715830#流程受理流水号：20240703205032150548466501200165 客户号码:15054846650 客户姓名:李** 投诉地市:潍坊 来话流水:2024070320500520420834842 宽带账号:15054846650 宽带账号归属地市:潍坊 宽带账号归属区县:临朐县 故障地址:潍坊临朐县城关街道骈邑路御景花园2号楼********* 联系电话:15054846650 联系人:先生/女士 工单紧急程度:一般 是否有升级投诉倾向:否 是否重复投诉:否 是否携转意向:否 是否投诉倾向:否 是否智能网关:智能网关 当前是否在线:否 接入方式:FTTH 端到端诊断结果:状态正常 是否质差终端:无质差信息 光功率:无 故障大类:宽带/电视 故障细类:宽带无法上网 携转原因: 故障时间:2024-07-03 20:50:55 具体故障现象:打不开网页， 客户其他诉求: ;宽带小区$[御景花园]$ | H15: 2024-07-03 20:58:59 | I15: 家宽咨询->网络质量->家庭宽带->全局流转->功能使用->网络无法连接->全局流转 | J15: 韩太永 | K15: 15706307573 | L15: 临朐县 | M15: 家客铁通潍坊临朐-城关城区装维组 | N15: 重新熔接皮线 | O15: dw3_jk_hantaiyong | P15: 2024-07-03 21:05:42 | R15: =IF(OR(LEFT(L15,2)="高新"),"奎文",IF(LEFT(L15,2)="峡山","坊子",IF(LEFT(L15,2)="滨海","寒亭",LEFT(L15,2)))) -> 临朐 | S15: =TEXT(B15,"mmdd") -> 0703
A16: SD-057-240703-670325-142 | B16: 2024-07-03 08:07:16 | C16: 潍坊 | D16: 【调研】-普通区域-奎文区-金玉豪府-13406618893-200M-业务受理宽带-次数0-202407030000093176 | E16: 2024-07-04 08:08:00 | F16: 202407030000093176 | G16: 202407030000093176#【已关注中国移动10086微信公众号】 宽带账号:13406618893; 联系电话：13406618893，问题类型：此工单为群障修复工单，根据群障全量闭环修复管理要求，为确保客户网络通畅，请装维人员跟进修复网络问题，谢谢！ 群障标题：公告。故障描述：分支光纤断或OLT检测不到ONT的预期的光信号(LOSi/LOBi)主叫号码：13406618893.0;该号码仅供参考，请优先联系宽带账号。 | H16: 2024-07-03 08:14:03 | I16: 业务受理->线上义诊->家庭业务->全局流转->功能使用->群障弹窗->全局流转 | J16: 吕开迪 | K16: 15706307454 | L16: 奎文区 | M16: 家客铁通潍坊奎文-北宫街城区装维组 | N16: 更换尾纤 | O16: dw3_jk_lvkaidi | P16: 2024-07-03 08:14:24 | Q16: SD-852-290447-2351-5113 | R16: =IF(OR(LEFT(L16,2)="高新"),"奎文",IF(LEFT(L16,2)="峡山","坊子",IF(LEFT(L16,2)="滨海","寒亭",LEFT(L16,2)))) -> 奎文 | S16: =TEXT(B16,"mmdd") -> 0703
A17: SD-057-240703-315097-7752 | B17: 2024-07-03 20:53:34 | C17: 潍坊 | D17: 80+金卡-普通区域-奎文区-舜华园-13646467963-500M-宽带上网投诉-次数0-20240703205250X170928541 | E17: 2024-07-04 19:00:00 | F17: 20240703205250X170928541 | G17: 流程受理流水号：20240703205132136464679631200295 客户号码:13646467963 客户姓名:张** 投诉地市:潍坊 来话流水:2024070320505323720838474 宽带账号:13646467963 宽带账号归属地市:潍坊 宽带账号归属区县:奎文区 故障地址:潍坊奎文区大虞街道北宫街舜华园4号楼********* 联系电话:18263672507 联系人:先生/女士 工单紧急程度:非常紧急 是否有升级投诉倾向:否 是否重复投诉:否 是否携转意向:否 是否投诉倾向:否 是否智能网关:智能网关 当前是否在线:是 接入方式:FTTH 端到端诊断结果:客户侧设备问题（新增） 是否质差终端:无质差信息 光功率:-19.82 故障大类:宽带/电视 故障细类:宽带无法上网 携转原因: 故障时间:2024-07-03 20:51:54 具体故障现象:光猫灯正常但电脑手机无法上网， 客户其他诉求:客户来电要求尽快回电处理 | H17: 2024-07-03 20:55:07 | I17: 家宽业务->网络质量->家庭宽带->全局流转->功能使用->网络无法连接->全局流转 | J17: 李春龙 | K17: 15706366503 | L17: 奎文区 | M17: 家客铁通潍坊奎文-鸢飞路城区装维组 | N17: 更换热缩管 | O17: dw3_jk_lichunlong | P17: 2024-07-03 20:59:43 | Q17: SD-851-303890-2620-15513 | R17: =IF(OR(LEFT(L17,2)="高新"),"奎文",IF(LEFT(L17,2)="峡山","坊子",IF(LEFT(L17,2)="滨海","寒亭",LEFT(L17,2)))) -> 奎文 | S17: =TEXT(B17,"mmdd") -> 0703
A18: SD-057-240703-524103-7751 | B18: 2024-07-03 20:53:30 | C18: 潍坊 | D18: 【调研】-80+金卡-普通区域-奎文区-锦绣苑-13964638833-1000M-宽带上网投诉-次数0-20240703205231X151615755 | E18: 2024-07-04 19:00:00 | F18: 20240703205231X151615755 | G18: 流程受理流水号：20240703205109139646388331200245 客户号码:13964638833 客户姓名:赵** 投诉地市:潍坊 来话流水:2024070320475819120825156 宽带账号:13964638833 宽带账号归属地市:潍坊 宽带账号归属区县:奎文区 故障地址:潍坊奎文区北苑街道玉清街锦绣苑14号楼********* 联系电话:13964638833 联系人:先生/女士 工单紧急程度:非常紧急 是否有升级投诉倾向:否 是否重复投诉:否 是否携转意向:否 是否投诉倾向:否 是否智能网关:智能网关 当前是否在线:否 接入方式:FTTH 端到端诊断结果:设备告警 是否质差终端:无质差信息 光功率:无 故障大类:宽带/电视 故障细类:宽带无法上网(专席) 携转原因: 故障时间:2024-07-03 20:50:23 具体故障现象:客户来电反映无法上网，光信号亮红灯：拔插捋直光纤线未恢复，请处理，谢谢。 客户其他诉求: | H18: 2024-07-03 20:55:52 | I18: 家宽业务->网络质量->家庭宽带->全局流转->功能使用->网络无法连接->全局流转 | J18: 张根涛 | K18: 15706307406 | L18: 奎文区 | M18: 家客铁通潍坊奎文-鸢飞路城区装维组 | O18: dw3_jk_zhangentao | P18: 2024-07-03 20:56:23 | Q18: SD-851-255278-20071-11623 | R18: =IF(OR(LEFT(L18,2)="高新"),"奎文",IF(LEFT(L18,2)="峡山","坊子",IF(LEFT(L18,2)="滨海","寒亭",LEFT(L18,2)))) -> 奎文 | S18: =TEXT(B18,"mmdd") -> 0703
A19: SD-057-240703-526913-3320 | B19: 2024-07-03 13:20:38 | C19: 潍坊 | D19: 【调研】-(目标)普通区域-安丘市-坡庄村自然村-13863641309-300M-宽带上网投诉-次数0-20240703131840X920574522 | E19: 2024-07-04 08:00:00 | F19: 20240703131840X920574522 | G19: 【农村网络投诉】流程受理流水号：20240703131545138636413091090219 客户号码:13863641309 客户姓名:李* 投诉地市:潍坊 来话流水:2024070313141761520809073 宽带账号:13863641309 宽带账号归属地市:潍坊 宽带账号归属区县:安丘市 故障地址:潍坊安丘市官庄镇坡庄村坡庄村自然村坡庄三次追加9号箱游成敏********* 联系电话:15753680705 联系人:先生 工单紧急程度:一般 是否有升级投诉倾向:否 是否重复投诉:否 是否携转意向:否 是否投诉倾向:否 是否智能网关:智能网关 当前是否在线:否 接入方式:FTTH 端到端诊断结果:状态正常 是否质差终端:无质差信息 光功率:无 故障大类:宽带/电视 故障细类:宽带无法上网 携转原因: 故障时间:2024-07-03 13:17:11 具体故障现象:提示网络无法连接， 客户其他诉求: | H19: 2024-07-03 13:28:36 | I19: 家宽业务->网络质量->家庭宽带->全局流转->功能使用->网络无法连接->全局流转 | J19: 李焕江 | K19: 15706307048 | L19: 安丘市 | M19: 家客铁通潍坊安丘-官庄乡镇装维组 | O19: dw3_jk_lihuanjiang | P19: 2024-07-03 13:29:11 | R19: =IF(OR(LEFT(L19,2)="高新"),"奎文",IF(LEFT(L19,2)="峡山","坊子",IF(LEFT(L19,2)="滨海","寒亭",LEFT(L19,2)))) -> 安丘 | S19: =TEXT(B19,"mmdd") -> 0703
A20: SD-057-240703-583196-3340 | B20: 2024-07-03 13:23:36 | C20: 潍坊 | D20: 普通区域-安丘市-蒯沟-15966153193-300M-宽带上网投诉-次数0-20240703132230X150476217 | E20: 2024-07-04 08:00:00 | F20: 20240703132230X150476217 | G20: 【农村网络投诉】流程受理流水号：20240703132130159661531931091407 客户号码:15966153193 客户姓名:殷** 投诉地市:潍坊 来话流水:2024070313200418120852632 宽带账号:15966153193 宽带账号归属地市:潍坊 宽带账号归属区县:安丘市 故障地址:潍坊安丘市石埠子镇蒯沟村蒯沟蒯沟二次追加5号箱张杰********* 联系电话:15954415739 联系人:先生/女士 工单紧急程度:一般 是否有升级投诉倾向:否 是否重复投诉:否 是否携转意向:否 是否投诉倾向:否 是否智能网关:智能网关 当前是否在线:否 接入方式:FTTH 端到端诊断结果:状态正常 是否质差终端:无质差信息 光功率:无 故障大类:宽带/电视 故障细类:宽带无法上网(专席) 携转原因: 故障时间:2024-07-03 13:22:28 具体故障现象:光猫亮红灯， 客户其他诉求: | H20: 2024-07-03 13:30:06 | I20: 家宽业务->网络质量->家庭宽带->全局流转->功能使用->网络无法连接->全局流转 | J20: 鞠知彬 | K20: 15706307020 | L20: 安丘市 | M20: 家客铁通潍坊安丘-石埠子乡镇装维组 | N20: 更换二级分光器 | O20: dw3_jk_juzhibin | P20: 2024-07-03 13:30:38 | R20: =IF(OR(LEFT(L20,2)="高新"),"奎文",IF(LEFT(L20,2)="峡山","坊子",IF(LEFT(L20,2)="滨海","寒亭",LEFT(L20,2)))) -> 安丘 | S20: =TEXT(B20,"mmdd") -> 0703
A21: SD-057-240703-160972-4549 | B21: 2024-07-03 15:41:07 | C21: 潍坊 | D21: 【调研】-80+银卡-普通区域-高密市-梓潼家园-13853628968-1000M-宽带上网投诉-次数0-20240703153832X312157112 | E21: 2024-07-04 08:00:00 | F21: 20240703153832X312157112 | G21: 流程受理流水号：20240703153725138536289681127368 客户号码:13853628968 客户姓名:单** 投诉地市:潍坊 来话流水:2024070315370080820812386 宽带账号:13853628968 宽带账号归属地市:潍坊 宽带账号归属区县:高密市 故障地址:潍坊高密市朝阳街道夷安大道梓潼家园101号箱********* 联系电话:13853628968 联系人:先生/女士 工单紧急程度:非常紧急 是否有升级投诉倾向:否 是否重复投诉:否 是否携转意向:否 是否投诉倾向:否 是否智能网关:智能网关 当前是否在线:是 接入方式:FTTH 端到端诊断结果:客户侧设备问题（新增） 是否质差终端:无质差信息 光功率:-17.03 故障大类:宽带/电视 故障细类:宽带无法上网(专席) 携转原因: 故障时间:2024-07-03 15:39:08 具体故障现象:提示网络无法连接， 客户其他诉求: | H21: 2024-07-03 16:02:22 | I21: 家宽业务->网络质量->家庭宽带->全局流转->功能使用->网络无法连接->全局流转 | J21: 满勇 | K21: 15706307304 | L21: 高密市 | M21: 家客铁通潍坊高密-朝阳城区装维组 | N21: 更换二级分光器 | O21: dw3_jk_manyong | P21: 2024-07-03 16:02:54 | Q21: SD-851-300127-29120-17453 | R21: =IF(OR(LEFT(L21,2)="高新"),"奎文",IF(LEFT(L21,2)="峡山","坊子",IF(LEFT(L21,2)="滨海","寒亭",LEFT(L21,2)))) -> 高密 | S21: =TEXT(B21,"mmdd") -> 0703
A22: SD-057-240703-982607-5107 | B22: 2024-07-03 16:50:20 | C22: 潍坊 | D22: 【重投】-普通区域-安丘市-乐山原墅-13646463446-200M-魔百和投诉-次数0-202407030000543681 | E22: 2024-07-04 17:51:00 | F22: 202407030000543681 | G22: 202407030000543681#【已关注中国移动10086微信公众号】流程受理流水号：20240703164938136464634461149054 客户号码:13646463446 客户姓名:李** 投诉地市:潍坊 来话流水:2024070316434570620829899 宽带账号:13646463446 宽带账号归属地市:潍坊 宽带账号归属区县:安丘市 故障地址:潍坊安丘市新安街道莲花山路乐山原墅乐山原墅Y3号楼********* 联系电话:13646463446 联系人:女士 工单紧急程度:一般 是否有升级投诉倾向:否 是否重复投诉:否 是否携转意向:否 是否投诉倾向:否 是否智能网关:智能网关 当前是否在线:是 接入方式:FTTH 端到端诊断结果:客户侧设备问题（新增） 是否质差终端:无质差信息 光功率:-22.21 故障大类:宽带/电视 故障细类:移动高清电视故障(专席) 携转原因: 故障时间:2024-07-03 16:48:32 魔百和单播/组播:组播 具体故障现象:电视机提示无信号 客户其他诉求:尽快处理 谢谢 魔百和单/组播：组播;宽带小区$[乐山原墅]$ | H22: 2024-07-03 16:53:27 | I22: 家庭咨询->产品质量->互联网电视(移动高清)->全局流转->售后服务->电视机提示“无信号”->全局流转 | J22: 苏凯明 | K22: 15706307021 | L22: 安丘市 | M22: 家客铁通潍坊安丘-刘家尧乡镇装维组 | N22: 机顶盒恢复出厂 | O22: dw3_jk_sukaiming | P22: 2024-07-03 16:53:45 | R22: =IF(OR(LEFT(L22,2)="高新"),"奎文",IF(LEFT(L22,2)="峡山","坊子",IF(LEFT(L22,2)="滨海","寒亭",LEFT(L22,2)))) -> 安丘 | S22: =TEXT(B22,"mmdd") -> 0703
A23: SD-057-240703-649735-7685 | B23: 2024-07-03 20:43:42 | C23: 潍坊 | D23: 普通区域-寒亭区-元和新城-15163615099-300M-宽带延伸服务-次数0-202407030000712984 | E23: 2024-07-04 18:00:00 | F23: 202407030000712984 | G23: 202407030000712984#流程受理流水号：20240703204219151636150991199085 客户号码:15163615099 客户姓名:董** 投诉地市:潍坊 来话流水:2024070320412863720894673 宽带账号:15163615099 宽带账号归属地市:潍坊 宽带账号归属区县:寒亭区 故障地址:潍坊寒亭区寒亭街道益新街元和新城29号楼********* 联系电话:15163615099 联系人:先生/女士 工单紧急程度:紧急 是否有升级投诉倾向:否 是否重复投诉:否 是否携转意向:否 是否投诉倾向:否 是否智能网关:智能网关 当前是否在线:是 接入方式:FTTH 是否质差终端:是 光功率:-18.99 故障大类:宽带/电视 故障细类:宽带延伸服务 携转原因: 故障时间:2024-07-03 20:42:31 具体故障现象:客户对换光锚收费100元不认可，请处理谢谢！ | H23: 2024-07-03 20:45:49 | I23: 业务受理->宽带延伸服务->家庭业务->全局流转->功能使用->代装终端->全局流转 | J23: 刘兴涛 | K23: 15706307476 | L23: 寒亭区 | M23: 家客铁通潍坊寒亭-城东城区装维组 | N23: 指导用户加固线缆 | O23: dw3_jk_liuxingtao | P23: 2024-07-03 20:46:24 | R23: =IF(OR(LEFT(L23,2)="高新"),"奎文",IF(LEFT(L23,2)="峡山","坊子",IF(LEFT(L23,2)="滨海","寒亭",LEFT(L23,2)))) -> 寒亭 | S23: =TEXT(B23,"mmdd") -> 0703
A24: SD-057-240703-860543-7667 | B24: 2024-07-03 20:41:43 | C24: 潍坊 | D24: 【调研】-80+普通-普通区域-昌乐县-前孔自然村（含前孔、南刘家沟）-18763687627-1000M-宽带上网投诉-次数0-20240703204055X455900115 | E24: 2024-07-04 19:00:00 | F24: 20240703204055X455900115 | G24: 【农村网络投诉】流程受理流水号：20240703203918187636876271198669 客户号码:18763687627 客户姓名:赵** 投诉地市:潍坊 来话流水:2024070320353267320865783 宽带账号:18763687627 宽带账号归属地市:潍坊 宽带账号归属区县:昌乐县 故障地址:潍坊昌乐县鄌郚镇前孔前孔自然村前孔村5#（村东北吴汉亮）********* 联系电话:18706537286 联系人:先生/女士 工单紧急程度:非常紧急 是否有升级投诉倾向:否 是否重复投诉:否 是否携转意向:否 是否投诉倾向:否 是否智能网关:智能网关 当前是否在线:否 接入方式:FTTH 端到端诊断结果:状态正常 是否质差终端:无质差信息 光功率:无 故障大类:宽带/电视 故障细类:宽带无法上网(专席) 携转原因: 故障时间:2024-07-03 20:39:21 具体故障现象:注册灯闪烁，引导客户将光纤线插紧，将弯折的位置捋直后重启无效，请协助处理，谢谢。 客户其他诉求: | H24: 2024-07-03 20:43:25 | I24: 家宽业务->网络质量->家庭宽带->全局流转->功能使用->网络无法连接->全局流转 | J24: 刘志诚 | K24: 15706307122 | L24: 昌乐县 | M24: 家客铁通潍坊昌乐-唐吾乡镇装维组 | N24: 重新熔接皮线 | O24: dw3_jk_liuzhicheng | P24: 2024-07-03 20:47:09 | Q24: SD-851-237769-28867-17713 | R24: =IF(OR(LEFT(L24,2)="高新"),"奎文",IF(LEFT(L24,2)="峡山","坊子",IF(LEFT(L24,2)="滨海","寒亭",LEFT(L24,2)))) -> 昌乐 | S24: =TEXT(B24,"mmdd") -> 0703
A25: SD-057-240703-857264-3420 | B25: 2024-07-03 13:38:05 | C25: 潍坊 | D25: (目标)普通区域-青州市-西水渠-13853644178-300M-宽带上网投诉-次数0-20240703133539X939467998 | E25: 2024-07-04 08:00:00 | F25: 20240703133539X939467998 | G25: 【农村网络投诉】流程受理流水号：20240703133450138536441781094087 客户号码:13853644178 客户姓名:闫** 投诉地市:潍坊 来话流水:2024070313321974820846158 宽带账号:13853644178 宽带账号归属地市:潍坊 宽带账号归属区县:青州市 故障地址:潍坊青州市高柳镇西水渠村西水渠西水渠村12号箱（闫炳河）********* 联系电话:15006685166 联系人:先生/女士 工单紧急程度:紧急 是否有升级投诉倾向:否 是否重复投诉:否 是否携转意向:否 是否投诉倾向:否 是否智能网关:智能网关 当前是否在线:否 接入方式:FTTH 端到端诊断结果:设备告警 是否质差终端:无质差信息 光功率:无 故障大类:宽带/电视 故障细类:宽带无法上网(专席) 携转原因: 故障时间:2024-07-03 13:34:30 具体故障现象:光猫亮红灯，客户表示室外线断了 ，家里不能上网 客户其他诉求: | H25: 2024-07-03 13:41:37 | I25: 家宽业务->网络质量->家庭宽带->全局流转->功能使用->网络无法连接->全局流转 | J25: 李超 | K25: 15706307648 | L25: 青州市 | M25: 家客铁通潍坊青州-高柳乡镇装维组 | N25: 重新连接机顶盒网络 | O25: dw3_jk_weixiaoliang | P25: 2024-07-03 13:42:01 | R25: =IF(OR(LEFT(L25,2)="高新"),"奎文",IF(LEFT(L25,2)="峡山","坊子",IF(LEFT(L25,2)="滨海","寒亭",LEFT(L25,2)))) -> 青州 | S25: =TEXT(B25,"mmdd") -> 0703
A26: SD-057-240703-085762-307 | B26: 2024-07-03 08:39:19 | C26: 潍坊 | D26: 【调研】-80+普通-普通区域-奎文区-帝景苑-15905361026-500M-宽带上网投诉-次数0-202407030000100853 | E26: 2024-07-04 08:00:00 | F26: 202407030000100853 | G26: 202407030000100853#流程受理流水号：20240703083600159053610261002999 客户号码:15905361026 客户姓名:王* 投诉地市:潍坊 来话流水:2024070308350727620841880 宽带账号:15905361026 宽带账号归属地市:潍坊 宽带账号归属区县:奎文区 故障地址:潍坊奎文区广文街道民生东街帝景苑35********* 联系电话:18615088887 联系人:先生/女士 工单紧急程度:紧急 是否有升级投诉倾向:否 是否重复投诉:否 是否携转意向:否 是否投诉倾向:否 是否智能网关:智能网关 当前是否在线:否 接入方式:FTTH 端到端诊断结果:状态正常 是否质差终端:无质差信息 光功率:无 故障大类:宽带/电视 故障细类:宽带无法上网 携转原因: 故障时间:2024-07-03 08:37:56 具体故障现象:光猫亮红灯， 客户其他诉求:要求尽快处理 ;宽带小区$[帝景苑]$ | H26: 2024-07-03 08:50:09 | I26: 家宽咨询->网络质量->家庭宽带->全局流转->功能使用->网络无法连接->全局流转 | J26: 姚克胜 | K26: 15706307480 | L26: 奎文区 | M26: 家客铁通潍坊奎文-樱前街城区装维组 | N26: 更换光猫 | O26: dw3_jk_yaokesheng | P26: 2024-07-03 08:56:03 | Q26: SD-851-285398-20429-7221 | R26: =IF(OR(LEFT(L26,2)="高新"),"奎文",IF(LEFT(L26,2)="峡山","坊子",IF(LEFT(L26,2)="滨海","寒亭",LEFT(L26,2)))) -> 奎文 | S26: =TEXT(B26,"mmdd") -> 0703
A27: SD-057-240703-185734-281 | B27: 2024-07-03 08:37:29 | C27: 潍坊 | D27: 普通区域-寿光市-杨家庄村自然村-15163698310-300M-宽带上网投诉-次数0-202407030000099778 | E27: 2024-07-04 08:00:00 | F27: 202407030000099778 | G27: 202407030000099778#导航立单,客户通过语音导航反馈宽带故障问题,经诊断光猫设备性能不佳,要求装维回访处理,请协助.联系电话：15163698310 | H27: 2024-07-03 08:54:18 | I27: 家庭咨询->网络质量->家庭宽带->全局流转->功能使用->光猫设备故障->全局流转 | J27: 赵坤 | K27: 15706307757 | L27: 寿光市 | M27: 家客铁通潍坊寿光-古城乡镇装维组 | N27: 重新施工布放光缆 | O27: dw3_jk_zhaokun | P27: 2024-07-03 08:57:06 | R27: =IF(OR(LEFT(L27,2)="高新"),"奎文",IF(LEFT(L27,2)="峡山","坊子",IF(LEFT(L27,2)="滨海","寒亭",LEFT(L27,2)))) -> 寿光 | S27: =TEXT(B27,"mmdd") -> 0703
A28: SD-057-240703-045693-6451 | B28: 2024-07-03 19:02:45 | C28: 潍坊 | D28: 普通区域-奎文区-府佑居-19558555993-100M-宽带上网投诉-次数0-20240703190118X478903156 | E28: 2024-07-04 19:00:00 | F28: 20240703190118X478903156 | G28: 流程受理流水号：20240703185954195585559931183092 客户号码:19558555993 客户姓名:张** 投诉地市:潍坊 来话流水:2024070318581418720879651 宽带账号:19558555993 宽带账号归属地市:潍坊 宽带账号归属区县:奎文区 故障地址:潍坊奎文区高新城区金马路府佑居25号楼********* 联系电话:19558555993 联系人:先生/女士 工单紧急程度:一般 是否有升级投诉倾向:否 是否重复投诉:否 是否携转意向:否 是否投诉倾向:否 是否智能网关:智能网关 当前是否在线:是 接入方式:FTTH 端到端诊断结果:客户侧设备问题（新增） 是否质差终端:无质差信息 光功率:-16.02 故障大类:宽带/电视 故障细类:宽带网速慢/卡顿 携转原因: 故障时间:2024-07-03 19:00:38 网站/APP/游戏名称:电脑游戏 具体故障现象:网速慢卡顿， 客户其他诉求: | H28: 2024-07-03 19:06:33 | I28: 家宽业务->网络质量->家庭宽带->全局流转->功能使用->部分视频无法播放->全局流转 | J28: 李先圣 | K28: 15706307393 | L28: 奎文区 | M28: 家客铁通潍坊奎文-健康街城区装维组 | N28: 用户感觉网速慢，但测速达标 | O28: dw3_jk_lixiansheng | P28: 2024-07-03 19:06:58 | Q28: SD-851-302211-9443-10331 | R28: =IF(OR(LEFT(L28,2)="高新"),"奎文",IF(LEFT(L28,2)="峡山","坊子",IF(LEFT(L28,2)="滨海","寒亭",LEFT(L28,2)))) -> 奎文 | S28: =TEXT(B28,"mmdd") -> 0703
A29: SD-057-240703-130278-6806 | B29: 2024-07-03 19:21:50 | C29: 潍坊 | D29: 普通区域-昌邑市-政亨小区3-18866730028-1000M-业务受理宽带-次数0-202407030000673728 | E29: 2024-07-04 18:00:00 | F29: 202407030000673728 | G29: 202407030000673728#导航立单,用户所在位置有群障,已向客户播报,客户要求装维回访.此工单为群障修复工单,根据群障全量闭环管理要求,为确保客户网络通畅,请装维人员跟进修复网络问题,谢谢.联系电话：18866730028 | H29: 2024-07-03 19:40:57 | I29: 业务受理->线上义诊->家庭业务->全局流转->功能使用->群障弹窗->全局流转 | J29: 徐瑞鹏 | K29: 15706307210 | L29: 昌邑市 | M29: 家客铁通潍坊昌邑-柳疃乡镇装维组 | N29: 更换皮线或网线 | O29: dw3_jk_xuruipeng | P29: 2024-07-03 19:41:40 | Q29: SD-851-267886-3747-7240 | R29: =IF(OR(LEFT(L29,2)="高新"),"奎文",IF(LEFT(L29,2)="峡山","坊子",IF(LEFT(L29,2)="滨海","寒亭",LEFT(L29,2)))) -> 昌邑 | S29: =TEXT(B29,"mmdd") -> 0703
A30: SD-057-240703-126045-7055 | B30: 2024-07-03 19:47:39 | C30: 潍坊 | D30: 普通区域-青州市-平安庄-13869602147-300M-宽带上网投诉-次数0-20240703194622X182424852 | E30: 2024-07-04 19:00:00 | F30: 20240703194622X182424852 | G30: 【农村网络投诉】流程受理流水号：20240703194521138696021471190975 客户号码:13869602147 客户姓名:林** 投诉地市:潍坊 来话流水:2024070319433355120878901 宽带账号:13869602147 宽带账号归属地市:潍坊 宽带账号归属区县:青州市 故障地址:潍坊青州市王坟镇平安庄村平安庄12号箱（村北刘洪义西邻墙头）********* 联系电话:13869602147 联系人:先生/女士 工单紧急程度:紧急 是否有升级投诉倾向:否 是否重复投诉:否 是否携转意向:否 是否投诉倾向:否 是否智能网关:智能网关 当前是否在线:否 接入方式:FTTH 端到端诊断结果:状态正常 是否质差终端:无质差信息 光功率:无 故障大类:宽带/电视 故障细类:宽带无法上网(专席) 携转原因: 故障时间:2024-07-03 19:45:40 具体故障现象:光猫亮红灯，线上指导插紧捋直未恢复 客户其他诉求: | H30: 2024-07-03 19:49:09 | I30: 家宽业务->网络质量->家庭宽带->全局流转->功能使用->网络无法连接->全局流转 | J30: 张礼杰 | K30: 15706307691 | L30: 青州市 | M30: 家客铁通潍坊青州-弥河乡镇装维组 | N30: 指导用户重启光猫3分钟后重启机顶盒 | O30: dw3_jk_zhanglijie | P30: 2024-07-03 19:57:46 | R30: =IF(OR(LEFT(L30,2)="高新"),"奎文",IF(LEFT(L30,2)="峡山","坊子",IF(LEFT(L30,2)="滨海","寒亭",LEFT(L30,2)))) -> 青州 | S30: =TEXT(B30,"mmdd") -> 0703
A31: SD-057-240703-150487-6467 | B31: 2024-07-03 19:05:02 | C31: 潍坊 | D31: 普通区域-高密市-福润花园（酒厂宿舍、东关殷家屋子）-13953642233-1000M-宽带上网投诉-次数0-20240703190220X540286149 | E31: 2024-07-04 19:00:00 | F31: 20240703190220X540286149 | G31: 流程受理流水号：20240703185758139536422331182715 客户号码:13953642233 客户姓名:綦* 投诉地市:潍坊 来话流水:2024070318571101120871860 宽带账号:13953642233 宽带账号归属地市:潍坊 宽带账号归属区县:高密市 故障地址:潍坊高密市密水街道立新街福润花园（酒厂宿舍、东关殷家屋子）东关殷家屋子金文酒店北墙2号********* 联系电话:13280756478 联系人:先生/女士 工单紧急程度:非常紧急 是否有升级投诉倾向:否 是否重复投诉:否 是否携转意向:否 是否投诉倾向:否 是否智能网关:智能网关 当前是否在线:否 接入方式:FTTH 端到端诊断结果:状态正常 是否质差终端:无质差信息 光功率:无 故障大类:宽带/电视 故障细类:宽带无法上网(专席) 携转原因: 故障时间:2024-07-03 19:02:02 具体故障现象:光猫亮红灯， 客户其他诉求: | H31: 2024-07-03 19:07:14 | I31: 家宽业务->网络质量->家庭宽带->全局流转->功能使用->网络无法连接->全局流转 | J31: 刘志刚 | K31: 15706307359 | L31: 高密市 | M31: 家客铁通潍坊高密-朝阳城区装维组 | N31: 重新熔接皮线 | O31: dw3_jk_liuzhigang | P31: 2024-07-03 19:08:01 | R31: =IF(OR(LEFT(L31,2)="高新"),"奎文",IF(LEFT(L31,2)="峡山","坊子",IF(LEFT(L31,2)="滨海","寒亭",LEFT(L31,2)))) -> 高密 | S31: =TEXT(B31,"mmdd") -> 0703
A32: SD-057-240703-456102-2430 | B32: 2024-07-03 11:56:08 | C32: 潍坊 | D32: 【调研】-80+银卡-(目标)普通区域-寿光市-前尹小区-15244449919-1000M-宽带上网投诉-次数0-202407030000299030 | E32: 2024-07-04 08:00:00 | F32: 202407030000299030 | G32: 202407030000299030#宽带账号：15244449919；宽带地址：潍坊寿光市留吕前尹村前尹小区6号楼；客户来电反映机顶盒不亮了，，要求师傅上门，请协助处理，谢谢！联系电话：15863432041；联系人：先生；来电流水：2024070311541782620833924。 | H32: 2024-07-03 11:56:55 | I32: 家庭咨询->网络质量->家庭宽带->全局流转->功能使用->客户要求装维上门服务->全局流转 | J32: 吕会涛 | K32: 15706307819 | L32: 寿光市 | M32: 家客铁通潍坊寿光-洛城乡镇装维组 | N32: 重新连接机顶盒网络 | O32: dw3_jk_lvhuitao | P32: 2024-07-03 11:57:14 | Q32: SD-851-308131-5528-5220 | R32: =IF(OR(LEFT(L32,2)="高新"),"奎文",IF(LEFT(L32,2)="峡山","坊子",IF(LEFT(L32,2)="滨海","寒亭",LEFT(L32,2)))) -> 寿光 | S32: =TEXT(B32,"mmdd") -> 0703
A33: SD-057-240703-406385-7705 | B33: 2024-07-03 20:47:15 | C33: 潍坊 | D33: 80+普通-普通区域-寿光市-李家官庄村自然村-15964038968-200M-宽带上网投诉-次数0-20240703204543X743840546 | E33: 2024-07-04 19:00:00 | F33: 20240703204543X743840546 | G33: 【农村网络投诉】流程受理流水号：20240703204124159640389681198968 客户号码:15964038968 客户姓名:李** 投诉地市:潍坊 来话流水:2024070320403027820889965 宽带账号:15964038968 宽带账号归属地市:潍坊 宽带账号归属区县:寿光市 故障地址:潍坊寿光市侯镇李家官庄村 联系电话:15964038968 联系人:先生/女士 工单紧急程度:一般 是否有升级投诉倾向:否 是否重复投诉:否 是否携转意向:否 是否投诉倾向:否 是否智能网关:智能网关 当前是否在线:否 接入方式:FTTH 端到端诊断结果:状态正常 是否质差终端:无质差信息 光功率:无 故障大类:宽带/电视 故障细类:宽带无法上网(专席) 携转原因: 故障时间:2024-07-03 20:43:20 具体故障现象:提示网络无法连接， 客户其他诉求:上不去网，重启无效，路由使用两年 | H33: 2024-07-03 21:01:14 | I33: 家宽业务->网络质量->家庭宽带->全局流转->功能使用->网络无法连接->全局流转 | J33: 王艳庆 | K33: 15706307761 | L33: 寿光市 | M33: 家客铁通潍坊寿光-侯镇乡镇装维组 | N33: 选择正确信号源 | O33: dw3_jk_wangyanqing | P33: 2024-07-03 21:01:55 | R33: =IF(OR(LEFT(L33,2)="高新"),"奎文",IF(LEFT(L33,2)="峡山","坊子",IF(LEFT(L33,2)="滨海","寒亭",LEFT(L33,2)))) -> 寿光 | S33: =TEXT(B33,"mmdd") -> 0703
A34: SD-057-240703-108254-7062 | B34: 2024-07-03 19:49:24 | C34: 潍坊 | D34: 80+银卡-普通区域-安丘市-百合学府-15065650220-200M-宽带上网投诉-次数0-202407030000683941 | E34: 2024-07-04 19:00:00 | F34: 202407030000683941 | G34: 202407030000683941#宽带账号：15065650220；宽带地址：潍坊安丘市兴安街道潍徐路百合学府2号楼；客户来电反映宽带无法上网，客户不在现场，无法配合线上指导/客户不配合排障，要求上门，请协助处理，谢谢！联系电话：15065650220；联系人：女士；来电流水：2024070319435168020880644 | H34: 2024-07-03 19:52:48 | I34: 家庭咨询->网络质量->家庭宽带->全局流转->功能使用->客户要求装维上门服务->全局流转 | J34: 辛成孝 | K34: 15706307075 | L34: 安丘市 | M34: 家客铁通潍坊安丘-永安路城区装维组 | N34: 更换皮线或网线 | O34: dw3_jk_xinchengxiao | P34: 2024-07-03 19:53:16 | R34: =IF(OR(LEFT(L34,2)="高新"),"奎文",IF(LEFT(L34,2)="峡山","坊子",IF(LEFT(L34,2)="滨海","寒亭",LEFT(L34,2)))) -> 安丘 | S34: =TEXT(B34,"mmdd") -> 0703
A35: SD-057-240703-986723-3972 | B35: 2024-07-03 14:35:55 | C35: 潍坊 | D35: 【调研】-普通区域-青州市-二府村-18763638595-200M-宽带上网投诉-次数0-202407030000415554 | E35: 2024-07-04 15:36:00 | F35: 202407030000415554 | G35: 202407030000415554#宽带账号：18763638595；宽带地址：潍坊青州市东夏镇二府村二府村东夏镇二府村1号箱（中南张传利）******；客户来电反映宽带/移动高清*****，客户不在现场，无法配合线上指导/客户不配合排障，要求上门，请协助处理，谢谢！联系电话：15153638680；联系人：女士；来电流水：2024070314331051720831831。 | H35: 2024-07-03 14:42:32 | I35: 家庭咨询->网络质量->家庭宽带->全局流转->功能使用->客户要求装维上门服务->全局流转 | J35: 董宝泉 | K35: 15706307670 | L35: 青州市 | M35: 家客铁通潍坊青州-开发区城区装维组 | N35: 重新配置数据 | O35: dw3_jk_dongbaoquan | P35: 2024-07-03 14:43:08 | Q35: SD-851-241392-12835-8845 | R35: =IF(OR(LEFT(L35,2)="高新"),"奎文",IF(LEFT(L35,2)="峡山","坊子",IF(LEFT(L35,2)="滨海","寒亭",LEFT(L35,2)))) -> 青州 | S35: =TEXT(B35,"mmdd") -> 0703
A36: SD-057-240703-917536-5165 | B36: 2024-07-03 16:57:15 | C36: 潍坊 | D36: 普通区域-奎文区-阳光100二期-13011657323-300M-宽带上网投诉-次数1-20240703140727X847099229 | E36: 2024-07-04 17:58:00 | F36: 20240703140727X847099229 | G36: 【预处理派单】宽带账号：13011657323，宽带地址： 潍坊奎文区广文街道胜利街阳光100二期13号楼*********，故障现象：，故障现象类型：，客户诉求：客户来电反映对宽带师傅上门收费，安装收费600元不认可，咨询宽带安装范围，是安装到走廊里面还是光纤入户都要收费，请协助处理，谢谢，联系电话：13011657323，通话流水：2024070314003354020823268。接入方式：，当前是否在线：不在线，端到端诊断结果：宽带业务状态未激活，是否智能网关：否，光功率。 | H36: 2024-07-03 17:01:01 | I36: 家庭业务->基础服务->家庭宽带->全局流转->售后服务->宽带未覆盖办理后无法装移机->全局流转 | J36: 孙晓波 | K36: 15706366530 | L36: 奎文区 | M36: 家客铁通潍坊奎文-樱前街城区装维组 | N36: 无覆盖价值，建议转派至家庭业务-业务营销-家庭宽带-全局流转-办理规范-宽带无覆盖办理后无法安装 | O36: dw3_jk_sunxiaobo | Q36: SD-851-274929-2546-1806 | R36: =IF(OR(LEFT(L36,2)="高新"),"奎文",IF(LEFT(L36,2)="峡山","坊子",IF(LEFT(L36,2)="滨海","寒亭",LEFT(L36,2)))) -> 奎文 | S36: =TEXT(B36,"mmdd") -> 0703
A37: SD-057-240703-301946-6429 | B37: 2024-07-03 19:00:27 | C37: 潍坊 | D37: 普通区域-高密市-东小庄小区-13563686444-300M-宽带上网投诉-次数0-202407030000658173 | E37: 2024-07-04 19:00:00 | F37: 202407030000658173 | G37: 202407030000658173#【已关注中国移动10086微信公众号】流程受理流水号：20240703185854135636864441182895 客户号码:13563686444 客户姓名:毛** 投诉地市:潍坊 来话流水:2024070318561415020865048 宽带账号:13563686444 宽带账号归属地市:潍坊 宽带账号归属区县:高密市 故障地址:潍坊高密市朝阳街道人民大街东小庄小区新7号楼********* 联系电话:15610444989 联系人:先生 工单紧急程度:一般 是否有升级投诉倾向:否 是否重复投诉:否 是否携转意向:否 是否投诉倾向:否 是否智能网关:智能网关 当前是否在线:否 接入方式:FTTH 端到端诊断结果:状态正常 是否质差终端:无质差信息 光功率:无 故障大类:宽带/电视 故障细类:宽带无法上网 携转原因: 故障时间:2024-07-03 18:59:37 具体故障现象:光猫亮红灯， 客户其他诉求: ;宽带小区$[东小庄小区]$ | H37: 2024-07-03 19:04:17 | I37: 家宽咨询->网络质量->家庭宽带->全局流转->功能使用->LOS红灯，无法上网->全局流转 | J37: 刘志刚 | K37: 15706307359 | L37: 高密市 | M37: 家客铁通潍坊高密-朝阳城区装维组 | N37: 重新熔接皮线 | O37: dw3_jk_liuzhigang | P37: 2024-07-03 19:04:41 | R37: =IF(OR(LEFT(L37,2)="高新"),"奎文",IF(LEFT(L37,2)="峡山","坊子",IF(LEFT(L37,2)="滨海","寒亭",LEFT(L37,2)))) -> 高密 | S37: =TEXT(B37,"mmdd") -> 0703
A38: SD-057-240703-943752-6474 | B38: 2024-07-03 19:05:26 | C38: 潍坊 | D38: 【调研】-80+银卡-普通区域-奎文区-金马家园-15269648061-1000M-宽带上网投诉-次数0-20240703190323X603498225 | E38: 2024-07-04 19:00:00 | F38: 20240703190323X603498225 | G38: 流程受理流水号：20240703190258152696480611183670 客户号码:15269648061 客户姓名:赵** 投诉地市:潍坊 来话流水:2024070318591935920887476 宽带账号:15269648061 宽带账号归属地市:潍坊 宽带账号归属区县:高新 故障地址:潍坊市高新高新城区金马路金马家园10号3-201 联系电话:15269648061 联系人:先生/女士 工单紧急程度:非常紧急 是否有升级投诉倾向:否 是否重复投诉:否 是否携转意向:否 是否投诉倾向:否 是否智能网关:智能网关 当前是否在线:是 接入方式:FTTH 端到端诊断结果:客户侧设备问题（新增） 是否质差终端:无质差信息 光功率:-21.24 故障大类:宽带/电视 故障细类:宽带无法上网(专席) 携转原因: 故障时间:2024-07-03 19:03:07 具体故障现象:光猫灯正常但电脑手机无法上网， 客户其他诉求:请协助谢谢 | H38: 2024-07-03 19:07:48 | I38: 家宽业务->网络质量->家庭宽带->全局流转->功能使用->部分网页内容无法正常访问->全局流转 | J38: 王新刚 | K38: 15706307389 | L38: 奎文区 | M38: 家客铁通潍坊奎文-北宫街城区装维组 | N38: 重启路由器 | O38: dw3_jk_wangxingang | P38: 2024-07-03 19:10:37 | Q38: SD-851-270323-16085-16356 | R38: =IF(OR(LEFT(L38,2)="高新"),"奎文",IF(LEFT(L38,2)="峡山","坊子",IF(LEFT(L38,2)="滨海","寒亭",LEFT(L38,2)))) -> 奎文 | S38: =TEXT(B38,"mmdd") -> 0703
A39: SD-057-240703-230516-6479 | B39: 2024-07-03 19:05:41 | C39: 潍坊 | D39: 【调研】-80+银卡-普通区域-诸城市-东城名苑-15206467876-1000M-宽带上网投诉-次数0-20240703190400X640050844 | E39: 2024-07-04 19:00:00 | F39: 20240703190400X640050844 | G39: 流程受理流水号：20240703190239152064678761183617 客户号码:15206467876 客户姓名:郑** 投诉地市:潍坊 来话流水:2024070319012136220801934 宽带账号:15206467876 宽带账号归属地市:潍坊 宽带账号归属区县:诸城市 故障地址:潍坊诸城市密州街道东坡街东城名苑26号楼********* 联系电话:13562683699 联系人:先生/女士 工单紧急程度:非常紧急 是否有升级投诉倾向:否 是否重复投诉:否 是否携转意向:否 是否投诉倾向:否 是否智能网关:智能网关 当前是否在线:否 接入方式:FTTH 端到端诊断结果:状态正常 是否质差终端:无质差信息 光功率:无 故障大类:宽带/电视 故障细类:宽带无法上网(专席) 携转原因: 故障时间:2024-07-03 19:02:41 具体故障现象:PON灯闪，已排查客户设备指示灯，已指导重启设备捋顺插紧光纤线未恢复，记录反馈、 客户其他诉求:谢谢处理 | H39: 2024-07-03 19:07:01 | I39: 家宽业务->网络质量->家庭宽带->全局流转->功能使用->网络无法连接->全局流转 | J39: 袁凯 | K39: 15706307712 | L39: 诸城市 | M39: 家客铁通潍坊诸城-繁荣路城区装维组 | N39: 重新熔接线缆 | O39: dw3_jk_yuankai | P39: 2024-07-03 19:07:53 | Q39: SD-851-260755-22861-17685 | R39: =IF(OR(LEFT(L39,2)="高新"),"奎文",IF(LEFT(L39,2)="峡山","坊子",IF(LEFT(L39,2)="滨海","寒亭",LEFT(L39,2)))) -> 诸城 | S39: =TEXT(B39,"mmdd") -> 0703
A40: SD-057-240703-136847-2442 | B40: 2024-07-03 11:56:55 | C40: 潍坊 | D40: 【调研】-普通区域-安丘市-金地太阳城(含小庄子安置楼)-15244405552-1000M-宽带上网投诉-次数0-202407030000298786 一级督办 | E40: 2024-07-04 08:00:00 | F40: 202407030000298786 | G40: 202407030000298786#15244405552客户来电反映对前期工单处理结果不认可，要求回电处理，前期工单流水：202405270000201921，本次通话流水：2024070311485682820866598，联系人：先生，联系电话：15244405552，请协助处理，谢谢 | H40: 2024-07-03 11:57:58 | I40: 家庭咨询->网络质量->家庭宽带->全局流转->功能使用->用户测速与签约速率不符->全局流转 | J40: 孙浩 | K40: 15706307039 | L40: 安丘市 | M40: 家客铁通潍坊安丘-潍安路城区装维组 | N40: 用户感觉网速慢，但测速达标 | O40: dw3_jk_sunhao | P40: 2024-07-03 11:58:11 | Q40: SD-851-306635-20500-27344 | R40: =IF(OR(LEFT(L40,2)="高新"),"奎文",IF(LEFT(L40,2)="峡山","坊子",IF(LEFT(L40,2)="滨海","寒亭",LEFT(L40,2)))) -> 安丘 | S40: =TEXT(B40,"mmdd") -> 0703
A41: SD-057-240703-780639-2493 | B41: 2024-07-03 12:03:31 | C41: 潍坊 | D41: 80+普通-普通区域-安丘市-曹家楼村-13583677309-1000M-宽带延伸服务-次数0-202407030000307349 | E41: 2024-07-04 00:00:00 | F41: 202407030000307349 | G41: 202407030000307349#流程受理流水号：20240703120158135836773091073849 客户号码:13583677309 客户姓名:吕** 投诉地市:潍坊 来话流水:2024070312000654220802669 宽带账号:13583677309 宽带账号归属地市:潍坊 宽带账号归属区县:安丘市 故障地址:潍坊安丘市刘家尧镇田家庄曹家楼村大城埠田家庄 联系电话:15589699737 联系人:先生/女士 工单紧急程度:一般 是否有升级投诉倾向:否 是否重复投诉:否 是否携转意向:否 是否投诉倾向:否 是否智能网关:非智能网关 当前是否在线:否 接入方式:FTTH 是否质差终端:是 光功率:无 故障大类:宽带/电视 故障细类:宽带延伸服务 携转原因: 故障时间:2024-07-03 12:13:26 具体故障现象:重新布置网线，地址:潍坊安丘市刘家尧镇田家庄曹家楼村大城埠田家庄 | H41: 2024-07-03 12:07:57 | I41: 业务受理->宽带延伸服务->家庭业务->全局流转->功能使用->代装终端->全局流转 | J41: 宋龙海 | K41: 15706307016 | L41: 安丘市 | M41: 家客铁通潍坊安丘-刘家尧乡镇装维组 | N41: 重新熔接线缆 | O41: dw3_jk_songlonghai | P41: 2024-07-03 12:08:27 | Q41: SD-851-283604-20886-29680 | R41: =IF(OR(LEFT(L41,2)="高新"),"奎文",IF(LEFT(L41,2)="峡山","坊子",IF(LEFT(L41,2)="滨海","寒亭",LEFT(L41,2)))) -> 安丘 | S41: =TEXT(B41,"mmdd") -> 0703
A42: SD-057-240703-014258-3436 | B42: 2024-07-03 13:39:36 | C42: 潍坊 | D42: 普通区域-昌乐县-温泉公寓-15966125669-300M-宽带上网投诉-次数0-202407030000368945 | E42: 2024-07-04 08:00:00 | F42: 202407030000368945 | G42: 202407030000368945#流程受理流水号：20240703133739159661256691094696 客户号码:15966125669 客户姓名:郝** 投诉地市:潍坊 来话流水:2024070313360583520879645 宽带账号:15966125669 宽带账号归属地市:潍坊 宽带账号归属区县:昌乐县 故障地址:潍坊昌乐县宝城街道新昌路温泉公寓3号楼********* 联系电话:15169565180 联系人:先生 工单紧急程度:紧急 是否有升级投诉倾向:否 是否重复投诉:否 是否携转意向:否 是否投诉倾向:否 是否智能网关:智能网关 当前是否在线:是 接入方式:FTTH 端到端诊断结果:客户侧设备问题（新增） 是否质差终端:无质差信息 光功率:-16.32 故障大类:宽带/电视 故障细类:宽带无法上网(专席) 携转原因: 故障时间:2024-07-03 13:37:25 具体故障现象:提示网络无法连接，线上指导未恢复 请师傅协助处理谢谢 客户其他诉求:谢谢 ;宽带小区$[温泉公寓]$ | H42: 2024-07-03 13:42:27 | I42: 家宽咨询->网络质量->家庭宽带->全局流转->功能使用->网络无法连接->全局流转 | J42: 闫锦洲 | K42: 15706307131 | L42: 昌乐县 | M42: 家客铁通潍坊昌乐-美联城区装维组 | N42: 指导用户重新连接线缆 | O42: dw3_jk_yanjinzhou | P42: 2024-07-03 13:42:53 | R42: =IF(OR(LEFT(L42,2)="高新"),"奎文",IF(LEFT(L42,2)="峡山","坊子",IF(LEFT(L42,2)="滨海","寒亭",LEFT(L42,2)))) -> 昌乐 | S42: =TEXT(B42,"mmdd") -> 0703
A43: SD-057-240703-512498-6985 | B43: 2024-07-03 19:40:53 | C43: 潍坊 | D43: 80+普通-普通区域-奎文区-兴源国际-18764618188-500M-宽带上网投诉-次数0-202407030000682407 | E43: 2024-07-04 19:00:00 | F43: 202407030000682407 | G43: 202407030000682407#流程受理流水号：20240703193628187646181881189566 客户号码:18764618188 客户姓名:曹** 投诉地市:潍坊 来话流水:2024070319264932320872641 宽带账号:18764618188 宽带账号归属地市:潍坊 宽带账号归属区县:奎文区 故障地址:潍坊奎文区潍州路街道道口路兴源国际城2号楼1-1201 联系电话:18764618188 联系人:先生/女士 工单紧急程度:紧急 是否有升级投诉倾向:否 是否重复投诉:否 是否携转意向:否 是否投诉倾向:否 是否智能网关:智能网关 当前是否在线:是 接入方式:FTTH 端到端诊断结果:客户侧设备问题（新增） 是否质差终端:无质差信息 光功率:-17.82 故障大类:宽带/电视 故障细类:宽带无法上网(专席) 携转原因: 故障时间:2024-07-03 19:39:05 具体故障现象:光猫灯正常但电脑手机无法上网，按顺序重启后未恢复，请协助谢谢！ 客户其他诉求: ;宽带小区$[兴源国际]$ | H43: 2024-07-03 19:43:28 | I43: 家宽咨询->网络质量->家庭宽带->全局流转->功能使用->网络无法连接->全局流转 | J43: 朱文杰 | K43: 15706366520 | L43: 奎文区 | M43: 家客铁通潍坊奎文-潍州路城区装维组 | N43: 重启路由器 | O43: dw3_jk_zhuwenjie | P43: 2024-07-03 19:44:03 | R43: =IF(OR(LEFT(L43,2)="高新"),"奎文",IF(LEFT(L43,2)="峡山","坊子",IF(LEFT(L43,2)="滨海","寒亭",LEFT(L43,2)))) -> 奎文 | S43: =TEXT(B43,"mmdd") -> 0703
A44: SD-057-240703-745089-258 | B44: 2024-07-03 08:35:04 | C44: 潍坊 | D44: 【调研】-普通区域-安丘市-大朱聊村自然村-15169694678-1000M-宽带上网投诉-次数0-202407030000098899 | E44: 2024-07-04 08:00:00 | F44: 202407030000098899 | G44: 202407030000098899#要求装维上门服务：宽带账号：15169694678；宽带地址潍坊安丘市担山镇大朱聊村大朱聊村自然村大朱聊；客户来电反映宽带连不上，客户不在现场，无法配合线上指导/客户不配合排障，要求上门，请协助处理，谢谢！联系电话：15169694678；联系人：15169694678；来电流水：*2024070308331661620827313 | H44: 2024-07-03 08:36:50 | I44: 家庭咨询->网络质量->家庭宽带->全局流转->功能使用->客户要求装维上门服务->全局流转 | J44: 王永琳 | K44: 13406613524 | L44: 安丘市 | M44: 家客铁通潍坊安丘-贾戈乡镇装维组 | N44: 重新熔接皮线 | O44: dw3_jk_wangyonglinaq | P44: 2024-07-03 08:37:28 | R44: =IF(OR(LEFT(L44,2)="高新"),"奎文",IF(LEFT(L44,2)="峡山","坊子",IF(LEFT(L44,2)="滨海","寒亭",LEFT(L44,2)))) -> 安丘 | S44: =TEXT(B44,"mmdd") -> 0703
A45: SD-057-240703-043165-302 | B45: 2024-07-03 08:38:40 | C45: 潍坊 | D45: 【调研】-普通区域-高密市-杜一村自然村-15866122722-300M-宽带上网投诉-次数0-20240703083753X730389140 | E45: 2024-07-04 08:00:00 | F45: 20240703083753X730389140 | G45: 【农村网络投诉】流程受理流水号：20240703083437158661227221002561 客户号码:15866122722 客户姓名:王** 投诉地市:潍坊 来话流水:2024070308332870320828930 宽带账号:15866122722 宽带账号归属地市:潍坊 宽带账号归属区县:高密市 故障地址:潍坊高密市夏庄镇杜一村杜一村自然村杜一村杜金一31号箱********* 联系电话:15866122722 联系人:女士 工单紧急程度:紧急 是否有升级投诉倾向:否 是否重复投诉:否 是否携转意向:否 是否投诉倾向:否 是否智能网关:智能网关 当前是否在线:否 接入方式:FTTH 端到端诊断结果:状态正常 是否质差终端:无质差信息 光功率:无 故障大类:宽带 故障细类:宽带无法上网(专席) 携转原因: 故障时间:2024-07-03 08:35:46 具体故障现象:注册灯闪亮 客户其他诉求: | H45: 2024-07-03 08:42:41 | I45: 家宽业务->网络质量->家庭宽带->全局流转->功能使用->网络无法连接->全局流转 | J45: 高强 | K45: 15706307285 | L45: 高密市 | M45: 家客铁通潍坊高密-夏庄乡镇装维组 | N45: 指导用户加固线缆 | O45: dw3_jk_gaoqiang | P45: 2024-07-03 11:53:41 | Q45: SD-852-274315-1087-23267 | R45: =IF(OR(LEFT(L45,2)="高新"),"奎文",IF(LEFT(L45,2)="峡山","坊子",IF(LEFT(L45,2)="滨海","寒亭",LEFT(L45,2)))) -> 高密 | S45: =TEXT(B45,"mmdd") -> 0703
A46: SD-057-240703-795103-6574 | B46: 2024-07-03 19:09:48 | C46: 潍坊 | D46: 80+普通-普通区域-奎文区-奎文区宏伟北区-13406643000-1000M-业务受理宽带-次数0-202407030000664815 | E46: 2024-07-04 18:00:00 | F46: 202407030000664815 | G46: 202407030000664815# 宽带账号:13406643000; 联系电话：13406643000，问题类型：此工单为群障修复工单，根据群障全量闭环修复管理要求，为确保客户网络通畅，请装维人员跟进修复网络问题，谢谢！ 群障标题：告警。故障标题：分支光纤断或OLT检测不到ONT的预期的光信号(LOSi/LOBi)主叫号码：13406643000.0;该号码仅供参考，请优先联系宽带账号。 | H46: 2024-07-03 19:33:55 | I46: 业务受理->线上义诊->家庭业务->全局流转->功能使用->群障弹窗->全局流转 | J46: 朱文杰 | K46: 15706366520 | L46: 奎文区 | M46: 家客铁通潍坊奎文-潍州路城区装维组 | N46: 重新熔缆 | O46: dw3_jk_zhuwenjie | P46: 2024-07-03 19:34:15 | Q46: SD-851-312059-17303-19567 | R46: =IF(OR(LEFT(L46,2)="高新"),"奎文",IF(LEFT(L46,2)="峡山","坊子",IF(LEFT(L46,2)="滨海","寒亭",LEFT(L46,2)))) -> 奎文 | S46: =TEXT(B46,"mmdd") -> 0703
A47: SD-057-240703-084975-2384 | B47: 2024-07-03 11:50:29 | C47: 潍坊 | D47: 普通区域-昌邑市-杜卢-15963446296-100M-宽带延伸服务-次数0-202407030000296890 | E47: 2024-07-04 11:51:00 | F47: 202407030000296890 | G47: 202407030000296890#流程受理流水号：20240703114741159634462961069573 客户号码:15963446296 客户姓名:王** 投诉地市:潍坊 来话流水:2024070311470788420843018 宽带账号:15963446296 宽带账号归属地市:潍坊 宽带账号归属区县:昌邑市 故障地址:潍坊昌邑市北孟镇杜卢村杜卢杜卢村2号箱卢秀强********* 联系电话:15963446296 联系人:先生/女士 工单紧急程度:非常紧急 是否有升级投诉倾向:否 是否重复投诉:否 是否携转意向:否 是否投诉倾向:否 是否智能网关:智能网关 当前是否在线:否 接入方式:FTTH 是否质差终端:无质差信息 光功率:无 故障大类:宽带/电视 故障细类:宽带延伸服务 携转原因: 故障时间:2024-07-03 11:46:06 具体故障现象:调测其它设备， | H47: 2024-07-03 11:52:09 | I47: 业务受理->宽带延伸服务->家庭业务->全局流转->功能使用->代装终端->全局流转 | J47: 于浩 | K47: 15706307207 | L47: 昌邑市 | M47: 家客铁通潍坊昌邑-北孟乡镇装维组 | N47: 重新调试终端 | O47: dw3_jk_yuhaocy | P47: 2024-07-03 11:53:12 | R47: =IF(OR(LEFT(L47,2)="高新"),"奎文",IF(LEFT(L47,2)="峡山","坊子",IF(LEFT(L47,2)="滨海","寒亭",LEFT(L47,2)))) -> 昌邑 | S47: =TEXT(B47,"mmdd") -> 0703
A48: SD-057-240703-173869-2498 | B48: 2024-07-03 12:04:41 | C48: 潍坊 | D48: 【调研】-80+银卡-普通区域-安丘市-石埠子三村自然村-15094992110-200M-宽带上网投诉-次数0-202407030000304761 | E48: 2024-07-04 13:00:00 | F48: 202407030000304761 | G48: 202407030000304761#宽带账号15094992110：宽带地址：潍坊安丘市石埠子镇石埠二村石埠子二村自然村石埠子五村中心街；客户来电反映宽带不能上网，无法配合线上指导，请协助处理，谢谢！联系电话；联系人：15053636110；来电流水：2024070311584481920887467 | H48: 2024-07-03 12:08:38 | I48: 家庭咨询->网络质量->家庭宽带->全局流转->功能使用->客户要求装维上门服务->全局流转 | J48: 鞠知彬 | K48: 15706307020 | L48: 安丘市 | M48: 家客铁通潍坊安丘-石埠子乡镇装维组 | N48: 重新熔接皮线 | O48: dw3_jk_juzhibin | P48: 2024-07-03 12:11:38 | R48: =IF(OR(LEFT(L48,2)="高新"),"奎文",IF(LEFT(L48,2)="峡山","坊子",IF(LEFT(L48,2)="滨海","寒亭",LEFT(L48,2)))) -> 安丘 | S48: =TEXT(B48,"mmdd") -> 0703
A49: SD-057-240703-395162-7695 | B49: 2024-07-03 20:45:12 | C49: 潍坊 | D49: 【调研】-80+钻石-普通区域-寿光市-父子候-18765165119-1000M-宽带上网投诉-次数0-202407030000712785 | E49: 2024-07-04 19:00:00 | F49: 202407030000712785 | G49: 202407030000712785#宽带账号：2024070320425090520801253 宽带地址：潍坊寿光市圣城街道父子候父子候34号箱***** 客户来电反映网速慢，请协助上门更换终端并一并处理故障问题，谢谢！ 联系电话：潍坊寿光市圣城街道父子候父子候34号箱***** 联系人：先生 来电流水:2024070320425090520801253 | H49: 2024-07-03 20:52:13 | I49: 家庭咨询->网络质量->家庭宽带->全局流转->功能使用->光猫设备故障->全局流转 | J49: 崔景强 | K49: 15706307810 | L49: 寿光市 | M49: 家客铁通潍坊寿光-东城城区装维组 | N49: 重启路由器 | O49: dw3_jk_cuijingqiang | P49: 2024-07-03 20:52:52 | Q49: SD-851-221095-21453-13798 | R49: =IF(OR(LEFT(L49,2)="高新"),"奎文",IF(LEFT(L49,2)="峡山","坊子",IF(LEFT(L49,2)="滨海","寒亭",LEFT(L49,2)))) -> 寿光 | S49: =TEXT(B49,"mmdd") -> 0703
A50: SD-057-240703-067549-6993 | B50: 2024-07-03 19:41:28 | C50: 潍坊 | D50: 普通区域-高密市-秀水苑-1321068816902-300M-宽带上网投诉-次数0-20240703193958X798157791 | E50: 2024-07-04 19:00:00 | F50: 20240703193958X798157791 | G50: 流程受理流水号：2024070319381613210688169021189877 客户号码:1321068816902 客户姓名: 投诉地市:潍坊 来话流水:2024070319345541220824983 宽带账号:1321068816902 宽带账号归属地市:潍坊 宽带账号归属区县:高密市 故障地址:潍坊高密市朝阳街道张鲁驻地秀水苑5号楼********* 联系电话:13210688169 联系人:先生/女士 工单紧急程度:一般 是否有升级投诉倾向:否 是否重复投诉:否 是否携转意向:否 是否投诉倾向:否 是否智能网关:智能网关 当前是否在线:是 接入方式:FTTH 端到端诊断结果:客户侧设备问题 是否质差终端:无质差信息 光功率:-19.10 故障大类:宽带/电视 故障细类:网速慢/上网掉线(专席) 携转原因: 故障时间:2024-07-03 19:38:07 具体故障现象:网速慢卡顿，自己测速达不到，千兆路由器使用位置宽阔，重启未恢复要求马上处理 客户其他诉求: | H50: 2024-07-03 19:48:54 | I50: 家宽业务->网络质量->家庭宽带->全局流转->功能使用->频繁出现故障、网速慢->全局流转 | J50: 张金磊 | K50: 15706307305 | L50: 高密市 | M50: 家客铁通潍坊高密-朝阳城区装维组 | O50: dw3_jk_zhangjinlei | P50: 2024-07-03 19:49:15 | Q50: SD-851-236078-2345-14172 | R50: =IF(OR(LEFT(L50,2)="高新"),"奎文",IF(LEFT(L50,2)="峡山","坊子",IF(LEFT(L50,2)="滨海","寒亭",LEFT(L50,2)))) -> 高密 | S50: =TEXT(B50,"mmdd") -> 0703
A51: SD-057-240703-791560-7012 | B51: 2024-07-03 19:42:56 | C51: 潍坊 | D51: 【调研】-普通区域-寿光市-刘家河头村自然村-18866794361-300M-宽带上网投诉-次数0-202407030000682987 | E51: 2024-07-04 19:00:00 | F51: 202407030000682987 | G51: 202407030000682987#宽带账号：18866794361宽带地址：潍坊寿光市台头镇刘家河头村刘家河头村自然村刘家河头村东北；客户来电反映宽带卡，无法配合线上指导，请协助处理，谢谢！联系电话；联系人：18866794361；来电流水2024070319350314920825802 | H51: 2024-07-03 19:47:16 | I51: 家庭咨询->网络质量->家庭宽带->全局流转->功能使用->客户要求装维上门服务->全局流转 | J51: 陈锦旭 | K51: 15706307751 | L51: 寿光市 | M51: 家客铁通潍坊寿光-台头乡镇装维组 | N51: 用户感觉网速慢，但测速达标 | O51: dw3_jk_chenjinxu | P51: 2024-07-03 19:47:35 | R51: =IF(OR(LEFT(L51,2)="高新"),"奎文",IF(LEFT(L51,2)="峡山","坊子",IF(LEFT(L51,2)="滨海","寒亭",LEFT(L51,2)))) -> 寿光 | S51: =TEXT(B51,"mmdd") -> 0703
A52: SD-057-240703-328957-93 | B52: 2024-07-03 07:48:15 | C52: 潍坊 | D52: 普通区域-诸城市-殷家涧-13666367307-1000M-宽带上网投诉-次数0-202407030000091760 | E52: 2024-07-03 19:00:00 | F52: 202407030000091760 | G52: 202407030000091760#流程受理流水号：20240703074645136663673071000415 客户号码:13666367307 客户姓名:张** 投诉地市:潍坊 来话流水:2024070307462519320861063 宽带账号:13666367307 宽带账号归属地市:潍坊 宽带账号归属区县:诸城市 故障地址:潍坊诸城市林家村镇殷家涧村殷家涧殷家涧村西8#箱********* 联系电话:15265686619 联系人:先生/女士 工单紧急程度:非常紧急 是否有升级投诉倾向:否 是否重复投诉:否 是否携转意向:否 是否投诉倾向:否 是否智能网关:智能网关 当前是否在线:是 接入方式:FTTH 端到端诊断结果:客户侧设备问题（新增） 是否质差终端:无质差信息 光功率:-19.06 故障大类:宽带/电视 故障细类:宽带无法上网 携转原因: 故障时间:2024-07-03 07:46:55 具体故障现象:提示网络无法连接， 客户其他诉求: ;宽带小区$[殷家涧]$ | H52: 2024-07-03 07:51:56 | I52: 家宽咨询->网络质量->家庭宽带->全局流转->功能使用->网络无法连接->全局流转 | J52: 管延文 | K52: 15706307976 | L52: 诸城市 | M52: 家客铁通潍坊诸城-林家村乡镇装维组 | N52: 重新调试终端 | O52: dw3_jk_guanyanwen | P52: 2024-07-03 07:52:37 | Q52: SD-851-283340-13952-5091 | R52: =IF(OR(LEFT(L52,2)="高新"),"奎文",IF(LEFT(L52,2)="峡山","坊子",IF(LEFT(L52,2)="滨海","寒亭",LEFT(L52,2)))) -> 诸城 | S52: =TEXT(B52,"mmdd") -> 0703
A53: SD-057-240703-712586-2390 | B53: 2024-07-03 11:50:50 | C53: 潍坊 | D53: 【调研】-80+普通-(目标)普通区域-诸城市-天一城小区-15165682938-1000M-宽带上网投诉-次数0-20240703114812X492986451 | E53: 2024-07-04 08:00:00 | F53: 20240703114812X492986451 | G53: 流程受理流水号：20240703114730151656829381069516 客户号码:15165682938 客户姓名:许** 投诉地市:潍坊 来话流水:2024070311434676920899945 宽带账号:15165682938 宽带账号归属地市:潍坊 宽带账号归属区县:诸城市 故障地址:潍坊诸城市龙都街道潍徐街天一城小区26号楼********* 联系电话:15165682938 联系人:先生/女士 工单紧急程度:非常紧急 是否有升级投诉倾向:否 是否重复投诉:否 是否携转意向:否 是否投诉倾向:否 是否智能网关:智能网关 当前是否在线:否 接入方式:FTTH 端到端诊断结果:状态正常 是否质差终端:无质差信息 光功率:无 故障大类:宽带/电视 故障细类:宽带无法上网(专席) 携转原因: 故障时间:2024-07-03 11:47:02 具体故障现象:光猫亮红灯，将光纤线两头插紧，将弯折的位置捋直后重启一下光猫，未恢复 客户其他诉求: | H53: 2024-07-03 11:55:38 | I53: 家宽业务->网络质量->家庭宽带->全局流转->功能使用->网络无法连接->全局流转 | J53: 封冠宇 | K53: 15684303176 | L53: 诸城市 | M53: 家客铁通潍坊诸城-繁荣路城区装维组 | N53: 魔百和账号销户重开户后 | O53: dw3_jk_fengguanyu | P53: 2024-07-03 11:56:28 | Q53: SD-851-276290-31516-16148 | R53: =IF(OR(LEFT(L53,2)="高新"),"奎文",IF(LEFT(L53,2)="峡山","坊子",IF(LEFT(L53,2)="滨海","寒亭",LEFT(L53,2)))) -> 诸城 | S53: =TEXT(B53,"mmdd") -> 0703
A54: SD-057-240703-746893-3403 | B54: 2024-07-03 13:35:07 | C54: 潍坊 | D54: 普通区域-安丘市-徐家沟-15064457492-200M-宽带上网投诉-次数0-20240703133219X739390556 | E54: 2024-07-04 13:00:00 | F54: 20240703133219X739390556 | G54: 【农村网络投诉】流程受理流水号：20240703132637150644574921092408 客户号码:15064457492 客户姓名:郑** 投诉地市:潍坊 来话流水:2024070313221855920869501 宽带账号:15064457492 宽带账号归属地市:潍坊 宽带账号归属区县:安丘市 故障地址:潍坊安丘市辉渠镇徐家沟村徐家沟徐家沟3号箱徐小峰********* 联系电话:15064457492 联系人:先生 工单紧急程度:一般 是否有升级投诉倾向:否 是否重复投诉:否 是否携转意向:否 是否投诉倾向:否 是否智能网关:智能网关 当前是否在线:否 接入方式:FTTH 端到端诊断结果:状态正常 是否质差终端:无质差信息 光功率:无 故障大类:宽带/电视 故障细类:宽带无法上网 携转原因: 故障时间:2024-07-03 13:30:20 具体故障现象:客户来电说两个多月没有信号 客户其他诉求: | H54: 2024-07-03 13:39:42 | I54: 家宽业务->网络质量->家庭宽带->全局流转->功能使用->网络无法连接->全局流转 | J54: 李连强 | K54: 15706307054 | L54: 安丘市 | M54: 家客铁通潍坊安丘-官庄乡镇装维组 | O54: dw3_jk_lilianqiang | P54: 2024-07-03 13:40:11 | R54: =IF(OR(LEFT(L54,2)="高新"),"奎文",IF(LEFT(L54,2)="峡山","坊子",IF(LEFT(L54,2)="滨海","寒亭",LEFT(L54,2)))) -> 安丘 | S54: =TEXT(B54,"mmdd") -> 0703
A55: SD-057-240703-094263-18 | B55: 2024-07-03 06:29:35 | C55: 潍坊 | D55: 80+金卡-普通区域-昌邑市-（铁通）昌邑沁园春小区-15965360226-100M-宽带上网投诉-次数0-202407030000093939 | E55: 2024-07-03 19:00:00 | F55: 202407030000093939 | G55: 202407030000093939#【已关注中国移动10086微信公众号】流程受理流水号：20240703062917159653602261000106 客户号码:15965360226 客户姓名:王* 投诉地市:潍坊 来话流水:2024070306282838220845613 宽带账号:15965360226 宽带账号归属地市:潍坊 宽带账号归属区县:昌邑市 故障地址:潍坊昌邑市都昌街道山前街（铁通）昌邑沁园春小区昌邑沁园春小区A15********* 联系电话:15965360226 联系人:先生/女士 工单紧急程度:一般 是否有升级投诉倾向:否 是否重复投诉:否 是否携转意向:否 是否投诉倾向:否 是否智能网关:非智能网关 当前是否在线:否 接入方式:FTTH 端到端诊断结果:状态正常 是否质差终端:是 光功率:无 故障大类:宽带/电视 故障细类:宽带无法上网 携转原因: 故障时间:2024-07-03 06:30:33 具体故障现象:打不开网页， 客户其他诉求:客户侧为质差终端，要求上门更换终端并一并处理故障问题。 | H55: 2024-07-03 07:24:49 | I55: 家庭咨询->网络质量->家庭宽带->全局流转->功能使用->光猫设备故障->全局流转 | J55: 徐童童 | K55: 15706307209 | L55: 昌邑市 | M55: 家客铁通潍坊昌邑-城西城区装维组 | N55: 为用户调试路由器 | O55: dw3_jk_xutongtong | P55: 2024-07-03 07:25:21 | R55: =IF(OR(LEFT(L55,2)="高新"),"奎文",IF(LEFT(L55,2)="峡山","坊子",IF(LEFT(L55,2)="滨海","寒亭",LEFT(L55,2)))) -> 昌邑 | S55: =TEXT(B55,"mmdd") -> 0703
A56: SD-057-240703-348670-4393 | B56: 2024-07-03 15:18:56 | C56: 潍坊 | D56: 80+银卡-普通区域-诸城市-龙泉庄园-15863610594-500M-宽带延伸服务-次数0-202407030000454115 | E56: 2024-07-04 00:00:00 | F56: 202407030000454115 | G56: 202407030000454115#客户来电反映换过路由器后监控连接不上显示网关未激活解绑未恢复请协助谢谢；联系电话；18853632162；联系人；女士；来电流水；2024070315115961420863606；地址；潍坊诸城市密州街道东武街龙泉庄园 | H56: 2024-07-03 15:22:44 | I56: 业务受理->宽带延伸服务->家庭业务->全局流转->功能使用->代装终端->全局流转 | J56: 李梦超 | K56: 15706307958 | L56: 诸城市 | M56: 家客铁通潍坊诸城-兴华东路城区装维组 | N56: 重新调试终端 | O56: dw3_jk_limengchao | P56: 2024-07-03 15:24:03 | Q56: SD-851-298839-3640-5065 | R56: =IF(OR(LEFT(L56,2)="高新"),"奎文",IF(LEFT(L56,2)="峡山","坊子",IF(LEFT(L56,2)="滨海","寒亭",LEFT(L56,2)))) -> 诸城 | S56: =TEXT(B56,"mmdd") -> 0703
A57: SD-057-240703-382960-6457 | B57: 2024-07-03 19:03:29 | C57: 潍坊 | D57: 80+普通-普通区域-潍城区-金源公寓-15165369037-1000M-宽带上网投诉-次数0-202407030000661874 | E57: 2024-07-04 19:00:00 | F57: 202407030000661874 | G57: 202407030000661874#【已关注中国移动10086微信公众号】流程受理流水号：20240703185956151653690371183096 客户号码:15165369037 客户姓名:刘** 投诉地市:潍坊 来话流水:2024070318564165920868355 宽带账号:15165369037 宽带账号归属地市:潍坊 宽带账号归属区县:潍城区 故障地址:潍坊高新区祥泰世家西门 联系电话:13721971517 联系人:女士 工单紧急程度:非常紧急 是否有升级投诉倾向:否 是否重复投诉:否 是否携转意向:否 是否投诉倾向:否 是否智能网关:智能网关 当前是否在线:是 接入方式:FTTH 端到端诊断结果:客户侧设备问题（新增） 是否质差终端:无质差信息 光功率:-19.58 故障大类:宽带/电视 故障细类:宽带无法上网(专席) 携转原因: 故障时间:2024-07-03 19:00:05 具体故障现象:光猫亮红灯，客户来电反映宽带无法上网，我处核实到光信号亮红灯，将光纤线插紧弄直后未恢复，请协助处理谢谢 客户其他诉求: ;宽带小区$[金源公寓]$ | H57: 2024-07-03 19:08:18 | I57: 家宽咨询->网络质量->家庭宽带->全局流转->功能使用->部分网页内容无法正常访问->全局流转 | J57: 张传阳 | K57: 15706307885 | L57: 潍城区 | M57: 家客铁通潍坊潍城-胜利街城区装维组 | N57: 重启终端 | O57: dw3_jk_zhangchuanyang | P57: 2024-07-03 19:08:50 | Q57: SD-851-279535-9603-8529 | R57: =IF(OR(LEFT(L57,2)="高新"),"奎文",IF(LEFT(L57,2)="峡山","坊子",IF(LEFT(L57,2)="滨海","寒亭",LEFT(L57,2)))) -> 潍城 | S57: =TEXT(B57,"mmdd") -> 0703
A58: SD-057-240703-425963-2406 | B58: 2024-07-03 11:53:06 | C58: 潍坊 | D58: 普通区域-寿光市-羊口保障房小区-13792222700-200M-宽带上网投诉-次数0-20240703115028X628734226 | E58: 2024-07-04 12:54:00 | F58: 20240703115028X628734226 | G58: 流程受理流水号：20240703114936137922227001070125 客户号码:13792222700 客户姓名:赵** 投诉地市:德州 来话流水:2024070311490425620868226 宽带账号:13792222700 宽带账号归属地市:德州 宽带账号归属区县:寿光市 故障地址:潍坊寿光市羊口镇学府街羊口保障房小区三期29号楼********* 联系电话:13792222700 联系人:先生/女士 工单紧急程度:紧急 是否有升级投诉倾向:否 是否重复投诉:否 是否携转意向:否 是否投诉倾向:否 是否智能网关:智能网关 当前是否在线:否 接入方式:FTTH 端到端诊断结果:状态正常 是否质差终端:无质差信息 光功率:无 故障大类:宽带/电视 故障细类:宽带无法上网 携转原因: 故障时间:2024-07-03 11:50:06 具体故障现象:光猫亮红灯， 客户其他诉求: | H58: 2024-07-03 11:54:56 | I58: 家宽业务->网络质量->家庭宽带->全局流转->功能使用->LOS红灯，无法上网->全局流转 | J58: 张鹏 | K58: 15706307827 | L58: 寿光市 | M58: 家客铁通潍坊寿光-羊口乡镇装维组 | N58: 重新熔缆 | O58: dw3_jk_zhangpeng | P58: 2024-07-03 11:55:22 | Q58: SD-851-289782-426-1231 | R58: =IF(OR(LEFT(L58,2)="高新"),"奎文",IF(LEFT(L58,2)="峡山","坊子",IF(LEFT(L58,2)="滨海","寒亭",LEFT(L58,2)))) -> 寿光 | S58: =TEXT(B58,"mmdd") -> 0703
A59: SD-057-240703-452789-7039 | B59: 2024-07-03 19:46:52 | C59: 潍坊 | D59: 普通区域-昌邑市-埠头自然村-15269617731-300M-宽带上网投诉-次数0-202407030000685442 | E59: 2024-07-04 19:00:00 | F59: 202407030000685442 | G59: 202407030000685442#导航立单,客户通过语音导航反馈宽带故障问题,经诊断光猫设备性能不佳,要求装维回访处理,请协助.联系电话：15269617731 | H59: 2024-07-03 19:48:29 | I59: 家庭咨询->网络质量->家庭宽带->全局流转->功能使用->光猫设备故障->全局流转 | J59: 翟旭辉 | K59: 15706307193 | L59: 昌邑市 | M59: 家客铁通潍坊昌邑-饮马乡镇装维组 | N59: 更换皮线或网线 | O59: dw3_jk_zhaixuhui | P59: 2024-07-03 19:53:58 | R59: =IF(OR(LEFT(L59,2)="高新"),"奎文",IF(LEFT(L59,2)="峡山","坊子",IF(LEFT(L59,2)="滨海","寒亭",LEFT(L59,2)))) -> 昌邑 | S59: =TEXT(B59,"mmdd") -> 0703
A60: SD-057-240703-720534-294 | B60: 2024-07-03 08:38:18 | C60: 潍坊 | D60: 普通区域-诸城市-新郎商贸城-15005361220-300M-宽带上网投诉-次数0-202407030000095012 | E60: 2024-07-04 08:00:00 | F60: 202407030000095012 | G60: 202407030000095012#宽带账号：15005361220；宽带地址：潍坊诸城市密州街道人民东路新郎商贸城新郎商贸城7#箱*********；客户来电反映宽带 不能看，客户不在现场，无法配合线上指导/客户不配合排障，要求上门，请协助处理，谢谢！联系电话：***；联系人：18369688688；来电流水：2024070308360597220849878。 | H60: 2024-07-03 08:40:09 | I60: 家庭咨询->网络质量->家庭宽带->全局流转->功能使用->客户要求装维上门服务->全局流转 | J60: 李梦超 | K60: 15706307958 | L60: 诸城市 | M60: 家客铁通潍坊诸城-兴华东路城区装维组 | N60: 建议用户更换路由器 | O60: dw3_jk_limengchao | P60: 2024-07-03 08:40:27 | Q60: SD-851-336270-1852-2519 | R60: =IF(OR(LEFT(L60,2)="高新"),"奎文",IF(LEFT(L60,2)="峡山","坊子",IF(LEFT(L60,2)="滨海","寒亭",LEFT(L60,2)))) -> 诸城 | S60: =TEXT(B60,"mmdd") -> 0703
A61: SD-057-240703-421965-6449 | B61: 2024-07-03 19:02:38 | C61: 潍坊 | D61: 【调研】-80+银卡-普通区域-寿光市-防疫站小区-15853661612-1000M-宽带上网投诉-次数0-20240703190107X467526156 | E61: 2024-07-04 19:00:00 | F61: 20240703190107X467526156 | G61: 流程受理流水号：20240703190035158536616121183209 客户号码:15853661612 客户姓名:曹** 投诉地市:潍坊 来话流水:2024070318563366920867420 宽带账号:15853661612 宽带账号归属地市:潍坊 宽带账号归属区县:寿光市 故障地址:潍坊寿光市圣城街道永安路防疫站小区1号楼********* 联系电话:15853661612 联系人:先生/女士 工单紧急程度:非常紧急 是否有升级投诉倾向:否 是否重复投诉:否 是否携转意向:否 是否投诉倾向:否 是否智能网关:智能网关 当前是否在线:是 接入方式:FTTH 端到端诊断结果:客户侧设备问题（新增） 是否质差终端:无质差信息 光功率:-18.04 故障大类:宽带/电视 故障细类:宽带无法上网(专席) 携转原因: 故障时间:2024-07-03 18:58:44 具体故障现象:宽带在线无法使用：网口指示灯正常，网线连接正确，外接路由器，未操作恢复出厂或者换新，指导断电重启设备无效，请协助处理，谢谢 客户其他诉求: | H61: 2024-07-03 19:04:00 | I61: 家宽业务->网络质量->家庭宽带->全局流转->功能使用->网络无法连接->全局流转 | J61: 王晓宁 | K61: 15053691091 | L61: 寿光市 | M61: 家客铁通潍坊寿光-西城城区装维组 | O61: dw3_jk_wangxiaoning | P61: 2024-07-03 19:04:31 | Q61: SD-851-296023-1532-23084 | R61: =IF(OR(LEFT(L61,2)="高新"),"奎文",IF(LEFT(L61,2)="峡山","坊子",IF(LEFT(L61,2)="滨海","寒亭",LEFT(L61,2)))) -> 寿光 | S61: =TEXT(B61,"mmdd") -> 0703
A62: SD-057-240703-859170-6500 | B62: 2024-07-03 19:06:54 | C62: 潍坊 | D62: 普通区域-青州市-北关村-15105366202-1000M-业务受理宽带-次数0-202407030000662126 | E62: 2024-07-04 18:00:00 | F62: 202407030000662126 | G62: 202407030000662126#【已关注中国移动10086微信公众号】 宽带账号:15105366202; 联系电话：15105366202，问题类型：此工单为群障修复工单，根据群障全量闭环修复管理要求，为确保客户网络通畅，请装维人员跟进修复网络问题，谢谢！ 群障标题：公告。故障描述：分支光纤断或OLT检测不到ONT的预期的光信号(LOSi/LOBi)主叫号码：15105366202.0;该号码仅供参考，请优先联系宽带账号。 | H62: 2024-07-03 19:24:53 | I62: 业务受理->线上义诊->家庭业务->全局流转->功能使用->群障弹窗->全局流转 | J62: 许振山 | K62: 15706307646 | L62: 青州市 | M62: 家客铁通潍坊青州-云门路城区装维组 | O62: dw3_jk_xuzhenshan | P62: 2024-07-03 19:26:31 | R62: =IF(OR(LEFT(L62,2)="高新"),"奎文",IF(LEFT(L62,2)="峡山","坊子",IF(LEFT(L62,2)="滨海","寒亭",LEFT(L62,2)))) -> 青州 | S62: =TEXT(B62,"mmdd") -> 0703
A63: SD-057-240703-986705-2408 | B63: 2024-07-03 11:53:13 | C63: 潍坊 | D63: 普通区域-临朐县-营子自然村-15163618056-1000M-宽带上网投诉-次数0-20240703115046X646881104 | E63: 2024-07-04 08:00:00 | F63: 20240703115046X646881104 | G63: 【农村网络投诉】流程受理流水号：20240703114806151636180561069694 客户号码:15163618056 客户姓名:张** 投诉地市:潍坊 来话流水:2024070311471166420843799 宽带账号:15163618056 宽带账号归属地市:潍坊 宽带账号归属区县:临朐县 故障地址:潍坊临朐县东城街道营子营子自然村营子（扩容）5号箱王斌（外墙）********* 联系电话:13583682449 联系人:先生/女士 工单紧急程度:非常紧急 是否有升级投诉倾向:否 是否重复投诉:否 是否携转意向:否 是否投诉倾向:否 是否智能网关:智能网关 当前是否在线:否 接入方式:FTTH 端到端诊断结果:状态正常 是否质差终端:无质差信息 光功率:无 故障大类:宽带/电视 故障细类:宽带无法上网 携转原因: 故障时间:2024-07-03 11:47:52 具体故障现象:用户无法提供具体故障现象， 客户其他诉求: | H63: 2024-07-03 11:55:10 | I63: 家宽业务->网络质量->家庭宽带->全局流转->功能使用->网络无法连接->全局流转 | J63: 赵睿 | K63: 19853686624 | L63: 临朐县 | M63: 家客铁通潍坊临朐-东城城区装维组 | N63: 更换法兰头 | O63: dw3_jk_zhaorui | P63: 2024-07-03 11:56:19 | Q63: SD-851-274484-17295-24084 | R63: =IF(OR(LEFT(L63,2)="高新"),"奎文",IF(LEFT(L63,2)="峡山","坊子",IF(LEFT(L63,2)="滨海","寒亭",LEFT(L63,2)))) -> 临朐 | S63: =TEXT(B63,"mmdd") -> 0703
A64: SD-057-240703-032658-6858 | B64: 2024-07-03 19:26:29 | C64: 潍坊 | D64: 【调研】-(目标)普通区域-临朐县-如意家园-13805366516-300M-魔百和投诉-次数0-202407030000675928 | E64: 2024-07-04 19:00:00 | F64: 202407030000675928 | G64: 202407030000675928#流程受理流水号：20240703192528138053665161187704 客户号码:13805366516 客户姓名:张** 投诉地市:潍坊 来话流水:2024070319195106020827295 宽带账号:13805366516 宽带账号归属地市:潍坊 宽带账号归属区县:临朐县 故障地址:潍坊临朐县城关街道工业街如意家园6号楼********* 联系电话:13805366516 联系人:先生 工单紧急程度:一般 是否有升级投诉倾向:否 是否重复投诉:否 是否携转意向:否 是否投诉倾向:否 是否智能网关:智能网关 当前是否在线:是 接入方式:FTTH 端到端诊断结果:客户侧设备问题（新增） 是否质差终端:无质差信息 光功率:-25.37 故障大类:宽带/电视 故障细类:移动高清电视故障(专席) 携转原因: 故障时间:2024-07-03 19:27:30 魔百和单播/组播:组播 具体故障现象:电视直播或点播无法观看， 客户其他诉求: 魔百和单/组播：组播;宽带小区$[如意家园]$ | H64: 2024-07-03 19:29:37 | I64: 家庭咨询->产品质量->互联网电视(移动高清)->全局流转->售后服务->电视机提示“无信号”->全局流转 | J64: 谭龙杰 | K64: 15706307558 | L64: 临朐县 | M64: 家客铁通潍坊临朐-城关城区装维组 | N64: 重启或检修后恢复 | O64: dw3_jk_tanlongjie | P64: 2024-07-03 19:29:57 | R64: =IF(OR(LEFT(L64,2)="高新"),"奎文",IF(LEFT(L64,2)="峡山","坊子",IF(LEFT(L64,2)="滨海","寒亭",LEFT(L64,2)))) -> 临朐 | S64: =TEXT(B64,"mmdd") -> 0703
A65: SD-057-240703-857012-3946 | B65: 2024-07-03 14:32:30 | C65: 潍坊 | D65: 普通区域-坊子区-张家庄自然村-18706674188-1000M-宽带上网投诉-次数0-20240703143156X316680369 | E65: 2024-07-04 08:00:00 | F65: 20240703143156X316680369 | G65: 【农村网络投诉】流程受理流水号：20240703143045187066741881108483 客户号码:18706674188 客户姓名:郭** 投诉地市:潍坊 来话流水:2024070314293373820882424 宽带账号:18706674188 宽带账号归属地市:潍坊 宽带账号归属区县:坊子区 故障地址:潍坊坊子区黄旗堡街道张家庄村张家庄自然村潍坊坊子黄旗堡张家庄扩容08号分纤箱********* 联系电话:18706674188 联系人:先生/女士 工单紧急程度:非常紧急 是否有升级投诉倾向:否 是否重复投诉:否 是否携转意向:否 是否投诉倾向:否 是否智能网关:智能网关 当前是否在线:否 接入方式:FTTH 端到端诊断结果:状态正常 是否质差终端:无质差信息 光功率:无 故障大类:宽带/电视 故障细类:宽带无法上网(专席) 携转原因: 故障时间:2024-07-03 14:27:07 具体故障现象:光猫亮红灯，把光猫后面的光纤线插紧，捋直，重启也不行。 客户其他诉求: | H65: 2024-07-03 14:39:11 | I65: 家宽业务->网络质量->家庭宽带->全局流转->功能使用->网络无法连接->全局流转 | J65: 王松业 | K65: 15706307916 | L65: 坊子区 | M65: 家客铁通潍坊坊子-王家庄乡镇装维组 | N65: 重新熔接皮线 | O65: dw3_jk_wangsongye | P65: 2024-07-03 14:44:35 | Q65: SD-851-252460-29218-7265 | R65: =IF(OR(LEFT(L65,2)="高新"),"奎文",IF(LEFT(L65,2)="峡山","坊子",IF(LEFT(L65,2)="滨海","寒亭",LEFT(L65,2)))) -> 坊子 | S65: =TEXT(B65,"mmdd") -> 0703
A66: SD-057-240703-253071-4372 | B66: 2024-07-03 15:17:09 | C66: 潍坊 | D66: 普通区域-高密市-柴沟村自然村-15054428382-300M-宽带上网投诉-次数0-20240703151459X899474713 | E66: 2024-07-04 08:00:00 | F66: 20240703151459X899474713 | G66: 【农村网络投诉】检测结果：1、手机账号余额检测：手机账户余额正常；2、宽带账号登录状态检测：账号登录状态正常；3、宽带速率检测：宽带速率正常；4、宽带状态检测：宽带状态正常；5、群体故障检测：存在大面积群障；6、线路检测：线路状态异常；7、光猫在线检测：光猫不在线；故障类型：网络无法连接。故障描述：最近天天断网 服务不到位 你们是不是赔偿。联系人：邱法启。联系电话：15054428382。。 | H66: 2024-07-03 15:19:14 | I66: 家宽业务->网络质量->家庭宽带->全局流转->功能使用->网络无法连接->全局流转 | J66: 郑义 | K66: 15706307306 | L66: 高密市 | M66: 家客铁通潍坊高密-柴沟乡镇装维组 | N66: 重新熔接皮线 | O66: dw3_jk_zhengyi | P66: 2024-07-03 15:19:48 | R66: =IF(OR(LEFT(L66,2)="高新"),"奎文",IF(LEFT(L66,2)="峡山","坊子",IF(LEFT(L66,2)="滨海","寒亭",LEFT(L66,2)))) -> 高密 | S66: =TEXT(B66,"mmdd") -> 0703
A67: SD-057-240703-348052-6471 | B67: 2024-07-03 19:05:18 | C67: 潍坊 | D67: 普通区域-高密市-山水名苑-15064608833-300M-宽带上网投诉-次数0-20240703190249X569030415 | E67: 2024-07-04 19:00:00 | F67: 20240703190249X569030415 | G67: 流程受理流水号：20240703190058150646088331183282 客户号码:15064608833 客户姓名:李** 投诉地市:潍坊 来话流水:2024070319003036620895968 宽带账号:15064608833 宽带账号归属地市:潍坊 宽带账号归属区县:高密市 故障地址:潍坊高密市醴泉街道站南街山水名苑19号楼********* 联系电话:15064608833 联系人:先生/女士 工单紧急程度:一般 是否有升级投诉倾向:否 是否重复投诉:否 是否携转意向:否 是否投诉倾向:否 是否智能网关:智能网关 当前是否在线:否 接入方式:FTTH 端到端诊断结果:状态正常 是否质差终端:无质差信息 光功率:无 故障大类:宽带/电视 故障细类:宽带无法上网(专席) 携转原因: 故障时间:2024-07-03 19:01:48 具体故障现象:光信号红灯:屡直插紧光纤线,重启，未恢复 客户其他诉求:要求取消宽带并退还费用， | H67: 2024-07-03 19:06:52 | I67: 家宽业务->网络质量->家庭宽带->全局流转->功能使用->网络无法连接->全局流转 | J67: 张建华 | K67: 15706307318 | L67: 高密市 | M67: 家客铁通潍坊高密-醴泉城区装维组 | N67: 重新熔接线缆 | O67: dw3_jk_zhangjianhua | P67: 2024-07-03 19:07:13 | Q67: SD-851-249884-17297-22738 | R67: =IF(OR(LEFT(L67,2)="高新"),"奎文",IF(LEFT(L67,2)="峡山","坊子",IF(LEFT(L67,2)="滨海","寒亭",LEFT(L67,2)))) -> 高密 | S67: =TEXT(B67,"mmdd") -> 0703
A68: SD-057-240703-796835-4363 | B68: 2024-07-03 15:15:51 | C68: 潍坊 | D68: 【调研】-80+银卡-(目标)普通区域--null--宽带上网投诉-次数0-202407030000427843 | E68: 2024-07-04 15:16:00 | F68: 202407030000427843 | G68: 202407030000427843#*YWDZ01 服务号码：15053651789， 号码归属地：潍坊寿光 ， 请查原因； 用户品牌：全球通； 是否外呼开通：否； 客户质疑：2022版宽带提速包（硬件专用）、（硬件专用-分月）30元/月下行提速至1000M，上行提速至50M，客户表示拿到设备了，但忙未安装，对每月扣费不认可，且办理时未告知费用 接触录音流水号：2024070314473588520830526；联系电话：15053651789； 受理明细：536240329927123752，争议业务名称：（硬件专用-分月）30元/月下行提速至1000M，上行提速至50M，刘**，15053651789，产品变更，2024-03-29 20:49:11,刘鑫平(f226703c)，寿光-化龙-随销泛渠道-中移铁通(SD.LF.02.02.66.17.0H)； 备注： | I68: 家庭咨询->网络质量->家庭宽带->全局流转->功能使用->网络无法连接->全局流转 | R68: =IF(OR(LEFT(L68,2)="高新"),"奎文",IF(LEFT(L68,2)="峡山","坊子",IF(LEFT(L68,2)="滨海","寒亭",LEFT(L68,2)))) | S68: =TEXT(B68,"mmdd") -> 0703
A69: SD-057-240703-205137-6528 | B69: 2024-07-03 19:08:10 | C69: 潍坊 | D69: 普通区域-高密市-代家屯-13666363833-300M-业务受理宽带-次数0-202407030000662806 | E69: 2024-07-04 18:00:00 | F69: 202407030000662806 | G69: 202407030000662806# 宽带账号:13666363833; 联系电话：13666363833，问题类型：此工单为群障修复工单，根据群障全量闭环修复管理要求，为确保客户网络通畅，请装维人员跟进修复网络问题，谢谢！ 群障标题：告警。故障标题：LINK_LOSS主叫号码：17866630290.0;该号码仅供参考，请优先联系宽带账号。 | H69: 2024-07-03 19:13:17 | I69: 业务受理->线上义诊->家庭业务->全局流转->功能使用->群障弹窗->全局流转 | J69: 张金磊 | K69: 15706307305 | L69: 高密市 | M69: 家客铁通潍坊高密-朝阳城区装维组 | N69: 重新熔缆 | O69: dw3_jk_zhangjinlei | Q69: SD-851-326931-25459-4070 | R69: =IF(OR(LEFT(L69,2)="高新"),"奎文",IF(LEFT(L69,2)="峡山","坊子",IF(LEFT(L69,2)="滨海","寒亭",LEFT(L69,2)))) -> 高密 | S69: =TEXT(B69,"mmdd") -> 0703
A70: SD-057-240703-096124-2461 | B70: 2024-07-03 11:59:33 | C70: 潍坊 | D70: 80+金卡-普通区域-临朐县-景观小区-15949855985-500M-魔百和投诉-次数0-202407030000306142 | E70: 2024-07-04 08:00:00 | F70: 202407030000306142 | G70: 202407030000306142#流程受理流水号：20240703115509159498559851071857 客户号码:15949855985 客户姓名:郝* 投诉地市:潍坊 来话流水:2024070311535469320829152 宽带账号:15949855985 宽带账号归属地市:潍坊 宽带账号归属区县:临朐县 故障地址:潍坊临朐县城关街道新华路景观小区2号楼2—402********* 联系电话:15949855985 联系人:先生 工单紧急程度:一般 是否有升级投诉倾向:否 是否重复投诉:否 是否携转意向:否 是否投诉倾向:否 是否智能网关:智能网关 当前是否在线:是 接入方式:FTTH 端到端诊断结果:客户侧设备问题（新增） 是否质差终端:无质差信息 光功率:-16.73 故障大类:宽带/电视 故障细类:移动高清电视故障(专席) 携转原因: 故障时间:2024-07-03 11:56:54 魔百和单播/组播:组播 具体故障现象:客户来电反映机顶盒亮红灯，拔插过网线重启过机顶盒未恢复，拒绝排障 客户其他诉求: 魔百和单/组播：组播;宽带小区$[景观小区]$ | H70: 2024-07-03 12:04:59 | I70: 家庭咨询->产品质量->互联网电视(移动高清)->全局流转->售后服务->电视机提示“无信号”->全局流转 | J70: 尹筱 | K70: 15706307601 | L70: 临朐县 | M70: 家客铁通潍坊临朐-城关城区装维组 | N70: 指导用户正确使用遥控器 | O70: dw3_jk_yinxiao | P70: 2024-07-03 12:05:34 | R70: =IF(OR(LEFT(L70,2)="高新"),"奎文",IF(LEFT(L70,2)="峡山","坊子",IF(LEFT(L70,2)="滨海","寒亭",LEFT(L70,2)))) -> 临朐 | S70: =TEXT(B70,"mmdd") -> 0703
A71: SD-057-240703-735402-2504 | B71: 2024-07-03 12:05:27 | C71: 潍坊 | D71: 【调研】-80+白金-普通区域-潍城区-恒信玫瑰公馆二期-15953692822-1000M-宽带上网投诉-次数0-20240703120359X439850191 一级督办 | E71: 2024-07-04 08:00:00 | F71: 20240703120359X439850191 | G71: 流程受理流水号：20240703120102159536928221073605 客户号码:15953692822 客户姓名:杨** 投诉地市:潍坊 来话流水:2024070311591672620893501 宽带账号:15953692822 宽带账号归属地市:潍坊 宽带账号归属区县:潍城区 故障地址:潍坊潍城区北关街道永安路恒信玫瑰公馆二期13号楼********* 联系电话:15953692822 联系人:先生/女士 工单紧急程度:非常紧急 是否有升级投诉倾向:否 是否重复投诉:否 是否携转意向:否 是否投诉倾向:否 是否智能网关:智能网关 当前是否在线:是 接入方式:FTTH 端到端诊断结果:客户侧设备问题（新增） 是否质差终端:无质差信息 光功率:-22.67 故障大类:宽带/电视 故障细类:网速慢/上网掉线(专席) 携转原因: 故障时间:2024-07-03 12:01:03 具体故障现象:光猫频繁掉线，重启设备未恢复，客户要求换工作人员处理，客户要求换光猫设备，解释不认可，请核实处理谢谢 客户其他诉求: | H71: 2024-07-03 12:08:21 | I71: 家宽业务->网络质量->家庭宽带->全局流转->功能使用->频繁出现故障、网速慢->全局流转 | J71: 付光杰 | K71: 15706307897 | L71: 潍城区 | M71: 家客铁通潍坊潍城-和平路城区装维组 | O71: dw3_jk_wcfuguangjie | P71: 2024-07-03 12:10:38 | Q71: SD-851-261304-3390-2604 | R71: =IF(OR(LEFT(L71,2)="高新"),"奎文",IF(LEFT(L71,2)="峡山","坊子",IF(LEFT(L71,2)="滨海","寒亭",LEFT(L71,2)))) -> 潍城 | S71: =TEXT(B71,"mmdd") -> 0703
A72: SD-057-240703-652783-6520 | B72: 2024-07-03 19:07:53 | C72: 潍坊 | D72: 【调研】-80+银卡-普通区域-诸城市-王家清河-13964695183-300M-业务受理宽带-次数0-202407030000663731 | E72: 2024-07-04 18:00:00 | F72: 202407030000663731 | G72: 202407030000663731# 宽带账号:13964695183; 联系电话：13964695183，问题类型：此工单为群障修复工单，根据群障全量闭环修复管理要求，为确保客户网络通畅，请装维人员跟进修复网络问题，谢谢！ 群障标题：公告。故障描述：分支光纤断或OLT检测不到ONT的预期的光信号(LOSi/LOBi)主叫号码：13964695183.0;该号码仅供参考，请优先联系宽带账号。 | H72: 2024-07-03 19:10:40 | I72: 业务受理->线上义诊->家庭业务->全局流转->功能使用->群障弹窗->全局流转 | J72: 周宝龙 | K72: 15706307992 | L72: 诸城市 | M72: 家客铁通潍坊诸城-石桥子乡镇装维组 | O72: dw3_jk_zhoubaolong | P72: 2024-07-03 19:11:29 | R72: =IF(OR(LEFT(L72,2)="高新"),"奎文",IF(LEFT(L72,2)="峡山","坊子",IF(LEFT(L72,2)="滨海","寒亭",LEFT(L72,2)))) -> 诸城 | S72: =TEXT(B72,"mmdd") -> 0703
A73: SD-057-240703-197305-2469 | B73: 2024-07-03 11:59:51 | C73: 潍坊 | D73: 【调研】-普通区域-寿光市-羊口保障房小区-15853620644-300M-宽带上网投诉-次数0-202407030000305472 | E73: 2024-07-04 08:00:00 | F73: 202407030000305472 | G73: 202407030000305472#流程受理流水号：20240703115824158536206441072847 客户号码:15853620644 客户姓名:董* 投诉地市:潍坊 来话流水:2024070311574158520875112 宽带账号:15853620644 宽带账号归属地市:潍坊 宽带账号归属区县:寿光市 故障地址:潍坊寿光市羊口镇学府街羊口保障房小区南区5号楼********* 联系电话:15853620644 联系人:女士 工单紧急程度:非常紧急 是否有升级投诉倾向:否 是否重复投诉:否 是否携转意向:否 是否投诉倾向:否 是否智能网关:智能网关 当前是否在线:是 接入方式:FTTH 端到端诊断结果:客户侧设备问题 是否质差终端:是 光功率:-18.89 故障大类:宽带/电视 故障细类:移动高清电视故障 携转原因: 故障时间:2024-07-03 11:58:59 魔百和单播/组播:组播 具体故障现象:电视提示网络类错误， 客户其他诉求:客户侧为质差终端，要求上门更换终端并一并处理故障问题。 | H73: 2024-07-03 12:00:45 | I73: 家庭咨询->网络质量->家庭宽带->全局流转->功能使用->光猫设备故障->全局流转 | J73: 张鹏 | K73: 15706307827 | L73: 寿光市 | M73: 家客铁通潍坊寿光-羊口乡镇装维组 | N73: 重新熔缆 | O73: dw3_jk_zhangpeng | P73: 2024-07-03 12:01:14 | R73: =IF(OR(LEFT(L73,2)="高新"),"奎文",IF(LEFT(L73,2)="峡山","坊子",IF(LEFT(L73,2)="滨海","寒亭",LEFT(L73,2)))) -> 寿光 | S73: =TEXT(B73,"mmdd") -> 0703
A74: SD-057-240703-352189-6789 | B74: 2024-07-03 19:20:07 | C74: 潍坊 | D74: 普通区域-诸城市-邱家七吉自然村-13953667727-300M-宽带上网投诉-次数0-20240703191752X472733894 | E74: 2024-07-04 19:00:00 | F74: 20240703191752X472733894 | G74: 【农村网络投诉】流程受理流水号：20240703191627139536677271186160 客户号码:13953667727 客户姓名:孙** 投诉地市:潍坊 来话流水:2024070319154601120800069 宽带账号:13953667727 宽带账号归属地市:潍坊 宽带账号归属区县:诸城市 故障地址:潍坊诸城市龙都街道邱家七吉邱家七吉自然村邱家七吉村116号 联系电话:13953667727 联系人:先生 工单紧急程度:一般 是否有升级投诉倾向:否 是否重复投诉:否 是否携转意向:否 是否投诉倾向:否 是否智能网关:智能网关 当前是否在线:否 接入方式:FTTH 端到端诊断结果:状态正常 是否质差终端:无质差信息 光功率:无 故障大类:宽带/电视 故障细类:宽带无法上网(专席) 携转原因: 故障时间:2024-07-03 19:29:39 具体故障现象:宽带无法上网， 客户其他诉求: | H74: 2024-07-03 19:27:15 | I74: 家宽业务->网络质量->家庭宽带->全局流转->功能使用->网络无法连接->全局流转 | J74: 王智伟 | K74: 15706307970 | L74: 诸城市 | M74: 家客铁通潍坊诸城-兴华西路城区装维组 | O74: dw3_jk_wangzhiwei | P74: 2024-07-03 19:28:09 | R74: =IF(OR(LEFT(L74,2)="高新"),"奎文",IF(LEFT(L74,2)="峡山","坊子",IF(LEFT(L74,2)="滨海","寒亭",LEFT(L74,2)))) -> 诸城 | S74: =TEXT(B74,"mmdd") -> 0703
A75: SD-057-240703-572913-6519 | B75: 2024-07-03 19:07:48 | C75: 潍坊 | D75: 普通区域-高密市-大屯自然村-15966107647-300M-业务受理宽带-次数0-202407030000663495 | E75: 2024-07-04 18:00:00 | F75: 202407030000663495 | G75: 202407030000663495# 宽带账号:15966107647; 联系电话：15966107647，问题类型：此工单为群障修复工单，根据群障全量闭环修复管理要求，为确保客户网络通畅，请装维人员跟进修复网络问题，谢谢！ 群障标题：告警。故障标题：分支光纤断或OLT检测不到ONT的预期的光信号(LOSi/LOBi)主叫号码：15966107647.0;该号码仅供参考，请优先联系宽带账号。 | H75: 2024-07-03 19:10:12 | I75: 业务受理->线上义诊->家庭业务->全局流转->功能使用->群障弹窗->全局流转 | J75: 官潭潭 | K75: 15706307302 | L75: 高密市 | M75: 家客铁通潍坊高密-醴泉城区装维组 | O75: dw3_jk_guantantan | P75: 2024-07-03 19:15:04 | R75: =IF(OR(LEFT(L75,2)="高新"),"奎文",IF(LEFT(L75,2)="峡山","坊子",IF(LEFT(L75,2)="滨海","寒亭",LEFT(L75,2)))) -> 高密 | S75: =TEXT(B75,"mmdd") -> 0703
A76: SD-057-240703-927534-6482 | B76: 2024-07-03 19:05:49 | C76: 潍坊 | D76: 80+普通-普通区域-青州市-后营村-15244442848-1000M-宽带上网投诉-次数0-20240703190443X683440198 | E76: 2024-07-04 19:00:00 | F76: 20240703190443X683440198 | G76: 【农村网络投诉】流程受理流水号：20240703190348152444428481183840 客户号码:15244442848 客户姓名:张** 投诉地市:潍坊 来话流水:2024070319001923820894656 宽带账号:15244442848 宽带账号归属地市:潍坊 宽带账号归属区县:青州市 故障地址:潍坊青州市弥河镇后营村后营村2号箱（东北张学富）********* 联系电话:15163682239 联系人:先生/女士 工单紧急程度:非常紧急 是否有升级投诉倾向:否 是否重复投诉:否 是否携转意向:否 是否投诉倾向:否 是否智能网关:智能网关 当前是否在线:是 接入方式:FTTH 端到端诊断结果:客户侧设备问题（新增） 是否质差终端:无质差信息 光功率:-21.30 故障大类:宽带/电视 故障细类:网速慢/上网掉线(专席) 携转原因: 故障时间:2024-07-03 19:04:00 具体故障现象:网速慢卡顿，路由器年限未超过，位置开阔，重启未恢复 客户其他诉求: | H76: 2024-07-03 19:11:45 | I76: 家宽业务->网络质量->家庭宽带->全局流转->功能使用->频繁出现故障、网速慢->全局流转 | J76: 刘霄 | K76: 15706307663 | L76: 青州市 | M76: 家客铁通潍坊青州-弥河乡镇装维组 | N76: 指导用户输入正确宽带账号密码 | O76: dw3_jk_liuxiao | P76: 2024-07-03 19:12:18 | R76: =IF(OR(LEFT(L76,2)="高新"),"奎文",IF(LEFT(L76,2)="峡山","坊子",IF(LEFT(L76,2)="滨海","寒亭",LEFT(L76,2)))) -> 青州 | S76: =TEXT(B76,"mmdd") -> 0703
A77: SD-057-240703-416920-7688 | B77: 2024-07-03 20:44:11 | C77: 潍坊 | D77: 【调研】-80+银卡-普通区域-临朐县-晨辉丽都城小区-13964639777-500M-宽带上网投诉-次数0-20240703204140X500323875 | E77: 2024-07-04 19:00:00 | F77: 20240703204140X500323875 | G77: 流程受理流水号：20240703204008139646397771198791 客户号码:13964639777 客户姓名:刘* 投诉地市:潍坊 来话流水:2024070320393708020885697 宽带账号:13964639777 宽带账号归属地市:潍坊 宽带账号归属区县:临朐县 故障地址:潍坊临朐县城关街道朐山路晨辉丽都城小区17号楼********* 联系电话:13964639777 联系人:先生/女士 工单紧急程度:一般 是否有升级投诉倾向:否 是否重复投诉:否 是否携转意向:否 是否投诉倾向:否 是否智能网关:智能网关 当前是否在线:否 接入方式:FTTH 端到端诊断结果:状态正常 是否质差终端:无质差信息 光功率:无 故障大类:宽带/电视 故障细类:宽带无法上网(专席) 携转原因: 故障时间:2024-07-03 20:38:15 具体故障现象:注册灯闪烁：引导客户将光纤线插紧，将弯折的位置捋直后重启无效，请协助处理，谢谢。 客户其他诉求: | H77: 2024-07-03 20:48:08 | I77: 家宽业务->网络质量->家庭宽带->全局流转->功能使用->网络无法连接->全局流转 | J77: 衣学全 | K77: 15706307553 | L77: 临朐县 | M77: 家客铁通潍坊临朐-城关城区装维组 | N77: 维修光交箱 | O77: dw3_jk_yixuequan | P77: 2024-07-03 20:48:42 | Q77: SD-851-303816-281-20867 | R77: =IF(OR(LEFT(L77,2)="高新"),"奎文",IF(LEFT(L77,2)="峡山","坊子",IF(LEFT(L77,2)="滨海","寒亭",LEFT(L77,2)))) -> 临朐 | S77: =TEXT(B77,"mmdd") -> 0703
A78: SD-057-240703-452198-3934 | B78: 2024-07-03 14:30:05 | C78: 潍坊 | D78: 【调研】-80+金卡-普通区域-奎文区-水印幸福城-15169699831-300M-宽带上网投诉-次数0-202407030000408827 | E78: 2024-07-04 08:00:00 | F78: 202407030000408827 | G78: 202407030000408827#【已关注中国移动10086微信公众号】流程受理流水号：20240703142938151696998311108164 客户号码:15169699831 客户姓名:王** 投诉地市:潍坊 来话流水:2024070314292504720880431 宽带账号:15169699831 宽带账号归属地市:潍坊 宽带账号归属区县:奎文区 故障地址:潍坊奎文区北苑街道北宫街水印幸福城5号楼********* 联系电话:15169699831 联系人:先生/女士 工单紧急程度:一般 是否有升级投诉倾向:否 是否重复投诉:否 是否携转意向:否 是否投诉倾向:否 是否智能网关:非智能网关 当前是否在线:否 接入方式:FTTH 端到端诊断结果:状态正常 是否质差终端:是 光功率:无 故障大类:宽带/电视 故障细类:宽带无法上网 携转原因: 故障时间:2024-07-03 14:29:44 具体故障现象:光猫亮红灯， 客户其他诉求:客户侧为质差终端，要求上门更换终端并一并处理故障问题。 | H78: 2024-07-03 14:34:02 | I78: 家庭咨询->网络质量->家庭宽带->全局流转->功能使用->光猫设备故障->全局流转 | J78: 杨明新 | K78: 15706366537 | L78: 奎文区 | M78: 家客铁通潍坊奎文-鸢飞路城区装维组 | N78: 重新熔接皮线 | O78: dw3_jk_yangmingxin | P78: 2024-07-03 14:34:31 | R78: =IF(OR(LEFT(L78,2)="高新"),"奎文",IF(LEFT(L78,2)="峡山","坊子",IF(LEFT(L78,2)="滨海","寒亭",LEFT(L78,2)))) -> 奎文 | S78: =TEXT(B78,"mmdd") -> 0703
A79: SD-057-240703-603872-3975 | B79: 2024-07-03 14:36:13 | C79: 潍坊 | D79: 80+金卡-普通区域-青州市-庙子梨园店小区-13516366148-1000M-宽带上网投诉-次数0-202407030000414738 | E79: 2024-07-04 08:00:00 | F79: 202407030000414738 | G79: 202407030000414738# 13792153552 客户来电反映用 13516366148号码办理的第二条宽带，反映已经缴费半年了没有安装，安装地址： 潍坊市青州庙子乡镇西茂峪 ，要求投诉上报，请帮助联系。联系电话：13792153552，流水： 2024070314120555120857914 | H79: 2024-07-03 14:42:12 | I79: 家庭咨询->服务触点->装维人员->全局流转->售后服务->装维人员未及时联系客户->全局流转 | J79: 刘帅 | K79: 18253601114 | L79: 青州市 | M79: 家客铁通潍坊青州-王府乡镇装维组 | N79: 已上报建设部门建设 | O79: dw3_jk_qzliushuai | P79: 2024-07-03 14:44:23 | R79: =IF(OR(LEFT(L79,2)="高新"),"奎文",IF(LEFT(L79,2)="峡山","坊子",IF(LEFT(L79,2)="滨海","寒亭",LEFT(L79,2)))) -> 青州 | S79: =TEXT(B79,"mmdd") -> 0703
A80: SD-057-240703-796542-5144 | B80: 2024-07-03 16:54:09 | C80: 潍坊 | D80: 普通区域-高密市-高密丽都花园-13863637596-100M-宽带延伸服务-次数0-202407030000550083 | E80: 2024-07-04 16:55:00 | F80: 202407030000550083 | G80: 202407030000550083#流程受理流水号：20240703164930138636375961149018 客户号码:13863637596 客户姓名:荆** 投诉地市:潍坊 来话流水:2024070316472678320879190 宽带账号:13863637596 宽带账号归属地市:潍坊 宽带账号归属区县:高密市 故障地址:潍坊高密市密水街道利群路丽都花园2号楼*** 联系电话:13863637596 联系人:先生/女士 工单紧急程度:一般 是否有升级投诉倾向:否 是否重复投诉:否 是否携转意向:否 是否投诉倾向:否 是否智能网关:智能网关 当前是否在线:是 接入方式:FTTH 是否质差终端:无质差信息 光功率:-24.43 故障大类:宽带/电视 故障细类:宽带延伸服务 携转原因: 故障时间:2024-07-03 16:48:26 具体故障现象:只有一部手机无法连网，设备重启，未恢复请处理谢谢 | H80: 2024-07-03 16:58:56 | I80: 业务受理->宽带延伸服务->家庭业务->全局流转->功能使用->代装终端->全局流转 | J80: 王鹏 | K80: 15706307289 | L80: 高密市 | M80: 家客铁通潍坊高密-密水城区装维组 | N80: 重启路由器 | O80: dw3_jk_wangpeng | P80: 2024-07-03 16:59:39 | R80: =IF(OR(LEFT(L80,2)="高新"),"奎文",IF(LEFT(L80,2)="峡山","坊子",IF(LEFT(L80,2)="滨海","寒亭",LEFT(L80,2)))) -> 高密 | S80: =TEXT(B80,"mmdd") -> 0703
A81: SD-057-240703-018634-5172 | B81: 2024-07-03 16:59:11 | C81: 潍坊 | D81: 【追1】普通区域-高密市-王家官庄自然村（夏庄恒馨家园）-18663672748-300M-宽带上网投诉-次数0-20240703165722X424773420 | E81: 2024-07-04 18:00:00 | F81: 20240703165722X424773420 | G81: 【农村网络投诉】流程受理流水号：20240703165640186636727481151159 客户号码:18663672748 客户姓名:徐** 投诉地市:潍坊 来话流水:2024070316561826920897398 宽带账号:18663672748 宽带账号归属地市:潍坊 宽带账号归属区县:高密市 故障地址:潍坊高密市夏庄镇王家官庄王家官庄自然村高密王家官庄王金昌53号箱********* 联系电话:18663672748 联系人:先生/女士 工单紧急程度:一般 是否有升级投诉倾向:否 是否重复投诉:否 是否携转意向:否 是否投诉倾向:否 是否智能网关:智能网关 当前是否在线:否 接入方式:FTTH 端到端诊断结果:状态正常 是否质差终端:无质差信息 光功率:无 故障大类:宽带/电视 故障细类:宽带无法上网 携转原因: 故障时间:2024-07-03 16:57:04 具体故障现象:光猫亮红灯， 客户其他诉求: | H81: 2024-07-03 17:41:56 | I81: 家宽业务->网络质量->家庭宽带->全局流转->功能使用->LOS红灯，无法上网->全局流转 | J81: 高强 | K81: 15706307285 | L81: 高密市 | M81: 家客铁通潍坊高密-夏庄乡镇装维组 | N81: 指导用户加固线缆 | O81: dw3_jk_gaoqiang | P81: 2024-07-03 18:42:13 | R81: =IF(OR(LEFT(L81,2)="高新"),"奎文",IF(LEFT(L81,2)="峡山","坊子",IF(LEFT(L81,2)="滨海","寒亭",LEFT(L81,2)))) -> 高密 | S81: =TEXT(B81,"mmdd") -> 0703
A82: SD-057-240703-273640-2517 | B82: 2024-07-03 12:06:51 | C82: 潍坊 | D82: 普通区域-潍城区-(铁通)华景新城-18353635768-200M-魔百和投诉-次数0-202407030000308741 | E82: 2024-07-04 13:00:00 | F82: 202407030000308741 | G82: 202407030000308741#【已关注中国移动10086微信公众号】流程受理流水号：20240703120502183536357681074612 客户号码:18353635768 客户姓名:丁** 投诉地市:潍坊 来话流水:2024070312033471920837487 宽带账号:18353635768 宽带账号归属地市:潍坊 宽带账号归属区县:潍城区 故障地址:潍坊潍城区西关街道福寿街（铁通）华景新城华景新城33号楼********* 联系电话:18353635768 联系人:女士 工单紧急程度:一般 是否有升级投诉倾向:否 是否重复投诉:否 是否携转意向:否 是否投诉倾向:否 是否智能网关:智能网关 当前是否在线:是 接入方式:FTTH 端到端诊断结果:客户侧设备问题（新增） 是否质差终端:无质差信息 光功率:-20.60 故障大类:宽带/电视 故障细类:移动高清电视故障(专席) 携转原因: 故障时间:2024-07-03 12:05:54 魔百和单播/组播:单播 具体故障现象:18353635768客户来电反映电视无法观看，请协助处理谢谢 客户其他诉求:请审核 魔百和单/组播：单播;宽带小区$[(铁通)华景新城]$ | H82: 2024-07-03 12:17:15 | I82: 家庭咨询->产品质量->互联网电视(移动高清)->全局流转->售后服务->电视机提示“无信号”->全局流转 | J82: 杨勇 | K82: 15706307911 | L82: 潍城区 | M82: 家客铁通潍坊潍城-和平路城区装维组 | N82: 重新连接机顶盒网络 | O82: dw3_jk_yangyong | R82: =IF(OR(LEFT(L82,2)="高新"),"奎文",IF(LEFT(L82,2)="峡山","坊子",IF(LEFT(L82,2)="滨海","寒亭",LEFT(L82,2)))) -> 潍城 | S82: =TEXT(B82,"mmdd") -> 0703
A83: SD-057-240703-179503-3404 | B83: 2024-07-03 13:35:17 | C83: 潍坊 | D83: 普通区域-寿光市-幸福里沿街（小微）-15266363298-100M-宽带上网投诉-次数0-20240703133226X746484554 | E83: 2024-07-04 13:00:00 | F83: 20240703133226X746484554 | G83: 流程受理流水号：20240703133105152663632981093272 客户号码:15266363298 客户姓名:王** 投诉地市:潍坊 来话流水:2024070313295768920827007 宽带账号:15266363298 宽带账号归属地市:潍坊 宽带账号归属区县:寿光市 故障地址:潍坊寿光市洛城街道圣城街幸福里沿街（小微）2号箱********* 联系电话:15053635992 联系人:先生/女士 工单紧急程度:一般 是否有升级投诉倾向:否 是否重复投诉:否 是否携转意向:否 是否投诉倾向:否 是否智能网关:智能网关 当前是否在线:否 接入方式:FTTH 端到端诊断结果:状态正常 是否质差终端:无质差信息 光功率:无 故障大类:宽带/电视 故障细类:宽带无法上网(专席) 携转原因: 故障时间:2024-07-03 13:30:18 具体故障现象:客户来电反映无法上网，光信号亮红灯：拔插捋直光纤线未恢复，请处理，谢谢。 客户其他诉求: | H83: 2024-07-03 13:42:14 | I83: 家宽业务->网络质量->家庭宽带->全局流转->功能使用->网络无法连接->全局流转 | J83: 赵树全 | K83: 15169606966 | L83: 寿光市 | M83: 家客铁通潍坊寿光-洛城乡镇装维组 | N83: 重新放缆 | O83: dw3_jk_zhaoshuquan | P83: 2024-07-03 13:42:56 | R83: =IF(OR(LEFT(L83,2)="高新"),"奎文",IF(LEFT(L83,2)="峡山","坊子",IF(LEFT(L83,2)="滨海","寒亭",LEFT(L83,2)))) -> 寿光 | S83: =TEXT(B83,"mmdd") -> 0703
A84: SD-057-240703-360178-3974 | B84: 2024-07-03 14:36:05 | C84: 潍坊 | D84: 【调研】-普通区域-安丘市-苇园村自然村-15953678792-100M-宽带上网投诉-次数0-202407030000415984 | E84: 2024-07-04 15:37:00 | F84: 202407030000415984 | G84: 202407030000415984#流程受理流水号：20240703143323159536787921109232 客户号码:15953678792 客户姓名:李** 投诉地市:潍坊 来话流水:2024070314323233820823106 宽带账号:15953678792 宽带账号归属地市:潍坊 宽带账号归属区县:安丘市 故障地址:潍坊安丘市大城埠苇园村苇园村自然村苇园村东北2号箱徐守干********* 联系电话:15953678792 联系人:先生 工单紧急程度:一般 是否有升级投诉倾向:否 是否重复投诉:否 是否携转意向:否 是否投诉倾向:否 是否智能网关:非智能网关 当前是否在线:否 接入方式:FTTH 端到端诊断结果:状态正常 是否质差终端:是 光功率:无 故障大类:宽带/电视 故障细类:宽带无法上网 携转原因: 故障时间:2024-07-03 14:34:20 具体故障现象:光猫亮红灯， 客户其他诉求:客户侧为质差终端，要求上门更换终端并一并处理故障问题。 | H84: 2024-07-03 14:50:47 | I84: 家庭咨询->网络质量->家庭宽带->全局流转->功能使用->光猫设备故障->全局流转 | J84: 孙浩 | K84: 15706307039 | L84: 安丘市 | M84: 家客铁通潍坊安丘-潍安路城区装维组 | N84: 更换皮线或网线 | O84: dw3_jk_sunhao | P84: 2024-07-03 14:51:22 | R84: =IF(OR(LEFT(L84,2)="高新"),"奎文",IF(LEFT(L84,2)="峡山","坊子",IF(LEFT(L84,2)="滨海","寒亭",LEFT(L84,2)))) -> 安丘 | S84: =TEXT(B84,"mmdd") -> 0703
A85: SD-057-240703-215768-5152 | B85: 2024-07-03 16:56:08 | C85: 潍坊 | D85: 普通区域-奎文区-油坊小区-13655364545-1000M-宽带上网投诉-次数0-20240703165343X823244881 | E85: 2024-07-04 17:57:00 | F85: 20240703165343X823244881 | G85: 流程受理流水号：20240703165221136553645451149868 客户号码:13655364545 客户姓名:陈** 投诉地市:潍坊 来话流水:2024070316505348920825101 宽带账号:13655364545 宽带账号归属地市:潍坊 宽带账号归属区县:高新 故障地址:潍坊高新高新城区健康街油坊小区4号楼********* 联系电话:15094967968 联系人:先生/女士 工单紧急程度:非常紧急 是否有升级投诉倾向:否 是否重复投诉:否 是否携转意向:否 是否投诉倾向:否 是否智能网关:智能网关 当前是否在线:是 接入方式:FTTH 端到端诊断结果:客户侧设备问题（新增） 是否质差终端:无质差信息 光功率:-18.82 故障大类:宽带/电视 故障细类:网速慢/上网掉线(专席) 携转原因: 故障时间:2024-07-03 16:50:04 具体故障现象:清平小区 客户其他诉求: | H85: 2024-07-03 16:58:41 | I85: 家宽业务->网络质量->家庭宽带->全局流转->功能使用->频繁出现故障、网速慢->全局流转 | J85: 李先圣 | K85: 15706307393 | L85: 奎文区 | M85: 家客铁通潍坊奎文-健康街城区装维组 | N85: 更换水晶头 | O85: dw3_jk_lixiansheng | P85: 2024-07-03 16:59:13 | Q85: SD-851-273601-27482-6377 | R85: =IF(OR(LEFT(L85,2)="高新"),"奎文",IF(LEFT(L85,2)="峡山","坊子",IF(LEFT(L85,2)="滨海","寒亭",LEFT(L85,2)))) -> 奎文 | S85: =TEXT(B85,"mmdd") -> 0703
A86: SD-057-240703-237615-5158 | B86: 2024-07-03 16:56:39 | C86: 潍坊 | D86: 普通区域-寒亭区-元和新城-15163615099-300M-宽带上网投诉-次数0-202407030000552400 一级督办 | E86: 2024-07-04 17:57:00 | F86: 202407030000552400 | G86: 202407030000552400#流程受理流水号：20240703165457151636150991150667 客户号码:15163615099 客户姓名:董** 投诉地市:潍坊 来话流水:2024070316524804320850494 宽带账号:15163615099 宽带账号归属地市:潍坊 宽带账号归属区县:寒亭区 故障地址:潍坊寒亭区寒亭街道益新街元和新城29号楼********* 联系电话:15163615099 联系人:先生/女士 工单紧急程度:非常紧急 是否有升级投诉倾向:否 是否重复投诉:否 是否携转意向:否 是否投诉倾向:否 是否智能网关:智能网关 当前是否在线:是 接入方式:FTTH 端到端诊断结果:客户侧设备问题 是否质差终端:是 光功率:-18.96 故障大类:宽带/电视 故障细类:宽带无法上网 携转原因: 故障时间:2024-07-03 16:54:46 具体故障现象:网速慢卡顿， 客户其他诉求:客户侧为质差终端，要求上门更换终端并一并处理故障问题。 | H86: 2024-07-03 16:58:26 | I86: 家庭咨询->网络质量->家庭宽带->全局流转->功能使用->光猫设备故障->全局流转 | J86: 刘兴涛 | K86: 15706307476 | L86: 寒亭区 | M86: 家客铁通潍坊寒亭-城东城区装维组 | N86: 重启恢复 | O86: dw3_jk_liuxingtao | P86: 2024-07-03 16:59:24 | R86: =IF(OR(LEFT(L86,2)="高新"),"奎文",IF(LEFT(L86,2)="峡山","坊子",IF(LEFT(L86,2)="滨海","寒亭",LEFT(L86,2)))) -> 寒亭 | S86: =TEXT(B86,"mmdd") -> 0703
A87: SD-057-240703-084153-2401 | B87: 2024-07-03 11:52:19 | C87: 潍坊 | D87: 【调研】-(目标)普通区域-奎文区-德润铂悦-15763058300-300M-宽带上网投诉-次数0-202407030000298105 | E87: 2024-07-04 08:00:00 | F87: 202407030000298105 | G87: 202407030000298105#流程受理流水号：20240703115104157630583001070559 客户号码:15763058300 客户姓名:李** 投诉地市:潍坊 来话流水:2024070311502300120884784 宽带账号:15763058300 宽带账号归属地市:潍坊 宽带账号归属区县:奎文区 故障地址:潍坊奎文区北苑街道玉清街德润铂悦2号楼********* 联系电话:18306403384 联系人:先生/女士 工单紧急程度:非常紧急 是否有升级投诉倾向:否 是否重复投诉:否 是否携转意向:否 是否投诉倾向:否 是否智能网关:智能网关 当前是否在线:否 接入方式:FTTH 端到端诊断结果:状态正常 是否质差终端:是 光功率:无 故障大类:宽带/电视 故障细类:宽带无法上网 携转原因: 故障时间:2024-07-03 11:51:50 具体故障现象:提示网络无法连接， 客户其他诉求:客户侧为质差终端，要求上门更换终端并一并处理故障问题。 | H87: 2024-07-03 11:56:47 | I87: 家庭咨询->网络质量->家庭宽带->全局流转->功能使用->光猫设备故障->全局流转 | J87: 王玉升 | K87: 15706366509 | L87: 奎文区 | M87: 家客铁通潍坊奎文-鸢飞路城区装维组 | N87: 更换皮线或网线 | O87: dw3_jk_wangyusheng | P87: 2024-07-03 11:57:18 | R87: =IF(OR(LEFT(L87,2)="高新"),"奎文",IF(LEFT(L87,2)="峡山","坊子",IF(LEFT(L87,2)="滨海","寒亭",LEFT(L87,2)))) -> 奎文 | S87: =TEXT(B87,"mmdd") -> 0703
A88: SD-057-240703-368104-7344 | B88: 2024-07-03 20:11:10 | C88: 潍坊 | D88: 【调研】-80+白金-(目标)普通区域-诸城市-龙都新苑-13606476759-1000M-业务受理宽带-次数0-202407030000697976 | E88: 2024-07-04 18:00:00 | F88: 202407030000697976 | G88: 202407030000697976# 宽带账号:13606476759; 联系电话：13606476759，问题类型：此工单为群障修复工单，根据群障全量闭环修复管理要求，为确保客户网络通畅，请装维人员跟进修复网络问题，谢谢！ 群障标题：公告。故障描述：分支光纤断或OLT检测不到ONT的预期的光信号(LOSi/LOBi)主叫号码：13563617548.0;该号码仅供参考，请优先联系宽带账号。 | H88: 2024-07-03 20:14:27 | I88: 业务受理->线上义诊->家庭业务->全局流转->功能使用->群障弹窗->全局流转 | J88: 李勇男 | K88: 15706307962 | L88: 诸城市 | M88: 家客铁通潍坊诸城-兴华西路城区装维组 | N88: 重新熔接皮线 | O88: dw3_jk_liyongnan | P88: 2024-07-03 20:14:53 | R88: =IF(OR(LEFT(L88,2)="高新"),"奎文",IF(LEFT(L88,2)="峡山","坊子",IF(LEFT(L88,2)="滨海","寒亭",LEFT(L88,2)))) -> 诸城 | S88: =TEXT(B88,"mmdd") -> 0703
A89: SD-057-240703-317284-4661 | B89: 2024-07-03 15:56:10 | C89: 潍坊 | D89: 80+银卡-普通区域-诸城市-龙苑尚城三期-15726068805-1000M-宽带上网投诉-次数0-20240703155357X237036604 | E89: 2024-07-04 08:00:00 | F89: 20240703155357X237036604 | G89: 流程受理流水号：20240703155231157260688051131892 客户号码:15726068805 客户姓名:丁** 投诉地市:潍坊 来话流水:2024070315510365920806730 宽带账号:15726068805 宽带账号归属地市:潍坊 宽带账号归属区县:诸城市 故障地址:潍坊诸城市龙都街道兴华路龙苑尚城三期龙苑尚城6号楼 联系电话:15165618929 联系人:女士 工单紧急程度:非常紧急 是否有升级投诉倾向:否 是否重复投诉:否 是否携转意向:否 是否投诉倾向:否 是否智能网关:智能网关 当前是否在线:是 接入方式:FTTH 端到端诊断结果:客户侧设备问题 是否质差终端:是 光功率:-15.10 故障大类:宽带/电视 故障细类:宽带无法上网(专席) 携转原因: 故障时间:2024-07-03 15:53:37 具体故障现象:光猫灯正常但电脑手机无法上网，显示质差光猫 客户其他诉求: | H89: 2024-07-03 15:59:51 | I89: 家宽业务->网络质量->家庭宽带->全局流转->功能使用->网络无法连接->全局流转 | J89: 王勇 | K89: 15706307942 | L89: 诸城市 | M89: 家客铁通潍坊诸城-兴华西路城区装维组 | N89: 为用户更换路由器 | O89: dw3_jk_wangyongzc | P89: 2024-07-03 16:06:57 | Q89: SD-851-326013-12539-14129 | R89: =IF(OR(LEFT(L89,2)="高新"),"奎文",IF(LEFT(L89,2)="峡山","坊子",IF(LEFT(L89,2)="滨海","寒亭",LEFT(L89,2)))) -> 诸城 | S89: =TEXT(B89,"mmdd") -> 0703
A90: SD-057-240703-234615-3468 | B90: 2024-07-03 13:44:31 | C90: 潍坊 | D90: 普通区域-奎文区-奎文区宏伟北区-13573640143-500M-宽带上网投诉-次数0-202407030000371458 | E90: 2024-07-04 08:00:00 | F90: 202407030000371458 | G90: 202407030000371458#宽带账号：13573640143宽带地址：潍坊奎文区潍州路街道环湖路奎文区宏伟北区3号楼 客户来电反映宽带机顶盒无法使用，客户不会操作，无法配合线上指导，要求上门服务，请协助处理，谢谢！联系电话：本机联系人：女士来电流水：2024070313410363420825773 | H90: 2024-07-03 14:04:37 | I90: 家庭咨询->网络质量->家庭宽带->全局流转->功能使用->客户要求装维上门服务->全局流转 | J90: 朱文杰 | K90: 15706366520 | L90: 奎文区 | M90: 家客铁通潍坊奎文-潍州路城区装维组 | N90: 重启路由器 | O90: dw3_jk_zhuwenjie | P90: 2024-07-03 14:05:00 | Q90: SD-851-269365-2970-17199 | R90: =IF(OR(LEFT(L90,2)="高新"),"奎文",IF(LEFT(L90,2)="峡山","坊子",IF(LEFT(L90,2)="滨海","寒亭",LEFT(L90,2)))) -> 奎文 | S90: =TEXT(B90,"mmdd") -> 0703
A91: SD-057-240703-178963-7352 | B91: 2024-07-03 20:11:23 | C91: 潍坊 | D91: 普通区域-诸城市-芝灵家园-15953666536-200M-宽带上网投诉-次数0-20240703200942X582756597 | E91: 2024-07-04 19:00:00 | F91: 20240703200942X582756597 | G91: 流程受理流水号：20240703200903159536665361194558 客户号码:15953666536 客户姓名:王** 投诉地市:潍坊 来话流水:2024070320063905320814784 宽带账号:15953666536 宽带账号归属地市:潍坊 宽带账号归属区县:诸城市 故障地址:潍坊诸城市昌城街道昌城驻地芝灵家园东区23号楼********* 联系电话:15854441991 联系人:先生/女士 工单紧急程度:一般 是否有升级投诉倾向:否 是否重复投诉:否 是否携转意向:否 是否投诉倾向:否 是否智能网关:智能网关 当前是否在线:是 接入方式:FTTH 端到端诊断结果:客户侧设备问题（新增） 是否质差终端:无质差信息 光功率:-18.15 故障大类:宽带/电视 故障细类:宽带无法上网(专席) 携转原因: 故障时间:2024-07-03 20:09:21 具体故障现象:打不开网页， 客户其他诉求:谢谢 | H91: 2024-07-03 20:13:26 | I91: 家宽业务->网络质量->家庭宽带->全局流转->功能使用->网络无法连接->全局流转 | J91: 姜勇 | K91: 15706307710 | L91: 诸城市 | M91: 家客铁通潍坊诸城-昌城乡镇装维组 | N91: 重启路由器 | O91: dw3_jk_jiangyong | P91: 2024-07-03 20:14:30 | R91: =IF(OR(LEFT(L91,2)="高新"),"奎文",IF(LEFT(L91,2)="峡山","坊子",IF(LEFT(L91,2)="滨海","寒亭",LEFT(L91,2)))) -> 诸城 | S91: =TEXT(B91,"mmdd") -> 0703
A92: SD-057-240703-805463-7359 | B92: 2024-07-03 20:11:30 | C92: 潍坊 | D92: 80+普通-普通区域-奎文区-锦绣樱园-15726057346-300M-魔百和投诉-次数0-20240703200951X591828231 | E92: 2024-07-04 19:00:00 | F92: 20240703200951X591828231 | G92: 流程受理流水号：20240703200341157260573461193775 客户号码:15726057346 客户姓名:胡** 投诉地市:潍坊 来话流水:2024070319563232020857140 宽带账号:15726057346 宽带账号归属地市:潍坊 宽带账号归属区县:奎文区 故障地址:潍坊奎文区梨园街道虞河路锦绣樱园36号楼********* 联系电话:15726057346 联系人:先生/女士 工单紧急程度:一般 是否有升级投诉倾向:否 是否重复投诉:否 是否携转意向:否 是否投诉倾向:否 是否智能网关:智能网关 当前是否在线:是 接入方式:FTTH 端到端诊断结果:客户侧设备问题（新增） 是否质差终端:无质差信息 光功率:-17.32 故障大类:宽带/电视 故障细类:移动高清电视故障(专席) 携转原因: 故障时间:2024-07-03 20:06:46 魔百和单播/组播:组播 具体故障现象:机顶盒无声音，调整av线，重启未恢复，联系电话不通请拨打13696364877 客户其他诉求: 魔百和单/组播：组播 | H92: 2024-07-03 20:13:05 | I92: 家庭业务->产品质量->互联网电视(移动高清)->全局流转->功能使用->无法进入播放界面->全局流转 | J92: 李三志 | K92: 15706366501 | L92: 奎文区 | M92: 家客铁通潍坊奎文-樱前街城区装维组 | N92: 建议用户联系终端厂商处理 | O92: dw3_jk_lisanzhi | P92: 2024-07-03 20:14:02 | R92: =IF(OR(LEFT(L92,2)="高新"),"奎文",IF(LEFT(L92,2)="峡山","坊子",IF(LEFT(L92,2)="滨海","寒亭",LEFT(L92,2)))) -> 奎文 | S92: =TEXT(B92,"mmdd") -> 0703
A93: SD-057-240703-583079-2204 | B93: 2024-07-03 11:29:06 | C93: 潍坊 | D93: 普通区域-安丘市-北院庄村自然村-18364614456-300M-宽带上网投诉-次数0-20240703112619X179530642 | E93: 2024-07-04 08:00:00 | F93: 20240703112619X179530642 | G93: 【农村网络投诉】流程受理流水号：20240703112454183646144561062546 客户号码:18364614456 客户姓名:刘** 投诉地市:潍坊 来话流水:2024070311205351720892293 宽带账号:18364614456 宽带账号归属地市:潍坊 宽带账号归属区县:安丘市 故障地址:潍坊安丘市担山镇北院庄村北院庄村自然村北院庄村 联系电话:15064460299 联系人:先生/女士 工单紧急程度:紧急 是否有升级投诉倾向:否 是否重复投诉:否 是否携转意向:否 是否投诉倾向:否 是否智能网关:智能网关 当前是否在线:是 接入方式:FTTH 端到端诊断结果:客户侧设备问题（新增） 是否质差终端:无质差信息 光功率:-15.88 故障大类:宽带/电视 故障细类:宽带无法上网(专席) 携转原因: 故障时间:2024-07-03 11:25:16 具体故障现象:客户来电表示宽带上不了网，我处检查网线，光猫情况，都未恢复，请协助处理谢谢 客户其他诉求: | H93: 2024-07-03 11:31:26 | I93: 家宽业务->网络质量->家庭宽带->全局流转->功能使用->网络无法连接->全局流转 | J93: 王永琳 | K93: 13406613524 | L93: 安丘市 | M93: 家客铁通潍坊安丘-贾戈乡镇装维组 | N93: 重新熔接皮线 | O93: dw3_jk_wangyonglinaq | P93: 2024-07-03 11:31:53 | R93: =IF(OR(LEFT(L93,2)="高新"),"奎文",IF(LEFT(L93,2)="峡山","坊子",IF(LEFT(L93,2)="滨海","寒亭",LEFT(L93,2)))) -> 安丘 | S93: =TEXT(B93,"mmdd") -> 0703
A94: SD-057-240703-546237-8017 | B94: 2024-07-03 21:26:29 | C94: 潍坊 | D94: 【重投】-【调研】-80+金卡-普通区域-潍城区-五道庙小区-13589162666-1000M-宽带上网投诉-次数0-20240703212522X122511733 | E94: 2024-07-04 19:00:00 | F94: 20240703212522X122511733 | G94: 流程受理流水号：20240703212455135891626661203807 客户号码:13589162666 客户姓名:滕** 投诉地市:潍坊 来话流水:2024070321213775620863190 宽带账号:13589162666 宽带账号归属地市:潍坊 宽带账号归属区县:潍城区 故障地址:潍坊潍城区城关街道胜利西街五道庙小区3号楼********* 联系电话:13589162666 联系人: 女士 工单紧急程度:非常紧急 是否有升级投诉倾向:否 是否重复投诉:否 是否携转意向:否 是否投诉倾向:否 是否智能网关:智能网关 当前是否在线:否 接入方式:FTTH 端到端诊断结果:状态正常 是否质差终端:无质差信息 光功率:无 故障大类:宽带/电视 故障细类:宽带无法上网 携转原因: 故障时间:2024-07-03 21:25:09 具体故障现象:光猫亮红灯， 客户其他诉求: | H94: 2024-07-03 21:28:22 | I94: 家宽业务->网络质量->家庭宽带->全局流转->功能使用->LOS红灯，无法上网->全局流转 | J94: 王晓虎 | K94: 15706307870 | L94: 潍城区 | M94: 家客铁通潍坊潍城-胜利街城区装维组 | N94: 重新熔接线缆 | O94: dw3_jk_wcwangxiaohu | P94: 2024-07-03 21:28:41 | Q94: SD-851-293382-23352-16797 | R94: =IF(OR(LEFT(L94,2)="高新"),"奎文",IF(LEFT(L94,2)="峡山","坊子",IF(LEFT(L94,2)="滨海","寒亭",LEFT(L94,2)))) -> 潍城 | S94: =TEXT(B94,"mmdd") -> 0703
A95: SD-057-240703-425139-2137 | B95: 2024-07-03 11:20:45 | C95: 潍坊 | D95: 【调研】-普通区域-昌邑市-南苏村自然村-15863416817-300M-宽带上网投诉-次数0-20240703111910X750915355 一级督办 | E95: 2024-07-04 08:00:00 | F95: 20240703111910X750915355 | G95: 【农村网络投诉】流程受理流水号：20240703111707158634168171060001 客户号码:15863416817 客户姓名:苏** 投诉地市:潍坊 来话流水:2024070311161618120826646 宽带账号:15863416817 宽带账号归属地市:潍坊 宽带账号归属区县:昌邑市 故障地址:潍坊昌邑市围子镇南苏村南苏村自然村5号箱苏海波********* 联系电话:15863416817 联系人:先生 工单紧急程度:非常紧急 是否有升级投诉倾向:否 是否重复投诉:否 是否携转意向:否 是否投诉倾向:否 是否智能网关:智能网关 当前是否在线:否 接入方式:FTTH 端到端诊断结果:状态正常 是否质差终端:无质差信息 光功率:无 故障大类:宽带/电视 故障细类:宽带无法上网 携转原因: 故障时间:2024-07-03 11:25:28 具体故障现象:光猫亮红灯 客户其他诉求: | H95: 2024-07-03 11:22:39 | I95: 家宽业务->网络质量->家庭宽带->全局流转->功能使用->LOS红灯，无法上网->全局流转 | J95: 董文琦 | K95: 15706307226 | L95: 昌邑市 | M95: 家客铁通潍坊昌邑-围子乡镇装维组 | O95: dw3_jk_dongwenqi | P95: 2024-07-03 11:23:04 | Q95: SD-851-268539-10718-29048 | R95: =IF(OR(LEFT(L95,2)="高新"),"奎文",IF(LEFT(L95,2)="峡山","坊子",IF(LEFT(L95,2)="滨海","寒亭",LEFT(L95,2)))) -> 昌邑 | S95: =TEXT(B95,"mmdd") -> 0703
A96: SD-057-240703-452713-2206 | B96: 2024-07-03 11:29:13 | C96: 潍坊 | D96: 【重投】-【调研】-80+普通-普通区域-奎文区-博悦世家-15762498213-300M-宽带上网投诉-次数0-20240703112638X198601858 | E96: 2024-07-04 08:00:00 | F96: 20240703112638X198601858 | G96: 流程受理流水号：20240703112556157624982131062871 客户号码:15762498213 客户姓名:刘** 投诉地市:潍坊 来话流水:2024070311195533120878518 宽带账号:15762498213 宽带账号归属地市:潍坊 宽带账号归属区县:奎文区 故障地址:潍坊奎文区北苑街道乐川街博悦世家8号楼********* 联系电话:15762498213 联系人:先生/女士 工单紧急程度:一般 是否有升级投诉倾向:否 是否重复投诉:否 是否携转意向:否 是否投诉倾向:否 是否智能网关:智能网关 当前是否在线:是 接入方式:FTTH 端到端诊断结果:客户侧设备问题（新增） 是否质差终端:无质差信息 光功率:-20.40 故障大类:宽带/电视 故障细类:宽带无法上网 携转原因: 故障时间:2024-07-03 11:26:09 具体故障现象:光猫亮红灯， 客户其他诉求:客户来电要求联系装维师傅上门查看，谢谢。 | H96: 2024-07-03 11:32:04 | I96: 家宽业务->网络质量->家庭宽带->全局流转->功能使用->网络连接掉线->全局流转 | J96: 王潇 | K96: 15706366502 | L96: 奎文区 | M96: 家客铁通潍坊奎文-鸢飞路城区装维组 | O96: dw3_jk_wangxiao | P96: 2024-07-03 11:32:37 | Q96: SD-851-315780-13352-16777 | R96: =IF(OR(LEFT(L96,2)="高新"),"奎文",IF(LEFT(L96,2)="峡山","坊子",IF(LEFT(L96,2)="滨海","寒亭",LEFT(L96,2)))) -> 奎文 | S96: =TEXT(B96,"mmdd") -> 0703
A97: SD-057-240703-096135-6380 | B97: 2024-07-03 18:53:59 | C97: 潍坊 | D97: 普通区域-昌邑市-六股村自然村-15094968015-200M-宽带上网投诉-次数0-202407030000650637 | E97: 2024-07-04 19:00:00 | F97: 202407030000650637 | G97: 202407030000650637#宽带账号：15094968015；宽带地址：潍坊昌邑市围子镇六股村六股村自然村扩容9号分线箱*********；；客户来电反映宽带故障，客户不配合排障，要求师傅上门，请协助处理，谢谢！联系电话：本机；联系人：女士；来电流水：2024070318520306320834421 | H97: 2024-07-03 18:55:14 | I97: 家庭咨询->网络质量->家庭宽带->全局流转->功能使用->客户要求装维上门服务->全局流转 | J97: 董文琦 | K97: 15706307226 | L97: 昌邑市 | M97: 家客铁通潍坊昌邑-围子乡镇装维组 | N97: 更换皮线或网线 | O97: dw3_jk_dongwenqi | P97: 2024-07-03 18:55:40 | R97: =IF(OR(LEFT(L97,2)="高新"),"奎文",IF(LEFT(L97,2)="峡山","坊子",IF(LEFT(L97,2)="滨海","寒亭",LEFT(L97,2)))) -> 昌邑 | S97: =TEXT(B97,"mmdd") -> 0703
A98: SD-057-240703-534890-7458 | B98: 2024-07-03 20:17:42 | C98: 潍坊 | D98: 80+银卡-普通区域-坊子区-望仙埠社区二期-18863651276-500M-宽带上网投诉-次数0-20240703201635X995722562 | E98: 2024-07-04 19:00:00 | F98: 20240703201635X995722562 | G98: 流程受理流水号：20240703201602188636512761195579 客户号码:18863651276 客户姓名:张** 投诉地市:潍坊 来话流水:2024070320154059020863382 宽带账号:18863651276 宽带账号归属地市:潍坊 宽带账号归属区县:峡山区 故障地址:潍坊峡山区太堡庄街道（太堡庄）兴峡路望仙埠社区二期望仙埠社区二期40#********* 联系电话:18863651276 联系人:先生/女士 工单紧急程度:一般 是否有升级投诉倾向:否 是否重复投诉:否 是否携转意向:否 是否投诉倾向:否 是否智能网关:智能网关 当前是否在线:否 接入方式:FTTH 端到端诊断结果:设备告警 是否质差终端:无质差信息 光功率:无 故障大类:宽带/电视 故障细类:宽带无法上网 携转原因: 故障时间:2024-07-03 12:16:40 具体故障现象:电脑无法上网， 客户其他诉求: | H98: 2024-07-03 20:27:00 | I98: 家宽业务->网络质量->家庭宽带->全局流转->功能使用->LOS红灯，无法上网->全局流转 | J98: 高先堂 | K98: 15706307920 | L98: 坊子区 | M98: 家客铁通潍坊坊子-太保庄乡镇装维组 | O98: dw3_jk_gaoxiantang | P98: 2024-07-03 20:27:35 | Q98: SD-851-292766-1647-29351 | R98: =IF(OR(LEFT(L98,2)="高新"),"奎文",IF(LEFT(L98,2)="峡山","坊子",IF(LEFT(L98,2)="滨海","寒亭",LEFT(L98,2)))) -> 坊子 | S98: =TEXT(B98,"mmdd") -> 0703
A99: SD-057-240703-872340-2145 | B99: 2024-07-03 11:21:55 | C99: 潍坊 | D99: 普通区域-寿光市-羊口保障房小区-17853615540-300M-业务受理宽带-次数0-202407030000269423 | E99: 2024-07-04 00:00:00 | F99: 202407030000269423 | G99: 202407030000269423#导航立单,用户所在位置有群障,已向客户播报,客户要求装维回访.此工单为群障修复工单,根据群障全量闭环管理要求,为确保客户网络通畅,请装维人员跟进修复网络问题,谢谢.联系电话：17853615540 | H99: 2024-07-03 11:24:42 | I99: 业务受理->线上义诊->家庭业务->全局流转->功能使用->群障弹窗->全局流转 | J99: 张鹏 | K99: 15706307827 | L99: 寿光市 | M99: 家客铁通潍坊寿光-羊口乡镇装维组 | N99: 重新熔缆 | O99: dw3_jk_zhangpeng | P99: 2024-07-03 11:25:12 | R99: =IF(OR(LEFT(L99,2)="高新"),"奎文",IF(LEFT(L99,2)="峡山","坊子",IF(LEFT(L99,2)="滨海","寒亭",LEFT(L99,2)))) -> 寿光 | S99: =TEXT(B99,"mmdd") -> 0703
A100: SD-057-240703-372681-5037 | B100: 2024-07-03 16:40:45 | C100: 潍坊 | D100: 80+银卡-普通区域-寿光市-弥河玉城-13562605338-300M-宽带上网投诉-次数0-202407030000515751 | E100: 2024-07-04 17:41:00 | F100: 202407030000515751 | G100: 202407030000515751#宽带账号：13562605338；宽带地址：潍坊寿光市圣城街道圣阳街弥河玉城南区5号；客户来电反映宽带无法上网，客户不配合排障，要求师傅上门，请协助处理，谢谢！联系电话：15725063621；联系人：女士；来电流水：2024070316384767920863530。 | H100: 2024-07-03 16:48:42 | I100: 家庭咨询->网络质量->家庭宽带->全局流转->功能使用->客户要求装维上门服务->全局流转 | J100: 韩海岩 | K100: 15244421603 | L100: 寿光市 | M100: 家客铁通潍坊寿光-东城城区装维组 | N100: 重启路由器 | O100: dw3_jk_hanhaiyan | P100: 2024-07-03 16:49:35 | R100: =IF(OR(LEFT(L100,2)="高新"),"奎文",IF(LEFT(L100,2)="峡山","坊子",IF(LEFT(L100,2)="滨海","寒亭",LEFT(L100,2)))) -> 寿光 | S100: =TEXT(B100,"mmdd") -> 0703
...

Sheet 网格情况
A1: =通报!N6&"日一级督办单情况网格投诉" -> 17日一级督办单情况网格投诉
A2: 序号 | B2: 区县 | C2: 归属网格 | D2: 累计情况 | G2: 昨日情况
D3: 投诉派单数量 | E3: 一级督办单数量 | F3: 一级督办占比 | G3: 投诉派单数量 | H3: 一级督办单数量 | I3: 一级督办占比 | K3: =通报!M6 -> 0717
A4: 1 | B4: 奎文 | C4: 家客铁通潍坊奎文-鸢飞路城区装维组 | D4: =COUNTIFS(累计派单!M:M,C:C)-COUNTIFS(累计派单!M:M,C:C,累计派单!I:I,"*群障*") -> 304 | E4: =COUNTIFS(督办单!Q:Q,C:C) -> 14 | F4: =IFERROR(E4/D4,0) -> 0.046052632 | G4: =COUNTIFS(累计派单!M:M,C:C,累计派单!S:S,$K$3)-COUNTIFS(累计派单!M:M,C:C,累计派单!I:I,"*群障*",累计派单!S:S,$K$3) -> 0 | H4: =COUNTIFS(督办单!Q:Q,C:C,督办单!M:M,$K$3) -> 0 | I4: =IFERROR(H4/G4,0) -> 0
A5: 2 | B5: 寿光 | C5: 家客铁通潍坊寿光-洛城乡镇装维组 | D5: =COUNTIFS(累计派单!M:M,C:C)-COUNTIFS(累计派单!M:M,C:C,累计派单!I:I,"*群障*") -> 138 | E5: =COUNTIFS(督办单!Q:Q,C:C) -> 8 | F5: =IFERROR(E5/D5,0) -> 0.057971014 | G5: =COUNTIFS(累计派单!M:M,C:C,累计派单!S:S,$K$3)-COUNTIFS(累计派单!M:M,C:C,累计派单!I:I,"*群障*",累计派单!S:S,$K$3) -> 0 | H5: =COUNTIFS(督办单!Q:Q,C:C,督办单!M:M,$K$3) -> 0 | I5: =IFERROR(H5/G5,0) -> 0
A6: 3 | B6: 高密 | C6: 家客铁通潍坊高密-朝阳城区装维组 | D6: =COUNTIFS(累计派单!M:M,C:C)-COUNTIFS(累计派单!M:M,C:C,累计派单!I:I,"*群障*") -> 214 | E6: =COUNTIFS(督办单!Q:Q,C:C) -> 6 | F6: =IFERROR(E6/D6,0) -> 0.028037383 | G6: =COUNTIFS(累计派单!M:M,C:C,累计派单!S:S,$K$3)-COUNTIFS(累计派单!M:M,C:C,累计派单!I:I,"*群障*",累计派单!S:S,$K$3) -> 0 | H6: =COUNTIFS(督办单!Q:Q,C:C,督办单!M:M,$K$3) -> 0 | I6: =IFERROR(H6/G6,0) -> 0
A7: 4 | B7: 寒亭 | C7: 家客铁通潍坊寒亭-开发区乡镇装维组 | D7: =COUNTIFS(累计派单!M:M,C:C)-COUNTIFS(累计派单!M:M,C:C,累计派单!I:I,"*群障*") -> 57 | E7: =COUNTIFS(督办单!Q:Q,C:C) -> 2 | F7: =IFERROR(E7/D7,0) -> 0.035087719 | G7: =COUNTIFS(累计派单!M:M,C:C,累计派单!S:S,$K$3)-COUNTIFS(累计派单!M:M,C:C,累计派单!I:I,"*群障*",累计派单!S:S,$K$3) -> 0 | H7: =COUNTIFS(督办单!Q:Q,C:C,督办单!M:M,$K$3) -> 0 | I7: =IFERROR(H7/G7,0) -> 0
A8: 5 | B8: 奎文 | C8: 家客铁通潍坊奎文-北宫街城区装维组 | D8: =COUNTIFS(累计派单!M:M,C:C)-COUNTIFS(累计派单!M:M,C:C,累计派单!I:I,"*群障*") -> 113 | E8: =COUNTIFS(督办单!Q:Q,C:C) -> 3 | F8: =IFERROR(E8/D8,0) -> 0.026548673 | G8: =COUNTIFS(累计派单!M:M,C:C,累计派单!S:S,$K$3)-COUNTIFS(累计派单!M:M,C:C,累计派单!I:I,"*群障*",累计派单!S:S,$K$3) -> 0 | H8: =COUNTIFS(督办单!Q:Q,C:C,督办单!M:M,$K$3) -> 0 | I8: =IFERROR(H8/G8,0) -> 0
A9: 6 | B9: 奎文 | C9: 家客铁通潍坊奎文-健康街城区装维组 | D9: =COUNTIFS(累计派单!M:M,C:C)-COUNTIFS(累计派单!M:M,C:C,累计派单!I:I,"*群障*") -> 50 | E9: =COUNTIFS(督办单!Q:Q,C:C) -> 0 | F9: =IFERROR(E9/D9,0) -> 0 | G9: =COUNTIFS(累计派单!M:M,C:C,累计派单!S:S,$K$3)-COUNTIFS(累计派单!M:M,C:C,累计派单!I:I,"*群障*",累计派单!S:S,$K$3) -> 0 | H9: =COUNTIFS(督办单!Q:Q,C:C,督办单!M:M,$K$3) -> 0 | I9: =IFERROR(H9/G9,0) -> 0
A10: 7 | B10: 奎文 | C10: 家客铁通潍坊奎文-潍州路城区装维组 | D10: =COUNTIFS(累计派单!M:M,C:C)-COUNTIFS(累计派单!M:M,C:C,累计派单!I:I,"*群障*") -> 174 | E10: =COUNTIFS(督办单!Q:Q,C:C) -> 9 | F10: =IFERROR(E10/D10,0) -> 0.051724138 | G10: =COUNTIFS(累计派单!M:M,C:C,累计派单!S:S,$K$3)-COUNTIFS(累计派单!M:M,C:C,累计派单!I:I,"*群障*",累计派单!S:S,$K$3) -> 0 | H10: =COUNTIFS(督办单!Q:Q,C:C,督办单!M:M,$K$3) -> 0 | I10: =IFERROR(H10/G10,0) -> 0
A11: 8 | B11: 青州 | C11: 家客铁通潍坊青州-高柳乡镇装维组 | D11: =COUNTIFS(累计派单!M:M,C:C)-COUNTIFS(累计派单!M:M,C:C,累计派单!I:I,"*群障*") -> 58 | E11: =COUNTIFS(督办单!Q:Q,C:C) -> 1 | F11: =IFERROR(E11/D11,0) -> 0.017241379 | G11: =COUNTIFS(累计派单!M:M,C:C,累计派单!S:S,$K$3)-COUNTIFS(累计派单!M:M,C:C,累计派单!I:I,"*群障*",累计派单!S:S,$K$3) -> 0 | H11: =COUNTIFS(督办单!Q:Q,C:C,督办单!M:M,$K$3) -> 0 | I11: =IFERROR(H11/G11,0) -> 0
A12: 9 | B12: 青州 | C12: 家客铁通潍坊青州-黄楼乡镇装维组 | D12: =COUNTIFS(累计派单!M:M,C:C)-COUNTIFS(累计派单!M:M,C:C,累计派单!I:I,"*群障*") -> 112 | E12: =COUNTIFS(督办单!Q:Q,C:C) -> 3 | F12: =IFERROR(E12/D12,0) -> 0.026785714 | G12: =COUNTIFS(累计派单!M:M,C:C,累计派单!S:S,$K$3)-COUNTIFS(累计派单!M:M,C:C,累计派单!I:I,"*群障*",累计派单!S:S,$K$3) -> 0 | H12: =COUNTIFS(督办单!Q:Q,C:C,督办单!M:M,$K$3) -> 0 | I12: =IFERROR(H12/G12,0) -> 0
A13: 10 | B13: 寿光 | C13: 家客铁通潍坊寿光-古城乡镇装维组 | D13: =COUNTIFS(累计派单!M:M,C:C)-COUNTIFS(累计派单!M:M,C:C,累计派单!I:I,"*群障*") -> 74 | E13: =COUNTIFS(督办单!Q:Q,C:C) -> 2 | F13: =IFERROR(E13/D13,0) -> 0.027027027 | G13: =COUNTIFS(累计派单!M:M,C:C,累计派单!S:S,$K$3)-COUNTIFS(累计派单!M:M,C:C,累计派单!I:I,"*群障*",累计派单!S:S,$K$3) -> 0 | H13: =COUNTIFS(督办单!Q:Q,C:C,督办单!M:M,$K$3) -> 0 | I13: =IFERROR(H13/G13,0) -> 0
A14: 11 | B14: 寿光 | C14: 家客铁通潍坊寿光-孙集乡镇装维组 | D14: =COUNTIFS(累计派单!M:M,C:C)-COUNTIFS(累计派单!M:M,C:C,累计派单!I:I,"*群障*") -> 79 | E14: =COUNTIFS(督办单!Q:Q,C:C) -> 3 | F14: =IFERROR(E14/D14,0) -> 0.037974684 | G14: =COUNTIFS(累计派单!M:M,C:C,累计派单!S:S,$K$3)-COUNTIFS(累计派单!M:M,C:C,累计派单!I:I,"*群障*",累计派单!S:S,$K$3) -> 0 | H14: =COUNTIFS(督办单!Q:Q,C:C,督办单!M:M,$K$3) -> 0 | I14: =IFERROR(H14/G14,0) -> 0
A15: 12 | B15: 潍城 | C15: 家客铁通潍坊潍城-东风街城区装维组 | D15: =COUNTIFS(累计派单!M:M,C:C)-COUNTIFS(累计派单!M:M,C:C,累计派单!I:I,"*群障*") -> 173 | E15: =COUNTIFS(督办单!Q:Q,C:C) -> 10 | F15: =IFERROR(E15/D15,0) -> 0.057803468 | G15: =COUNTIFS(累计派单!M:M,C:C,累计派单!S:S,$K$3)-COUNTIFS(累计派单!M:M,C:C,累计派单!I:I,"*群障*",累计派单!S:S,$K$3) -> 0 | H15: =COUNTIFS(督办单!Q:Q,C:C,督办单!M:M,$K$3) -> 0 | I15: =IFERROR(H15/G15,0) -> 0
... A102: 99 | B102: 诸城 | C102: 家客铁通潍坊诸城-枳沟乡镇装维组 | D102: =COUNTIFS(累计派单!M:M,C:C)-COUNTIFS(累计派单!M:M,C:C,累计派单!I:I,"*群障*") -> 16 | E102: =COUNTIFS(督办单!Q:Q,C:C) -> 1 | F102: =IFERROR(E102/D102,0) -> 0.0625 | G102: =COUNTIFS(累计派单!M:M,C:C,累计派单!S:S,$K$3)-COUNTIFS(累计派单!M:M,C:C,累计派单!I:I,"*群障*",累计派单!S:S,$K$3) -> 0 | H102: =COUNTIFS(督办单!Q:Q,C:C,督办单!M:M,$K$3) -> 0 | I102: =IFERROR(H102/G102,0) -> 0

Sheet 个人情况
A1: =通报!N6&"日一级督办单情况个人投诉" -> 17日一级督办单情况个人投诉
A2: 序号 | B2: 区县 | C2: 姓名 | D2: 装维账号 | E2: 归属网格 | F2: 昨日情况
F3: 投诉派单数量 | G3: 一级督办单数量 | H3: 一级督办占比 | J3: =通报!M6 -> 0717
A4: 1 | B4: 安丘 | C4: 都荣亮 | D4: dw3_jk_durongliang2 | E4: 家客铁通潍坊安丘-石埠子乡镇装维组 | F4: =COUNTIFS(累计派单!O:O,D:D,累计派单!S:S,$J$3)-COUNTIFS(累计派单!O:O,D:D,累计派单!I:I,"*群障*",累计派单!S:S,$J$3) -> 0 | G4: =COUNTIFS(督办单!N:N,D:D,督办单!M:M,$J$3) -> 0 | H4: =IFERROR(G4/F4,0) -> 0
A5: 2 | B5: 安丘 | C5: 徐中华 | D5: dw3_jk_xuzhonghua | E5: 家客铁通潍坊安丘-官庄乡镇装维组 | F5: =COUNTIFS(累计派单!O:O,D:D,累计派单!S:S,$J$3)-COUNTIFS(累计派单!O:O,D:D,累计派单!I:I,"*群障*",累计派单!S:S,$J$3) -> 0 | G5: =COUNTIFS(督办单!N:N,D:D,督办单!M:M,$J$3) -> 0 | H5: =IFERROR(G5/F5,0) -> 0
A6: 3 | B6: 安丘 | C6: 周龙涛 | D6: dw3_jk_zhoulongtao | E6: 家客铁通潍坊安丘-潍安路城区装维组 | F6: =COUNTIFS(累计派单!O:O,D:D,累计派单!S:S,$J$3)-COUNTIFS(累计派单!O:O,D:D,累计派单!I:I,"*群障*",累计派单!S:S,$J$3) -> 0 | G6: =COUNTIFS(督办单!N:N,D:D,督办单!M:M,$J$3) -> 0 | H6: =IFERROR(G6/F6,0) -> 0
A7: 4 | B7: 高密 | C7: 单文涛 | D7: dw3_jk_shanwentao | E7: 家客铁通潍坊高密-朝阳城区装维组 | F7: =COUNTIFS(累计派单!O:O,D:D,累计派单!S:S,$J$3)-COUNTIFS(累计派单!O:O,D:D,累计派单!I:I,"*群障*",累计派单!S:S,$J$3) -> 0 | G7: =COUNTIFS(督办单!N:N,D:D,督办单!M:M,$J$3) -> 0 | H7: =IFERROR(G7/F7,0) -> 0
A8: 5 | B8: 奎文 | C8: 李春龙 | D8: dw3_jk_lichunlong | E8: 家客铁通潍坊奎文-鸢飞路城区装维组 | F8: =COUNTIFS(累计派单!O:O,D:D,累计派单!S:S,$J$3)-COUNTIFS(累计派单!O:O,D:D,累计派单!I:I,"*群障*",累计派单!S:S,$J$3) -> 0 | G8: =COUNTIFS(督办单!N:N,D:D,督办单!M:M,$J$3) -> 0 | H8: =IFERROR(G8/F8,0) -> 0
A9: 6 | B9: 奎文 | C9: 田永生 | D9: dw3_jk_tianyongsheng | E9: 家客铁通潍坊奎文-鸢飞路城区装维组 | F9: =COUNTIFS(累计派单!O:O,D:D,累计派单!S:S,$J$3)-COUNTIFS(累计派单!O:O,D:D,累计派单!I:I,"*群障*",累计派单!S:S,$J$3) -> 0 | G9: =COUNTIFS(督办单!N:N,D:D,督办单!M:M,$J$3) -> 0 | H9: =IFERROR(G9/F9,0) -> 0
A10: 7 | B10: 奎文 | C10: 闫晗 | D10: dw3_jk_yanhan | E10: 家客铁通潍坊奎文-樱前街城区装维组 | F10: =COUNTIFS(累计派单!O:O,D:D,累计派单!S:S,$J$3)-COUNTIFS(累计派单!O:O,D:D,累计派单!I:I,"*群障*",累计派单!S:S,$J$3) -> 0 | G10: =COUNTIFS(督办单!N:N,D:D,督办单!M:M,$J$3) -> 0 | H10: =IFERROR(G10/F10,0) -> 0
A11: 8 | B11: 奎文 | C11: 张强 | D11: dw3_jk_zhangqiang | E11: 家客铁通潍坊奎文-金光路城区装维组 | F11: =COUNTIFS(累计派单!O:O,D:D,累计派单!S:S,$J$3)-COUNTIFS(累计派单!O:O,D:D,累计派单!I:I,"*群障*",累计派单!S:S,$J$3) -> 0 | G11: =COUNTIFS(督办单!N:N,D:D,督办单!M:M,$J$3) -> 0 | H11: =IFERROR(G11/F11,0) -> 0
A12: 9 | B12: 临朐 | C12: 邓兆然 | D12: dw3_jk_dengzhaoran | E12: 家客铁通潍坊临朐-城关城区装维组 | F12: =COUNTIFS(累计派单!O:O,D:D,累计派单!S:S,$J$3)-COUNTIFS(累计派单!O:O,D:D,累计派单!I:I,"*群障*",累计派单!S:S,$J$3) -> 0 | G12: =COUNTIFS(督办单!N:N,D:D,督办单!M:M,$J$3) -> 0 | H12: =IFERROR(G12/F12,0) -> 0
A13: 10 | B13: 临朐 | C13: 马全兴 | D13: dw3_jk_maquanxing | E13: 家客铁通潍坊临朐-五井乡镇装维组 | F13: =COUNTIFS(累计派单!O:O,D:D,累计派单!S:S,$J$3)-COUNTIFS(累计派单!O:O,D:D,累计派单!I:I,"*群障*",累计派单!S:S,$J$3) -> 0 | G13: =COUNTIFS(督办单!N:N,D:D,督办单!M:M,$J$3) -> 0 | H13: =IFERROR(G13/F13,0) -> 0
A14: 11 | B14: 临朐 | C14: 赵京龙 | D14: dw3_jk_zhaojinglong | E14: 家客铁通潍坊临朐-蒋峪乡镇装维组 | F14: =COUNTIFS(累计派单!O:O,D:D,累计派单!S:S,$J$3)-COUNTIFS(累计派单!O:O,D:D,累计派单!I:I,"*群障*",累计派单!S:S,$J$3) -> 0 | G14: =COUNTIFS(督办单!N:N,D:D,督办单!M:M,$J$3) -> 0 | H14: =IFERROR(G14/F14,0) -> 0
A15: 12 | B15: 青州 | C15: 王建国 | D15: dw3_jk_wangjianguo | E15: 家客铁通潍坊青州-谭坊乡镇装维组 | F15: =COUNTIFS(累计派单!O:O,D:D,累计派单!S:S,$J$3)-COUNTIFS(累计派单!O:O,D:D,累计派单!I:I,"*群障*",累计派单!S:S,$J$3) -> 0 | G15: =COUNTIFS(督办单!N:N,D:D,督办单!M:M,$J$3) -> 0 | H15: =IFERROR(G15/F15,0) -> 0
... A571: 568 | B571: 诸城 | C571: 邹大伟 | D571: dw3_jk_zoudawei | E571: 家客铁通潍坊诸城-相州乡镇装维组 | F571: =COUNTIFS(累计派单!O:O,D:D,累计派单!S:S,$J$3)-COUNTIFS(累计派单!O:O,D:D,累计派单!I:I,"*群障*",累计派单!S:S,$J$3) -> 0 | G571: =COUNTIFS(督办单!N:N,D:D,督办单!M:M,$J$3) -> 0 | H571: =IFERROR(G571/F571,0) -> 0
